Workbook
Name \a: #REF!
Name \a: #REF!
Name \a: #REF!
Name \b: #REF!
Name \b: #REF!
Name \b: #REF!
Name \c: #REF!
Name \c: #REF!
Name \d: #REF!
Name \d: #REF!
Name \e: #REF!
Name \e: #REF!
Name \f: #REF!
Name \f: #REF!
Name \g: #REF!
Name \g: #REF!
Name \h: #REF!
Name \h: #REF!
Name \i: #REF!
Name \i: #REF!
Name \j: #REF!
Name \j: #REF!
Name \m: #REF!
Name \m: #REF!
Name \s: #REF!
Name \s: #REF!
Name _____1.2: [1]BOQ!#REF!
Name _____1.2: [1]BOQ!#REF!
Name _____1.3: [1]BOQ!#REF!
Name _____1.3: [1]BOQ!#REF!
Name _____1.4: [1]BOQ!#REF!
Name _____1.4: [1]BOQ!#REF!
Name _____5A.1: [1]BOQ!#REF!
Name _____5A.1: [1]BOQ!#REF!
Name _____5A.2: [1]BOQ!#REF!
Name _____5A.2: [1]BOQ!#REF!
Name _____5A.3: [1]BOQ!#REF!
Name _____5A.3: [1]BOQ!#REF!
Name _____5B.1: [1]BOQ!#REF!
Name _____5B.1: [1]BOQ!#REF!
Name _____5B.2: [1]BOQ!#REF!
Name _____5B.2: [1]BOQ!#REF!
Name _____5B.3: [1]BOQ!#REF!
Name _____5B.3: [1]BOQ!#REF!
Name _____5B.4: [1]BOQ!#REF!
Name _____5B.4: [1]BOQ!#REF!
Name _____6.2: [1]BOQ!#REF!
Name _____6.2: [1]BOQ!#REF!
Name _____6.3: [1]BOQ!#REF!
Name _____6.3: [1]BOQ!#REF!
Name _____6.4: [1]BOQ!#REF!
Name _____6.4: [1]BOQ!#REF!
Name ____1.2: [1]BOQ!#REF!
Name ____1.2: [1]BOQ!#REF!
Name ____1.3: [1]BOQ!#REF!
Name ____1.3: [1]BOQ!#REF!
Name ____1.4: [1]BOQ!#REF!
Name ____1.4: [1]BOQ!#REF!
Name ____5A.1: [1]BOQ!#REF!
Name ____5A.1: [1]BOQ!#REF!

Sheet Machinery 
A1: Vehicle Running Summary - January 2026
A3: No | B3: Vehicle No | C3: Type | D3: actual days/machine hours | E3: Days/machine hours consider for costing | F3: Distance (Km) | G3: Fuel | H3: rate | I3: Rate Unit | J3: Actual Work Done | K3: Consumption | L3: RATE HOUR /DAY | M3: Amount without Idling | N3: Amount with Idling | O3: Owner | P3: Package | Q3: Remarks
A4: 1 | B4: LA-1359 | C4: Diesel bowser | H4: =IF(COUNTIF(Sheet1!$C$13:$C$530,Table44[[#This Row],[Vehicle No]])>0,_xlfn.XLOOKUP(Table44[[#This Row],[Vehicle No]],Sheet1!$C$13:$C$530,Sheet1!$K$13:$K$530,"",0),_xlfn.XLOOKUP(Table44[[#This Row],[Vehicle No]],Sheet1!$B$13:$B$530,Sheet1!$K$13:$K$530,"",0)) -> 5 | I4: =IF(COUNTIF(Sheet1!$C$13:$C$530,Table44[[#This Row],[Vehicle No]])>0,_xlfn.XLOOKUP(Table44[[#This Row],[Vehicle No]],Sheet1!$C$13:$C$530,Sheet1!$J$13:$J$530,"-",0),_xlfn.XLOOKUP(Table44[[#This Row],[Vehicle No]],Sheet1!$B$13:$B$530,Sheet1!$J$13:$J$530,"-",0)) -> L/hr | J4: =IF(Table44[[#This Row],[rate]]=0,"-",IF(Table44[[#This Row],[Rate Unit]]="L/hr",IF(Table44[[#This Row],[Fuel]]=0,"-",Table44[[#This Row],[Fuel]]/Table44[[#This Row],[rate]]),IF(Table44[[#This Row],[Fuel]]=0,"-",Table44[[#This Row],[Fuel]]*Table44[[#This Row],[rate]]))) -> - | K4: =Table44[[#This Row],[Distance (Km)]]/Table44[[#This Row],[Fuel]] -> #DIV/0! | L4: =IF(COUNTIF(Sheet1!$C$13:$C$530,Table44[[#This Row],[Vehicle No]])>0,_xlfn.XLOOKUP(Table44[[#This Row],[Vehicle No]],Sheet1!$C$13:$C$530,Sheet1!$O$13:$O$530,"",0),_xlfn.XLOOKUP(Table44[[#This Row],[Vehicle No]],Sheet1!$B$13:$B$530,Sheet1!$O$13:$O$530,"",0)) -> 2808.25 | M4: =Table44[[#This Row],[RATE HOUR /DAY]]*Table44[[#This Row],[actual days/machine hours]] -> 0 | N4: =Table44[[#This Row],[RATE HOUR /DAY]]*Table44[[#This Row],[Days/machine hours consider for costing]] -> 0 | O4: E & C
A5: 2 | B5: LL-0920 | C5: 01 Cube | D5: 24 | E5: 24 | G5: 460 | H5: =IF(COUNTIF(Sheet1!$C$13:$C$530,Table44[[#This Row],[Vehicle No]])>0,_xlfn.XLOOKUP(Table44[[#This Row],[Vehicle No]],Sheet1!$C$13:$C$530,Sheet1!$K$13:$K$530,"",0),_xlfn.XLOOKUP(Table44[[#This Row],[Vehicle No]],Sheet1!$B$13:$B$530,Sheet1!$K$13:$K$530,"",0)) -> 6.4 | I5: =IF(COUNTIF(Sheet1!$C$13:$C$530,Table44[[#This Row],[Vehicle No]])>0,_xlfn.XLOOKUP(Table44[[#This Row],[Vehicle No]],Sheet1!$C$13:$C$530,Sheet1!$J$13:$J$530,"-",0),_xlfn.XLOOKUP(Table44[[#This Row],[Vehicle No]],Sheet1!$B$13:$B$530,Sheet1!$J$13:$J$530,"-",0)) -> km/L | J5: =IF(Table44[[#This Row],[rate]]=0,"-",IF(Table44[[#This Row],[Rate Unit]]="L/hr",IF(Table44[[#This Row],[Fuel]]=0,"-",Table44[[#This Row],[Fuel]]/Table44[[#This Row],[rate]]),IF(Table44[[#This Row],[Fuel]]=0,"-",Table44[[#This Row],[Fuel]]*Table44[[#This Row],[rate]]))) -> 2944 | L5: =IF(COUNTIF(Sheet1!$C$13:$C$530,Table44[[#This Row],[Vehicle No]])>0,_xlfn.XLOOKUP(Table44[[#This Row],[Vehicle No]],Sheet1!$C$13:$C$530,Sheet1!$O$13:$O$530,"",0),_xlfn.XLOOKUP(Table44[[#This Row],[Vehicle No]],Sheet1!$B$13:$B$530,Sheet1!$O$13:$O$530,"",0)) -> 81.484062 | M5: =Table44[[#This Row],[RATE HOUR /DAY]]*Table44[[#This Row],[actual days/machine hours]] -> 1955.6175 | N5: =Table44[[#This Row],[RATE HOUR /DAY]]*Table44[[#This Row],[Days/machine hours consider for costing]] -> 1955.6175 | O5: E & C
A6: 3 | B6: LP-1573 | C6: 3 Cube | D6: 21 | E6: 21 | F6: 2356 | G6: 869 | H6: =IF(COUNTIF(Sheet1!$C$13:$C$530,Table44[[#This Row],[Vehicle No]])>0,_xlfn.XLOOKUP(Table44[[#This Row],[Vehicle No]],Sheet1!$C$13:$C$530,Sheet1!$K$13:$K$530,"",0),_xlfn.XLOOKUP(Table44[[#This Row],[Vehicle No]],Sheet1!$B$13:$B$530,Sheet1!$K$13:$K$530,"",0)) -> 3.8 | I6: =IF(COUNTIF(Sheet1!$C$13:$C$530,Table44[[#This Row],[Vehicle No]])>0,_xlfn.XLOOKUP(Table44[[#This Row],[Vehicle No]],Sheet1!$C$13:$C$530,Sheet1!$J$13:$J$530,"-",0),_xlfn.XLOOKUP(Table44[[#This Row],[Vehicle No]],Sheet1!$B$13:$B$530,Sheet1!$J$13:$J$530,"-",0)) -> km/L | J6: =IF(Table44[[#This Row],[rate]]=0,"-",IF(Table44[[#This Row],[Rate Unit]]="L/hr",IF(Table44[[#This Row],[Fuel]]=0,"-",Table44[[#This Row],[Fuel]]/Table44[[#This Row],[rate]]),IF(Table44[[#This Row],[Fuel]]=0,"-",Table44[[#This Row],[Fuel]]*Table44[[#This Row],[rate]]))) -> 3302.2 | K6: =F6/G6 -> 2.7111623 | L6: =IF(COUNTIF(Sheet1!$C$13:$C$530,Table44[[#This Row],[Vehicle No]])>0,_xlfn.XLOOKUP(Table44[[#This Row],[Vehicle No]],Sheet1!$C$13:$C$530,Sheet1!$O$13:$O$530,"",0),_xlfn.XLOOKUP(Table44[[#This Row],[Vehicle No]],Sheet1!$B$13:$B$530,Sheet1!$O$13:$O$530,"",0)) -> 130.19211 | M6: =Table44[[#This Row],[RATE HOUR /DAY]]*Table44[[#This Row],[actual days/machine hours]] -> 2734.0342 | N6: =Table44[[#This Row],[RATE HOUR /DAY]]*Table44[[#This Row],[Days/machine hours consider for costing]] -> 2734.0342 | O6: E & C
A7: 4 | B7: LP-1577 | C7: 3 Cube | D7: 19 | E7: 19 | F7: 1807 | G7: 710 | H7: =IF(COUNTIF(Sheet1!$C$13:$C$530,Table44[[#This Row],[Vehicle No]])>0,_xlfn.XLOOKUP(Table44[[#This Row],[Vehicle No]],Sheet1!$C$13:$C$530,Sheet1!$K$13:$K$530,"",0),_xlfn.XLOOKUP(Table44[[#This Row],[Vehicle No]],Sheet1!$B$13:$B$530,Sheet1!$K$13:$K$530,"",0)) -> 3.8 | I7: =IF(COUNTIF(Sheet1!$C$13:$C$530,Table44[[#This Row],[Vehicle No]])>0,_xlfn.XLOOKUP(Table44[[#This Row],[Vehicle No]],Sheet1!$C$13:$C$530,Sheet1!$J$13:$J$530,"-",0),_xlfn.XLOOKUP(Table44[[#This Row],[Vehicle No]],Sheet1!$B$13:$B$530,Sheet1!$J$13:$J$530,"-",0)) -> km/L | J7: =IF(Table44[[#This Row],[rate]]=0,"-",IF(Table44[[#This Row],[Rate Unit]]="L/hr",IF(Table44[[#This Row],[Fuel]]=0,"-",Table44[[#This Row],[Fuel]]/Table44[[#This Row],[rate]]),IF(Table44[[#This Row],[Fuel]]=0,"-",Table44[[#This Row],[Fuel]]*Table44[[#This Row],[rate]]))) -> 2698 | K7: =F7/G7 -> 2.5450704 | L7: =IF(COUNTIF(Sheet1!$C$13:$C$530,Table44[[#This Row],[Vehicle No]])>0,_xlfn.XLOOKUP(Table44[[#This Row],[Vehicle No]],Sheet1!$C$13:$C$530,Sheet1!$O$13:$O$530,"",0),_xlfn.XLOOKUP(Table44[[#This Row],[Vehicle No]],Sheet1!$B$13:$B$530,Sheet1!$O$13:$O$530,"",0)) -> 130.19211 | M7: =Table44[[#This Row],[RATE HOUR /DAY]]*Table44[[#This Row],[actual days/machine hours]] -> 2473.65 | N7: =Table44[[#This Row],[RATE HOUR /DAY]]*Table44[[#This Row],[Days/machine hours consider for costing]] -> 2473.65 | O7: E & C
A8: 5 | B8: LM-5719 | C8: 3 Cube | D8: 8 | E8: 8 | G8: 210 | H8: =IF(COUNTIF(Sheet1!$C$13:$C$530,Table44[[#This Row],[Vehicle No]])>0,_xlfn.XLOOKUP(Table44[[#This Row],[Vehicle No]],Sheet1!$C$13:$C$530,Sheet1!$K$13:$K$530,"",0),_xlfn.XLOOKUP(Table44[[#This Row],[Vehicle No]],Sheet1!$B$13:$B$530,Sheet1!$K$13:$K$530,"",0)) -> 3.8 | I8: =IF(COUNTIF(Sheet1!$C$13:$C$530,Table44[[#This Row],[Vehicle No]])>0,_xlfn.XLOOKUP(Table44[[#This Row],[Vehicle No]],Sheet1!$C$13:$C$530,Sheet1!$J$13:$J$530,"-",0),_xlfn.XLOOKUP(Table44[[#This Row],[Vehicle No]],Sheet1!$B$13:$B$530,Sheet1!$J$13:$J$530,"-",0)) -> km/L | J8: =IF(Table44[[#This Row],[rate]]=0,"-",IF(Table44[[#This Row],[Rate Unit]]="L/hr",IF(Table44[[#This Row],[Fuel]]=0,"-",Table44[[#This Row],[Fuel]]/Table44[[#This Row],[rate]]),IF(Table44[[#This Row],[Fuel]]=0,"-",Table44[[#This Row],[Fuel]]*Table44[[#This Row],[rate]]))) -> 798 | K8: =F8/G8 -> 0 | L8: =IF(COUNTIF(Sheet1!$C$13:$C$530,Table44[[#This Row],[Vehicle No]])>0,_xlfn.XLOOKUP(Table44[[#This Row],[Vehicle No]],Sheet1!$C$13:$C$530,Sheet1!$O$13:$O$530,"",0),_xlfn.XLOOKUP(Table44[[#This Row],[Vehicle No]],Sheet1!$B$13:$B$530,Sheet1!$O$13:$O$530,"",0)) -> 134.59474 | M8: =Table44[[#This Row],[RATE HOUR /DAY]]*Table44[[#This Row],[actual days/machine hours]] -> 1076.7579 | N8: =Table44[[#This Row],[RATE HOUR /DAY]]*Table44[[#This Row],[Days/machine hours consider for costing]] -> 1076.7579 | O8: E & C
A9: 6 | B9: LM-7940 | C9: 3 Cube | H9: =IF(COUNTIF(Sheet1!$C$13:$C$530,Table44[[#This Row],[Vehicle No]])>0,_xlfn.XLOOKUP(Table44[[#This Row],[Vehicle No]],Sheet1!$C$13:$C$530,Sheet1!$K$13:$K$530,"",0),_xlfn.XLOOKUP(Table44[[#This Row],[Vehicle No]],Sheet1!$B$13:$B$530,Sheet1!$K$13:$K$530,"",0)) -> 3.8 | I9: =IF(COUNTIF(Sheet1!$C$13:$C$530,Table44[[#This Row],[Vehicle No]])>0,_xlfn.XLOOKUP(Table44[[#This Row],[Vehicle No]],Sheet1!$C$13:$C$530,Sheet1!$J$13:$J$530,"-",0),_xlfn.XLOOKUP(Table44[[#This Row],[Vehicle No]],Sheet1!$B$13:$B$530,Sheet1!$J$13:$J$530,"-",0)) -> km/L | J9: =IF(Table44[[#This Row],[rate]]=0,"-",IF(Table44[[#This Row],[Rate Unit]]="L/hr",IF(Table44[[#This Row],[Fuel]]=0,"-",Table44[[#This Row],[Fuel]]/Table44[[#This Row],[rate]]),IF(Table44[[#This Row],[Fuel]]=0,"-",Table44[[#This Row],[Fuel]]*Table44[[#This Row],[rate]]))) -> - | K9: =F9/G9 -> #DIV/0! | L9: =IF(COUNTIF(Sheet1!$C$13:$C$530,Table44[[#This Row],[Vehicle No]])>0,_xlfn.XLOOKUP(Table44[[#This Row],[Vehicle No]],Sheet1!$C$13:$C$530,Sheet1!$O$13:$O$530,"",0),_xlfn.XLOOKUP(Table44[[#This Row],[Vehicle No]],Sheet1!$B$13:$B$530,Sheet1!$O$13:$O$530,"",0)) -> 134.59474 | M9: =Table44[[#This Row],[RATE HOUR /DAY]]*Table44[[#This Row],[actual days/machine hours]] -> 0 | N9: =Table44[[#This Row],[RATE HOUR /DAY]]*Table44[[#This Row],[Days/machine hours consider for costing]] -> 0 | O9: E & C
A10: 7 | B10: LM-7948 | C10: 3 Cube | D10: 5 | E10: 5 | G10: 50 | H10: =IF(COUNTIF(Sheet1!$C$13:$C$530,Table44[[#This Row],[Vehicle No]])>0,_xlfn.XLOOKUP(Table44[[#This Row],[Vehicle No]],Sheet1!$C$13:$C$530,Sheet1!$K$13:$K$530,"",0),_xlfn.XLOOKUP(Table44[[#This Row],[Vehicle No]],Sheet1!$B$13:$B$530,Sheet1!$K$13:$K$530,"",0)) -> 3.8 | I10: =IF(COUNTIF(Sheet1!$C$13:$C$530,Table44[[#This Row],[Vehicle No]])>0,_xlfn.XLOOKUP(Table44[[#This Row],[Vehicle No]],Sheet1!$C$13:$C$530,Sheet1!$J$13:$J$530,"-",0),_xlfn.XLOOKUP(Table44[[#This Row],[Vehicle No]],Sheet1!$B$13:$B$530,Sheet1!$J$13:$J$530,"-",0)) -> km/L | J10: =IF(Table44[[#This Row],[rate]]=0,"-",IF(Table44[[#This Row],[Rate Unit]]="L/hr",IF(Table44[[#This Row],[Fuel]]=0,"-",Table44[[#This Row],[Fuel]]/Table44[[#This Row],[rate]]),IF(Table44[[#This Row],[Fuel]]=0,"-",Table44[[#This Row],[Fuel]]*Table44[[#This Row],[rate]]))) -> 190 | K10: =F10/G10 -> 0 | L10: =IF(COUNTIF(Sheet1!$C$13:$C$530,Table44[[#This Row],[Vehicle No]])>0,_xlfn.XLOOKUP(Table44[[#This Row],[Vehicle No]],Sheet1!$C$13:$C$530,Sheet1!$O$13:$O$530,"",0),_xlfn.XLOOKUP(Table44[[#This Row],[Vehicle No]],Sheet1!$B$13:$B$530,Sheet1!$O$13:$O$530,"",0)) -> 134.59474 | M10: =Table44[[#This Row],[RATE HOUR /DAY]]*Table44[[#This Row],[actual days/machine hours]] -> 672.97368 | N10: =Table44[[#This Row],[RATE HOUR /DAY]]*Table44[[#This Row],[Days/machine hours consider for costing]] -> 672.97368 | O10: E & C
A11: 8 | B11: LO-5983 | C11: 3 Cube | D11: 23 | E11: 23 | G11: 605 | H11: =IF(COUNTIF(Sheet1!$C$13:$C$530,Table44[[#This Row],[Vehicle No]])>0,_xlfn.XLOOKUP(Table44[[#This Row],[Vehicle No]],Sheet1!$C$13:$C$530,Sheet1!$K$13:$K$530,"",0),_xlfn.XLOOKUP(Table44[[#This Row],[Vehicle No]],Sheet1!$B$13:$B$530,Sheet1!$K$13:$K$530,"",0)) -> 3.8 | I11: =IF(COUNTIF(Sheet1!$C$13:$C$530,Table44[[#This Row],[Vehicle No]])>0,_xlfn.XLOOKUP(Table44[[#This Row],[Vehicle No]],Sheet1!$C$13:$C$530,Sheet1!$J$13:$J$530,"-",0),_xlfn.XLOOKUP(Table44[[#This Row],[Vehicle No]],Sheet1!$B$13:$B$530,Sheet1!$J$13:$J$530,"-",0)) -> km/L | J11: =IF(Table44[[#This Row],[rate]]=0,"-",IF(Table44[[#This Row],[Rate Unit]]="L/hr",IF(Table44[[#This Row],[Fuel]]=0,"-",Table44[[#This Row],[Fuel]]/Table44[[#This Row],[rate]]),IF(Table44[[#This Row],[Fuel]]=0,"-",Table44[[#This Row],[Fuel]]*Table44[[#This Row],[rate]]))) -> 2299 | K11: =F11/G11 -> 0 | L11: =IF(COUNTIF(Sheet1!$C$13:$C$530,Table44[[#This Row],[Vehicle No]])>0,_xlfn.XLOOKUP(Table44[[#This Row],[Vehicle No]],Sheet1!$C$13:$C$530,Sheet1!$O$13:$O$530,"",0),_xlfn.XLOOKUP(Table44[[#This Row],[Vehicle No]],Sheet1!$B$13:$B$530,Sheet1!$O$13:$O$530,"",0)) -> 134.59474 | M11: =Table44[[#This Row],[RATE HOUR /DAY]]*Table44[[#This Row],[actual days/machine hours]] -> 3095.6789 | N11: =Table44[[#This Row],[RATE HOUR /DAY]]*Table44[[#This Row],[Days/machine hours consider for costing]] -> 3095.6789 | O11: E & C
A12: 9 | B12: LO-7182 | C12: 3 Cube | D12: 26 | E12: 26 | G12: 810 | H12: =IF(COUNTIF(Sheet1!$C$13:$C$530,Table44[[#This Row],[Vehicle No]])>0,_xlfn.XLOOKUP(Table44[[#This Row],[Vehicle No]],Sheet1!$C$13:$C$530,Sheet1!$K$13:$K$530,"",0),_xlfn.XLOOKUP(Table44[[#This Row],[Vehicle No]],Sheet1!$B$13:$B$530,Sheet1!$K$13:$K$530,"",0)) -> 3.8 | I12: =IF(COUNTIF(Sheet1!$C$13:$C$530,Table44[[#This Row],[Vehicle No]])>0,_xlfn.XLOOKUP(Table44[[#This Row],[Vehicle No]],Sheet1!$C$13:$C$530,Sheet1!$J$13:$J$530,"-",0),_xlfn.XLOOKUP(Table44[[#This Row],[Vehicle No]],Sheet1!$B$13:$B$530,Sheet1!$J$13:$J$530,"-",0)) -> km/L | J12: =IF(Table44[[#This Row],[rate]]=0,"-",IF(Table44[[#This Row],[Rate Unit]]="L/hr",IF(Table44[[#This Row],[Fuel]]=0,"-",Table44[[#This Row],[Fuel]]/Table44[[#This Row],[rate]]),IF(Table44[[#This Row],[Fuel]]=0,"-",Table44[[#This Row],[Fuel]]*Table44[[#This Row],[rate]]))) -> 3078 | K12: =F12/G12 -> 0 | L12: =IF(COUNTIF(Sheet1!$C$13:$C$530,Table44[[#This Row],[Vehicle No]])>0,_xlfn.XLOOKUP(Table44[[#This Row],[Vehicle No]],Sheet1!$C$13:$C$530,Sheet1!$O$13:$O$530,"",0),_xlfn.XLOOKUP(Table44[[#This Row],[Vehicle No]],Sheet1!$B$13:$B$530,Sheet1!$O$13:$O$530,"",0)) -> 132.83368 | M12: =Table44[[#This Row],[RATE HOUR /DAY]]*Table44[[#This Row],[actual days/machine hours]] -> 3453.6758 | N12: =Table44[[#This Row],[RATE HOUR /DAY]]*Table44[[#This Row],[Days/machine hours consider for costing]] -> 3453.6758 | O12: E & C
A13: 10 | B13: LO-7183 | C13: 3 Cube | H13: =IF(COUNTIF(Sheet1!$C$13:$C$530,Table44[[#This Row],[Vehicle No]])>0,_xlfn.XLOOKUP(Table44[[#This Row],[Vehicle No]],Sheet1!$C$13:$C$530,Sheet1!$K$13:$K$530,"",0),_xlfn.XLOOKUP(Table44[[#This Row],[Vehicle No]],Sheet1!$B$13:$B$530,Sheet1!$K$13:$K$530,"",0)) -> 3.8 | I13: =IF(COUNTIF(Sheet1!$C$13:$C$530,Table44[[#This Row],[Vehicle No]])>0,_xlfn.XLOOKUP(Table44[[#This Row],[Vehicle No]],Sheet1!$C$13:$C$530,Sheet1!$J$13:$J$530,"-",0),_xlfn.XLOOKUP(Table44[[#This Row],[Vehicle No]],Sheet1!$B$13:$B$530,Sheet1!$J$13:$J$530,"-",0)) -> km/L | J13: =IF(Table44[[#This Row],[rate]]=0,"-",IF(Table44[[#This Row],[Rate Unit]]="L/hr",IF(Table44[[#This Row],[Fuel]]=0,"-",Table44[[#This Row],[Fuel]]/Table44[[#This Row],[rate]]),IF(Table44[[#This Row],[Fuel]]=0,"-",Table44[[#This Row],[Fuel]]*Table44[[#This Row],[rate]]))) -> - | L13: =IF(COUNTIF(Sheet1!$C$13:$C$530,Table44[[#This Row],[Vehicle No]])>0,_xlfn.XLOOKUP(Table44[[#This Row],[Vehicle No]],Sheet1!$C$13:$C$530,Sheet1!$O$13:$O$530,"",0),_xlfn.XLOOKUP(Table44[[#This Row],[Vehicle No]],Sheet1!$B$13:$B$530,Sheet1!$O$13:$O$530,"",0)) -> 132.83368 | M13: =Table44[[#This Row],[RATE HOUR /DAY]]*Table44[[#This Row],[actual days/machine hours]] -> 0 | N13: =Table44[[#This Row],[RATE HOUR /DAY]]*Table44[[#This Row],[Days/machine hours consider for costing]] -> 0
A14: 11 | B14: LN-8277 | C14: Boom Truck | D14: 20 | E14: 20 | F14: 2041 | G14: 830 | H14: =IF(COUNTIF(Sheet1!$C$13:$C$530,Table44[[#This Row],[Vehicle No]])>0,_xlfn.XLOOKUP(Table44[[#This Row],[Vehicle No]],Sheet1!$C$13:$C$530,Sheet1!$K$13:$K$530,"",0),_xlfn.XLOOKUP(Table44[[#This Row],[Vehicle No]],Sheet1!$B$13:$B$530,Sheet1!$K$13:$K$530,"",0)) -> 7.2 | I14: =IF(COUNTIF(Sheet1!$C$13:$C$530,Table44[[#This Row],[Vehicle No]])>0,_xlfn.XLOOKUP(Table44[[#This Row],[Vehicle No]],Sheet1!$C$13:$C$530,Sheet1!$J$13:$J$530,"-",0),_xlfn.XLOOKUP(Table44[[#This Row],[Vehicle No]],Sheet1!$B$13:$B$530,Sheet1!$J$13:$J$530,"-",0)) -> L/hr | J14: =IF(Table44[[#This Row],[rate]]=0,"-",IF(Table44[[#This Row],[Rate Unit]]="L/hr",IF(Table44[[#This Row],[Fuel]]=0,"-",Table44[[#This Row],[Fuel]]/Table44[[#This Row],[rate]]),IF(Table44[[#This Row],[Fuel]]=0,"-",Table44[[#This Row],[Fuel]]*Table44[[#This Row],[rate]]))) -> 115.27778 | K14: =F14/G14 -> 2.4590361 | L14: =IF(COUNTIF(Sheet1!$C$13:$C$530,Table44[[#This Row],[Vehicle No]])>0,_xlfn.XLOOKUP(Table44[[#This Row],[Vehicle No]],Sheet1!$C$13:$C$530,Sheet1!$O$13:$O$530,"",0),_xlfn.XLOOKUP(Table44[[#This Row],[Vehicle No]],Sheet1!$B$13:$B$530,Sheet1!$O$13:$O$530,"",0)) -> 3947.5152 | M14: =Table44[[#This Row],[RATE HOUR /DAY]]*Table44[[#This Row],[actual days/machine hours]] -> 78950.304 | N14: =Table44[[#This Row],[RATE HOUR /DAY]]*Table44[[#This Row],[Days/machine hours consider for costing]] -> 78950.304 | O14: E & C
A15: 12 | B15: HEX-01 | C15: Volvo 220 | D15: 95.8 | E15: 95.8 | G15: 1145 | H15: =IF(COUNTIF(Sheet1!$C$13:$C$530,Table44[[#This Row],[Vehicle No]])>0,_xlfn.XLOOKUP(Table44[[#This Row],[Vehicle No]],Sheet1!$C$13:$C$530,Sheet1!$K$13:$K$530,"",0),_xlfn.XLOOKUP(Table44[[#This Row],[Vehicle No]],Sheet1!$B$13:$B$530,Sheet1!$K$13:$K$530,"",0)) -> 11.5 | I15: =IF(COUNTIF(Sheet1!$C$13:$C$530,Table44[[#This Row],[Vehicle No]])>0,_xlfn.XLOOKUP(Table44[[#This Row],[Vehicle No]],Sheet1!$C$13:$C$530,Sheet1!$J$13:$J$530,"-",0),_xlfn.XLOOKUP(Table44[[#This Row],[Vehicle No]],Sheet1!$B$13:$B$530,Sheet1!$J$13:$J$530,"-",0)) -> L/hr | J15: =IF(Table44[[#This Row],[rate]]=0,"-",IF(Table44[[#This Row],[Rate Unit]]="L/hr",IF(Table44[[#This Row],[Fuel]]=0,"-",Table44[[#This Row],[Fuel]]/Table44[[#This Row],[rate]]),IF(Table44[[#This Row],[Fuel]]=0,"-",Table44[[#This Row],[Fuel]]*Table44[[#This Row],[rate]]))) -> 99.565217 | K15: =Table44[[#This Row],[Fuel]]/Table44[[#This Row],[actual days/machine hours]] -> 11.951983 | L15: =IF(COUNTIF(Sheet1!$C$13:$C$530,Table44[[#This Row],[Vehicle No]])>0,_xlfn.XLOOKUP(Table44[[#This Row],[Vehicle No]],Sheet1!$C$13:$C$530,Sheet1!$O$13:$O$530,"",0),_xlfn.XLOOKUP(Table44[[#This Row],[Vehicle No]],Sheet1!$B$13:$B$530,Sheet1!$O$13:$O$530,"",0)) -> 5997.227 | M15: =Table44[[#This Row],[RATE HOUR /DAY]]*Table44[[#This Row],[actual days/machine hours]] -> 574534.35 | N15: =Table44[[#This Row],[RATE HOUR /DAY]]*Table44[[#This Row],[Days/machine hours consider for costing]] -> 574534.35 | O15: E & C
A16: 13 | B16: HEX-19 | C16: Komatsu 120 | D16: 126.9 | E16: 126.9 | G16: 855 | H16: =IF(COUNTIF(Sheet1!$C$13:$C$530,Table44[[#This Row],[Vehicle No]])>0,_xlfn.XLOOKUP(Table44[[#This Row],[Vehicle No]],Sheet1!$C$13:$C$530,Sheet1!$K$13:$K$530,"",0),_xlfn.XLOOKUP(Table44[[#This Row],[Vehicle No]],Sheet1!$B$13:$B$530,Sheet1!$K$13:$K$530,"",0)) -> 7.2 | I16: =IF(COUNTIF(Sheet1!$C$13:$C$530,Table44[[#This Row],[Vehicle No]])>0,_xlfn.XLOOKUP(Table44[[#This Row],[Vehicle No]],Sheet1!$C$13:$C$530,Sheet1!$J$13:$J$530,"-",0),_xlfn.XLOOKUP(Table44[[#This Row],[Vehicle No]],Sheet1!$B$13:$B$530,Sheet1!$J$13:$J$530,"-",0)) -> L/hr | J16: =IF(Table44[[#This Row],[rate]]=0,"-",IF(Table44[[#This Row],[Rate Unit]]="L/hr",IF(Table44[[#This Row],[Fuel]]=0,"-",Table44[[#This Row],[Fuel]]/Table44[[#This Row],[rate]]),IF(Table44[[#This Row],[Fuel]]=0,"-",Table44[[#This Row],[Fuel]]*Table44[[#This Row],[rate]]))) -> 118.75 | K16: =Table44[[#This Row],[Fuel]]/Table44[[#This Row],[actual days/machine hours]] -> 6.7375887 | L16: =IF(COUNTIF(Sheet1!$C$13:$C$530,Table44[[#This Row],[Vehicle No]])>0,_xlfn.XLOOKUP(Table44[[#This Row],[Vehicle No]],Sheet1!$C$13:$C$530,Sheet1!$O$13:$O$530,"",0),_xlfn.XLOOKUP(Table44[[#This Row],[Vehicle No]],Sheet1!$B$13:$B$530,Sheet1!$O$13:$O$530,"",0)) -> 3851.1504 | M16: =Table44[[#This Row],[RATE HOUR /DAY]]*Table44[[#This Row],[actual days/machine hours]] -> 488710.99 | N16: =Table44[[#This Row],[RATE HOUR /DAY]]*Table44[[#This Row],[Days/machine hours consider for costing]] -> 488710.99 | O16: E & C
B17: HEX-42 | C17: Case 220 | D17: 43.9 | E17: 43.9 | G17: 570 | H17: =IF(COUNTIF(Sheet1!$C$13:$C$530,Table44[[#This Row],[Vehicle No]])>0,_xlfn.XLOOKUP(Table44[[#This Row],[Vehicle No]],Sheet1!$C$13:$C$530,Sheet1!$K$13:$K$530,"",0),_xlfn.XLOOKUP(Table44[[#This Row],[Vehicle No]],Sheet1!$B$13:$B$530,Sheet1!$K$13:$K$530,"",0)) -> 11.5 | I17: =IF(COUNTIF(Sheet1!$C$13:$C$530,Table44[[#This Row],[Vehicle No]])>0,_xlfn.XLOOKUP(Table44[[#This Row],[Vehicle No]],Sheet1!$C$13:$C$530,Sheet1!$J$13:$J$530,"-",0),_xlfn.XLOOKUP(Table44[[#This Row],[Vehicle No]],Sheet1!$B$13:$B$530,Sheet1!$J$13:$J$530,"-",0)) -> L/hr | J17: =IF(Table44[[#This Row],[rate]]=0,"-",IF(Table44[[#This Row],[Rate Unit]]="L/hr",IF(Table44[[#This Row],[Fuel]]=0,"-",Table44[[#This Row],[Fuel]]/Table44[[#This Row],[rate]]),IF(Table44[[#This Row],[Fuel]]=0,"-",Table44[[#This Row],[Fuel]]*Table44[[#This Row],[rate]]))) -> 49.565217 | K17: =Table44[[#This Row],[Fuel]]/Table44[[#This Row],[actual days/machine hours]] -> 12.984055 | L17: =IF(COUNTIF(Sheet1!$C$13:$C$530,Table44[[#This Row],[Vehicle No]])>0,_xlfn.XLOOKUP(Table44[[#This Row],[Vehicle No]],Sheet1!$C$13:$C$530,Sheet1!$O$13:$O$530,"",0),_xlfn.XLOOKUP(Table44[[#This Row],[Vehicle No]],Sheet1!$B$13:$B$530,Sheet1!$O$13:$O$530,"",0)) -> 5689.395 | M17: =Table44[[#This Row],[RATE HOUR /DAY]]*Table44[[#This Row],[actual days/machine hours]] -> 249764.44 | N17: =Table44[[#This Row],[RATE HOUR /DAY]]*Table44[[#This Row],[Days/machine hours consider for costing]] -> 249764.44
A18: 14 | B18: 51-8083 | C18: D/Cab | D18: 23 | E18: 23 | G18: 616 | H18: =IF(COUNTIF(Sheet1!$C$13:$C$530,Table44[[#This Row],[Vehicle No]])>0,_xlfn.XLOOKUP(Table44[[#This Row],[Vehicle No]],Sheet1!$C$13:$C$530,Sheet1!$K$13:$K$530,"",0),_xlfn.XLOOKUP(Table44[[#This Row],[Vehicle No]],Sheet1!$B$13:$B$530,Sheet1!$K$13:$K$530,"",0)) -> 12.8 | I18: =IF(COUNTIF(Sheet1!$C$13:$C$530,Table44[[#This Row],[Vehicle No]])>0,_xlfn.XLOOKUP(Table44[[#This Row],[Vehicle No]],Sheet1!$C$13:$C$530,Sheet1!$J$13:$J$530,"-",0),_xlfn.XLOOKUP(Table44[[#This Row],[Vehicle No]],Sheet1!$B$13:$B$530,Sheet1!$J$13:$J$530,"-",0)) -> km/L | J18: =IF(Table44[[#This Row],[rate]]=0,"-",IF(Table44[[#This Row],[Rate Unit]]="L/hr",IF(Table44[[#This Row],[Fuel]]=0,"-",Table44[[#This Row],[Fuel]]/Table44[[#This Row],[rate]]),IF(Table44[[#This Row],[Fuel]]=0,"-",Table44[[#This Row],[Fuel]]*Table44[[#This Row],[rate]]))) -> 7884.8 | K18: =F18/G18 -> 0 | L18: =IF(COUNTIF(Sheet1!$C$13:$C$530,Table44[[#This Row],[Vehicle No]])>0,_xlfn.XLOOKUP(Table44[[#This Row],[Vehicle No]],Sheet1!$C$13:$C$530,Sheet1!$O$13:$O$530,"",0),_xlfn.XLOOKUP(Table44[[#This Row],[Vehicle No]],Sheet1!$B$13:$B$530,Sheet1!$O$13:$O$530,"",0)) -> 37.34375 | M18: =Table44[[#This Row],[RATE HOUR /DAY]]*Table44[[#This Row],[actual days/machine hours]] -> 858.90625 | N18: =Table44[[#This Row],[RATE HOUR /DAY]]*Table44[[#This Row],[Days/machine hours consider for costing]] -> 858.90625 | O18: E & C
B19: DAH-2230 | C19: S/Cab | D19: 8 | E19: 8 | F19: 859 | G19: 114 | H19: =IF(COUNTIF(Sheet1!$C$13:$C$530,Table44[[#This Row],[Vehicle No]])>0,_xlfn.XLOOKUP(Table44[[#This Row],[Vehicle No]],Sheet1!$C$13:$C$530,Sheet1!$K$13:$K$530,"",0),_xlfn.XLOOKUP(Table44[[#This Row],[Vehicle No]],Sheet1!$B$13:$B$530,Sheet1!$K$13:$K$530,"",0)) -> 14.1 | I19: =IF(COUNTIF(Sheet1!$C$13:$C$530,Table44[[#This Row],[Vehicle No]])>0,_xlfn.XLOOKUP(Table44[[#This Row],[Vehicle No]],Sheet1!$C$13:$C$530,Sheet1!$J$13:$J$530,"-",0),_xlfn.XLOOKUP(Table44[[#This Row],[Vehicle No]],Sheet1!$B$13:$B$530,Sheet1!$J$13:$J$530,"-",0)) -> km/L | J19: =IF(Table44[[#This Row],[rate]]=0,"-",IF(Table44[[#This Row],[Rate Unit]]="L/hr",IF(Table44[[#This Row],[Fuel]]=0,"-",Table44[[#This Row],[Fuel]]/Table44[[#This Row],[rate]]),IF(Table44[[#This Row],[Fuel]]=0,"-",Table44[[#This Row],[Fuel]]*Table44[[#This Row],[rate]]))) -> 1607.4 | L19: =IF(COUNTIF(Sheet1!$C$13:$C$530,Table44[[#This Row],[Vehicle No]])>0,_xlfn.XLOOKUP(Table44[[#This Row],[Vehicle No]],Sheet1!$C$13:$C$530,Sheet1!$O$13:$O$530,"",0),_xlfn.XLOOKUP(Table44[[#This Row],[Vehicle No]],Sheet1!$B$13:$B$530,Sheet1!$O$13:$O$530,"",0)) -> 35.561844 | M19: =Table44[[#This Row],[RATE HOUR /DAY]]*Table44[[#This Row],[actual days/machine hours]] -> 284.49475 | N19: =Table44[[#This Row],[RATE HOUR /DAY]]*Table44[[#This Row],[Days/machine hours consider for costing]] -> 284.49475
A20: 15 | B20: PT-1569 | C20: S/Cab | D20: 10 | E20: 10 | G20: 144 | H20: =IF(COUNTIF(Sheet1!$C$13:$C$530,Table44[[#This Row],[Vehicle No]])>0,_xlfn.XLOOKUP(Table44[[#This Row],[Vehicle No]],Sheet1!$C$13:$C$530,Sheet1!$K$13:$K$530,"",0),_xlfn.XLOOKUP(Table44[[#This Row],[Vehicle No]],Sheet1!$B$13:$B$530,Sheet1!$K$13:$K$530,"",0)) -> 14.1 | I20: =IF(COUNTIF(Sheet1!$C$13:$C$530,Table44[[#This Row],[Vehicle No]])>0,_xlfn.XLOOKUP(Table44[[#This Row],[Vehicle No]],Sheet1!$C$13:$C$530,Sheet1!$J$13:$J$530,"-",0),_xlfn.XLOOKUP(Table44[[#This Row],[Vehicle No]],Sheet1!$B$13:$B$530,Sheet1!$J$13:$J$530,"-",0)) -> km/L | J20: =IF(Table44[[#This Row],[rate]]=0,"-",IF(Table44[[#This Row],[Rate Unit]]="L/hr",IF(Table44[[#This Row],[Fuel]]=0,"-",Table44[[#This Row],[Fuel]]/Table44[[#This Row],[rate]]),IF(Table44[[#This Row],[Fuel]]=0,"-",Table44[[#This Row],[Fuel]]*Table44[[#This Row],[rate]]))) -> 2030.4 | L20: =IF(COUNTIF(Sheet1!$C$13:$C$530,Table44[[#This Row],[Vehicle No]])>0,_xlfn.XLOOKUP(Table44[[#This Row],[Vehicle No]],Sheet1!$C$13:$C$530,Sheet1!$O$13:$O$530,"",0),_xlfn.XLOOKUP(Table44[[#This Row],[Vehicle No]],Sheet1!$B$13:$B$530,Sheet1!$O$13:$O$530,"",0)) -> 37.222979 | M20: =Table44[[#This Row],[RATE HOUR /DAY]]*Table44[[#This Row],[actual days/machine hours]] -> 372.22979 | N20: =Table44[[#This Row],[RATE HOUR /DAY]]*Table44[[#This Row],[Days/machine hours consider for costing]] -> 372.22979
A21: 16 | B21: PH-6742 | C21: C/Cab | H21: =IF(COUNTIF(Sheet1!$C$13:$C$530,Table44[[#This Row],[Vehicle No]])>0,_xlfn.XLOOKUP(Table44[[#This Row],[Vehicle No]],Sheet1!$C$13:$C$530,Sheet1!$K$13:$K$530,"",0),_xlfn.XLOOKUP(Table44[[#This Row],[Vehicle No]],Sheet1!$B$13:$B$530,Sheet1!$K$13:$K$530,"",0)) -> 12.8 | I21: =IF(COUNTIF(Sheet1!$C$13:$C$530,Table44[[#This Row],[Vehicle No]])>0,_xlfn.XLOOKUP(Table44[[#This Row],[Vehicle No]],Sheet1!$C$13:$C$530,Sheet1!$J$13:$J$530,"-",0),_xlfn.XLOOKUP(Table44[[#This Row],[Vehicle No]],Sheet1!$B$13:$B$530,Sheet1!$J$13:$J$530,"-",0)) -> km/L | J21: =IF(Table44[[#This Row],[rate]]=0,"-",IF(Table44[[#This Row],[Rate Unit]]="L/hr",IF(Table44[[#This Row],[Fuel]]=0,"-",Table44[[#This Row],[Fuel]]/Table44[[#This Row],[rate]]),IF(Table44[[#This Row],[Fuel]]=0,"-",Table44[[#This Row],[Fuel]]*Table44[[#This Row],[rate]]))) -> - | K21: =F21/G21 -> #DIV/0! | L21: =IF(COUNTIF(Sheet1!$C$13:$C$530,Table44[[#This Row],[Vehicle No]])>0,_xlfn.XLOOKUP(Table44[[#This Row],[Vehicle No]],Sheet1!$C$13:$C$530,Sheet1!$O$13:$O$530,"",0),_xlfn.XLOOKUP(Table44[[#This Row],[Vehicle No]],Sheet1!$B$13:$B$530,Sheet1!$O$13:$O$530,"",0)) -> 39.957813 | M21: =Table44[[#This Row],[RATE HOUR /DAY]]*Table44[[#This Row],[actual days/machine hours]] -> 0 | N21: =Table44[[#This Row],[RATE HOUR /DAY]]*Table44[[#This Row],[Days/machine hours consider for costing]] -> 0 | O21: E & C
A22: 17 | B22: 325-3448 | C22: C/Cab | H22: =IF(COUNTIF(Sheet1!$C$13:$C$530,Table44[[#This Row],[Vehicle No]])>0,_xlfn.XLOOKUP(Table44[[#This Row],[Vehicle No]],Sheet1!$C$13:$C$530,Sheet1!$K$13:$K$530,"",0),_xlfn.XLOOKUP(Table44[[#This Row],[Vehicle No]],Sheet1!$B$13:$B$530,Sheet1!$K$13:$K$530,"",0)) -> 12.8 | I22: =IF(COUNTIF(Sheet1!$C$13:$C$530,Table44[[#This Row],[Vehicle No]])>0,_xlfn.XLOOKUP(Table44[[#This Row],[Vehicle No]],Sheet1!$C$13:$C$530,Sheet1!$J$13:$J$530,"-",0),_xlfn.XLOOKUP(Table44[[#This Row],[Vehicle No]],Sheet1!$B$13:$B$530,Sheet1!$J$13:$J$530,"-",0)) -> km/L | J22: =IF(Table44[[#This Row],[rate]]=0,"-",IF(Table44[[#This Row],[Rate Unit]]="L/hr",IF(Table44[[#This Row],[Fuel]]=0,"-",Table44[[#This Row],[Fuel]]/Table44[[#This Row],[rate]]),IF(Table44[[#This Row],[Fuel]]=0,"-",Table44[[#This Row],[Fuel]]*Table44[[#This Row],[rate]]))) -> - | K22: =F22/G22 -> #DIV/0! | L22: =IF(COUNTIF(Sheet1!$C$13:$C$530,Table44[[#This Row],[Vehicle No]])>0,_xlfn.XLOOKUP(Table44[[#This Row],[Vehicle No]],Sheet1!$C$13:$C$530,Sheet1!$O$13:$O$530,"",0),_xlfn.XLOOKUP(Table44[[#This Row],[Vehicle No]],Sheet1!$B$13:$B$530,Sheet1!$O$13:$O$530,"",0)) -> 43.878906 | M22: =Table44[[#This Row],[RATE HOUR /DAY]]*Table44[[#This Row],[actual days/machine hours]] -> 0 | N22: =Table44[[#This Row],[RATE HOUR /DAY]]*Table44[[#This Row],[Days/machine hours consider for costing]] -> 0 | O22: E & C
A23: 18 | B23: PD-6917 | C23: D/Cab | H23: =IF(COUNTIF(Sheet1!$C$13:$C$530,Table44[[#This Row],[Vehicle No]])>0,_xlfn.XLOOKUP(Table44[[#This Row],[Vehicle No]],Sheet1!$C$13:$C$530,Sheet1!$K$13:$K$530,"",0),_xlfn.XLOOKUP(Table44[[#This Row],[Vehicle No]],Sheet1!$B$13:$B$530,Sheet1!$K$13:$K$530,"",0)) -> 12.8 | I23: =IF(COUNTIF(Sheet1!$C$13:$C$530,Table44[[#This Row],[Vehicle No]])>0,_xlfn.XLOOKUP(Table44[[#This Row],[Vehicle No]],Sheet1!$C$13:$C$530,Sheet1!$J$13:$J$530,"-",0),_xlfn.XLOOKUP(Table44[[#This Row],[Vehicle No]],Sheet1!$B$13:$B$530,Sheet1!$J$13:$J$530,"-",0)) -> km/L | J23: =IF(Table44[[#This Row],[rate]]=0,"-",IF(Table44[[#This Row],[Rate Unit]]="L/hr",IF(Table44[[#This Row],[Fuel]]=0,"-",Table44[[#This Row],[Fuel]]/Table44[[#This Row],[rate]]),IF(Table44[[#This Row],[Fuel]]=0,"-",Table44[[#This Row],[Fuel]]*Table44[[#This Row],[rate]]))) -> - | K23: =F23/G23 -> #DIV/0! | L23: =IF(COUNTIF(Sheet1!$C$13:$C$530,Table44[[#This Row],[Vehicle No]])>0,_xlfn.XLOOKUP(Table44[[#This Row],[Vehicle No]],Sheet1!$C$13:$C$530,Sheet1!$O$13:$O$530,"",0),_xlfn.XLOOKUP(Table44[[#This Row],[Vehicle No]],Sheet1!$B$13:$B$530,Sheet1!$O$13:$O$530,"",0)) -> 41.264844 | M23: =Table44[[#This Row],[RATE HOUR /DAY]]*Table44[[#This Row],[actual days/machine hours]] -> 0 | N23: =Table44[[#This Row],[RATE HOUR /DAY]]*Table44[[#This Row],[Days/machine hours consider for costing]] -> 0 | O23: E & C
A24: 19 | B24: MG-06 | C24: Motor Grader | D24: 87.8 | E24: 87.8 | G24: 830 | H24: =IF(COUNTIF(Sheet1!$C$13:$C$530,Table44[[#This Row],[Vehicle No]])>0,_xlfn.XLOOKUP(Table44[[#This Row],[Vehicle No]],Sheet1!$C$13:$C$530,Sheet1!$K$13:$K$530,"",0),_xlfn.XLOOKUP(Table44[[#This Row],[Vehicle No]],Sheet1!$B$13:$B$530,Sheet1!$K$13:$K$530,"",0)) -> 13 | I24: =IF(COUNTIF(Sheet1!$C$13:$C$530,Table44[[#This Row],[Vehicle No]])>0,_xlfn.XLOOKUP(Table44[[#This Row],[Vehicle No]],Sheet1!$C$13:$C$530,Sheet1!$J$13:$J$530,"-",0),_xlfn.XLOOKUP(Table44[[#This Row],[Vehicle No]],Sheet1!$B$13:$B$530,Sheet1!$J$13:$J$530,"-",0)) -> L/hr | J24: =IF(Table44[[#This Row],[rate]]=0,"-",IF(Table44[[#This Row],[Rate Unit]]="L/hr",IF(Table44[[#This Row],[Fuel]]=0,"-",Table44[[#This Row],[Fuel]]/Table44[[#This Row],[rate]]),IF(Table44[[#This Row],[Fuel]]=0,"-",Table44[[#This Row],[Fuel]]*Table44[[#This Row],[rate]]))) -> 63.846154 | K24: =Table44[[#This Row],[Fuel]]/Table44[[#This Row],[actual days/machine hours]] -> 9.453303 | L24: =IF(COUNTIF(Sheet1!$C$13:$C$530,Table44[[#This Row],[Vehicle No]])>0,_xlfn.XLOOKUP(Table44[[#This Row],[Vehicle No]],Sheet1!$C$13:$C$530,Sheet1!$O$13:$O$530,"",0),_xlfn.XLOOKUP(Table44[[#This Row],[Vehicle No]],Sheet1!$B$13:$B$530,Sheet1!$O$13:$O$530,"",0)) -> 6214 | M24: =Table44[[#This Row],[RATE HOUR /DAY]]*Table44[[#This Row],[actual days/machine hours]] -> 545589.2 | N24: =Table44[[#This Row],[RATE HOUR /DAY]]*Table44[[#This Row],[Days/machine hours consider for costing]] -> 545589.2 | O24: E & C
A25: 20 | B25: MG-12 | C25: Motor Grader | D25: 16.5 | E25: 16.5 | G25: 200 | H25: =IF(COUNTIF(Sheet1!$C$13:$C$530,Table44[[#This Row],[Vehicle No]])>0,_xlfn.XLOOKUP(Table44[[#This Row],[Vehicle No]],Sheet1!$C$13:$C$530,Sheet1!$K$13:$K$530,"",0),_xlfn.XLOOKUP(Table44[[#This Row],[Vehicle No]],Sheet1!$B$13:$B$530,Sheet1!$K$13:$K$530,"",0)) -> 13 | I25: =IF(COUNTIF(Sheet1!$C$13:$C$530,Table44[[#This Row],[Vehicle No]])>0,_xlfn.XLOOKUP(Table44[[#This Row],[Vehicle No]],Sheet1!$C$13:$C$530,Sheet1!$J$13:$J$530,"-",0),_xlfn.XLOOKUP(Table44[[#This Row],[Vehicle No]],Sheet1!$B$13:$B$530,Sheet1!$J$13:$J$530,"-",0)) -> L/hr | J25: =IF(Table44[[#This Row],[rate]]=0,"-",IF(Table44[[#This Row],[Rate Unit]]="L/hr",IF(Table44[[#This Row],[Fuel]]=0,"-",Table44[[#This Row],[Fuel]]/Table44[[#This Row],[rate]]),IF(Table44[[#This Row],[Fuel]]=0,"-",Table44[[#This Row],[Fuel]]*Table44[[#This Row],[rate]]))) -> 15.384615 | K25: =Table44[[#This Row],[Fuel]]/Table44[[#This Row],[actual days/machine hours]] -> 12.121212 | L25: =IF(COUNTIF(Sheet1!$C$13:$C$530,Table44[[#This Row],[Vehicle No]])>0,_xlfn.XLOOKUP(Table44[[#This Row],[Vehicle No]],Sheet1!$C$13:$C$530,Sheet1!$O$13:$O$530,"",0),_xlfn.XLOOKUP(Table44[[#This Row],[Vehicle No]],Sheet1!$B$13:$B$530,Sheet1!$O$13:$O$530,"",0)) -> 6431.49 | M25: =Table44[[#This Row],[RATE HOUR /DAY]]*Table44[[#This Row],[actual days/machine hours]] -> 106119.58 | N25: =Table44[[#This Row],[RATE HOUR /DAY]]*Table44[[#This Row],[Days/machine hours consider for costing]] -> 106119.58
A26: 21 | B26: ZA-8395 | C26: Crane | H26: =IF(COUNTIF(Sheet1!$C$13:$C$530,Table44[[#This Row],[Vehicle No]])>0,_xlfn.XLOOKUP(Table44[[#This Row],[Vehicle No]],Sheet1!$C$13:$C$530,Sheet1!$K$13:$K$530,"",0),_xlfn.XLOOKUP(Table44[[#This Row],[Vehicle No]],Sheet1!$B$13:$B$530,Sheet1!$K$13:$K$530,"",0)) -> 10.8 | I26: =IF(COUNTIF(Sheet1!$C$13:$C$530,Table44[[#This Row],[Vehicle No]])>0,_xlfn.XLOOKUP(Table44[[#This Row],[Vehicle No]],Sheet1!$C$13:$C$530,Sheet1!$J$13:$J$530,"-",0),_xlfn.XLOOKUP(Table44[[#This Row],[Vehicle No]],Sheet1!$B$13:$B$530,Sheet1!$J$13:$J$530,"-",0)) -> L/hr | J26: =IF(Table44[[#This Row],[rate]]=0,"-",IF(Table44[[#This Row],[Rate Unit]]="L/hr",IF(Table44[[#This Row],[Fuel]]=0,"-",Table44[[#This Row],[Fuel]]/Table44[[#This Row],[rate]]),IF(Table44[[#This Row],[Fuel]]=0,"-",Table44[[#This Row],[Fuel]]*Table44[[#This Row],[rate]]))) -> - | K26: =Table44[[#This Row],[Fuel]]/Table44[[#This Row],[actual days/machine hours]] -> #DIV/0! | L26: =IF(COUNTIF(Sheet1!$C$13:$C$530,Table44[[#This Row],[Vehicle No]])>0,_xlfn.XLOOKUP(Table44[[#This Row],[Vehicle No]],Sheet1!$C$13:$C$530,Sheet1!$O$13:$O$530,"",0),_xlfn.XLOOKUP(Table44[[#This Row],[Vehicle No]],Sheet1!$B$13:$B$530,Sheet1!$O$13:$O$530,"",0)) -> 6065.82 | M26: =Table44[[#This Row],[RATE HOUR /DAY]]*Table44[[#This Row],[actual days/machine hours]] -> 0 | N26: =Table44[[#This Row],[RATE HOUR /DAY]]*Table44[[#This Row],[Days/machine hours consider for costing]] -> 0 | O26: E & C
A27: 22 | B27: ZA-8373 | C27: Pump Car | H27: =IF(COUNTIF(Sheet1!$C$13:$C$530,Table44[[#This Row],[Vehicle No]])>0,_xlfn.XLOOKUP(Table44[[#This Row],[Vehicle No]],Sheet1!$C$13:$C$530,Sheet1!$K$13:$K$530,"",0),_xlfn.XLOOKUP(Table44[[#This Row],[Vehicle No]],Sheet1!$B$13:$B$530,Sheet1!$K$13:$K$530,"",0)) -> 13 | I27: =IF(COUNTIF(Sheet1!$C$13:$C$530,Table44[[#This Row],[Vehicle No]])>0,_xlfn.XLOOKUP(Table44[[#This Row],[Vehicle No]],Sheet1!$C$13:$C$530,Sheet1!$J$13:$J$530,"-",0),_xlfn.XLOOKUP(Table44[[#This Row],[Vehicle No]],Sheet1!$B$13:$B$530,Sheet1!$J$13:$J$530,"-",0)) -> L/hr | J27: =IF(Table44[[#This Row],[rate]]=0,"-",IF(Table44[[#This Row],[Rate Unit]]="L/hr",IF(Table44[[#This Row],[Fuel]]=0,"-",Table44[[#This Row],[Fuel]]/Table44[[#This Row],[rate]]),IF(Table44[[#This Row],[Fuel]]=0,"-",Table44[[#This Row],[Fuel]]*Table44[[#This Row],[rate]]))) -> - | K27: =Table44[[#This Row],[Fuel]]/Table44[[#This Row],[actual days/machine hours]] -> #DIV/0! | L27: =IF(COUNTIF(Sheet1!$C$13:$C$530,Table44[[#This Row],[Vehicle No]])>0,_xlfn.XLOOKUP(Table44[[#This Row],[Vehicle No]],Sheet1!$C$13:$C$530,Sheet1!$O$13:$O$530,"",0),_xlfn.XLOOKUP(Table44[[#This Row],[Vehicle No]],Sheet1!$B$13:$B$530,Sheet1!$O$13:$O$530,"",0)) -> 6996.964 | O27: E & C
A28: 23 | B28: SR-19 | C28: 10 ton roller | D28: 61.9 | E28: 61.9 | G28: 630 | H28: =IF(COUNTIF(Sheet1!$C$13:$C$530,Table44[[#This Row],[Vehicle No]])>0,_xlfn.XLOOKUP(Table44[[#This Row],[Vehicle No]],Sheet1!$C$13:$C$530,Sheet1!$K$13:$K$530,"",0),_xlfn.XLOOKUP(Table44[[#This Row],[Vehicle No]],Sheet1!$B$13:$B$530,Sheet1!$K$13:$K$530,"",0)) -> 4.3 | I28: =IF(COUNTIF(Sheet1!$C$13:$C$530,Table44[[#This Row],[Vehicle No]])>0,_xlfn.XLOOKUP(Table44[[#This Row],[Vehicle No]],Sheet1!$C$13:$C$530,Sheet1!$J$13:$J$530,"-",0),_xlfn.XLOOKUP(Table44[[#This Row],[Vehicle No]],Sheet1!$B$13:$B$530,Sheet1!$J$13:$J$530,"-",0)) -> L/hr | J28: =IF(Table44[[#This Row],[rate]]=0,"-",IF(Table44[[#This Row],[Rate Unit]]="L/hr",IF(Table44[[#This Row],[Fuel]]=0,"-",Table44[[#This Row],[Fuel]]/Table44[[#This Row],[rate]]),IF(Table44[[#This Row],[Fuel]]=0,"-",Table44[[#This Row],[Fuel]]*Table44[[#This Row],[rate]]))) -> 146.51163 | K28: =Table44[[#This Row],[Fuel]]/Table44[[#This Row],[actual days/machine hours]] -> 10.177706 | L28: =IF(COUNTIF(Sheet1!$C$13:$C$530,Table44[[#This Row],[Vehicle No]])>0,_xlfn.XLOOKUP(Table44[[#This Row],[Vehicle No]],Sheet1!$C$13:$C$530,Sheet1!$O$13:$O$530,"",0),_xlfn.XLOOKUP(Table44[[#This Row],[Vehicle No]],Sheet1!$B$13:$B$530,Sheet1!$O$13:$O$530,"",0)) -> 2127.339 | M28: =Table44[[#This Row],[RATE HOUR /DAY]]*Table44[[#This Row],[actual days/machine hours]] -> 131682.28 | N28: =Table44[[#This Row],[RATE HOUR /DAY]]*Table44[[#This Row],[Days/machine hours consider for costing]] -> 131682.28
A29: 24 | B29: VR-65 | C29: 4 ton roller | D29: 79 | E29: 79 | G29: 425 | H29: =IF(COUNTIF(Sheet1!$C$13:$C$530,Table44[[#This Row],[Vehicle No]])>0,_xlfn.XLOOKUP(Table44[[#This Row],[Vehicle No]],Sheet1!$C$13:$C$530,Sheet1!$K$13:$K$530,"",0),_xlfn.XLOOKUP(Table44[[#This Row],[Vehicle No]],Sheet1!$B$13:$B$530,Sheet1!$K$13:$K$530,"",0)) -> 7.2 | I29: =IF(COUNTIF(Sheet1!$C$13:$C$530,Table44[[#This Row],[Vehicle No]])>0,_xlfn.XLOOKUP(Table44[[#This Row],[Vehicle No]],Sheet1!$C$13:$C$530,Sheet1!$J$13:$J$530,"-",0),_xlfn.XLOOKUP(Table44[[#This Row],[Vehicle No]],Sheet1!$B$13:$B$530,Sheet1!$J$13:$J$530,"-",0)) -> L/hr | J29: =IF(Table44[[#This Row],[rate]]=0,"-",IF(Table44[[#This Row],[Rate Unit]]="L/hr",IF(Table44[[#This Row],[Fuel]]=0,"-",Table44[[#This Row],[Fuel]]/Table44[[#This Row],[rate]]),IF(Table44[[#This Row],[Fuel]]=0,"-",Table44[[#This Row],[Fuel]]*Table44[[#This Row],[rate]]))) -> 59.027778 | K29: =Table44[[#This Row],[Fuel]]/Table44[[#This Row],[actual days/machine hours]] -> 5.3797468 | L29: =IF(COUNTIF(Sheet1!$C$13:$C$530,Table44[[#This Row],[Vehicle No]])>0,_xlfn.XLOOKUP(Table44[[#This Row],[Vehicle No]],Sheet1!$C$13:$C$530,Sheet1!$O$13:$O$530,"",0),_xlfn.XLOOKUP(Table44[[#This Row],[Vehicle No]],Sheet1!$B$13:$B$530,Sheet1!$O$13:$O$530,"",0)) -> 3441.6 | M29: =Table44[[#This Row],[RATE HOUR /DAY]]*Table44[[#This Row],[actual days/machine hours]] -> 271886.4 | N29: =Table44[[#This Row],[RATE HOUR /DAY]]*Table44[[#This Row],[Days/machine hours consider for costing]] -> 271886.4 | O29: E & C
A30: 25 | B30: ZA-6069 | C30: JCB | D30: 131.9 | E30: 131.9 | G30: 640 | H30: =IF(COUNTIF(Sheet1!$C$13:$C$530,Table44[[#This Row],[Vehicle No]])>0,_xlfn.XLOOKUP(Table44[[#This Row],[Vehicle No]],Sheet1!$C$13:$C$530,Sheet1!$K$13:$K$530,"",0),_xlfn.XLOOKUP(Table44[[#This Row],[Vehicle No]],Sheet1!$B$13:$B$530,Sheet1!$K$13:$K$530,"",0)) -> 5 | I30: =IF(COUNTIF(Sheet1!$C$13:$C$530,Table44[[#This Row],[Vehicle No]])>0,_xlfn.XLOOKUP(Table44[[#This Row],[Vehicle No]],Sheet1!$C$13:$C$530,Sheet1!$J$13:$J$530,"-",0),_xlfn.XLOOKUP(Table44[[#This Row],[Vehicle No]],Sheet1!$B$13:$B$530,Sheet1!$J$13:$J$530,"-",0)) -> L/hr | J30: =IF(Table44[[#This Row],[rate]]=0,"-",IF(Table44[[#This Row],[Rate Unit]]="L/hr",IF(Table44[[#This Row],[Fuel]]=0,"-",Table44[[#This Row],[Fuel]]/Table44[[#This Row],[rate]]),IF(Table44[[#This Row],[Fuel]]=0,"-",Table44[[#This Row],[Fuel]]*Table44[[#This Row],[rate]]))) -> 128 | K30: =Table44[[#This Row],[Fuel]]/Table44[[#This Row],[actual days/machine hours]] -> 4.8521607 | L30: =IF(COUNTIF(Sheet1!$C$13:$C$530,Table44[[#This Row],[Vehicle No]])>0,_xlfn.XLOOKUP(Table44[[#This Row],[Vehicle No]],Sheet1!$C$13:$C$530,Sheet1!$O$13:$O$530,"",0),_xlfn.XLOOKUP(Table44[[#This Row],[Vehicle No]],Sheet1!$B$13:$B$530,Sheet1!$O$13:$O$530,"",0)) -> 2574.03 | M30: =Table44[[#This Row],[RATE HOUR /DAY]]*Table44[[#This Row],[actual days/machine hours]] -> 339514.56 | N30: =Table44[[#This Row],[RATE HOUR /DAY]]*Table44[[#This Row],[Days/machine hours consider for costing]] -> 339514.56 | O30: E & C
A31: 26 | B31: ZB-1546 | C31: JCB | H31: =IF(COUNTIF(Sheet1!$C$13:$C$530,Table44[[#This Row],[Vehicle No]])>0,_xlfn.XLOOKUP(Table44[[#This Row],[Vehicle No]],Sheet1!$C$13:$C$530,Sheet1!$K$13:$K$530,"",0),_xlfn.XLOOKUP(Table44[[#This Row],[Vehicle No]],Sheet1!$B$13:$B$530,Sheet1!$K$13:$K$530,"",0)) -> 5 | I31: =IF(COUNTIF(Sheet1!$C$13:$C$530,Table44[[#This Row],[Vehicle No]])>0,_xlfn.XLOOKUP(Table44[[#This Row],[Vehicle No]],Sheet1!$C$13:$C$530,Sheet1!$J$13:$J$530,"-",0),_xlfn.XLOOKUP(Table44[[#This Row],[Vehicle No]],Sheet1!$B$13:$B$530,Sheet1!$J$13:$J$530,"-",0)) -> L/hr | J31: =IF(Table44[[#This Row],[rate]]=0,"-",IF(Table44[[#This Row],[Rate Unit]]="L/hr",IF(Table44[[#This Row],[Fuel]]=0,"-",Table44[[#This Row],[Fuel]]/Table44[[#This Row],[rate]]),IF(Table44[[#This Row],[Fuel]]=0,"-",Table44[[#This Row],[Fuel]]*Table44[[#This Row],[rate]]))) -> - | K31: =Table44[[#This Row],[Fuel]]/Table44[[#This Row],[actual days/machine hours]] -> #DIV/0! | L31: =IF(COUNTIF(Sheet1!$C$13:$C$530,Table44[[#This Row],[Vehicle No]])>0,_xlfn.XLOOKUP(Table44[[#This Row],[Vehicle No]],Sheet1!$C$13:$C$530,Sheet1!$O$13:$O$530,"",0),_xlfn.XLOOKUP(Table44[[#This Row],[Vehicle No]],Sheet1!$B$13:$B$530,Sheet1!$O$13:$O$530,"",0)) -> 2490.38 | M31: =Table44[[#This Row],[RATE HOUR /DAY]]*Table44[[#This Row],[actual days/machine hours]] -> 0 | N31: =Table44[[#This Row],[RATE HOUR /DAY]]*Table44[[#This Row],[Days/machine hours consider for costing]] -> 0 | O31: E & C
A32: 27 | B32: SL-14 | C32: Skid Loader | D32: 108.5 | E32: 108.5 | G32: 495 | H32: =IF(COUNTIF(Sheet1!$C$13:$C$530,Table44[[#This Row],[Vehicle No]])>0,_xlfn.XLOOKUP(Table44[[#This Row],[Vehicle No]],Sheet1!$C$13:$C$530,Sheet1!$K$13:$K$530,"",0),_xlfn.XLOOKUP(Table44[[#This Row],[Vehicle No]],Sheet1!$B$13:$B$530,Sheet1!$K$13:$K$530,"",0)) -> 3.2 | I32: =IF(COUNTIF(Sheet1!$C$13:$C$530,Table44[[#This Row],[Vehicle No]])>0,_xlfn.XLOOKUP(Table44[[#This Row],[Vehicle No]],Sheet1!$C$13:$C$530,Sheet1!$J$13:$J$530,"-",0),_xlfn.XLOOKUP(Table44[[#This Row],[Vehicle No]],Sheet1!$B$13:$B$530,Sheet1!$J$13:$J$530,"-",0)) -> L/hr | J32: =IF(Table44[[#This Row],[rate]]=0,"-",IF(Table44[[#This Row],[Rate Unit]]="L/hr",IF(Table44[[#This Row],[Fuel]]=0,"-",Table44[[#This Row],[Fuel]]/Table44[[#This Row],[rate]]),IF(Table44[[#This Row],[Fuel]]=0,"-",Table44[[#This Row],[Fuel]]*Table44[[#This Row],[rate]]))) -> 154.6875 | K32: =Table44[[#This Row],[Fuel]]/Table44[[#This Row],[actual days/machine hours]] -> 4.562212 | L32: =IF(COUNTIF(Sheet1!$C$13:$C$530,Table44[[#This Row],[Vehicle No]])>0,_xlfn.XLOOKUP(Table44[[#This Row],[Vehicle No]],Sheet1!$C$13:$C$530,Sheet1!$O$13:$O$530,"",0),_xlfn.XLOOKUP(Table44[[#This Row],[Vehicle No]],Sheet1!$B$13:$B$530,Sheet1!$O$13:$O$530,"",0)) -> 1636.672 | M32: =Table44[[#This Row],[RATE HOUR /DAY]]*Table44[[#This Row],[actual days/machine hours]] -> 177578.91 | N32: =Table44[[#This Row],[RATE HOUR /DAY]]*Table44[[#This Row],[Days/machine hours consider for costing]] -> 177578.91 | O32: E & C
M34: =SUM(M4:M33) -> 2981309 | N34: =SUM(N4:N33) -> 2981309

Sheet Plant expenses
B1: Vehicle Running Summary -January
A3: No | B3: Vehicle No | C3: Type | D3: actual days/machine hours | E3: Days/machine hours consider for costing | F3: Cons Econ | G3: Fuel Rate Unit | H3: Distance | I3: Fuel | J3: Actual Work Done | K3: RATE HOUR /DAY | L3: Actual amount | M3: Amount (idling included) | N3: Owner | O3: Remarks
A4: 1 | B4: ZA-7290 | C4: Truck Mixer | F4: =IF(COUNTIF(Sheet1!$C$13:$C$530,Table443[[#This Row],[Vehicle No]])>0,_xlfn.XLOOKUP(Table443[[#This Row],[Vehicle No]],Sheet1!$C$13:$C$530,Sheet1!$K$13:$K$530,"-",0),_xlfn.XLOOKUP(Table443[[#This Row],[Vehicle No]],Sheet1!$B$13:$B$530,Sheet1!$K$13:$K$530,"-",0)) -> 7.9 | G4: =IF(COUNTIF(Sheet1!$C$13:$C$530,Table443[[#This Row],[Vehicle No]])>0,_xlfn.XLOOKUP(Table443[[#This Row],[Vehicle No]],Sheet1!$C$13:$C$530,Sheet1!$J$13:$J$530,"-",0),_xlfn.XLOOKUP(Table443[[#This Row],[Vehicle No]],Sheet1!$B$13:$B$530,Sheet1!$J$13:$J$530,"-",0)) -> L/hr | J4: =IF(Table443[[#This Row],[Cons Econ]]="-","-",IF(Table443[[#This Row],[Fuel Rate Unit]]="KM/L",IF(Table443[[#This Row],[Fuel]]=0,"-",Table443[[#This Row],[Fuel]]*Table443[[#This Row],[Cons Econ]]),IF(Table443[[#This Row],[Fuel]]=0,"-",Table443[[#This Row],[Fuel]]/Table443[[#This Row],[Cons Econ]]))) -> - | K4: =IF(COUNTIF(Sheet1!$C$13:$C$530,Table443[[#This Row],[Vehicle No]])>0,_xlfn.XLOOKUP(Table443[[#This Row],[Vehicle No]],Sheet1!$C$13:$C$530,Sheet1!$O$13:$O$530,"",0),_xlfn.XLOOKUP(Table443[[#This Row],[Vehicle No]],Sheet1!$B$13:$B$530,Sheet1!$O$13:$O$530,"",0)) -> 4040.534 | L4: =Table443[[#This Row],[RATE HOUR /DAY]]*Table443[[#This Row],[actual days/machine hours]] -> 0 | M4: =Table443[[#This Row],[RATE HOUR /DAY]]*Table443[[#This Row],[Days/machine hours consider for costing]] -> 0 | N4: E & C
A5: 2 | B5: ZA-7291 | C5: Truck Mixer | F5: =IF(COUNTIF(Sheet1!$C$13:$C$530,Table443[[#This Row],[Vehicle No]])>0,_xlfn.XLOOKUP(Table443[[#This Row],[Vehicle No]],Sheet1!$C$13:$C$530,Sheet1!$K$13:$K$530,"-",0),_xlfn.XLOOKUP(Table443[[#This Row],[Vehicle No]],Sheet1!$B$13:$B$530,Sheet1!$K$13:$K$530,"-",0)) -> 7.9 | G5: =IF(COUNTIF(Sheet1!$C$13:$C$530,Table443[[#This Row],[Vehicle No]])>0,_xlfn.XLOOKUP(Table443[[#This Row],[Vehicle No]],Sheet1!$C$13:$C$530,Sheet1!$J$13:$J$530,"-",0),_xlfn.XLOOKUP(Table443[[#This Row],[Vehicle No]],Sheet1!$B$13:$B$530,Sheet1!$J$13:$J$530,"-",0)) -> L/hr | J5: =IF(Table443[[#This Row],[Cons Econ]]="-","-",IF(Table443[[#This Row],[Fuel Rate Unit]]="KM/L",IF(Table443[[#This Row],[Fuel]]=0,"-",Table443[[#This Row],[Fuel]]*Table443[[#This Row],[Cons Econ]]),IF(Table443[[#This Row],[Fuel]]=0,"-",Table443[[#This Row],[Fuel]]/Table443[[#This Row],[Cons Econ]]))) -> - | K5: =IF(COUNTIF(Sheet1!$C$13:$C$530,Table443[[#This Row],[Vehicle No]])>0,_xlfn.XLOOKUP(Table443[[#This Row],[Vehicle No]],Sheet1!$C$13:$C$530,Sheet1!$O$13:$O$530,"",0),_xlfn.XLOOKUP(Table443[[#This Row],[Vehicle No]],Sheet1!$B$13:$B$530,Sheet1!$O$13:$O$530,"",0)) -> 4040.534 | L5: =Table443[[#This Row],[RATE HOUR /DAY]]*Table443[[#This Row],[actual days/machine hours]] -> 0 | M5: =Table443[[#This Row],[RATE HOUR /DAY]]*Table443[[#This Row],[Days/machine hours consider for costing]] -> 0
A6: 3 | B6: ZA-8511 | C6: Truck Mixer | D6: 16 | E6: 16 | F6: =IF(COUNTIF(Sheet1!$C$13:$C$530,Table443[[#This Row],[Vehicle No]])>0,_xlfn.XLOOKUP(Table443[[#This Row],[Vehicle No]],Sheet1!$C$13:$C$530,Sheet1!$K$13:$K$530,"-",0),_xlfn.XLOOKUP(Table443[[#This Row],[Vehicle No]],Sheet1!$B$13:$B$530,Sheet1!$K$13:$K$530,"-",0)) -> 7.9 | G6: =IF(COUNTIF(Sheet1!$C$13:$C$530,Table443[[#This Row],[Vehicle No]])>0,_xlfn.XLOOKUP(Table443[[#This Row],[Vehicle No]],Sheet1!$C$13:$C$530,Sheet1!$J$13:$J$530,"-",0),_xlfn.XLOOKUP(Table443[[#This Row],[Vehicle No]],Sheet1!$B$13:$B$530,Sheet1!$J$13:$J$530,"-",0)) -> L/hr | I6: 555 | J6: =IF(Table443[[#This Row],[Cons Econ]]="-","-",IF(Table443[[#This Row],[Fuel Rate Unit]]="KM/L",IF(Table443[[#This Row],[Fuel]]=0,"-",Table443[[#This Row],[Fuel]]*Table443[[#This Row],[Cons Econ]]),IF(Table443[[#This Row],[Fuel]]=0,"-",Table443[[#This Row],[Fuel]]/Table443[[#This Row],[Cons Econ]]))) -> 70.253165 | K6: =IF(COUNTIF(Sheet1!$C$13:$C$530,Table443[[#This Row],[Vehicle No]])>0,_xlfn.XLOOKUP(Table443[[#This Row],[Vehicle No]],Sheet1!$C$13:$C$530,Sheet1!$O$13:$O$530,"",0),_xlfn.XLOOKUP(Table443[[#This Row],[Vehicle No]],Sheet1!$B$13:$B$530,Sheet1!$O$13:$O$530,"",0)) -> 4014.1006 | L6: =Table443[[#This Row],[RATE HOUR /DAY]]*Table443[[#This Row],[actual days/machine hours]] -> 64225.61 | M6: =Table443[[#This Row],[RATE HOUR /DAY]]*Table443[[#This Row],[Days/machine hours consider for costing]] -> 64225.61
A7: 4 | B7: ZA-7810 | C7: Truck Mixer | F7: =IF(COUNTIF(Sheet1!$C$13:$C$530,Table443[[#This Row],[Vehicle No]])>0,_xlfn.XLOOKUP(Table443[[#This Row],[Vehicle No]],Sheet1!$C$13:$C$530,Sheet1!$K$13:$K$530,"-",0),_xlfn.XLOOKUP(Table443[[#This Row],[Vehicle No]],Sheet1!$B$13:$B$530,Sheet1!$K$13:$K$530,"-",0)) -> 9.4 | G7: =IF(COUNTIF(Sheet1!$C$13:$C$530,Table443[[#This Row],[Vehicle No]])>0,_xlfn.XLOOKUP(Table443[[#This Row],[Vehicle No]],Sheet1!$C$13:$C$530,Sheet1!$J$13:$J$530,"-",0),_xlfn.XLOOKUP(Table443[[#This Row],[Vehicle No]],Sheet1!$B$13:$B$530,Sheet1!$J$13:$J$530,"-",0)) -> L/hr | J7: =IF(Table443[[#This Row],[Cons Econ]]="-","-",IF(Table443[[#This Row],[Fuel Rate Unit]]="KM/L",IF(Table443[[#This Row],[Fuel]]=0,"-",Table443[[#This Row],[Fuel]]*Table443[[#This Row],[Cons Econ]]),IF(Table443[[#This Row],[Fuel]]=0,"-",Table443[[#This Row],[Fuel]]/Table443[[#This Row],[Cons Econ]]))) -> - | K7: =IF(COUNTIF(Sheet1!$C$13:$C$530,Table443[[#This Row],[Vehicle No]])>0,_xlfn.XLOOKUP(Table443[[#This Row],[Vehicle No]],Sheet1!$C$13:$C$530,Sheet1!$O$13:$O$530,"",0),_xlfn.XLOOKUP(Table443[[#This Row],[Vehicle No]],Sheet1!$B$13:$B$530,Sheet1!$O$13:$O$530,"",0)) -> 4807.724 | L7: =Table443[[#This Row],[RATE HOUR /DAY]]*Table443[[#This Row],[actual days/machine hours]] -> 0 | M7: =Table443[[#This Row],[RATE HOUR /DAY]]*Table443[[#This Row],[Days/machine hours consider for costing]] -> 0 | N7: E & C
A8: 5 | B8: LD-09 | C8: Loader | D8: 190 | E8: 190 | F8: =IF(COUNTIF(Sheet1!$C$13:$C$530,Table443[[#This Row],[Vehicle No]])>0,_xlfn.XLOOKUP(Table443[[#This Row],[Vehicle No]],Sheet1!$C$13:$C$530,Sheet1!$K$13:$K$530,"-",0),_xlfn.XLOOKUP(Table443[[#This Row],[Vehicle No]],Sheet1!$B$13:$B$530,Sheet1!$K$13:$K$530,"-",0)) -> 10.8 | G8: =IF(COUNTIF(Sheet1!$C$13:$C$530,Table443[[#This Row],[Vehicle No]])>0,_xlfn.XLOOKUP(Table443[[#This Row],[Vehicle No]],Sheet1!$C$13:$C$530,Sheet1!$J$13:$J$530,"-",0),_xlfn.XLOOKUP(Table443[[#This Row],[Vehicle No]],Sheet1!$B$13:$B$530,Sheet1!$J$13:$J$530,"-",0)) -> L/hr | I8: 1719 | J8: =IF(Table443[[#This Row],[Cons Econ]]="-","-",IF(Table443[[#This Row],[Fuel Rate Unit]]="KM/L",IF(Table443[[#This Row],[Fuel]]=0,"-",Table443[[#This Row],[Fuel]]*Table443[[#This Row],[Cons Econ]]),IF(Table443[[#This Row],[Fuel]]=0,"-",Table443[[#This Row],[Fuel]]/Table443[[#This Row],[Cons Econ]]))) -> 159.16667 | K8: =IF(COUNTIF(Sheet1!$C$13:$C$530,Table443[[#This Row],[Vehicle No]])>0,_xlfn.XLOOKUP(Table443[[#This Row],[Vehicle No]],Sheet1!$C$13:$C$530,Sheet1!$O$13:$O$530,"",0),_xlfn.XLOOKUP(Table443[[#This Row],[Vehicle No]],Sheet1!$B$13:$B$530,Sheet1!$O$13:$O$530,"",0)) -> 5379.2208 | L8: =Table443[[#This Row],[RATE HOUR /DAY]]*Table443[[#This Row],[actual days/machine hours]] -> 1022052 | M8: =Table443[[#This Row],[RATE HOUR /DAY]]*Table443[[#This Row],[Days/machine hours consider for costing]] -> 1022052 | N8: E & C | O8: Meter broken
A9: 6 | B9: ZA-8373 | C9: Truck Mixer | F9: =IF(COUNTIF(Sheet1!$C$13:$C$530,Table443[[#This Row],[Vehicle No]])>0,_xlfn.XLOOKUP(Table443[[#This Row],[Vehicle No]],Sheet1!$C$13:$C$530,Sheet1!$K$13:$K$530,"-",0),_xlfn.XLOOKUP(Table443[[#This Row],[Vehicle No]],Sheet1!$B$13:$B$530,Sheet1!$K$13:$K$530,"-",0)) -> 13 | G9: =IF(COUNTIF(Sheet1!$C$13:$C$530,Table443[[#This Row],[Vehicle No]])>0,_xlfn.XLOOKUP(Table443[[#This Row],[Vehicle No]],Sheet1!$C$13:$C$530,Sheet1!$J$13:$J$530,"-",0),_xlfn.XLOOKUP(Table443[[#This Row],[Vehicle No]],Sheet1!$B$13:$B$530,Sheet1!$J$13:$J$530,"-",0)) -> L/hr | J9: =IF(Table443[[#This Row],[Cons Econ]]="-","-",IF(Table443[[#This Row],[Fuel Rate Unit]]="KM/L",IF(Table443[[#This Row],[Fuel]]=0,"-",Table443[[#This Row],[Fuel]]*Table443[[#This Row],[Cons Econ]]),IF(Table443[[#This Row],[Fuel]]=0,"-",Table443[[#This Row],[Fuel]]/Table443[[#This Row],[Cons Econ]]))) -> - | K9: =IF(COUNTIF(Sheet1!$C$13:$C$530,Table443[[#This Row],[Vehicle No]])>0,_xlfn.XLOOKUP(Table443[[#This Row],[Vehicle No]],Sheet1!$C$13:$C$530,Sheet1!$O$13:$O$530,"",0),_xlfn.XLOOKUP(Table443[[#This Row],[Vehicle No]],Sheet1!$B$13:$B$530,Sheet1!$O$13:$O$530,"",0)) -> 6996.964 | L9: =Table443[[#This Row],[RATE HOUR /DAY]]*Table443[[#This Row],[actual days/machine hours]] -> 0 | M9: =Table443[[#This Row],[RATE HOUR /DAY]]*Table443[[#This Row],[Days/machine hours consider for costing]] -> 0 | N9: E & C
A10: 7 | B10: ZB-1496 | C10: Truck Mixer | D10: 21 | E10: 21 | F10: =IF(COUNTIF(Sheet1!$C$13:$C$530,Table443[[#This Row],[Vehicle No]])>0,_xlfn.XLOOKUP(Table443[[#This Row],[Vehicle No]],Sheet1!$C$13:$C$530,Sheet1!$K$13:$K$530,"-",0),_xlfn.XLOOKUP(Table443[[#This Row],[Vehicle No]],Sheet1!$B$13:$B$530,Sheet1!$K$13:$K$530,"-",0)) -> 13 | G10: =IF(COUNTIF(Sheet1!$C$13:$C$530,Table443[[#This Row],[Vehicle No]])>0,_xlfn.XLOOKUP(Table443[[#This Row],[Vehicle No]],Sheet1!$C$13:$C$530,Sheet1!$J$13:$J$530,"-",0),_xlfn.XLOOKUP(Table443[[#This Row],[Vehicle No]],Sheet1!$B$13:$B$530,Sheet1!$J$13:$J$530,"-",0)) -> L/hr | I10: 1290 | J10: =IF(Table443[[#This Row],[Cons Econ]]="-","-",IF(Table443[[#This Row],[Fuel Rate Unit]]="KM/L",IF(Table443[[#This Row],[Fuel]]=0,"-",Table443[[#This Row],[Fuel]]*Table443[[#This Row],[Cons Econ]]),IF(Table443[[#This Row],[Fuel]]=0,"-",Table443[[#This Row],[Fuel]]/Table443[[#This Row],[Cons Econ]]))) -> 99.230769 | K10: =IF(COUNTIF(Sheet1!$C$13:$C$530,Table443[[#This Row],[Vehicle No]])>0,_xlfn.XLOOKUP(Table443[[#This Row],[Vehicle No]],Sheet1!$C$13:$C$530,Sheet1!$O$13:$O$530,"",0),_xlfn.XLOOKUP(Table443[[#This Row],[Vehicle No]],Sheet1!$B$13:$B$530,Sheet1!$O$13:$O$530,"",0)) -> 6518.486 | L10: =Table443[[#This Row],[RATE HOUR /DAY]]*Table443[[#This Row],[actual days/machine hours]] -> 136888.21 | M10: =Table443[[#This Row],[RATE HOUR /DAY]]*Table443[[#This Row],[Days/machine hours consider for costing]] -> 136888.21 | N10: E & C
A11: 8 | B11: HEX-19 | C11: Komatsu 120 | F11: =IF(COUNTIF(Sheet1!$C$13:$C$530,Table443[[#This Row],[Vehicle No]])>0,_xlfn.XLOOKUP(Table443[[#This Row],[Vehicle No]],Sheet1!$C$13:$C$530,Sheet1!$K$13:$K$530,"-",0),_xlfn.XLOOKUP(Table443[[#This Row],[Vehicle No]],Sheet1!$B$13:$B$530,Sheet1!$K$13:$K$530,"-",0)) -> 7.2 | G11: =IF(COUNTIF(Sheet1!$C$13:$C$530,Table443[[#This Row],[Vehicle No]])>0,_xlfn.XLOOKUP(Table443[[#This Row],[Vehicle No]],Sheet1!$C$13:$C$530,Sheet1!$J$13:$J$530,"-",0),_xlfn.XLOOKUP(Table443[[#This Row],[Vehicle No]],Sheet1!$B$13:$B$530,Sheet1!$J$13:$J$530,"-",0)) -> L/hr | J11: =IF(Table443[[#This Row],[Cons Econ]]="-","-",IF(Table443[[#This Row],[Fuel Rate Unit]]="KM/L",IF(Table443[[#This Row],[Fuel]]=0,"-",Table443[[#This Row],[Fuel]]*Table443[[#This Row],[Cons Econ]]),IF(Table443[[#This Row],[Fuel]]=0,"-",Table443[[#This Row],[Fuel]]/Table443[[#This Row],[Cons Econ]]))) -> - | K11: =IF(COUNTIF(Sheet1!$C$13:$C$530,Table443[[#This Row],[Vehicle No]])>0,_xlfn.XLOOKUP(Table443[[#This Row],[Vehicle No]],Sheet1!$C$13:$C$530,Sheet1!$O$13:$O$530,"",0),_xlfn.XLOOKUP(Table443[[#This Row],[Vehicle No]],Sheet1!$B$13:$B$530,Sheet1!$O$13:$O$530,"",0)) -> 3851.1504 | L11: =Table443[[#This Row],[RATE HOUR /DAY]]*Table443[[#This Row],[actual days/machine hours]] -> 0 | M11: =Table443[[#This Row],[RATE HOUR /DAY]]*Table443[[#This Row],[Days/machine hours consider for costing]] -> 0 | N11: E & C | O11: Crusher Plant
A12: 9 | B12: ZA-0050 | C12: Truck Mixer | D12: 18 | E12: 18 | F12: =IF(COUNTIF(Sheet1!$C$13:$C$530,Table443[[#This Row],[Vehicle No]])>0,_xlfn.XLOOKUP(Table443[[#This Row],[Vehicle No]],Sheet1!$C$13:$C$530,Sheet1!$K$13:$K$530,"-",0),_xlfn.XLOOKUP(Table443[[#This Row],[Vehicle No]],Sheet1!$B$13:$B$530,Sheet1!$K$13:$K$530,"-",0)) -> 9.4 | G12: =IF(COUNTIF(Sheet1!$C$13:$C$530,Table443[[#This Row],[Vehicle No]])>0,_xlfn.XLOOKUP(Table443[[#This Row],[Vehicle No]],Sheet1!$C$13:$C$530,Sheet1!$J$13:$J$530,"-",0),_xlfn.XLOOKUP(Table443[[#This Row],[Vehicle No]],Sheet1!$B$13:$B$530,Sheet1!$J$13:$J$530,"-",0)) -> L/hr | I12: 1095 | J12: =IF(Table443[[#This Row],[Cons Econ]]="-","-",IF(Table443[[#This Row],[Fuel Rate Unit]]="KM/L",IF(Table443[[#This Row],[Fuel]]=0,"-",Table443[[#This Row],[Fuel]]*Table443[[#This Row],[Cons Econ]]),IF(Table443[[#This Row],[Fuel]]=0,"-",Table443[[#This Row],[Fuel]]/Table443[[#This Row],[Cons Econ]]))) -> 116.48936 | K12: =IF(COUNTIF(Sheet1!$C$13:$C$530,Table443[[#This Row],[Vehicle No]])>0,_xlfn.XLOOKUP(Table443[[#This Row],[Vehicle No]],Sheet1!$C$13:$C$530,Sheet1!$O$13:$O$530,0,0),_xlfn.XLOOKUP(Table443[[#This Row],[Vehicle No]],Sheet1!$B$13:$B$530,Sheet1!$O$13:$O$530,0,0)) -> 4776.2716 | L12: =Table443[[#This Row],[RATE HOUR /DAY]]*Table443[[#This Row],[actual days/machine hours]] -> 85972.889 | M12: =Table443[[#This Row],[RATE HOUR /DAY]]*Table443[[#This Row],[Days/machine hours consider for costing]] -> 85972.889 | N12: E & C
L14: =SUM(L4:L13) -> 1309138.7 | M14: =SUM(M4:M13) -> 1309138.7

Sheet Sheet2
A1: Vehicle Running Summary - April 2026 (Package E)
A3: No | B3: Vehicle No | C3: 58 | D3: Actual working days/machine hours | E3: Days/hours consider for costing | F3: 6 | G3: Fuel | H3: Actual Consumption Rate | I3: Column2 | J3: Actual Consumption | K3: Consumption | L3: RATE HOUR /DAY | M3: Total Amount with idling | N3: Total amount without idling | O3: Owner | P3: Remarks
A4: 1 | B4: LH-5586 | C4: 5 Cube | D4: 1 | E4: 1 | F4: 26 | G4: 20 | H4: =IFERROR(_xlfn.XLOOKUP(B4,[20]Sheet1!$C:$C,[20]Sheet1!$K:$K,_xlfn.XLOOKUP(B4,[20]Sheet1!$B:$B,[20]Sheet1!$K:$K,"")),"") -> 2.9 | I4: =IFERROR(_xlfn.XLOOKUP(B4,[20]Sheet1!$C:$C,[20]Sheet1!$J:$J,_xlfn.XLOOKUP(B4,[20]Sheet1!$B:$B,[20]Sheet1!$J:$J,"")),"") -> km/L | J4: =IF(OR(H4="",H4=0),"",IF(ISNUMBER(SEARCH("hr",I4)),G4/H4,H4*G4)) -> 58 | K4: =F4/G4 -> 1.3 | L4: 7000 | M4: =Table4434[[#This Row],[RATE HOUR /DAY]]*Table4434[[#This Row],[Days/hours consider for costing]] -> 7000 | N4: =Table4434[[#This Row],[Actual working days/machine hours ]]*Table4434[[#This Row],[RATE HOUR /DAY]] -> 7000 | O4: E & C
A5: 2 | B5: LI-7618 | C5: 3 Cube | D5: 14 | E5: 14 | G5: 60 | H5: =IFERROR(_xlfn.XLOOKUP(B5,[20]Sheet1!$C:$C,[20]Sheet1!$K:$K,_xlfn.XLOOKUP(B5,[20]Sheet1!$B:$B,[20]Sheet1!$K:$K,"")),"") -> 3.8 | I5: =IFERROR(_xlfn.XLOOKUP(B5,[20]Sheet1!$C:$C,[20]Sheet1!$J:$J,_xlfn.XLOOKUP(B5,[20]Sheet1!$B:$B,[20]Sheet1!$J:$J,"")),"") -> km/L | J5: =IF(OR(H5="",H5=0),"",IF(ISNUMBER(SEARCH("hr",I5)),G5/H5,H5*G5)) -> 228 | K5: =F5/G5 -> 0 | L5: 6440 | M5: =Table4434[[#This Row],[RATE HOUR /DAY]]*Table4434[[#This Row],[Days/hours consider for costing]] -> 90160 | N5: =Table4434[[#This Row],[Actual working days/machine hours ]]*Table4434[[#This Row],[RATE HOUR /DAY]] -> 90160 | O5: E & C
A6: 3 | B6: LP-1713 | C6: 3 Cube | D6: 5 | E6: 5 | F6: 126 | G6: 60 | H6: =IFERROR(_xlfn.XLOOKUP(B6,[20]Sheet1!$C:$C,[20]Sheet1!$K:$K,_xlfn.XLOOKUP(B6,[20]Sheet1!$B:$B,[20]Sheet1!$K:$K,"")),"") -> 3.8 | I6: =IFERROR(_xlfn.XLOOKUP(B6,[20]Sheet1!$C:$C,[20]Sheet1!$J:$J,_xlfn.XLOOKUP(B6,[20]Sheet1!$B:$B,[20]Sheet1!$J:$J,"")),"") -> km/L | J6: =IF(OR(H6="",H6=0),"",IF(ISNUMBER(SEARCH("hr",I6)),G6/H6,H6*G6)) -> 228 | L6: 6440 | M6: =Table4434[[#This Row],[RATE HOUR /DAY]]*Table4434[[#This Row],[Days/hours consider for costing]] -> 32200 | N6: =Table4434[[#This Row],[Actual working days/machine hours ]]*Table4434[[#This Row],[RATE HOUR /DAY]] -> 32200
A7: 4 | B7: LM-5723 | C7: 3 Cube | D7: 4 | E7: 4 | F7: 100 | G7: 40 | H7: =IFERROR(_xlfn.XLOOKUP(B7,[20]Sheet1!$C:$C,[20]Sheet1!$K:$K,_xlfn.XLOOKUP(B7,[20]Sheet1!$B:$B,[20]Sheet1!$K:$K,"")),"") -> 3.8 | I7: =IFERROR(_xlfn.XLOOKUP(B7,[20]Sheet1!$C:$C,[20]Sheet1!$J:$J,_xlfn.XLOOKUP(B7,[20]Sheet1!$B:$B,[20]Sheet1!$J:$J,"")),"") -> km/L | J7: =IF(OR(H7="",H7=0),"",IF(ISNUMBER(SEARCH("hr",I7)),G7/H7,H7*G7)) -> 152 | K7: =F7/G7 -> 2.5 | L7: 6440 | M7: =Table4434[[#This Row],[RATE HOUR /DAY]]*Table4434[[#This Row],[Days/hours consider for costing]] -> 25760 | N7: =Table4434[[#This Row],[Actual working days/machine hours ]]*Table4434[[#This Row],[RATE HOUR /DAY]] -> 25760 | O7: E & C
A8: 5 | B8: LM-7951 | C8: 3 Cube | D8: 8 | E8: 8 | F8: 166 | G8: 45 | H8: =IFERROR(_xlfn.XLOOKUP(B8,[20]Sheet1!$C:$C,[20]Sheet1!$K:$K,_xlfn.XLOOKUP(B8,[20]Sheet1!$B:$B,[20]Sheet1!$K:$K,"")),"") -> 3.8 | I8: =IFERROR(_xlfn.XLOOKUP(B8,[20]Sheet1!$C:$C,[20]Sheet1!$J:$J,_xlfn.XLOOKUP(B8,[20]Sheet1!$B:$B,[20]Sheet1!$J:$J,"")),"") -> km/L | J8: =IF(OR(H8="",H8=0),"",IF(ISNUMBER(SEARCH("hr",I8)),G8/H8,H8*G8)) -> 171 | K8: =F8/G8 -> 3.6888889 | L8: 6440 | M8: =Table4434[[#This Row],[RATE HOUR /DAY]]*Table4434[[#This Row],[Days/hours consider for costing]] -> 51520 | N8: =Table4434[[#This Row],[Actual working days/machine hours ]]*Table4434[[#This Row],[RATE HOUR /DAY]] -> 51520 | O8: E & C
A9: 6 | B9: LJ-5203 | C9: 3 Cube | H9: =IFERROR(_xlfn.XLOOKUP(B9,[20]Sheet1!$C:$C,[20]Sheet1!$K:$K,_xlfn.XLOOKUP(B9,[20]Sheet1!$B:$B,[20]Sheet1!$K:$K,"")),"") -> 3.8 | I9: =IFERROR(_xlfn.XLOOKUP(B9,[20]Sheet1!$C:$C,[20]Sheet1!$J:$J,_xlfn.XLOOKUP(B9,[20]Sheet1!$B:$B,[20]Sheet1!$J:$J,"")),"") -> km/L | J9: =IF(OR(H9="",H9=0),"",IF(ISNUMBER(SEARCH("hr",I9)),G9/H9,H9*G9)) -> 0 | K9: =F9/G9 -> #DIV/0! | L9: 6440 | M9: =Table4434[[#This Row],[RATE HOUR /DAY]]*Table4434[[#This Row],[Days/hours consider for costing]] -> 0 | N9: =Table4434[[#This Row],[Actual working days/machine hours ]]*Table4434[[#This Row],[RATE HOUR /DAY]] -> 0 | O9: E & C
A10: 7 | B10: ZA-8033 | C10: Truck Mixer | D10: 3 | E10: 3 | G10: 100 | H10: =IFERROR(_xlfn.XLOOKUP(B10,[20]Sheet1!$C:$C,[20]Sheet1!$K:$K,_xlfn.XLOOKUP(B10,[20]Sheet1!$B:$B,[20]Sheet1!$K:$K,"")),"") -> 9.4 | I10: =IFERROR(_xlfn.XLOOKUP(B10,[20]Sheet1!$C:$C,[20]Sheet1!$J:$J,_xlfn.XLOOKUP(B10,[20]Sheet1!$B:$B,[20]Sheet1!$J:$J,"")),"") -> L/hr | J10: =IF(OR(H10="",H10=0),"",IF(ISNUMBER(SEARCH("hr",I10)),G10/H10,H10*G10)) -> 10.638298 | K10: =F10/G10 -> 0 | L10: 8000 | M10: =Table4434[[#This Row],[RATE HOUR /DAY]]*Table4434[[#This Row],[Days/hours consider for costing]] -> 24000 | N10: =Table4434[[#This Row],[Actual working days/machine hours ]]*Table4434[[#This Row],[RATE HOUR /DAY]] -> 24000 | O10: E & C
A11: 8 | B11: ZA-7810 | C11: Truck Mixer | D11: 2 | E11: 2 | G11: 65 | H11: =IFERROR(_xlfn.XLOOKUP(B11,[20]Sheet1!$C:$C,[20]Sheet1!$K:$K,_xlfn.XLOOKUP(B11,[20]Sheet1!$B:$B,[20]Sheet1!$K:$K,"")),"") -> 9.4 | I11: =IFERROR(_xlfn.XLOOKUP(B11,[20]Sheet1!$C:$C,[20]Sheet1!$J:$J,_xlfn.XLOOKUP(B11,[20]Sheet1!$B:$B,[20]Sheet1!$J:$J,"")),"") -> L/hr | J11: =IF(OR(H11="",H11=0),"",IF(ISNUMBER(SEARCH("hr",I11)),G11/H11,H11*G11)) -> 6.9148936 | K11: =F11/G11 -> 0 | L11: 8000 | M11: =Table4434[[#This Row],[RATE HOUR /DAY]]*Table4434[[#This Row],[Days/hours consider for costing]] -> 16000 | N11: =Table4434[[#This Row],[Actual working days/machine hours ]]*Table4434[[#This Row],[RATE HOUR /DAY]] -> 16000 | O11: E & C
A12: 9 | B12: ZA-8445 | C12: Truck Mixer | H12: =IFERROR(_xlfn.XLOOKUP(B12,[20]Sheet1!$C:$C,[20]Sheet1!$K:$K,_xlfn.XLOOKUP(B12,[20]Sheet1!$B:$B,[20]Sheet1!$K:$K,"")),"") -> 9.4 | I12: =IFERROR(_xlfn.XLOOKUP(B12,[20]Sheet1!$C:$C,[20]Sheet1!$J:$J,_xlfn.XLOOKUP(B12,[20]Sheet1!$B:$B,[20]Sheet1!$J:$J,"")),"") -> L/hr | J12: =IF(OR(H12="",H12=0),"",IF(ISNUMBER(SEARCH("hr",I12)),G12/H12,H12*G12)) -> 0 | L12: 8000 | M12: =Table4434[[#This Row],[RATE HOUR /DAY]]*Table4434[[#This Row],[Days/hours consider for costing]] -> 0 | N12: =Table4434[[#This Row],[Actual working days/machine hours ]]*Table4434[[#This Row],[RATE HOUR /DAY]] -> 0
A13: 10 | B13: LP-1566 | C13: 3 Cube | D13: 11 | E13: 11 | F13: 158 | G13: 70 | H13: =IFERROR(_xlfn.XLOOKUP(B13,[20]Sheet1!$C:$C,[20]Sheet1!$K:$K,_xlfn.XLOOKUP(B13,[20]Sheet1!$B:$B,[20]Sheet1!$K:$K,"")),"") -> 3.8 | I13: =IFERROR(_xlfn.XLOOKUP(B13,[20]Sheet1!$C:$C,[20]Sheet1!$J:$J,_xlfn.XLOOKUP(B13,[20]Sheet1!$B:$B,[20]Sheet1!$J:$J,"")),"") -> km/L | J13: =IF(OR(H13="",H13=0),"",IF(ISNUMBER(SEARCH("hr",I13)),G13/H13,H13*G13)) -> 266 | K13: =F13/G13 -> 2.2571429 | L13: 6440 | M13: =L13*E13 -> 70840 | N13: =Table4434[[#This Row],[Actual working days/machine hours ]]*Table4434[[#This Row],[RATE HOUR /DAY]] -> 70840 | O13: E & C
A14: 11 | B14: LO-7181 | C14: 3 Cube | H14: =IFERROR(_xlfn.XLOOKUP(B14,[20]Sheet1!$C:$C,[20]Sheet1!$K:$K,_xlfn.XLOOKUP(B14,[20]Sheet1!$B:$B,[20]Sheet1!$K:$K,"")),"") -> 3.8 | I14: =IFERROR(_xlfn.XLOOKUP(B14,[20]Sheet1!$C:$C,[20]Sheet1!$J:$J,_xlfn.XLOOKUP(B14,[20]Sheet1!$B:$B,[20]Sheet1!$J:$J,"")),"") -> km/L | J14: =IF(OR(H14="",H14=0),"",IF(ISNUMBER(SEARCH("hr",I14)),G14/H14,H14*G14)) -> 0 | K14: =F14/G14 -> #DIV/0! | L14: 6440 | M14: =L14*E14 -> 0 | N14: =Table4434[[#This Row],[Actual working days/machine hours ]]*Table4434[[#This Row],[RATE HOUR /DAY]] -> 0 | O14: E & C
A15: 12 | B15: LP-1574 | C15: 3 Cube | D15: 11 | E15: 11 | F15: 187 | G15: 90 | H15: =IFERROR(_xlfn.XLOOKUP(B15,[20]Sheet1!$C:$C,[20]Sheet1!$K:$K,_xlfn.XLOOKUP(B15,[20]Sheet1!$B:$B,[20]Sheet1!$K:$K,"")),"") -> 3.8 | I15: =IFERROR(_xlfn.XLOOKUP(B15,[20]Sheet1!$C:$C,[20]Sheet1!$J:$J,_xlfn.XLOOKUP(B15,[20]Sheet1!$B:$B,[20]Sheet1!$J:$J,"")),"") -> km/L | J15: =IF(OR(H15="",H15=0),"",IF(ISNUMBER(SEARCH("hr",I15)),G15/H15,H15*G15)) -> 342 | K15: =F15/G15 -> 2.0777778 | L15: 6440 | M15: =L15*E15 -> 70840 | N15: =Table4434[[#This Row],[Actual working days/machine hours ]]*Table4434[[#This Row],[RATE HOUR /DAY]] -> 70840 | O15: E & C
A16: 13 | B16: LP-1572 | C16: 3 Cube | D16: 9 | E16: 9 | F16: 284 | G16: 105 | H16: =IFERROR(_xlfn.XLOOKUP(B16,[20]Sheet1!$C:$C,[20]Sheet1!$K:$K,_xlfn.XLOOKUP(B16,[20]Sheet1!$B:$B,[20]Sheet1!$K:$K,"")),"") -> 3.8 | I16: =IFERROR(_xlfn.XLOOKUP(B16,[20]Sheet1!$C:$C,[20]Sheet1!$J:$J,_xlfn.XLOOKUP(B16,[20]Sheet1!$B:$B,[20]Sheet1!$J:$J,"")),"") -> km/L | J16: =IF(OR(H16="",H16=0),"",IF(ISNUMBER(SEARCH("hr",I16)),G16/H16,H16*G16)) -> 399 | K16: =F16/G16 -> 2.7047619 | L16: 6440 | M16: =L16*E16 -> 57960 | N16: =Table4434[[#This Row],[Actual working days/machine hours ]]*Table4434[[#This Row],[RATE HOUR /DAY]] -> 57960 | O16: E & C
A17: 14 | B17: LP-1709 | C17: 3 Cube | D17: 10 | E17: 10 | F17: 313 | G17: 60 | H17: =IFERROR(_xlfn.XLOOKUP(B17,[20]Sheet1!$C:$C,[20]Sheet1!$K:$K,_xlfn.XLOOKUP(B17,[20]Sheet1!$B:$B,[20]Sheet1!$K:$K,"")),"") -> 3.8 | I17: =IFERROR(_xlfn.XLOOKUP(B17,[20]Sheet1!$C:$C,[20]Sheet1!$J:$J,_xlfn.XLOOKUP(B17,[20]Sheet1!$B:$B,[20]Sheet1!$J:$J,"")),"") -> km/L | J17: =IF(OR(H17="",H17=0),"",IF(ISNUMBER(SEARCH("hr",I17)),G17/H17,H17*G17)) -> 228 | K17: =F17/G17 -> 5.2166667 | L17: 6440 | M17: =L17*E17 -> 64400 | N17: =Table4434[[#This Row],[Actual working days/machine hours ]]*Table4434[[#This Row],[RATE HOUR /DAY]] -> 64400 | O17: E & C
A18: 15 | B18: DAH-2229 | C18: Single cab | D18: 5 | E18: 5 | F18: 480 | G18: 55 | H18: =IFERROR(_xlfn.XLOOKUP(B18,[20]Sheet1!$C:$C,[20]Sheet1!$K:$K,_xlfn.XLOOKUP(B18,[20]Sheet1!$B:$B,[20]Sheet1!$K:$K,"")),"") -> 14.1 | I18: =IFERROR(_xlfn.XLOOKUP(B18,[20]Sheet1!$C:$C,[20]Sheet1!$J:$J,_xlfn.XLOOKUP(B18,[20]Sheet1!$B:$B,[20]Sheet1!$J:$J,"")),"") -> km/L | J18: =IF(OR(H18="",H18=0),"",IF(ISNUMBER(SEARCH("hr",I18)),G18/H18,H18*G18)) -> 775.5 | K18: =F18/G18 -> 8.7272727 | L18: 3080 | M18: =L18*E18 -> 15400 | N18: =Table4434[[#This Row],[Actual working days/machine hours ]]*Table4434[[#This Row],[RATE HOUR /DAY]] -> 15400 | O18: E & C
A19: 16 | B19: LA-1359 | C19: Diesel Bowser | D19: 19 | E19: 19 | F19: 1063 | G19: 170 | H19: =IFERROR(_xlfn.XLOOKUP(B19,[20]Sheet1!$C:$C,[20]Sheet1!$K:$K,_xlfn.XLOOKUP(B19,[20]Sheet1!$B:$B,[20]Sheet1!$K:$K,"")),"") -> 5 | I19: =IFERROR(_xlfn.XLOOKUP(B19,[20]Sheet1!$C:$C,[20]Sheet1!$J:$J,_xlfn.XLOOKUP(B19,[20]Sheet1!$B:$B,[20]Sheet1!$J:$J,"")),"") -> L/hr | J19: =IF(OR(H19="",H19=0),"",IF(ISNUMBER(SEARCH("hr",I19)),G19/H19,H19*G19)) -> 34 | K19: =F19/G19 -> 6.2529412 | L19: 2800 | M19: =L19*E19 -> 53200 | N19: =Table4434[[#This Row],[Actual working days/machine hours ]]*Table4434[[#This Row],[RATE HOUR /DAY]] -> 53200 | O19: E & C
A20: 17 | B20: HEX-42 | C20: Case 220 | D20: 44.6 | E20: 44.6 | G20: 440 | H20: =IFERROR(_xlfn.XLOOKUP(B20,[20]Sheet1!$C:$C,[20]Sheet1!$K:$K,_xlfn.XLOOKUP(B20,[20]Sheet1!$B:$B,[20]Sheet1!$K:$K,"")),"") -> 11.5 | I20: =IFERROR(_xlfn.XLOOKUP(B20,[20]Sheet1!$C:$C,[20]Sheet1!$J:$J,_xlfn.XLOOKUP(B20,[20]Sheet1!$B:$B,[20]Sheet1!$J:$J,"")),"") -> L/hr | J20: =IF(OR(H20="",H20=0),"",IF(ISNUMBER(SEARCH("hr",I20)),G20/H20,H20*G20)) -> 38.26087 | K20: =Table4434[[#This Row],[Fuel]]/Table4434[[#This Row],[Actual working days/machine hours ]] -> 9.8654709 | L20: 3600 | M20: =L20*E20 -> 160560 | N20: =Table4434[[#This Row],[Actual working days/machine hours ]]*Table4434[[#This Row],[RATE HOUR /DAY]] -> 160560
A21: 18 | B21: HEX-45 | C21: Case 220 | D21: 15 | E21: 15 | G21: 180 | H21: =IFERROR(_xlfn.XLOOKUP(B21,[20]Sheet1!$C:$C,[20]Sheet1!$K:$K,_xlfn.XLOOKUP(B21,[20]Sheet1!$B:$B,[20]Sheet1!$K:$K,"")),"") -> 11.5 | I21: =IFERROR(_xlfn.XLOOKUP(B21,[20]Sheet1!$C:$C,[20]Sheet1!$J:$J,_xlfn.XLOOKUP(B21,[20]Sheet1!$B:$B,[20]Sheet1!$J:$J,"")),"") -> L/hr | J21: =IF(OR(H21="",H21=0),"",IF(ISNUMBER(SEARCH("hr",I21)),G21/H21,H21*G21)) -> 15.652174 | K21: =Table4434[[#This Row],[Fuel]]/Table4434[[#This Row],[Actual working days/machine hours ]] -> 12 | L21: 3600 | M21: =L21*E21 -> 54000 | N21: =Table4434[[#This Row],[Actual working days/machine hours ]]*Table4434[[#This Row],[RATE HOUR /DAY]] -> 54000 | O21: E & C
A22: 19 | B22: HEX-37 | C22: Hyundai 330 | H22: =IFERROR(_xlfn.XLOOKUP(B22,[20]Sheet1!$C:$C,[20]Sheet1!$K:$K,_xlfn.XLOOKUP(B22,[20]Sheet1!$B:$B,[20]Sheet1!$K:$K,"")),"") -> 15.8 | I22: =IFERROR(_xlfn.XLOOKUP(B22,[20]Sheet1!$C:$C,[20]Sheet1!$J:$J,_xlfn.XLOOKUP(B22,[20]Sheet1!$B:$B,[20]Sheet1!$J:$J,"")),"") -> L/hr | J22: =IF(OR(H22="",H22=0),"",IF(ISNUMBER(SEARCH("hr",I22)),G22/H22,H22*G22)) -> 0 | L22: 3600 | M22: =L22*E22 -> 0 | N22: =Table4434[[#This Row],[Actual working days/machine hours ]]*Table4434[[#This Row],[RATE HOUR /DAY]] -> 0
A23: 20 | B23: MG-18 | C23: Motor Grader | D23: 34.7 | E23: 34.7 | G23: 330 | H23: =IFERROR(_xlfn.XLOOKUP(B23,[20]Sheet1!$C:$C,[20]Sheet1!$K:$K,_xlfn.XLOOKUP(B23,[20]Sheet1!$B:$B,[20]Sheet1!$K:$K,"")),"") -> 13 | I23: =IFERROR(_xlfn.XLOOKUP(B23,[20]Sheet1!$C:$C,[20]Sheet1!$J:$J,_xlfn.XLOOKUP(B23,[20]Sheet1!$B:$B,[20]Sheet1!$J:$J,"")),"") -> L/hr | J23: =IF(OR(H23="",H23=0),"",IF(ISNUMBER(SEARCH("hr",I23)),G23/H23,H23*G23)) -> 25.384615 | K23: =Table4434[[#This Row],[Fuel]]/Table4434[[#This Row],[Actual working days/machine hours ]] -> 9.5100865 | L23: 3300 | M23: =Table4434[[#This Row],[Days/hours consider for costing]]*Table4434[[#This Row],[RATE HOUR /DAY]] -> 114510 | N23: =Table4434[[#This Row],[Actual working days/machine hours ]]*Table4434[[#This Row],[RATE HOUR /DAY]] -> 114510 | O23: E & C
A24: 21 | B24: ZA-4344 | C24: Motor Grader | D24: 10.3 | E24: 10.3 | G24: 120 | H24: =IFERROR(_xlfn.XLOOKUP(B24,[20]Sheet1!$C:$C,[20]Sheet1!$K:$K,_xlfn.XLOOKUP(B24,[20]Sheet1!$B:$B,[20]Sheet1!$K:$K,"")),"") -> 13 | I24: =IFERROR(_xlfn.XLOOKUP(B24,[20]Sheet1!$C:$C,[20]Sheet1!$J:$J,_xlfn.XLOOKUP(B24,[20]Sheet1!$B:$B,[20]Sheet1!$J:$J,"")),"") -> L/hr | J24: =IF(OR(H24="",H24=0),"",IF(ISNUMBER(SEARCH("hr",I24)),G24/H24,H24*G24)) -> 9.2307692 | L24: 3300 | M24: =Table4434[[#This Row],[Days/hours consider for costing]]*Table4434[[#This Row],[RATE HOUR /DAY]] -> 33990 | N24: =Table4434[[#This Row],[Actual working days/machine hours ]]*Table4434[[#This Row],[RATE HOUR /DAY]] -> 33990
A25: 22 | B25: ZB-1980 | C25: JCB | D25: 77.5 | E25: 77.5 | G25: 305 | H25: =IFERROR(_xlfn.XLOOKUP(B25,[20]Sheet1!$C:$C,[20]Sheet1!$K:$K,_xlfn.XLOOKUP(B25,[20]Sheet1!$B:$B,[20]Sheet1!$K:$K,"")),"") -> 5 | I25: =IFERROR(_xlfn.XLOOKUP(B25,[20]Sheet1!$C:$C,[20]Sheet1!$J:$J,_xlfn.XLOOKUP(B25,[20]Sheet1!$B:$B,[20]Sheet1!$J:$J,"")),"") -> L/hr | J25: =IF(OR(H25="",H25=0),"",IF(ISNUMBER(SEARCH("hr",I25)),G25/H25,H25*G25)) -> 61 | K25: =Table4434[[#This Row],[Fuel]]/Table4434[[#This Row],[Actual working days/machine hours ]] -> 3.9354839 | L25: 2000 | M25: =Table4434[[#This Row],[Days/hours consider for costing]]*Table4434[[#This Row],[RATE HOUR /DAY]] -> 155000 | N25: =Table4434[[#This Row],[Actual working days/machine hours ]]*Table4434[[#This Row],[RATE HOUR /DAY]] -> 155000 | O25: E & C
A26: 23 | B26: SR-18 | C26: 10 ton roller | D26: 17 | E26: 17 | G26: 140 | H26: =IFERROR(_xlfn.XLOOKUP(B26,[20]Sheet1!$C:$C,[20]Sheet1!$K:$K,_xlfn.XLOOKUP(B26,[20]Sheet1!$B:$B,[20]Sheet1!$K:$K,"")),"") -> 4.3 | I26: =IFERROR(_xlfn.XLOOKUP(B26,[20]Sheet1!$C:$C,[20]Sheet1!$J:$J,_xlfn.XLOOKUP(B26,[20]Sheet1!$B:$B,[20]Sheet1!$J:$J,"")),"") -> L/hr | J26: =IF(OR(H26="",H26=0),"",IF(ISNUMBER(SEARCH("hr",I26)),G26/H26,H26*G26)) -> 32.55814 | K26: =Table4434[[#This Row],[Fuel]]/Table4434[[#This Row],[Actual working days/machine hours ]] -> 8.2352941 | L26: 3200 | M26: =Table4434[[#This Row],[Days/hours consider for costing]]*Table4434[[#This Row],[RATE HOUR /DAY]] -> 54400 | N26: =Table4434[[#This Row],[Actual working days/machine hours ]]*Table4434[[#This Row],[RATE HOUR /DAY]] -> 54400 | O26: E & C
A27: 24 | B27: SL-24 | C27: BOB CAT | H27: =IFERROR(_xlfn.XLOOKUP(B27,[20]Sheet1!$C:$C,[20]Sheet1!$K:$K,_xlfn.XLOOKUP(B27,[20]Sheet1!$B:$B,[20]Sheet1!$K:$K,"")),"") -> 3.2 | I27: =IFERROR(_xlfn.XLOOKUP(B27,[20]Sheet1!$C:$C,[20]Sheet1!$J:$J,_xlfn.XLOOKUP(B27,[20]Sheet1!$B:$B,[20]Sheet1!$J:$J,"")),"") -> L/hr | J27: =IF(OR(H27="",H27=0),"",IF(ISNUMBER(SEARCH("hr",I27)),G27/H27,H27*G27)) -> 0 | K27: =Table4434[[#This Row],[Fuel]]/Table4434[[#This Row],[Actual working days/machine hours ]] -> #DIV/0! | L27: 1680 | M27: =Table4434[[#This Row],[Days/hours consider for costing]]*Table4434[[#This Row],[RATE HOUR /DAY]] -> 0 | N27: =Table4434[[#This Row],[Actual working days/machine hours ]]*Table4434[[#This Row],[RATE HOUR /DAY]] -> 0 | O27: E & C
M29: =SUM(M4:M28) -> 1151740 | N29: =SUM(N4:N28) -> 1151740

Sheet Sheet1
A1: FLEET FUEL RATES — estimated by model size-class & manufacturing year (518 units)
A2: Per-unit fuel-cost rate at three duty scenarios (Lowest / Medium / Highest). Typical consumption is set from each machine's model size/engine class, then adjusted for age via the manufacturing year. Machinery Rs./hr, road vehicles Rs./km. Edit the blue cells (fuel prices, age factor, or any vehicle's consumption) and rates recalculate. SL prices, Jun 2026.
A4: FUEL PRICE & AGE INPUTS (edit to update every rate)
A5: Auto Diesel (Rs./litre) | D5: 478 | E5: ← Ceypetco/LIOC 01-Jun-2026
A6: Petrol 92 Octane (Rs./litre) | D6: 434
A8: Base year (new = no penalty) | D8: 2026
A9: Extra fuel % per year of age | D9: 0.007 | E9: ← older engines burn more (e.g. 0.7%/yr)
A10: Cap age (years) | D10: 25
A11: PER-VEHICLE FUEL RATES (518 units) — by model class & year
A12: # | B12: E&C No | C12: Reg No | D12: Category | E12: Model | F12: Year | G12: Fuel | H12: Basis | I12: Size / Engine Class | J12: Unit | K12: Cons Econ | L12: Cons Typ | M12: Cons Heavy | N12: Age × | O12: Lowest Rate | P12: Medium Rate | Q12: Highest Rate | R12: Rate Unit
A13: 1 | B13: AP-01 | C13: — | D13: Asphalt Paver | E13: Sumitomo Ha45C-2065 | F13: 2012 | G13: Diesel | H13: Hour | I13: Standard (class avg) | J13: L/hr | K13: 10.1 | L13: 14 | M13: 18.9 | N13: =1+MIN(MAX($D$8-F13,0),$D$10)*$D$9 -> 1.098 | O13: =IF(H13="None",0,IF(H13="KM",IF(G13="Petrol",$D$6,$D$5)*N13/K13,K13*N13*IF(G13="Petrol",$D$6,$D$5))) -> 5300.9244 | P13: =IF(H13="None",0,IF(H13="KM",IF(G13="Petrol",$D$6,$D$5)*N13/L13,L13*N13*IF(G13="Petrol",$D$6,$D$5))) -> 7347.816 | Q13: =IF(H13="None",0,IF(H13="KM",IF(G13="Petrol",$D$6,$D$5)*N13/M13,M13*N13*IF(G13="Petrol",$D$6,$D$5))) -> 9919.5516 | R13: =IF(H13="None","—",IF(H13="KM","Rs./km","Rs./hr")) -> Rs./hr
A14: 2 | B14: AP-02 | C14: — | D14: Asphalt Paver | E14: Mitsubishi Mf40Wh | F14: 2013 | G14: Diesel | H14: Hour | I14: Standard (class avg) | J14: L/hr | K14: 10.1 | L14: 14 | M14: 18.9 | N14: =1+MIN(MAX($D$8-F14,0),$D$10)*$D$9 -> 1.091 | O14: =IF(H14="None",0,IF(H14="KM",IF(G14="Petrol",$D$6,$D$5)*N14/K14,K14*N14*IF(G14="Petrol",$D$6,$D$5))) -> 5267.1298 | P14: =IF(H14="None",0,IF(H14="KM",IF(G14="Petrol",$D$6,$D$5)*N14/L14,L14*N14*IF(G14="Petrol",$D$6,$D$5))) -> 7300.972 | Q14: =IF(H14="None",0,IF(H14="KM",IF(G14="Petrol",$D$6,$D$5)*N14/M14,M14*N14*IF(G14="Petrol",$D$6,$D$5))) -> 9856.3122 | R14: =IF(H14="None","—",IF(H14="KM","Rs./km","Rs./hr")) -> Rs./hr
A15: 3 | B15: AP-03 | C15: — | D15: Asphalt Paver | E15: Mitsubishi Mf-55Wh | F15: 2014 | G15: Diesel | H15: Hour | I15: Standard (class avg) | J15: L/hr | K15: 10.1 | L15: 14 | M15: 18.9 | N15: =1+MIN(MAX($D$8-F15,0),$D$10)*$D$9 -> 1.084 | O15: =IF(H15="None",0,IF(H15="KM",IF(G15="Petrol",$D$6,$D$5)*N15/K15,K15*N15*IF(G15="Petrol",$D$6,$D$5))) -> 5233.3352 | P15: =IF(H15="None",0,IF(H15="KM",IF(G15="Petrol",$D$6,$D$5)*N15/L15,L15*N15*IF(G15="Petrol",$D$6,$D$5))) -> 7254.128 | Q15: =IF(H15="None",0,IF(H15="KM",IF(G15="Petrol",$D$6,$D$5)*N15/M15,M15*N15*IF(G15="Petrol",$D$6,$D$5))) -> 9793.0728 | R15: =IF(H15="None","—",IF(H15="KM","Rs./km","Rs./hr")) -> Rs./hr
A16: 4 | B16: AP-04 | C16: — | D16: Asphalt Paver | E16: Mitsubishi Mf60Wd | F16: 2014 | G16: Diesel | H16: Hour | I16: Standard (class avg) | J16: L/hr | K16: 10.1 | L16: 14 | M16: 18.9 | N16: =1+MIN(MAX($D$8-F16,0),$D$10)*$D$9 -> 1.084 | O16: =IF(H16="None",0,IF(H16="KM",IF(G16="Petrol",$D$6,$D$5)*N16/K16,K16*N16*IF(G16="Petrol",$D$6,$D$5))) -> 5233.3352 | P16: =IF(H16="None",0,IF(H16="KM",IF(G16="Petrol",$D$6,$D$5)*N16/L16,L16*N16*IF(G16="Petrol",$D$6,$D$5))) -> 7254.128 | Q16: =IF(H16="None",0,IF(H16="KM",IF(G16="Petrol",$D$6,$D$5)*N16/M16,M16*N16*IF(G16="Petrol",$D$6,$D$5))) -> 9793.0728 | R16: =IF(H16="None","—",IF(H16="KM","Rs./km","Rs./hr")) -> Rs./hr
A17: 5 | B17: AP-05 | C17: — | D17: Asphalt Paver | E17: Nigata — | F17: 2012 | G17: Diesel | H17: Hour | I17: Standard (class avg) | J17: L/hr | K17: 10.1 | L17: 14 | M17: 18.9 | N17: =1+MIN(MAX($D$8-F17,0),$D$10)*$D$9 -> 1.098 | O17: =IF(H17="None",0,IF(H17="KM",IF(G17="Petrol",$D$6,$D$5)*N17/K17,K17*N17*IF(G17="Petrol",$D$6,$D$5))) -> 5300.9244 | P17: =IF(H17="None",0,IF(H17="KM",IF(G17="Petrol",$D$6,$D$5)*N17/L17,L17*N17*IF(G17="Petrol",$D$6,$D$5))) -> 7347.816 | Q17: =IF(H17="None",0,IF(H17="KM",IF(G17="Petrol",$D$6,$D$5)*N17/M17,M17*N17*IF(G17="Petrol",$D$6,$D$5))) -> 9919.5516 | R17: =IF(H17="None","—",IF(H17="KM","Rs./km","Rs./hr")) -> Rs./hr
A18: 6 | B18: AP-06 | C18: — | D18: Asphalt Paver | E18: (Unknown) — | F18: — | G18: Diesel | H18: Hour | I18: Standard (class avg) | J18: L/hr | K18: 10.1 | L18: 14 | M18: 18.9 | N18: =1 -> 1 | O18: =IF(H18="None",0,IF(H18="KM",IF(G18="Petrol",$D$6,$D$5)*N18/K18,K18*N18*IF(G18="Petrol",$D$6,$D$5))) -> 4827.8 | P18: =IF(H18="None",0,IF(H18="KM",IF(G18="Petrol",$D$6,$D$5)*N18/L18,L18*N18*IF(G18="Petrol",$D$6,$D$5))) -> 6692 | Q18: =IF(H18="None",0,IF(H18="KM",IF(G18="Petrol",$D$6,$D$5)*N18/M18,M18*N18*IF(G18="Petrol",$D$6,$D$5))) -> 9034.2 | R18: =IF(H18="None","—",IF(H18="KM","Rs./km","Rs./hr")) -> Rs./hr
A19: 7 | B19: AP-07 | C19: — | D19: Asphalt Paver | E19: (Unknown) — | F19: — | G19: Diesel | H19: Hour | I19: Standard (class avg) | J19: L/hr | K19: 10.1 | L19: 14 | M19: 18.9 | N19: =1 -> 1 | O19: =IF(H19="None",0,IF(H19="KM",IF(G19="Petrol",$D$6,$D$5)*N19/K19,K19*N19*IF(G19="Petrol",$D$6,$D$5))) -> 4827.8 | P19: =IF(H19="None",0,IF(H19="KM",IF(G19="Petrol",$D$6,$D$5)*N19/L19,L19*N19*IF(G19="Petrol",$D$6,$D$5))) -> 6692 | Q19: =IF(H19="None",0,IF(H19="KM",IF(G19="Petrol",$D$6,$D$5)*N19/M19,M19*N19*IF(G19="Petrol",$D$6,$D$5))) -> 9034.2 | R19: =IF(H19="None","—",IF(H19="KM","Rs./km","Rs./hr")) -> Rs./hr
A20: 8 | B20: AP-08 | C20: — | D20: Asphalt Paver | E20: Volvo P6820C | F20: 2019 | G20: Diesel | H20: Hour | I20: Standard (class avg) | J20: L/hr | K20: 10.1 | L20: 14 | M20: 18.9 | N20: =1+MIN(MAX($D$8-F20,0),$D$10)*$D$9 -> 1.049 | O20: =IF(H20="None",0,IF(H20="KM",IF(G20="Petrol",$D$6,$D$5)*N20/K20,K20*N20*IF(G20="Petrol",$D$6,$D$5))) -> 5064.3622 | P20: =IF(H20="None",0,IF(H20="KM",IF(G20="Petrol",$D$6,$D$5)*N20/L20,L20*N20*IF(G20="Petrol",$D$6,$D$5))) -> 7019.908 | Q20: =IF(H20="None",0,IF(H20="KM",IF(G20="Petrol",$D$6,$D$5)*N20/M20,M20*N20*IF(G20="Petrol",$D$6,$D$5))) -> 9476.8758 | R20: =IF(H20="None","—",IF(H20="KM","Rs./km","Rs./hr")) -> Rs./hr
A21: 9 | B21: AP-09 | C21: — | D21: Asphalt Paver | E21: Sumitomo Ha60W-7 | F21: 2012 | G21: Diesel | H21: Hour | I21: Standard (class avg) | J21: L/hr | K21: 10.1 | L21: 14 | M21: 18.9 | N21: =1+MIN(MAX($D$8-F21,0),$D$10)*$D$9 -> 1.098 | O21: =IF(H21="None",0,IF(H21="KM",IF(G21="Petrol",$D$6,$D$5)*N21/K21,K21*N21*IF(G21="Petrol",$D$6,$D$5))) -> 5300.9244 | P21: =IF(H21="None",0,IF(H21="KM",IF(G21="Petrol",$D$6,$D$5)*N21/L21,L21*N21*IF(G21="Petrol",$D$6,$D$5))) -> 7347.816 | Q21: =IF(H21="None",0,IF(H21="KM",IF(G21="Petrol",$D$6,$D$5)*N21/M21,M21*N21*IF(G21="Petrol",$D$6,$D$5))) -> 9919.5516 | R21: =IF(H21="None","—",IF(H21="KM","Rs./km","Rs./hr")) -> Rs./hr
A22: 10 | B22: AP-10 | C22: — | D22: Asphalt Paver | E22: Dynapac Sd2500C | F22: 2020 | G22: Diesel | H22: Hour | I22: Standard (class avg) | J22: L/hr | K22: 10.1 | L22: 14 | M22: 18.9 | N22: =1+MIN(MAX($D$8-F22,0),$D$10)*$D$9 -> 1.042 | O22: =IF(H22="None",0,IF(H22="KM",IF(G22="Petrol",$D$6,$D$5)*N22/K22,K22*N22*IF(G22="Petrol",$D$6,$D$5))) -> 5030.5676 | P22: =IF(H22="None",0,IF(H22="KM",IF(G22="Petrol",$D$6,$D$5)*N22/L22,L22*N22*IF(G22="Petrol",$D$6,$D$5))) -> 6973.064 | Q22: =IF(H22="None",0,IF(H22="KM",IF(G22="Petrol",$D$6,$D$5)*N22/M22,M22*N22*IF(G22="Petrol",$D$6,$D$5))) -> 9413.6364 | R22: =IF(H22="None","—",IF(H22="KM","Rs./km","Rs./hr")) -> Rs./hr
A23: 11 | B23: AP-11 | C23: — | D23: Asphalt Paver | E23: Sumitomo Ha60W-5 | F23: 2006 | G23: Diesel | H23: Hour | I23: Standard (class avg) | J23: L/hr | K23: 10.1 | L23: 14 | M23: 18.9 | N23: =1+MIN(MAX($D$8-F23,0),$D$10)*$D$9 -> 1.14 | O23: =IF(H23="None",0,IF(H23="KM",IF(G23="Petrol",$D$6,$D$5)*N23/K23,K23*N23*IF(G23="Petrol",$D$6,$D$5))) -> 5503.692 | P23: =IF(H23="None",0,IF(H23="KM",IF(G23="Petrol",$D$6,$D$5)*N23/L23,L23*N23*IF(G23="Petrol",$D$6,$D$5))) -> 7628.88 | Q23: =IF(H23="None",0,IF(H23="KM",IF(G23="Petrol",$D$6,$D$5)*N23/M23,M23*N23*IF(G23="Petrol",$D$6,$D$5))) -> 10298.988 | R23: =IF(H23="None","—",IF(H23="KM","Rs./km","Rs./hr")) -> Rs./hr
A24: 12 | B24: LB-01 | C24: ZA-2609 | D24: Backhoe Loader | E24: Jcb 3Dx | F24: 2012 | G24: Diesel | H24: Hour | I24: Standard (class avg) | J24: L/hr | K24: 5 | L24: 7 | M24: 9.5 | N24: =1+MIN(MAX($D$8-F24,0),$D$10)*$D$9 -> 1.098 | O24: =IF(H24="None",0,IF(H24="KM",IF(G24="Petrol",$D$6,$D$5)*N24/K24,K24*N24*IF(G24="Petrol",$D$6,$D$5))) -> 2624.22 | P24: =IF(H24="None",0,IF(H24="KM",IF(G24="Petrol",$D$6,$D$5)*N24/L24,L24*N24*IF(G24="Petrol",$D$6,$D$5))) -> 3673.908 | Q24: =IF(H24="None",0,IF(H24="KM",IF(G24="Petrol",$D$6,$D$5)*N24/M24,M24*N24*IF(G24="Petrol",$D$6,$D$5))) -> 4986.018 | R24: =IF(H24="None","—",IF(H24="KM","Rs./km","Rs./hr")) -> Rs./hr
A25: 13 | B25: LB-02 | C25: ZA-2963 | D25: Backhoe Loader | E25: Jcb 3Dx | F25: 2012 | G25: Diesel | H25: Hour | I25: Standard (class avg) | J25: L/hr | K25: 5 | L25: 7 | M25: 9.5 | N25: =1+MIN(MAX($D$8-F25,0),$D$10)*$D$9 -> 1.098 | O25: =IF(H25="None",0,IF(H25="KM",IF(G25="Petrol",$D$6,$D$5)*N25/K25,K25*N25*IF(G25="Petrol",$D$6,$D$5))) -> 2624.22 | P25: =IF(H25="None",0,IF(H25="KM",IF(G25="Petrol",$D$6,$D$5)*N25/L25,L25*N25*IF(G25="Petrol",$D$6,$D$5))) -> 3673.908 | Q25: =IF(H25="None",0,IF(H25="KM",IF(G25="Petrol",$D$6,$D$5)*N25/M25,M25*N25*IF(G25="Petrol",$D$6,$D$5))) -> 4986.018 | R25: =IF(H25="None","—",IF(H25="KM","Rs./km","Rs./hr")) -> Rs./hr
A26: 14 | B26: LB-03 | C26: ZA-2964 | D26: Backhoe Loader | E26: Jcb 3Dx | F26: 2012 | G26: Diesel | H26: Hour | I26: Standard (class avg) | J26: L/hr | K26: 5 | L26: 7 | M26: 9.5 | N26: =1+MIN(MAX($D$8-F26,0),$D$10)*$D$9 -> 1.098 | O26: =IF(H26="None",0,IF(H26="KM",IF(G26="Petrol",$D$6,$D$5)*N26/K26,K26*N26*IF(G26="Petrol",$D$6,$D$5))) -> 2624.22 | P26: =IF(H26="None",0,IF(H26="KM",IF(G26="Petrol",$D$6,$D$5)*N26/L26,L26*N26*IF(G26="Petrol",$D$6,$D$5))) -> 3673.908 | Q26: =IF(H26="None",0,IF(H26="KM",IF(G26="Petrol",$D$6,$D$5)*N26/M26,M26*N26*IF(G26="Petrol",$D$6,$D$5))) -> 4986.018 | R26: =IF(H26="None","—",IF(H26="KM","Rs./km","Rs./hr")) -> Rs./hr
A27: 15 | B27: LB-04 | C27: RS-0401 | D27: Backhoe Loader | E27: Jcb Slp3Cx | F27: 1999 | G27: Diesel | H27: Hour | I27: Standard (class avg) | J27: L/hr | K27: 5 | L27: 7 | M27: 9.5 | N27: =1+MIN(MAX($D$8-F27,0),$D$10)*$D$9 -> 1.175 | O27: =IF(H27="None",0,IF(H27="KM",IF(G27="Petrol",$D$6,$D$5)*N27/K27,K27*N27*IF(G27="Petrol",$D$6,$D$5))) -> 2808.25 | P27: =IF(H27="None",0,IF(H27="KM",IF(G27="Petrol",$D$6,$D$5)*N27/L27,L27*N27*IF(G27="Petrol",$D$6,$D$5))) -> 3931.55 | Q27: =IF(H27="None",0,IF(H27="KM",IF(G27="Petrol",$D$6,$D$5)*N27/M27,M27*N27*IF(G27="Petrol",$D$6,$D$5))) -> 5335.675 | R27: =IF(H27="None","—",IF(H27="KM","Rs./km","Rs./hr")) -> Rs./hr
A28: 16 | B28: LB-05 | C28: RS-0483 | D28: Backhoe Loader | E28: Jcb 3Dx | F28: 2006 | G28: Diesel | H28: Hour | I28: Standard (class avg) | J28: L/hr | K28: 5 | L28: 7 | M28: 9.5 | N28: =1+MIN(MAX($D$8-F28,0),$D$10)*$D$9 -> 1.14 | O28: =IF(H28="None",0,IF(H28="KM",IF(G28="Petrol",$D$6,$D$5)*N28/K28,K28*N28*IF(G28="Petrol",$D$6,$D$5))) -> 2724.6 | P28: =IF(H28="None",0,IF(H28="KM",IF(G28="Petrol",$D$6,$D$5)*N28/L28,L28*N28*IF(G28="Petrol",$D$6,$D$5))) -> 3814.44 | Q28: =IF(H28="None",0,IF(H28="KM",IF(G28="Petrol",$D$6,$D$5)*N28/M28,M28*N28*IF(G28="Petrol",$D$6,$D$5))) -> 5176.74 | R28: =IF(H28="None","—",IF(H28="KM","Rs./km","Rs./hr")) -> Rs./hr
A29: 17 | B29: LB-06 | C29: ZA-0447 | D29: Backhoe Loader | E29: Jcb 3Cx | F29: 2002 | G29: Diesel | H29: Hour | I29: Standard (class avg) | J29: L/hr | K29: 5 | L29: 7 | M29: 9.5 | N29: =1+MIN(MAX($D$8-F29,0),$D$10)*$D$9 -> 1.168 | O29: =IF(H29="None",0,IF(H29="KM",IF(G29="Petrol",$D$6,$D$5)*N29/K29,K29*N29*IF(G29="Petrol",$D$6,$D$5))) -> 2791.52 | P29: =IF(H29="None",0,IF(H29="KM",IF(G29="Petrol",$D$6,$D$5)*N29/L29,L29*N29*IF(G29="Petrol",$D$6,$D$5))) -> 3908.128 | Q29: =IF(H29="None",0,IF(H29="KM",IF(G29="Petrol",$D$6,$D$5)*N29/M29,M29*N29*IF(G29="Petrol",$D$6,$D$5))) -> 5303.888 | R29: =IF(H29="None","—",IF(H29="KM","Rs./km","Rs./hr")) -> Rs./hr
A30: 18 | B30: LB-07 | C30: ZA-2608 | D30: Backhoe Loader | E30: Jcb Jcb 3Cx | F30: 2004 | G30: Diesel | H30: Hour | I30: Standard (class avg) | J30: L/hr | K30: 5 | L30: 7 | M30: 9.5 | N30: =1+MIN(MAX($D$8-F30,0),$D$10)*$D$9 -> 1.154 | O30: =IF(H30="None",0,IF(H30="KM",IF(G30="Petrol",$D$6,$D$5)*N30/K30,K30*N30*IF(G30="Petrol",$D$6,$D$5))) -> 2758.06 | P30: =IF(H30="None",0,IF(H30="KM",IF(G30="Petrol",$D$6,$D$5)*N30/L30,L30*N30*IF(G30="Petrol",$D$6,$D$5))) -> 3861.284 | Q30: =IF(H30="None",0,IF(H30="KM",IF(G30="Petrol",$D$6,$D$5)*N30/M30,M30*N30*IF(G30="Petrol",$D$6,$D$5))) -> 5240.314 | R30: =IF(H30="None","—",IF(H30="KM","Rs./km","Rs./hr")) -> Rs./hr
A31: 19 | B31: LB-08 | C31: ZA-6068 | D31: Backhoe Loader | E31: Jcb Jcb 3Dx | F31: 2015 | G31: Diesel | H31: Hour | I31: Standard (class avg) | J31: L/hr | K31: 5 | L31: 7 | M31: 9.5 | N31: =1+MIN(MAX($D$8-F31,0),$D$10)*$D$9 -> 1.077 | O31: =IF(H31="None",0,IF(H31="KM",IF(G31="Petrol",$D$6,$D$5)*N31/K31,K31*N31*IF(G31="Petrol",$D$6,$D$5))) -> 2574.03 | P31: =IF(H31="None",0,IF(H31="KM",IF(G31="Petrol",$D$6,$D$5)*N31/L31,L31*N31*IF(G31="Petrol",$D$6,$D$5))) -> 3603.642 | Q31: =IF(H31="None",0,IF(H31="KM",IF(G31="Petrol",$D$6,$D$5)*N31/M31,M31*N31*IF(G31="Petrol",$D$6,$D$5))) -> 4890.657 | R31: =IF(H31="None","—",IF(H31="KM","Rs./km","Rs./hr")) -> Rs./hr
... A68: 56 | B68: DB-02 | C68: 68-5115 | D68: Diesel Bowser | E68: Isuzu 207 Di | F68: 1990 | G68: Diesel | H68: Hour | I68: Standard (class avg) | J68: L/hr | K68: 5 | L68: 7 | M68: 9.5 | N68: =1+MIN(MAX($D$8-F68,0),$D$10)*$D$9 -> 1.175 | O68: =IF(H68="None",0,IF(H68="KM",IF(G68="Petrol",$D$6,$D$5)*N68/K68,K68*N68*IF(G68="Petrol",$D$6,$D$5))) -> 2808.25 | P68: =IF(H68="None",0,IF(H68="KM",IF(G68="Petrol",$D$6,$D$5)*N68/L68,L68*N68*IF(G68="Petrol",$D$6,$D$5))) -> 3931.55 | Q68: =IF(H68="None",0,IF(H68="KM",IF(G68="Petrol",$D$6,$D$5)*N68/M68,M68*N68*IF(G68="Petrol",$D$6,$D$5))) -> 5335.675 | R68: =IF(H68="None","—",IF(H68="KM","Rs./km","Rs./hr")) -> Rs./hr
A69: 57 | B69: DB-03 | C69: 40-2955 | D69: Diesel Bowser | E69: Nissan Atlas | F69: — | G69: Diesel | H69: Hour | I69: Standard (class avg) | J69: L/hr | K69: 5 | L69: 7 | M69: 9.5 | N69: =1 -> 1 | O69: =IF(H69="None",0,IF(H69="KM",IF(G69="Petrol",$D$6,$D$5)*N69/K69,K69*N69*IF(G69="Petrol",$D$6,$D$5))) -> 2390 | P69: =IF(H69="None",0,IF(H69="KM",IF(G69="Petrol",$D$6,$D$5)*N69/L69,L69*N69*IF(G69="Petrol",$D$6,$D$5))) -> 3346 | Q69: =IF(H69="None",0,IF(H69="KM",IF(G69="Petrol",$D$6,$D$5)*N69/M69,M69*N69*IF(G69="Petrol",$D$6,$D$5))) -> 4541 | R69: =IF(H69="None","—",IF(H69="KM","Rs./km","Rs./hr")) -> Rs./hr
A70: 58 | B70: DB-04 | C70: 41-1130 | D70: Diesel Bowser | E70: Isuzu — | F70: 2005 | G70: Diesel | H70: Hour | I70: Standard (class avg) | J70: L/hr | K70: 5 | L70: 7 | M70: 9.5 | N70: =1+MIN(MAX($D$8-F70,0),$D$10)*$D$9 -> 1.147 | O70: =IF(H70="None",0,IF(H70="KM",IF(G70="Petrol",$D$6,$D$5)*N70/K70,K70*N70*IF(G70="Petrol",$D$6,$D$5))) -> 2741.33 | P70: =IF(H70="None",0,IF(H70="KM",IF(G70="Petrol",$D$6,$D$5)*N70/L70,L70*N70*IF(G70="Petrol",$D$6,$D$5))) -> 3837.862 | Q70: =IF(H70="None",0,IF(H70="KM",IF(G70="Petrol",$D$6,$D$5)*N70/M70,M70*N70*IF(G70="Petrol",$D$6,$D$5))) -> 5208.527 | R70: =IF(H70="None","—",IF(H70="KM","Rs./km","Rs./hr")) -> Rs./hr
A71: 59 | B71: DB-05 | C71: LA-1359 | D71: Diesel Bowser | E71: Tata — | F71: 1990 | G71: Diesel | H71: Hour | I71: Standard (class avg) | J71: L/hr | K71: 5 | L71: 7 | M71: 9.5 | N71: =1+MIN(MAX($D$8-F71,0),$D$10)*$D$9 -> 1.175 | O71: =IF(H71="None",0,IF(H71="KM",IF(G71="Petrol",$D$6,$D$5)*N71/K71,K71*N71*IF(G71="Petrol",$D$6,$D$5))) -> 2808.25 | P71: =IF(H71="None",0,IF(H71="KM",IF(G71="Petrol",$D$6,$D$5)*N71/L71,L71*N71*IF(G71="Petrol",$D$6,$D$5))) -> 3931.55 | Q71: =IF(H71="None",0,IF(H71="KM",IF(G71="Petrol",$D$6,$D$5)*N71/M71,M71*N71*IF(G71="Petrol",$D$6,$D$5))) -> 5335.675 | R71: =IF(H71="None","—",IF(H71="KM","Rs./km","Rs./hr")) -> Rs./hr
A72: 60 | B72: — | C72: — | D72: Diesel Bowser | E72: Tata — | F72: — | G72: Diesel | H72: Hour | I72: Standard (class avg) | J72: L/hr | K72: 5 | L72: 7 | M72: 9.5 | N72: =1 -> 1 | O72: =IF(H72="None",0,IF(H72="KM",IF(G72="Petrol",$D$6,$D$5)*N72/K72,K72*N72*IF(G72="Petrol",$D$6,$D$5))) -> 2390 | P72: =IF(H72="None",0,IF(H72="KM",IF(G72="Petrol",$D$6,$D$5)*N72/L72,L72*N72*IF(G72="Petrol",$D$6,$D$5))) -> 3346 | Q72: =IF(H72="None",0,IF(H72="KM",IF(G72="Petrol",$D$6,$D$5)*N72/M72,M72*N72*IF(G72="Petrol",$D$6,$D$5))) -> 4541 | R72: =IF(H72="None","—",IF(H72="KM","Rs./km","Rs./hr")) -> Rs./hr
A73: 61 | B73: DC-06 | C73: PA-4193 | D73: Double Cab (Pickup) | E73: Toyota Hilux | F73: 2005 | G73: Diesel | H73: KM | I73: Standard (class avg) | J73: km/L | K73: 12.8 | L73: 10 | M73: 8 | N73: =1+MIN(MAX($D$8-F73,0),$D$10)*$D$9 -> 1.147 | O73: =IF(H73="None",0,IF(H73="KM",IF(G73="Petrol",$D$6,$D$5)*N73/K73,K73*N73*IF(G73="Petrol",$D$6,$D$5))) -> 42.833281 | P73: =IF(H73="None",0,IF(H73="KM",IF(G73="Petrol",$D$6,$D$5)*N73/L73,L73*N73*IF(G73="Petrol",$D$6,$D$5))) -> 54.8266 | Q73: =IF(H73="None",0,IF(H73="KM",IF(G73="Petrol",$D$6,$D$5)*N73/M73,M73*N73*IF(G73="Petrol",$D$6,$D$5))) -> 68.53325 | R73: =IF(H73="None","—",IF(H73="KM","Rs./km","Rs./hr")) -> Rs./km
A74: 62 | B74: DC-07 | C74: 51-8083 | D74: Double Cab (Pickup) | E74: Datzen Motor Pic-Up | F74: — | G74: Diesel | H74: KM | I74: Standard (class avg) | J74: km/L | K74: 12.8 | L74: 10 | M74: 8 | N74: =1 -> 1 | O74: =IF(H74="None",0,IF(H74="KM",IF(G74="Petrol",$D$6,$D$5)*N74/K74,K74*N74*IF(G74="Petrol",$D$6,$D$5))) -> 37.34375 | P74: =IF(H74="None",0,IF(H74="KM",IF(G74="Petrol",$D$6,$D$5)*N74/L74,L74*N74*IF(G74="Petrol",$D$6,$D$5))) -> 47.8 | Q74: =IF(H74="None",0,IF(H74="KM",IF(G74="Petrol",$D$6,$D$5)*N74/M74,M74*N74*IF(G74="Petrol",$D$6,$D$5))) -> 59.75 | R74: =IF(H74="None","—",IF(H74="KM","Rs./km","Rs./hr")) -> Rs./km
A75: 63 | B75: DC-08 | C75: 59-5421 | D75: Double Cab (Pickup) | E75: Isuzu Motor Pic-Up | F75: 1997 | G75: Diesel | H75: KM | I75: Standard (class avg) | J75: km/L | K75: 12.8 | L75: 10 | M75: 8 | N75: =1+MIN(MAX($D$8-F75,0),$D$10)*$D$9 -> 1.175 | O75: =IF(H75="None",0,IF(H75="KM",IF(G75="Petrol",$D$6,$D$5)*N75/K75,K75*N75*IF(G75="Petrol",$D$6,$D$5))) -> 43.878906 | P75: =IF(H75="None",0,IF(H75="KM",IF(G75="Petrol",$D$6,$D$5)*N75/L75,L75*N75*IF(G75="Petrol",$D$6,$D$5))) -> 56.165 | Q75: =IF(H75="None",0,IF(H75="KM",IF(G75="Petrol",$D$6,$D$5)*N75/M75,M75*N75*IF(G75="Petrol",$D$6,$D$5))) -> 70.20625 | R75: =IF(H75="None","—",IF(H75="KM","Rs./km","Rs./hr")) -> Rs./km
A76: 64 | B76: DC-10 | C76: 28-4314 | D76: Double Cab (Pickup) | E76: Datzen Motor Pic-Up | F76: 1985 | G76: Diesel | H76: KM | I76: Standard (class avg) | J76: km/L | K76: 12.8 | L76: 10 | M76: 8 | N76: =1+MIN(MAX($D$8-F76,0),$D$10)*$D$9 -> 1.175 | O76: =IF(H76="None",0,IF(H76="KM",IF(G76="Petrol",$D$6,$D$5)*N76/K76,K76*N76*IF(G76="Petrol",$D$6,$D$5))) -> 43.878906 | P76: =IF(H76="None",0,IF(H76="KM",IF(G76="Petrol",$D$6,$D$5)*N76/L76,L76*N76*IF(G76="Petrol",$D$6,$D$5))) -> 56.165 | Q76: =IF(H76="None",0,IF(H76="KM",IF(G76="Petrol",$D$6,$D$5)*N76/M76,M76*N76*IF(G76="Petrol",$D$6,$D$5))) -> 70.20625 | R76: =IF(H76="None","—",IF(H76="KM","Rs./km","Rs./hr")) -> Rs./km
A77: 65 | B77: DC-11 | C77: HU-5097 | D77: Double Cab (Pickup) | E77: Mitsubishi L 200 | F77: 2003 | G77: Diesel | H77: KM | I77: Standard (class avg) | J77: km/L | K77: 12.8 | L77: 10 | M77: 8 | N77: =1+MIN(MAX($D$8-F77,0),$D$10)*$D$9 -> 1.161 | O77: =IF(H77="None",0,IF(H77="KM",IF(G77="Petrol",$D$6,$D$5)*N77/K77,K77*N77*IF(G77="Petrol",$D$6,$D$5))) -> 43.356094 | P77: =IF(H77="None",0,IF(H77="KM",IF(G77="Petrol",$D$6,$D$5)*N77/L77,L77*N77*IF(G77="Petrol",$D$6,$D$5))) -> 55.4958 | Q77: =IF(H77="None",0,IF(H77="KM",IF(G77="Petrol",$D$6,$D$5)*N77/M77,M77*N77*IF(G77="Petrol",$D$6,$D$5))) -> 69.36975 | R77: =IF(H77="None","—",IF(H77="KM","Rs./km","Rs./hr")) -> Rs./km
A78: 66 | B78: DC-12 | C78: 253-2574 | D78: Double Cab (Pickup) | E78: Mitsubishi Motor Pic-Up | F78: 1999 | G78: Diesel | H78: KM | I78: Standard (class avg) | J78: km/L | K78: 12.8 | L78: 10 | M78: 8 | N78: =1+MIN(MAX($D$8-F78,0),$D$10)*$D$9 -> 1.175 | O78: =IF(H78="None",0,IF(H78="KM",IF(G78="Petrol",$D$6,$D$5)*N78/K78,K78*N78*IF(G78="Petrol",$D$6,$D$5))) -> 43.878906 | P78: =IF(H78="None",0,IF(H78="KM",IF(G78="Petrol",$D$6,$D$5)*N78/L78,L78*N78*IF(G78="Petrol",$D$6,$D$5))) -> 56.165 | Q78: =IF(H78="None",0,IF(H78="KM",IF(G78="Petrol",$D$6,$D$5)*N78/M78,M78*N78*IF(G78="Petrol",$D$6,$D$5))) -> 70.20625 | R78: =IF(H78="None","—",IF(H78="KM","Rs./km","Rs./hr")) -> Rs./km
A79: 67 | B79: DC-14 | C79: PD-6917 | D79: Double Cab (Pickup) | E79: Mahindra Bolero Camper Gold | F79: 2011 | G79: Diesel | H79: KM | I79: Standard (class avg) | J79: km/L | K79: 12.8 | L79: 10 | M79: 8 | N79: =1+MIN(MAX($D$8-F79,0),$D$10)*$D$9 -> 1.105 | O79: =IF(H79="None",0,IF(H79="KM",IF(G79="Petrol",$D$6,$D$5)*N79/K79,K79*N79*IF(G79="Petrol",$D$6,$D$5))) -> 41.264844 | P79: =IF(H79="None",0,IF(H79="KM",IF(G79="Petrol",$D$6,$D$5)*N79/L79,L79*N79*IF(G79="Petrol",$D$6,$D$5))) -> 52.819 | Q79: =IF(H79="None",0,IF(H79="KM",IF(G79="Petrol",$D$6,$D$5)*N79/M79,M79*N79*IF(G79="Petrol",$D$6,$D$5))) -> 66.02375 | R79: =IF(H79="None","—",IF(H79="KM","Rs./km","Rs./hr")) -> Rs./km
A80: 68 | B80: DC-15 | C80: PE-6582 | D80: Double Cab (Pickup) | E80: Mitsubishi L 200 | F80: 2008 | G80: Diesel | H80: KM | I80: Standard (class avg) | J80: km/L | K80: 12.8 | L80: 10 | M80: 8 | N80: =1+MIN(MAX($D$8-F80,0),$D$10)*$D$9 -> 1.126 | O80: =IF(H80="None",0,IF(H80="KM",IF(G80="Petrol",$D$6,$D$5)*N80/K80,K80*N80*IF(G80="Petrol",$D$6,$D$5))) -> 42.049062 | P80: =IF(H80="None",0,IF(H80="KM",IF(G80="Petrol",$D$6,$D$5)*N80/L80,L80*N80*IF(G80="Petrol",$D$6,$D$5))) -> 53.8228 | Q80: =IF(H80="None",0,IF(H80="KM",IF(G80="Petrol",$D$6,$D$5)*N80/M80,M80*N80*IF(G80="Petrol",$D$6,$D$5))) -> 67.2785 | R80: =IF(H80="None","—",IF(H80="KM","Rs./km","Rs./hr")) -> Rs./km
A81: 69 | B81: DC-16 | C81: PA-4102 | D81: Double Cab (Pickup) | E81: Volkswagon T5 Transporter | F81: 2005 | G81: Diesel | H81: KM | I81: Standard (class avg) | J81: km/L | K81: 12.8 | L81: 10 | M81: 8 | N81: =1+MIN(MAX($D$8-F81,0),$D$10)*$D$9 -> 1.147 | O81: =IF(H81="None",0,IF(H81="KM",IF(G81="Petrol",$D$6,$D$5)*N81/K81,K81*N81*IF(G81="Petrol",$D$6,$D$5))) -> 42.833281 | P81: =IF(H81="None",0,IF(H81="KM",IF(G81="Petrol",$D$6,$D$5)*N81/L81,L81*N81*IF(G81="Petrol",$D$6,$D$5))) -> 54.8266 | Q81: =IF(H81="None",0,IF(H81="KM",IF(G81="Petrol",$D$6,$D$5)*N81/M81,M81*N81*IF(G81="Petrol",$D$6,$D$5))) -> 68.53325 | R81: =IF(H81="None","—",IF(H81="KM","Rs./km","Rs./hr")) -> Rs./km
A82: 70 | B82: DC-18 | C82: PE-5879 | D82: Double Cab (Pickup) | E82: Toyota Hilux Vigo | F82: 2008 | G82: Diesel | H82: KM | I82: Standard (class avg) | J82: km/L | K82: 12.8 | L82: 10 | M82: 8 | N82: =1+MIN(MAX($D$8-F82,0),$D$10)*$D$9 -> 1.126 | O82: =IF(H82="None",0,IF(H82="KM",IF(G82="Petrol",$D$6,$D$5)*N82/K82,K82*N82*IF(G82="Petrol",$D$6,$D$5))) -> 42.049062 | P82: =IF(H82="None",0,IF(H82="KM",IF(G82="Petrol",$D$6,$D$5)*N82/L82,L82*N82*IF(G82="Petrol",$D$6,$D$5))) -> 53.8228 | Q82: =IF(H82="None",0,IF(H82="KM",IF(G82="Petrol",$D$6,$D$5)*N82/M82,M82*N82*IF(G82="Petrol",$D$6,$D$5))) -> 67.2785 | R82: =IF(H82="None","—",IF(H82="KM","Rs./km","Rs./hr")) -> Rs./km
A83: 71 | B83: DC-19 | C83: PD-8451 | D83: Double Cab (Pickup) | E83: Toyota Hilux Vigo | F83: 2007 | G83: Diesel | H83: KM | I83: Standard (class avg) | J83: km/L | K83: 12.8 | L83: 10 | M83: 8 | N83: =1+MIN(MAX($D$8-F83,0),$D$10)*$D$9 -> 1.133 | O83: =IF(H83="None",0,IF(H83="KM",IF(G83="Petrol",$D$6,$D$5)*N83/K83,K83*N83*IF(G83="Petrol",$D$6,$D$5))) -> 42.310469 | P83: =IF(H83="None",0,IF(H83="KM",IF(G83="Petrol",$D$6,$D$5)*N83/L83,L83*N83*IF(G83="Petrol",$D$6,$D$5))) -> 54.1574 | Q83: =IF(H83="None",0,IF(H83="KM",IF(G83="Petrol",$D$6,$D$5)*N83/M83,M83*N83*IF(G83="Petrol",$D$6,$D$5))) -> 67.69675 | R83: =IF(H83="None","—",IF(H83="KM","Rs./km","Rs./hr")) -> Rs./km
A84: 72 | B84: DC-20 | C84: PH-0765 | D84: Double Cab (Pickup) | E84: Mahindra Bolero Camper Gold | F84: 2015 | G84: Diesel | H84: KM | I84: Standard (class avg) | J84: km/L | K84: 12.8 | L84: 10 | M84: 8 | N84: =1+MIN(MAX($D$8-F84,0),$D$10)*$D$9 -> 1.077 | O84: =IF(H84="None",0,IF(H84="KM",IF(G84="Petrol",$D$6,$D$5)*N84/K84,K84*N84*IF(G84="Petrol",$D$6,$D$5))) -> 40.219219 | P84: =IF(H84="None",0,IF(H84="KM",IF(G84="Petrol",$D$6,$D$5)*N84/L84,L84*N84*IF(G84="Petrol",$D$6,$D$5))) -> 51.4806 | Q84: =IF(H84="None",0,IF(H84="KM",IF(G84="Petrol",$D$6,$D$5)*N84/M84,M84*N84*IF(G84="Petrol",$D$6,$D$5))) -> 64.35075 | R84: =IF(H84="None","—",IF(H84="KM","Rs./km","Rs./hr")) -> Rs./km
A85: 73 | B85: DC-21 | C85: PH-3945 | D85: Double Cab (Pickup) | E85: Mahindra Imperio Dcvx | F85: 2016 | G85: Diesel | H85: KM | I85: Standard (class avg) | J85: km/L | K85: 12.8 | L85: 10 | M85: 8 | N85: =1+MIN(MAX($D$8-F85,0),$D$10)*$D$9 -> 1.07 | O85: =IF(H85="None",0,IF(H85="KM",IF(G85="Petrol",$D$6,$D$5)*N85/K85,K85*N85*IF(G85="Petrol",$D$6,$D$5))) -> 39.957813 | P85: =IF(H85="None",0,IF(H85="KM",IF(G85="Petrol",$D$6,$D$5)*N85/L85,L85*N85*IF(G85="Petrol",$D$6,$D$5))) -> 51.146 | Q85: =IF(H85="None",0,IF(H85="KM",IF(G85="Petrol",$D$6,$D$5)*N85/M85,M85*N85*IF(G85="Petrol",$D$6,$D$5))) -> 63.9325 | R85: =IF(H85="None","—",IF(H85="KM","Rs./km","Rs./hr")) -> Rs./km
A86: 74 | B86: DC-22 | C86: PE-3911 | D86: Double Cab (Pickup) | E86: Toyota Hilux | F86: 2012 | G86: Diesel | H86: KM | I86: Standard (class avg) | J86: km/L | K86: 12.8 | L86: 10 | M86: 8 | N86: =1+MIN(MAX($D$8-F86,0),$D$10)*$D$9 -> 1.098 | O86: =IF(H86="None",0,IF(H86="KM",IF(G86="Petrol",$D$6,$D$5)*N86/K86,K86*N86*IF(G86="Petrol",$D$6,$D$5))) -> 41.003438 | P86: =IF(H86="None",0,IF(H86="KM",IF(G86="Petrol",$D$6,$D$5)*N86/L86,L86*N86*IF(G86="Petrol",$D$6,$D$5))) -> 52.4844 | Q86: =IF(H86="None",0,IF(H86="KM",IF(G86="Petrol",$D$6,$D$5)*N86/M86,M86*N86*IF(G86="Petrol",$D$6,$D$5))) -> 65.6055 | R86: =IF(H86="None","—",IF(H86="KM","Rs./km","Rs./hr")) -> Rs./km
... A96: 84 | B96: DC-32 | C96: PH-9072 | D96: Double Cab (Pickup) | E96: Toyota Hilux | F96: 2017 | G96: Diesel | H96: KM | I96: Standard (class avg) | J96: km/L | K96: 12.8 | L96: 10 | M96: 8 | N96: =1+MIN(MAX($D$8-F96,0),$D$10)*$D$9 -> 1.063 | O96: =IF(H96="None",0,IF(H96="KM",IF(G96="Petrol",$D$6,$D$5)*N96/K96,K96*N96*IF(G96="Petrol",$D$6,$D$5))) -> 39.696406 | P96: =IF(H96="None",0,IF(H96="KM",IF(G96="Petrol",$D$6,$D$5)*N96/L96,L96*N96*IF(G96="Petrol",$D$6,$D$5))) -> 50.8114 | Q96: =IF(H96="None",0,IF(H96="KM",IF(G96="Petrol",$D$6,$D$5)*N96/M96,M96*N96*IF(G96="Petrol",$D$6,$D$5))) -> 63.51425 | R96: =IF(H96="None","—",IF(H96="KM","Rs./km","Rs./hr")) -> Rs./km
A97: 85 | B97: — | C97: PJ-7604 | D97: Double Cab (Pickup) | E97: Toyota — | F97: — | G97: Diesel | H97: KM | I97: Standard (class avg) | J97: km/L | K97: 12.8 | L97: 10 | M97: 8 | N97: =1 -> 1 | O97: =IF(H97="None",0,IF(H97="KM",IF(G97="Petrol",$D$6,$D$5)*N97/K97,K97*N97*IF(G97="Petrol",$D$6,$D$5))) -> 37.34375 | P97: =IF(H97="None",0,IF(H97="KM",IF(G97="Petrol",$D$6,$D$5)*N97/L97,L97*N97*IF(G97="Petrol",$D$6,$D$5))) -> 47.8 | Q97: =IF(H97="None",0,IF(H97="KM",IF(G97="Petrol",$D$6,$D$5)*N97/M97,M97*N97*IF(G97="Petrol",$D$6,$D$5))) -> 59.75 | R97: =IF(H97="None","—",IF(H97="KM","Rs./km","Rs./hr")) -> Rs./km
A98: 86 | B98: DT-01 | C98: LB-9496 | D98: Dump Truck (Tipper) | E98: Ashok Leland Comet | F98: 2006 | G98: Diesel | H98: KM | I98: Standard ~16t | J98: km/L | K98: 3.8 | L98: 3 | M98: 2.4 | N98: =1+MIN(MAX($D$8-F98,0),$D$10)*$D$9 -> 1.14 | O98: =IF(H98="None",0,IF(H98="KM",IF(G98="Petrol",$D$6,$D$5)*N98/K98,K98*N98*IF(G98="Petrol",$D$6,$D$5))) -> 143.4 | P98: =IF(H98="None",0,IF(H98="KM",IF(G98="Petrol",$D$6,$D$5)*N98/L98,L98*N98*IF(G98="Petrol",$D$6,$D$5))) -> 181.64 | Q98: =IF(H98="None",0,IF(H98="KM",IF(G98="Petrol",$D$6,$D$5)*N98/M98,M98*N98*IF(G98="Petrol",$D$6,$D$5))) -> 227.05 | R98: =IF(H98="None","—",IF(H98="KM","Rs./km","Rs./hr")) -> Rs./km
A99: 87 | B99: DT-02 | C99: LL-0920 | D99: Dump Truck (Tipper) | E99: Tata Lpk 407 | F99: 2013 | G99: Diesel | H99: KM | I99: Light 4t | J99: km/L | K99: 6.4 | L99: 5 | M99: 4 | N99: =1+MIN(MAX($D$8-F99,0),$D$10)*$D$9 -> 1.091 | O99: =IF(H99="None",0,IF(H99="KM",IF(G99="Petrol",$D$6,$D$5)*N99/K99,K99*N99*IF(G99="Petrol",$D$6,$D$5))) -> 81.484062 | P99: =IF(H99="None",0,IF(H99="KM",IF(G99="Petrol",$D$6,$D$5)*N99/L99,L99*N99*IF(G99="Petrol",$D$6,$D$5))) -> 104.2996 | Q99: =IF(H99="None",0,IF(H99="KM",IF(G99="Petrol",$D$6,$D$5)*N99/M99,M99*N99*IF(G99="Petrol",$D$6,$D$5))) -> 130.3745 | R99: =IF(H99="None","—",IF(H99="KM","Rs./km","Rs./hr")) -> Rs./km
A100: 88 | B100: DT-03 | C100: LK-4057 | D100: Dump Truck (Tipper) | E100: Ashok Leland Commet Tipper 1613 | F100: 2012 | G100: Diesel | H100: KM | I100: Standard 16t | J100: km/L | K100: 3.8 | L100: 3 | M100: 2.4 | N100: =1+MIN(MAX($D$8-F100,0),$D$10)*$D$9 -> 1.098 | O100: =IF(H100="None",0,IF(H100="KM",IF(G100="Petrol",$D$6,$D$5)*N100/K100,K100*N100*IF(G100="Petrol",$D$6,$D$5))) -> 138.11684 | P100: =IF(H100="None",0,IF(H100="KM",IF(G100="Petrol",$D$6,$D$5)*N100/L100,L100*N100*IF(G100="Petrol",$D$6,$D$5))) -> 174.948 | Q100: =IF(H100="None",0,IF(H100="KM",IF(G100="Petrol",$D$6,$D$5)*N100/M100,M100*N100*IF(G100="Petrol",$D$6,$D$5))) -> 218.685 | R100: =IF(H100="None","—",IF(H100="KM","Rs./km","Rs./hr")) -> Rs./km
A101: 89 | B101: DT-04 | C101: HS-1794 | D101: Dump Truck (Tipper) | E101: Ashok Leland Comet | F101: 2003 | G101: Diesel | H101: KM | I101: Standard ~16t | J101: km/L | K101: 3.8 | L101: 3 | M101: 2.4 | N101: =1+MIN(MAX($D$8-F101,0),$D$10)*$D$9 -> 1.161 | O101: =IF(H101="None",0,IF(H101="KM",IF(G101="Petrol",$D$6,$D$5)*N101/K101,K101*N101*IF(G101="Petrol",$D$6,$D$5))) -> 146.04158 | P101: =IF(H101="None",0,IF(H101="KM",IF(G101="Petrol",$D$6,$D$5)*N101/L101,L101*N101*IF(G101="Petrol",$D$6,$D$5))) -> 184.986 | Q101: =IF(H101="None",0,IF(H101="KM",IF(G101="Petrol",$D$6,$D$5)*N101/M101,M101*N101*IF(G101="Petrol",$D$6,$D$5))) -> 231.2325 | R101: =IF(H101="None","—",IF(H101="KM","Rs./km","Rs./hr")) -> Rs./km
A102: 90 | B102: DT-05 | C102: HS-1773 | D102: Dump Truck (Tipper) | E102: Ashok Leland Commet Tipper 1613 | F102: 2003 | G102: Diesel | H102: KM | I102: Standard 16t | J102: km/L | K102: 3.8 | L102: 3 | M102: 2.4 | N102: =1+MIN(MAX($D$8-F102,0),$D$10)*$D$9 -> 1.161 | O102: =IF(H102="None",0,IF(H102="KM",IF(G102="Petrol",$D$6,$D$5)*N102/K102,K102*N102*IF(G102="Petrol",$D$6,$D$5))) -> 146.04158 | P102: =IF(H102="None",0,IF(H102="KM",IF(G102="Petrol",$D$6,$D$5)*N102/L102,L102*N102*IF(G102="Petrol",$D$6,$D$5))) -> 184.986 | Q102: =IF(H102="None",0,IF(H102="KM",IF(G102="Petrol",$D$6,$D$5)*N102/M102,M102*N102*IF(G102="Petrol",$D$6,$D$5))) -> 231.2325 | R102: =IF(H102="None","—",IF(H102="KM","Rs./km","Rs./hr")) -> Rs./km
A103: 91 | B103: DT-07 | C103: LI-7618 | D103: Dump Truck (Tipper) | E103: Tata Lpk 1615 | F103: 2011 | G103: Diesel | H103: KM | I103: Standard 16t | J103: km/L | K103: 3.8 | L103: 3 | M103: 2.4 | N103: =1+MIN(MAX($D$8-F103,0),$D$10)*$D$9 -> 1.105 | O103: =IF(H103="None",0,IF(H103="KM",IF(G103="Petrol",$D$6,$D$5)*N103/K103,K103*N103*IF(G103="Petrol",$D$6,$D$5))) -> 138.99737 | P103: =IF(H103="None",0,IF(H103="KM",IF(G103="Petrol",$D$6,$D$5)*N103/L103,L103*N103*IF(G103="Petrol",$D$6,$D$5))) -> 176.06333 | Q103: =IF(H103="None",0,IF(H103="KM",IF(G103="Petrol",$D$6,$D$5)*N103/M103,M103*N103*IF(G103="Petrol",$D$6,$D$5))) -> 220.07917 | R103: =IF(H103="None","—",IF(H103="KM","Rs./km","Rs./hr")) -> Rs./km
A104: 92 | B104: DT-08 | C104: LI-7620 | D104: Dump Truck (Tipper) | E104: Tata Lpk1618 | F104: 2011 | G104: Diesel | H104: KM | I104: Standard 16t | J104: km/L | K104: 3.8 | L104: 3 | M104: 2.4 | N104: =1+MIN(MAX($D$8-F104,0),$D$10)*$D$9 -> 1.105 | O104: =IF(H104="None",0,IF(H104="KM",IF(G104="Petrol",$D$6,$D$5)*N104/K104,K104*N104*IF(G104="Petrol",$D$6,$D$5))) -> 138.99737 | P104: =IF(H104="None",0,IF(H104="KM",IF(G104="Petrol",$D$6,$D$5)*N104/L104,L104*N104*IF(G104="Petrol",$D$6,$D$5))) -> 176.06333 | Q104: =IF(H104="None",0,IF(H104="KM",IF(G104="Petrol",$D$6,$D$5)*N104/M104,M104*N104*IF(G104="Petrol",$D$6,$D$5))) -> 220.07917 | R104: =IF(H104="None","—",IF(H104="KM","Rs./km","Rs./hr")) -> Rs./km
A105: 93 | B105: DT-09 | C105: LI-7701 | D105: Dump Truck (Tipper) | E105: Tata Lpk1618 | F105: 2011 | G105: Diesel | H105: KM | I105: Standard 16t | J105: km/L | K105: 3.8 | L105: 3 | M105: 2.4 | N105: =1+MIN(MAX($D$8-F105,0),$D$10)*$D$9 -> 1.105 | O105: =IF(H105="None",0,IF(H105="KM",IF(G105="Petrol",$D$6,$D$5)*N105/K105,K105*N105*IF(G105="Petrol",$D$6,$D$5))) -> 138.99737 | P105: =IF(H105="None",0,IF(H105="KM",IF(G105="Petrol",$D$6,$D$5)*N105/L105,L105*N105*IF(G105="Petrol",$D$6,$D$5))) -> 176.06333 | Q105: =IF(H105="None",0,IF(H105="KM",IF(G105="Petrol",$D$6,$D$5)*N105/M105,M105*N105*IF(G105="Petrol",$D$6,$D$5))) -> 220.07917 | R105: =IF(H105="None","—",IF(H105="KM","Rs./km","Rs./hr")) -> Rs./km
A106: 94 | B106: DT-10 | C106: LK-6740 | D106: Dump Truck (Tipper) | E106: Tata Lpk 407 | F106: 2012 | G106: Diesel | H106: KM | I106: Light 4t | J106: km/L | K106: 6.4 | L106: 5 | M106: 4 | N106: =1+MIN(MAX($D$8-F106,0),$D$10)*$D$9 -> 1.098 | O106: =IF(H106="None",0,IF(H106="KM",IF(G106="Petrol",$D$6,$D$5)*N106/K106,K106*N106*IF(G106="Petrol",$D$6,$D$5))) -> 82.006875 | P106: =IF(H106="None",0,IF(H106="KM",IF(G106="Petrol",$D$6,$D$5)*N106/L106,L106*N106*IF(G106="Petrol",$D$6,$D$5))) -> 104.9688 | Q106: =IF(H106="None",0,IF(H106="KM",IF(G106="Petrol",$D$6,$D$5)*N106/M106,M106*N106*IF(G106="Petrol",$D$6,$D$5))) -> 131.211 | R106: =IF(H106="None","—",IF(H106="KM","Rs./km","Rs./hr")) -> Rs./km
A107: 95 | B107: DT-11 | C107: LK-6738 | D107: Dump Truck (Tipper) | E107: Tata Lpk1618 | F107: 2012 | G107: Diesel | H107: KM | I107: Standard 16t | J107: km/L | K107: 3.8 | L107: 3 | M107: 2.4 | N107: =1+MIN(MAX($D$8-F107,0),$D$10)*$D$9 -> 1.098 | O107: =IF(H107="None",0,IF(H107="KM",IF(G107="Petrol",$D$6,$D$5)*N107/K107,K107*N107*IF(G107="Petrol",$D$6,$D$5))) -> 138.11684 | P107: =IF(H107="None",0,IF(H107="KM",IF(G107="Petrol",$D$6,$D$5)*N107/L107,L107*N107*IF(G107="Petrol",$D$6,$D$5))) -> 174.948 | Q107: =IF(H107="None",0,IF(H107="KM",IF(G107="Petrol",$D$6,$D$5)*N107/M107,M107*N107*IF(G107="Petrol",$D$6,$D$5))) -> 218.685 | R107: =IF(H107="None","—",IF(H107="KM","Rs./km","Rs./hr")) -> Rs./km
A108: 96 | B108: DT-12 | C108: LK-2276 | D108: Dump Truck (Tipper) | E108: Tata Lpk 909 | F108: 2012 | G108: Diesel | H108: KM | I108: Medium 9t | J108: km/L | K108: 4.9 | L108: 3.8 | M108: 3 | N108: =1+MIN(MAX($D$8-F108,0),$D$10)*$D$9 -> 1.098 | O108: =IF(H108="None",0,IF(H108="KM",IF(G108="Petrol",$D$6,$D$5)*N108/K108,K108*N108*IF(G108="Petrol",$D$6,$D$5))) -> 107.11102 | P108: =IF(H108="None",0,IF(H108="KM",IF(G108="Petrol",$D$6,$D$5)*N108/L108,L108*N108*IF(G108="Petrol",$D$6,$D$5))) -> 138.11684 | Q108: =IF(H108="None",0,IF(H108="KM",IF(G108="Petrol",$D$6,$D$5)*N108/M108,M108*N108*IF(G108="Petrol",$D$6,$D$5))) -> 174.948 | R108: =IF(H108="None","—",IF(H108="KM","Rs./km","Rs./hr")) -> Rs./km
A109: 97 | B109: DT-13 | C109: LK-2366 | D109: Dump Truck (Tipper) | E109: Tata Lpk1618 | F109: 2012 | G109: Diesel | H109: KM | I109: Standard 16t | J109: km/L | K109: 3.8 | L109: 3 | M109: 2.4 | N109: =1+MIN(MAX($D$8-F109,0),$D$10)*$D$9 -> 1.098 | O109: =IF(H109="None",0,IF(H109="KM",IF(G109="Petrol",$D$6,$D$5)*N109/K109,K109*N109*IF(G109="Petrol",$D$6,$D$5))) -> 138.11684 | P109: =IF(H109="None",0,IF(H109="KM",IF(G109="Petrol",$D$6,$D$5)*N109/L109,L109*N109*IF(G109="Petrol",$D$6,$D$5))) -> 174.948 | Q109: =IF(H109="None",0,IF(H109="KM",IF(G109="Petrol",$D$6,$D$5)*N109/M109,M109*N109*IF(G109="Petrol",$D$6,$D$5))) -> 218.685 | R109: =IF(H109="None","—",IF(H109="KM","Rs./km","Rs./hr")) -> Rs./km
... A193: 181 | B193: HEX-09 | C193: — | D193: Excavator | E193: Komatsu Pc27R-8 | F193: 2009 | G193: Diesel | H193: Hour | I193: Mini 2.7t | J193: L/hr | K193: 2.9 | L193: 4 | M193: 5.4 | N193: =1+MIN(MAX($D$8-F193,0),$D$10)*$D$9 -> 1.119 | O193: =IF(H193="None",0,IF(H193="KM",IF(G193="Petrol",$D$6,$D$5)*N193/K193,K193*N193*IF(G193="Petrol",$D$6,$D$5))) -> 1551.1578 | P193: =IF(H193="None",0,IF(H193="KM",IF(G193="Petrol",$D$6,$D$5)*N193/L193,L193*N193*IF(G193="Petrol",$D$6,$D$5))) -> 2139.528 | Q193: =IF(H193="None",0,IF(H193="KM",IF(G193="Petrol",$D$6,$D$5)*N193/M193,M193*N193*IF(G193="Petrol",$D$6,$D$5))) -> 2888.3628 | R193: =IF(H193="None","—",IF(H193="KM","Rs./km","Rs./hr")) -> Rs./hr
A194: 182 | B194: HEX-12 | C194: — | D194: Excavator | E194: (Unknown) — | F194: — | G194: Diesel | H194: Hour | I194: Standard (assumed) | J194: L/hr | K194: 11.5 | L194: 16 | M194: 21.6 | N194: =1 -> 1 | O194: =IF(H194="None",0,IF(H194="KM",IF(G194="Petrol",$D$6,$D$5)*N194/K194,K194*N194*IF(G194="Petrol",$D$6,$D$5))) -> 5497 | P194: =IF(H194="None",0,IF(H194="KM",IF(G194="Petrol",$D$6,$D$5)*N194/L194,L194*N194*IF(G194="Petrol",$D$6,$D$5))) -> 7648 | Q194: =IF(H194="None",0,IF(H194="KM",IF(G194="Petrol",$D$6,$D$5)*N194/M194,M194*N194*IF(G194="Petrol",$D$6,$D$5))) -> 10324.8 | R194: =IF(H194="None","—",IF(H194="KM","Rs./km","Rs./hr")) -> Rs./hr
A195: 183 | B195: HEX-13 | C195: — | D195: Excavator | E195: Kubota U-25-35 | F195: 2010 | G195: Diesel | H195: Hour | I195: Mini 2.5t | J195: L/hr | K195: 2.9 | L195: 4 | M195: 5.4 | N195: =1+MIN(MAX($D$8-F195,0),$D$10)*$D$9 -> 1.112 | O195: =IF(H195="None",0,IF(H195="KM",IF(G195="Petrol",$D$6,$D$5)*N195/K195,K195*N195*IF(G195="Petrol",$D$6,$D$5))) -> 1541.4544 | P195: =IF(H195="None",0,IF(H195="KM",IF(G195="Petrol",$D$6,$D$5)*N195/L195,L195*N195*IF(G195="Petrol",$D$6,$D$5))) -> 2126.144 | Q195: =IF(H195="None",0,IF(H195="KM",IF(G195="Petrol",$D$6,$D$5)*N195/M195,M195*N195*IF(G195="Petrol",$D$6,$D$5))) -> 2870.2944 | R195: =IF(H195="None","—",IF(H195="KM","Rs./km","Rs./hr")) -> Rs./hr
A196: 184 | B196: HEX-14 | C196: — | D196: Excavator | E196: Cat 303 Cr | F196: 2014 | G196: Diesel | H196: Hour | I196: Mini 3t | J196: L/hr | K196: 2.9 | L196: 4 | M196: 5.4 | N196: =1+MIN(MAX($D$8-F196,0),$D$10)*$D$9 -> 1.084 | O196: =IF(H196="None",0,IF(H196="KM",IF(G196="Petrol",$D$6,$D$5)*N196/K196,K196*N196*IF(G196="Petrol",$D$6,$D$5))) -> 1502.6408 | P196: =IF(H196="None",0,IF(H196="KM",IF(G196="Petrol",$D$6,$D$5)*N196/L196,L196*N196*IF(G196="Petrol",$D$6,$D$5))) -> 2072.608 | Q196: =IF(H196="None",0,IF(H196="KM",IF(G196="Petrol",$D$6,$D$5)*N196/M196,M196*N196*IF(G196="Petrol",$D$6,$D$5))) -> 2798.0208 | R196: =IF(H196="None","—",IF(H196="KM","Rs./km","Rs./hr")) -> Rs./hr
A197: 185 | B197: HEX-15 | C197: — | D197: Excavator | E197: Kubota Kx-040 | F197: 2013 | G197: Diesel | H197: Hour | I197: Mini 4t | J197: L/hr | K197: 2.9 | L197: 4 | M197: 5.4 | N197: =1+MIN(MAX($D$8-F197,0),$D$10)*$D$9 -> 1.091 | O197: =IF(H197="None",0,IF(H197="KM",IF(G197="Petrol",$D$6,$D$5)*N197/K197,K197*N197*IF(G197="Petrol",$D$6,$D$5))) -> 1512.3442 | P197: =IF(H197="None",0,IF(H197="KM",IF(G197="Petrol",$D$6,$D$5)*N197/L197,L197*N197*IF(G197="Petrol",$D$6,$D$5))) -> 2085.992 | Q197: =IF(H197="None",0,IF(H197="KM",IF(G197="Petrol",$D$6,$D$5)*N197/M197,M197*N197*IF(G197="Petrol",$D$6,$D$5))) -> 2816.0892 | R197: =IF(H197="None","—",IF(H197="KM","Rs./km","Rs./hr")) -> Rs./hr
A198: 186 | B198: HEX-17 | C198: — | D198: Excavator | E198: Hyundai 0Bex220Lc-9S | F198: — | G198: Diesel | H198: Hour | I198: Standard 22t | J198: L/hr | K198: 11.5 | L198: 16 | M198: 21.6 | N198: =1 -> 1 | O198: =IF(H198="None",0,IF(H198="KM",IF(G198="Petrol",$D$6,$D$5)*N198/K198,K198*N198*IF(G198="Petrol",$D$6,$D$5))) -> 5497 | P198: =IF(H198="None",0,IF(H198="KM",IF(G198="Petrol",$D$6,$D$5)*N198/L198,L198*N198*IF(G198="Petrol",$D$6,$D$5))) -> 7648 | Q198: =IF(H198="None",0,IF(H198="KM",IF(G198="Petrol",$D$6,$D$5)*N198/M198,M198*N198*IF(G198="Petrol",$D$6,$D$5))) -> 10324.8 | R198: =IF(H198="None","—",IF(H198="KM","Rs./km","Rs./hr")) -> Rs./hr
A199: 187 | B199: HEX-18 | C199: — | D199: Excavator | E199: Hithachi Ex75Ur-3 | F199: 2014 | G199: Diesel | H199: Hour | I199: Compact 7.5t | J199: L/hr | K199: 4.7 | L199: 6.5 | M199: 8.8 | N199: =1+MIN(MAX($D$8-F199,0),$D$10)*$D$9 -> 1.084 | O199: =IF(H199="None",0,IF(H199="KM",IF(G199="Petrol",$D$6,$D$5)*N199/K199,K199*N199*IF(G199="Petrol",$D$6,$D$5))) -> 2435.3144 | P199: =IF(H199="None",0,IF(H199="KM",IF(G199="Petrol",$D$6,$D$5)*N199/L199,L199*N199*IF(G199="Petrol",$D$6,$D$5))) -> 3367.988 | Q199: =IF(H199="None",0,IF(H199="KM",IF(G199="Petrol",$D$6,$D$5)*N199/M199,M199*N199*IF(G199="Petrol",$D$6,$D$5))) -> 4559.7376 | R199: =IF(H199="None","—",IF(H199="KM","Rs./km","Rs./hr")) -> Rs./hr
A200: 188 | B200: HEX-19 | C200: — | D200: Excavator | E200: Komatsu Pc-120-6Eo | F200: 2009 | G200: Diesel | H200: Hour | I200: Midi 12t | J200: L/hr | K200: 7.2 | L200: 10 | M200: 13.5 | N200: =1+MIN(MAX($D$8-F200,0),$D$10)*$D$9 -> 1.119 | O200: =IF(H200="None",0,IF(H200="KM",IF(G200="Petrol",$D$6,$D$5)*N200/K200,K200*N200*IF(G200="Petrol",$D$6,$D$5))) -> 3851.1504 | P200: =IF(H200="None",0,IF(H200="KM",IF(G200="Petrol",$D$6,$D$5)*N200/L200,L200*N200*IF(G200="Petrol",$D$6,$D$5))) -> 5348.82 | Q200: =IF(H200="None",0,IF(H200="KM",IF(G200="Petrol",$D$6,$D$5)*N200/M200,M200*N200*IF(G200="Petrol",$D$6,$D$5))) -> 7220.907 | R200: =IF(H200="None","—",IF(H200="KM","Rs./km","Rs./hr")) -> Rs./hr
A201: 189 | B201: HEX-20 | C201: — | D201: Excavator | E201: Komatsu Pc-40Mr-02 | F201: 2009 | G201: Diesel | H201: Hour | I201: Mini 4t | J201: L/hr | K201: 2.9 | L201: 4 | M201: 5.4 | N201: =1+MIN(MAX($D$8-F201,0),$D$10)*$D$9 -> 1.119 | O201: =IF(H201="None",0,IF(H201="KM",IF(G201="Petrol",$D$6,$D$5)*N201/K201,K201*N201*IF(G201="Petrol",$D$6,$D$5))) -> 1551.1578 | P201: =IF(H201="None",0,IF(H201="KM",IF(G201="Petrol",$D$6,$D$5)*N201/L201,L201*N201*IF(G201="Petrol",$D$6,$D$5))) -> 2139.528 | Q201: =IF(H201="None",0,IF(H201="KM",IF(G201="Petrol",$D$6,$D$5)*N201/M201,M201*N201*IF(G201="Petrol",$D$6,$D$5))) -> 2888.3628 | R201: =IF(H201="None","—",IF(H201="KM","Rs./km","Rs./hr")) -> Rs./hr
A202: 190 | B202: HEX-21 | C202: — | D202: Excavator | E202: Kobelko Sk115Sr | F202: 2012 | G202: Diesel | H202: Hour | I202: Midi 11.5t | J202: L/hr | K202: 7.2 | L202: 10 | M202: 13.5 | N202: =1+MIN(MAX($D$8-F202,0),$D$10)*$D$9 -> 1.098 | O202: =IF(H202="None",0,IF(H202="KM",IF(G202="Petrol",$D$6,$D$5)*N202/K202,K202*N202*IF(G202="Petrol",$D$6,$D$5))) -> 3778.8768 | P202: =IF(H202="None",0,IF(H202="KM",IF(G202="Petrol",$D$6,$D$5)*N202/L202,L202*N202*IF(G202="Petrol",$D$6,$D$5))) -> 5248.44 | Q202: =IF(H202="None",0,IF(H202="KM",IF(G202="Petrol",$D$6,$D$5)*N202/M202,M202*N202*IF(G202="Petrol",$D$6,$D$5))) -> 7085.394 | R202: =IF(H202="None","—",IF(H202="KM","Rs./km","Rs./hr")) -> Rs./hr
A203: 191 | B203: HEX-22 | C203: — | D203: Excavator | E203: Catapillar 314C | F203: 2014 | G203: Diesel | H203: Hour | I203: Midi 14t | J203: L/hr | K203: 7.2 | L203: 10 | M203: 13.5 | N203: =1+MIN(MAX($D$8-F203,0),$D$10)*$D$9 -> 1.084 | O203: =IF(H203="None",0,IF(H203="KM",IF(G203="Petrol",$D$6,$D$5)*N203/K203,K203*N203*IF(G203="Petrol",$D$6,$D$5))) -> 3730.6944 | P203: =IF(H203="None",0,IF(H203="KM",IF(G203="Petrol",$D$6,$D$5)*N203/L203,L203*N203*IF(G203="Petrol",$D$6,$D$5))) -> 5181.52 | Q203: =IF(H203="None",0,IF(H203="KM",IF(G203="Petrol",$D$6,$D$5)*N203/M203,M203*N203*IF(G203="Petrol",$D$6,$D$5))) -> 6995.052 | R203: =IF(H203="None","—",IF(H203="KM","Rs./km","Rs./hr")) -> Rs./hr
A204: 192 | B204: HEX-23 | C204: — | D204: Excavator | E204: Kobelko 200 | F204: 2015 | G204: Diesel | H204: Hour | I204: Standard 20t | J204: L/hr | K204: 11.5 | L204: 16 | M204: 21.6 | N204: =1+MIN(MAX($D$8-F204,0),$D$10)*$D$9 -> 1.077 | O204: =IF(H204="None",0,IF(H204="KM",IF(G204="Petrol",$D$6,$D$5)*N204/K204,K204*N204*IF(G204="Petrol",$D$6,$D$5))) -> 5920.269 | P204: =IF(H204="None",0,IF(H204="KM",IF(G204="Petrol",$D$6,$D$5)*N204/L204,L204*N204*IF(G204="Petrol",$D$6,$D$5))) -> 8236.896 | Q204: =IF(H204="None",0,IF(H204="KM",IF(G204="Petrol",$D$6,$D$5)*N204/M204,M204*N204*IF(G204="Petrol",$D$6,$D$5))) -> 11119.81 | R204: =IF(H204="None","—",IF(H204="KM","Rs./km","Rs./hr")) -> Rs./hr
A205: 193 | B205: HEX-24 | C205: — | D205: Excavator | E205: Komatsu Pc-40Mr-1 | F205: 2012 | G205: Diesel | H205: Hour | I205: Mini 4t | J205: L/hr | K205: 2.9 | L205: 4 | M205: 5.4 | N205: =1+MIN(MAX($D$8-F205,0),$D$10)*$D$9 -> 1.098 | O205: =IF(H205="None",0,IF(H205="KM",IF(G205="Petrol",$D$6,$D$5)*N205/K205,K205*N205*IF(G205="Petrol",$D$6,$D$5))) -> 1522.0476 | P205: =IF(H205="None",0,IF(H205="KM",IF(G205="Petrol",$D$6,$D$5)*N205/L205,L205*N205*IF(G205="Petrol",$D$6,$D$5))) -> 2099.376 | Q205: =IF(H205="None",0,IF(H205="KM",IF(G205="Petrol",$D$6,$D$5)*N205/M205,M205*N205*IF(G205="Petrol",$D$6,$D$5))) -> 2834.1576 | R205: =IF(H205="None","—",IF(H205="KM","Rs./km","Rs./hr")) -> Rs./hr
A206: 194 | B206: HEX-25 | C206: 14160 | D206: Excavator | E206: Hyundai R230Lm | F206: 2017 | G206: Diesel | H206: Hour | I206: Standard 20-23t | J206: L/hr | K206: 11.5 | L206: 16 | M206: 21.6 | N206: =1+MIN(MAX($D$8-F206,0),$D$10)*$D$9 -> 1.063 | O206: =IF(H206="None",0,IF(H206="KM",IF(G206="Petrol",$D$6,$D$5)*N206/K206,K206*N206*IF(G206="Petrol",$D$6,$D$5))) -> 5843.311 | P206: =IF(H206="None",0,IF(H206="KM",IF(G206="Petrol",$D$6,$D$5)*N206/L206,L206*N206*IF(G206="Petrol",$D$6,$D$5))) -> 8129.824 | Q206: =IF(H206="None",0,IF(H206="KM",IF(G206="Petrol",$D$6,$D$5)*N206/M206,M206*N206*IF(G206="Petrol",$D$6,$D$5))) -> 10975.262 | R206: =IF(H206="None","—",IF(H206="KM","Rs./km","Rs./hr")) -> Rs./hr
A207: 195 | B207: HEX-26 | C207: — | D207: Excavator | E207: Hyundai Robex330Lc-9S | F207: — | G207: Diesel | H207: Hour | I207: Large 33t | J207: L/hr | K207: 15.8 | L207: 22 | M207: 29.7 | N207: =1 -> 1 | O207: =IF(H207="None",0,IF(H207="KM",IF(G207="Petrol",$D$6,$D$5)*N207/K207,K207*N207*IF(G207="Petrol",$D$6,$D$5))) -> 7552.4 | P207: =IF(H207="None",0,IF(H207="KM",IF(G207="Petrol",$D$6,$D$5)*N207/L207,L207*N207*IF(G207="Petrol",$D$6,$D$5))) -> 10516 | Q207: =IF(H207="None",0,IF(H207="KM",IF(G207="Petrol",$D$6,$D$5)*N207/M207,M207*N207*IF(G207="Petrol",$D$6,$D$5))) -> 14196.6 | R207: =IF(H207="None","—",IF(H207="KM","Rs./km","Rs./hr")) -> Rs./hr
A208: 196 | B208: HEX-27 | C208: — | D208: Excavator | E208: Hyundai E55W | F208: — | G208: Diesel | H208: Hour | I208: Mini 5.5t | J208: L/hr | K208: 2.9 | L208: 4 | M208: 5.4 | N208: =1 -> 1 | O208: =IF(H208="None",0,IF(H208="KM",IF(G208="Petrol",$D$6,$D$5)*N208/K208,K208*N208*IF(G208="Petrol",$D$6,$D$5))) -> 1386.2 | P208: =IF(H208="None",0,IF(H208="KM",IF(G208="Petrol",$D$6,$D$5)*N208/L208,L208*N208*IF(G208="Petrol",$D$6,$D$5))) -> 1912 | Q208: =IF(H208="None",0,IF(H208="KM",IF(G208="Petrol",$D$6,$D$5)*N208/M208,M208*N208*IF(G208="Petrol",$D$6,$D$5))) -> 2581.2 | R208: =IF(H208="None","—",IF(H208="KM","Rs./km","Rs./hr")) -> Rs./hr
A209: 197 | B209: HEX-28 | C209: — | D209: Excavator | E209: Komatsu Pc-60-6 | F209: 2012 | G209: Diesel | H209: Hour | I209: Mini 6t | J209: L/hr | K209: 2.9 | L209: 4 | M209: 5.4 | N209: =1+MIN(MAX($D$8-F209,0),$D$10)*$D$9 -> 1.098 | O209: =IF(H209="None",0,IF(H209="KM",IF(G209="Petrol",$D$6,$D$5)*N209/K209,K209*N209*IF(G209="Petrol",$D$6,$D$5))) -> 1522.0476 | P209: =IF(H209="None",0,IF(H209="KM",IF(G209="Petrol",$D$6,$D$5)*N209/L209,L209*N209*IF(G209="Petrol",$D$6,$D$5))) -> 2099.376 | Q209: =IF(H209="None",0,IF(H209="KM",IF(G209="Petrol",$D$6,$D$5)*N209/M209,M209*N209*IF(G209="Petrol",$D$6,$D$5))) -> 2834.1576 | R209: =IF(H209="None","—",IF(H209="KM","Rs./km","Rs./hr")) -> Rs./hr
A210: 198 | B210: HEX-29 | C210: — | D210: Excavator | E210: Cat Cat308Ccr | F210: 2013 | G210: Diesel | H210: Hour | I210: Compact 8t | J210: L/hr | K210: 4.7 | L210: 6.5 | M210: 8.8 | N210: =1+MIN(MAX($D$8-F210,0),$D$10)*$D$9 -> 1.091 | O210: =IF(H210="None",0,IF(H210="KM",IF(G210="Petrol",$D$6,$D$5)*N210/K210,K210*N210*IF(G210="Petrol",$D$6,$D$5))) -> 2451.0406 | P210: =IF(H210="None",0,IF(H210="KM",IF(G210="Petrol",$D$6,$D$5)*N210/L210,L210*N210*IF(G210="Petrol",$D$6,$D$5))) -> 3389.737 | Q210: =IF(H210="None",0,IF(H210="KM",IF(G210="Petrol",$D$6,$D$5)*N210/M210,M210*N210*IF(G210="Petrol",$D$6,$D$5))) -> 4589.1824 | R210: =IF(H210="None","—",IF(H210="KM","Rs./km","Rs./hr")) -> Rs./hr
A211: 199 | B211: HEX-31 | C211: — | D211: Excavator | E211: Komatsu Pc-30 | F211: 2014 | G211: Diesel | H211: Hour | I211: Mini 3t | J211: L/hr | K211: 2.9 | L211: 4 | M211: 5.4 | N211: =1+MIN(MAX($D$8-F211,0),$D$10)*$D$9 -> 1.084 | O211: =IF(H211="None",0,IF(H211="KM",IF(G211="Petrol",$D$6,$D$5)*N211/K211,K211*N211*IF(G211="Petrol",$D$6,$D$5))) -> 1502.6408 | P211: =IF(H211="None",0,IF(H211="KM",IF(G211="Petrol",$D$6,$D$5)*N211/L211,L211*N211*IF(G211="Petrol",$D$6,$D$5))) -> 2072.608 | Q211: =IF(H211="None",0,IF(H211="KM",IF(G211="Petrol",$D$6,$D$5)*N211/M211,M211*N211*IF(G211="Petrol",$D$6,$D$5))) -> 2798.0208 | R211: =IF(H211="None","—",IF(H211="KM","Rs./km","Rs./hr")) -> Rs./hr
A212: 200 | B212: HEX-32 | C212: 14160 | D212: Excavator | E212: Hyundai R230Lm | F212: 2017 | G212: Diesel | H212: Hour | I212: Standard 20-23t | J212: L/hr | K212: 11.5 | L212: 16 | M212: 21.6 | N212: =1+MIN(MAX($D$8-F212,0),$D$10)*$D$9 -> 1.063 | O212: =IF(H212="None",0,IF(H212="KM",IF(G212="Petrol",$D$6,$D$5)*N212/K212,K212*N212*IF(G212="Petrol",$D$6,$D$5))) -> 5843.311 | P212: =IF(H212="None",0,IF(H212="KM",IF(G212="Petrol",$D$6,$D$5)*N212/L212,L212*N212*IF(G212="Petrol",$D$6,$D$5))) -> 8129.824 | Q212: =IF(H212="None",0,IF(H212="KM",IF(G212="Petrol",$D$6,$D$5)*N212/M212,M212*N212*IF(G212="Petrol",$D$6,$D$5))) -> 10975.262 | R212: =IF(H212="None","—",IF(H212="KM","Rs./km","Rs./hr")) -> Rs./hr
A213: 201 | B213: HEX-33 | C213: 14160 | D213: Excavator | E213: Hyundai R230Lm | F213: 2017 | G213: Diesel | H213: Hour | I213: Standard 20-23t | J213: L/hr | K213: 11.5 | L213: 16 | M213: 21.6 | N213: =1+MIN(MAX($D$8-F213,0),$D$10)*$D$9 -> 1.063 | O213: =IF(H213="None",0,IF(H213="KM",IF(G213="Petrol",$D$6,$D$5)*N213/K213,K213*N213*IF(G213="Petrol",$D$6,$D$5))) -> 5843.311 | P213: =IF(H213="None",0,IF(H213="KM",IF(G213="Petrol",$D$6,$D$5)*N213/L213,L213*N213*IF(G213="Petrol",$D$6,$D$5))) -> 8129.824 | Q213: =IF(H213="None",0,IF(H213="KM",IF(G213="Petrol",$D$6,$D$5)*N213/M213,M213*N213*IF(G213="Petrol",$D$6,$D$5))) -> 10975.262 | R213: =IF(H213="None","—",IF(H213="KM","Rs./km","Rs./hr")) -> Rs./hr
A214: 202 | B214: HEX-34 | C214: — | D214: Excavator | E214: Hyundai R220Lc-9S | F214: 2017 | G214: Diesel | H214: Hour | I214: Standard 22t | J214: L/hr | K214: 11.5 | L214: 16 | M214: 21.6 | N214: =1+MIN(MAX($D$8-F214,0),$D$10)*$D$9 -> 1.063 | O214: =IF(H214="None",0,IF(H214="KM",IF(G214="Petrol",$D$6,$D$5)*N214/K214,K214*N214*IF(G214="Petrol",$D$6,$D$5))) -> 5843.311 | P214: =IF(H214="None",0,IF(H214="KM",IF(G214="Petrol",$D$6,$D$5)*N214/L214,L214*N214*IF(G214="Petrol",$D$6,$D$5))) -> 8129.824 | Q214: =IF(H214="None",0,IF(H214="KM",IF(G214="Petrol",$D$6,$D$5)*N214/M214,M214*N214*IF(G214="Petrol",$D$6,$D$5))) -> 10975.262 | R214: =IF(H214="None","—",IF(H214="KM","Rs./km","Rs./hr")) -> Rs./hr
A215: 203 | B215: HEX-35 | C215: 14160 | D215: Excavator | E215: Hyundai R230Lm | F215: 2017 | G215: Diesel | H215: Hour | I215: Standard 20-23t | J215: L/hr | K215: 11.5 | L215: 16 | M215: 21.6 | N215: =1+MIN(MAX($D$8-F215,0),$D$10)*$D$9 -> 1.063 | O215: =IF(H215="None",0,IF(H215="KM",IF(G215="Petrol",$D$6,$D$5)*N215/K215,K215*N215*IF(G215="Petrol",$D$6,$D$5))) -> 5843.311 | P215: =IF(H215="None",0,IF(H215="KM",IF(G215="Petrol",$D$6,$D$5)*N215/L215,L215*N215*IF(G215="Petrol",$D$6,$D$5))) -> 8129.824 | Q215: =IF(H215="None",0,IF(H215="KM",IF(G215="Petrol",$D$6,$D$5)*N215/M215,M215*N215*IF(G215="Petrol",$D$6,$D$5))) -> 10975.262 | R215: =IF(H215="None","—",IF(H215="KM","Rs./km","Rs./hr")) -> Rs./hr
A216: 204 | B216: HEX-36 | C216: — | D216: Excavator | E216: Hyundai E55W | F216: 2018 | G216: Diesel | H216: Hour | I216: Mini 5.5t | J216: L/hr | K216: 2.9 | L216: 4 | M216: 5.4 | N216: =1+MIN(MAX($D$8-F216,0),$D$10)*$D$9 -> 1.056 | O216: =IF(H216="None",0,IF(H216="KM",IF(G216="Petrol",$D$6,$D$5)*N216/K216,K216*N216*IF(G216="Petrol",$D$6,$D$5))) -> 1463.8272 | P216: =IF(H216="None",0,IF(H216="KM",IF(G216="Petrol",$D$6,$D$5)*N216/L216,L216*N216*IF(G216="Petrol",$D$6,$D$5))) -> 2019.072 | Q216: =IF(H216="None",0,IF(H216="KM",IF(G216="Petrol",$D$6,$D$5)*N216/M216,M216*N216*IF(G216="Petrol",$D$6,$D$5))) -> 2725.7472 | R216: =IF(H216="None","—",IF(H216="KM","Rs./km","Rs./hr")) -> Rs./hr
A217: 205 | B217: HEX-37 | C217: — | D217: Excavator | E217: Hyundai (Robex330Lc-96) | F217: — | G217: Diesel | H217: Hour | I217: Large 33t | J217: L/hr | K217: 15.8 | L217: 22 | M217: 29.7 | N217: =1 -> 1 | O217: =IF(H217="None",0,IF(H217="KM",IF(G217="Petrol",$D$6,$D$5)*N217/K217,K217*N217*IF(G217="Petrol",$D$6,$D$5))) -> 7552.4 | P217: =IF(H217="None",0,IF(H217="KM",IF(G217="Petrol",$D$6,$D$5)*N217/L217,L217*N217*IF(G217="Petrol",$D$6,$D$5))) -> 10516 | Q217: =IF(H217="None",0,IF(H217="KM",IF(G217="Petrol",$D$6,$D$5)*N217/M217,M217*N217*IF(G217="Petrol",$D$6,$D$5))) -> 14196.6 | R217: =IF(H217="None","—",IF(H217="KM","Rs./km","Rs./hr")) -> Rs./hr
A218: 206 | B218: HEX-38 | C218: 14160 | D218: Excavator | E218: Hyundai R230Lm | F218: 2017 | G218: Diesel | H218: Hour | I218: Standard 20-23t | J218: L/hr | K218: 11.5 | L218: 16 | M218: 21.6 | N218: =1+MIN(MAX($D$8-F218,0),$D$10)*$D$9 -> 1.063 | O218: =IF(H218="None",0,IF(H218="KM",IF(G218="Petrol",$D$6,$D$5)*N218/K218,K218*N218*IF(G218="Petrol",$D$6,$D$5))) -> 5843.311 | P218: =IF(H218="None",0,IF(H218="KM",IF(G218="Petrol",$D$6,$D$5)*N218/L218,L218*N218*IF(G218="Petrol",$D$6,$D$5))) -> 8129.824 | Q218: =IF(H218="None",0,IF(H218="KM",IF(G218="Petrol",$D$6,$D$5)*N218/M218,M218*N218*IF(G218="Petrol",$D$6,$D$5))) -> 10975.262 | R218: =IF(H218="None","—",IF(H218="KM","Rs./km","Rs./hr")) -> Rs./hr
A219: 207 | B219: HEX-39 | C219: — | D219: Excavator | E219: Hyundai R220Lc-9S | F219: 2017 | G219: Diesel | H219: Hour | I219: Standard 22t | J219: L/hr | K219: 11.5 | L219: 16 | M219: 21.6 | N219: =1+MIN(MAX($D$8-F219,0),$D$10)*$D$9 -> 1.063 | O219: =IF(H219="None",0,IF(H219="KM",IF(G219="Petrol",$D$6,$D$5)*N219/K219,K219*N219*IF(G219="Petrol",$D$6,$D$5))) -> 5843.311 | P219: =IF(H219="None",0,IF(H219="KM",IF(G219="Petrol",$D$6,$D$5)*N219/L219,L219*N219*IF(G219="Petrol",$D$6,$D$5))) -> 8129.824 | Q219: =IF(H219="None",0,IF(H219="KM",IF(G219="Petrol",$D$6,$D$5)*N219/M219,M219*N219*IF(G219="Petrol",$D$6,$D$5))) -> 10975.262 | R219: =IF(H219="None","—",IF(H219="KM","Rs./km","Rs./hr")) -> Rs./hr
A220: 208 | B220: HEX-40 | C220: — | D220: Excavator | E220: Santui Se210 | F220: — | G220: Diesel | H220: Hour | I220: Standard 21t | J220: L/hr | K220: 11.5 | L220: 16 | M220: 21.6 | N220: =1 -> 1 | O220: =IF(H220="None",0,IF(H220="KM",IF(G220="Petrol",$D$6,$D$5)*N220/K220,K220*N220*IF(G220="Petrol",$D$6,$D$5))) -> 5497 | P220: =IF(H220="None",0,IF(H220="KM",IF(G220="Petrol",$D$6,$D$5)*N220/L220,L220*N220*IF(G220="Petrol",$D$6,$D$5))) -> 7648 | Q220: =IF(H220="None",0,IF(H220="KM",IF(G220="Petrol",$D$6,$D$5)*N220/M220,M220*N220*IF(G220="Petrol",$D$6,$D$5))) -> 10324.8 | R220: =IF(H220="None","—",IF(H220="KM","Rs./km","Rs./hr")) -> Rs./hr
A221: 209 | B221: HEX-41 | C221: — | D221: Excavator | E221: Hyundai 220Lc-7 | F221: — | G221: Diesel | H221: Hour | I221: Standard 22t | J221: L/hr | K221: 11.5 | L221: 16 | M221: 21.6 | N221: =1 -> 1 | O221: =IF(H221="None",0,IF(H221="KM",IF(G221="Petrol",$D$6,$D$5)*N221/K221,K221*N221*IF(G221="Petrol",$D$6,$D$5))) -> 5497 | P221: =IF(H221="None",0,IF(H221="KM",IF(G221="Petrol",$D$6,$D$5)*N221/L221,L221*N221*IF(G221="Petrol",$D$6,$D$5))) -> 7648 | Q221: =IF(H221="None",0,IF(H221="KM",IF(G221="Petrol",$D$6,$D$5)*N221/M221,M221*N221*IF(G221="Petrol",$D$6,$D$5))) -> 10324.8 | R221: =IF(H221="None","—",IF(H221="KM","Rs./km","Rs./hr")) -> Rs./hr
A222: 210 | B222: HEX-42 | C222: — | D222: Excavator | E222: Case Cx220C Lc Hd | F222: 2021 | G222: Diesel | H222: Hour | I222: Standard 22t | J222: L/hr | K222: 11.5 | L222: 16 | M222: 21.6 | N222: =1+MIN(MAX($D$8-F222,0),$D$10)*$D$9 -> 1.035 | O222: =IF(H222="None",0,IF(H222="KM",IF(G222="Petrol",$D$6,$D$5)*N222/K222,K222*N222*IF(G222="Petrol",$D$6,$D$5))) -> 5689.395 | P222: =IF(H222="None",0,IF(H222="KM",IF(G222="Petrol",$D$6,$D$5)*N222/L222,L222*N222*IF(G222="Petrol",$D$6,$D$5))) -> 7915.68 | Q222: =IF(H222="None",0,IF(H222="KM",IF(G222="Petrol",$D$6,$D$5)*N222/M222,M222*N222*IF(G222="Petrol",$D$6,$D$5))) -> 10686.168 | R222: =IF(H222="None","—",IF(H222="KM","Rs./km","Rs./hr")) -> Rs./hr
A223: 211 | B223: HEX-43 | C223: — | D223: Excavator | E223: Case Cx220C Lc Hd | F223: 2021 | G223: Diesel | H223: Hour | I223: Standard 22t | J223: L/hr | K223: 11.5 | L223: 16 | M223: 21.6 | N223: =1+MIN(MAX($D$8-F223,0),$D$10)*$D$9 -> 1.035 | O223: =IF(H223="None",0,IF(H223="KM",IF(G223="Petrol",$D$6,$D$5)*N223/K223,K223*N223*IF(G223="Petrol",$D$6,$D$5))) -> 5689.395 | P223: =IF(H223="None",0,IF(H223="KM",IF(G223="Petrol",$D$6,$D$5)*N223/L223,L223*N223*IF(G223="Petrol",$D$6,$D$5))) -> 7915.68 | Q223: =IF(H223="None",0,IF(H223="KM",IF(G223="Petrol",$D$6,$D$5)*N223/M223,M223*N223*IF(G223="Petrol",$D$6,$D$5))) -> 10686.168 | R223: =IF(H223="None","—",IF(H223="KM","Rs./km","Rs./hr")) -> Rs./hr
A224: 212 | B224: HEX-44 | C224: — | D224: Excavator | E224: Kobelco Sx 120 | F224: — | G224: Diesel | H224: Hour | I224: Midi 12t | J224: L/hr | K224: 7.2 | L224: 10 | M224: 13.5 | N224: =1 -> 1 | O224: =IF(H224="None",0,IF(H224="KM",IF(G224="Petrol",$D$6,$D$5)*N224/K224,K224*N224*IF(G224="Petrol",$D$6,$D$5))) -> 3441.6 | P224: =IF(H224="None",0,IF(H224="KM",IF(G224="Petrol",$D$6,$D$5)*N224/L224,L224*N224*IF(G224="Petrol",$D$6,$D$5))) -> 4780 | Q224: =IF(H224="None",0,IF(H224="KM",IF(G224="Petrol",$D$6,$D$5)*N224/M224,M224*N224*IF(G224="Petrol",$D$6,$D$5))) -> 6453 | R224: =IF(H224="None","—",IF(H224="KM","Rs./km","Rs./hr")) -> Rs./hr
A225: 213 | B225: HEX-45 | C225: — | D225: Excavator | E225: Case Cx220C Lc Hd | F225: 2021 | G225: Diesel | H225: Hour | I225: Standard 22t | J225: L/hr | K225: 11.5 | L225: 16 | M225: 21.6 | N225: =1+MIN(MAX($D$8-F225,0),$D$10)*$D$9 -> 1.035 | O225: =IF(H225="None",0,IF(H225="KM",IF(G225="Petrol",$D$6,$D$5)*N225/K225,K225*N225*IF(G225="Petrol",$D$6,$D$5))) -> 5689.395 | P225: =IF(H225="None",0,IF(H225="KM",IF(G225="Petrol",$D$6,$D$5)*N225/L225,L225*N225*IF(G225="Petrol",$D$6,$D$5))) -> 7915.68 | Q225: =IF(H225="None",0,IF(H225="KM",IF(G225="Petrol",$D$6,$D$5)*N225/M225,M225*N225*IF(G225="Petrol",$D$6,$D$5))) -> 10686.168 | R225: =IF(H225="None","—",IF(H225="KM","Rs./km","Rs./hr")) -> Rs./hr
A226: 214 | B226: HEX-46 | C226: — | D226: Excavator | E226: Case Cx220C Lc Hd | F226: 2021 | G226: Diesel | H226: Hour | I226: Standard 22t | J226: L/hr | K226: 11.5 | L226: 16 | M226: 21.6 | N226: =1+MIN(MAX($D$8-F226,0),$D$10)*$D$9 -> 1.035 | O226: =IF(H226="None",0,IF(H226="KM",IF(G226="Petrol",$D$6,$D$5)*N226/K226,K226*N226*IF(G226="Petrol",$D$6,$D$5))) -> 5689.395 | P226: =IF(H226="None",0,IF(H226="KM",IF(G226="Petrol",$D$6,$D$5)*N226/L226,L226*N226*IF(G226="Petrol",$D$6,$D$5))) -> 7915.68 | Q226: =IF(H226="None",0,IF(H226="KM",IF(G226="Petrol",$D$6,$D$5)*N226/M226,M226*N226*IF(G226="Petrol",$D$6,$D$5))) -> 10686.168 | R226: =IF(H226="None","—",IF(H226="KM","Rs./km","Rs./hr")) -> Rs./hr
A227: 215 | B227: FT-02 | C227: 49-2289 | D227: Farm Tractor | E227: Massey Furguson 135 | F227: 1974 | G227: Diesel | H227: Hour | I227: Standard (class avg) | J227: L/hr | K227: 4.3 | L227: 6 | M227: 8.1 | N227: =1+MIN(MAX($D$8-F227,0),$D$10)*$D$9 -> 1.175 | O227: =IF(H227="None",0,IF(H227="KM",IF(G227="Petrol",$D$6,$D$5)*N227/K227,K227*N227*IF(G227="Petrol",$D$6,$D$5))) -> 2415.095 | P227: =IF(H227="None",0,IF(H227="KM",IF(G227="Petrol",$D$6,$D$5)*N227/L227,L227*N227*IF(G227="Petrol",$D$6,$D$5))) -> 3369.9 | Q227: =IF(H227="None",0,IF(H227="KM",IF(G227="Petrol",$D$6,$D$5)*N227/M227,M227*N227*IF(G227="Petrol",$D$6,$D$5))) -> 4549.365 | R227: =IF(H227="None","—",IF(H227="KM","Rs./km","Rs./hr")) -> Rs./hr
A228: 216 | B228: FT-03 | C228: RA-3051 | D228: Farm Tractor | E228: Tafe 45Di | F228: 2005 | G228: Diesel | H228: Hour | I228: Standard (class avg) | J228: L/hr | K228: 4.3 | L228: 6 | M228: 8.1 | N228: =1+MIN(MAX($D$8-F228,0),$D$10)*$D$9 -> 1.147 | O228: =IF(H228="None",0,IF(H228="KM",IF(G228="Petrol",$D$6,$D$5)*N228/K228,K228*N228*IF(G228="Petrol",$D$6,$D$5))) -> 2357.5438 | P228: =IF(H228="None",0,IF(H228="KM",IF(G228="Petrol",$D$6,$D$5)*N228/L228,L228*N228*IF(G228="Petrol",$D$6,$D$5))) -> 3289.596 | Q228: =IF(H228="None",0,IF(H228="KM",IF(G228="Petrol",$D$6,$D$5)*N228/M228,M228*N228*IF(G228="Petrol",$D$6,$D$5))) -> 4440.9546 | R228: =IF(H228="None","—",IF(H228="KM","Rs./km","Rs./hr")) -> Rs./hr
A229: 217 | B229: FT-04 | C229: RA-3052 | D229: Farm Tractor | E229: Tafe 45Di | F229: 2005 | G229: Diesel | H229: Hour | I229: Standard (class avg) | J229: L/hr | K229: 4.3 | L229: 6 | M229: 8.1 | N229: =1+MIN(MAX($D$8-F229,0),$D$10)*$D$9 -> 1.147 | O229: =IF(H229="None",0,IF(H229="KM",IF(G229="Petrol",$D$6,$D$5)*N229/K229,K229*N229*IF(G229="Petrol",$D$6,$D$5))) -> 2357.5438 | P229: =IF(H229="None",0,IF(H229="KM",IF(G229="Petrol",$D$6,$D$5)*N229/L229,L229*N229*IF(G229="Petrol",$D$6,$D$5))) -> 3289.596 | Q229: =IF(H229="None",0,IF(H229="KM",IF(G229="Petrol",$D$6,$D$5)*N229/M229,M229*N229*IF(G229="Petrol",$D$6,$D$5))) -> 4440.9546 | R229: =IF(H229="None","—",IF(H229="KM","Rs./km","Rs./hr")) -> Rs./hr
A230: 218 | B230: FT-05 | C230: RF-0748 | D230: Farm Tractor | E230: Massey Ferouson Mf 240 | F230: — | G230: Diesel | H230: Hour | I230: Standard (class avg) | J230: L/hr | K230: 4.3 | L230: 6 | M230: 8.1 | N230: =1 -> 1 | O230: =IF(H230="None",0,IF(H230="KM",IF(G230="Petrol",$D$6,$D$5)*N230/K230,K230*N230*IF(G230="Petrol",$D$6,$D$5))) -> 2055.4 | P230: =IF(H230="None",0,IF(H230="KM",IF(G230="Petrol",$D$6,$D$5)*N230/L230,L230*N230*IF(G230="Petrol",$D$6,$D$5))) -> 2868 | Q230: =IF(H230="None",0,IF(H230="KM",IF(G230="Petrol",$D$6,$D$5)*N230/M230,M230*N230*IF(G230="Petrol",$D$6,$D$5))) -> 3871.8 | R230: =IF(H230="None","—",IF(H230="KM","Rs./km","Rs./hr")) -> Rs./hr
...

Sheet Data
B3: Package A
B4: Package B
B5: Package C
