Workbook

Sheet README
A1: FLEET & MACHINERY RENTAL PRICE SHEET — 2026 (3-TIER: DRY / DRY+OPERATOR / WET)
A2: Market: Sri Lanka | Currency: LKR, EXCLUDING 18% VAT | Prepared 04-Jul-2026
A4: RATE DEFINITIONS
A5: DRY — Bare machine/vehicle only. Client supplies fuel, operator/driver, lubricants; tolls, fines, operator food at client cost.
A6: DRY + OPERATOR (dry with driver) — Machine + our trained operator/driver. Fuel & lubricants supplied by client. Fleet: DRY + Rs.800/hr operator charge-out. Machinery: DRY + Rs.3,500/day operator (Rs.5,000/day skilled welder/cutter).
A7: WET (fully wet) — Machine + operator + fuel + routine consumables & normal maintenance. Fleet WET = market-engineered 2026 rate card (validated vs SLLDC & private market). Machinery WET = DRY+OPERATOR + fuel for stated duty hours/day at current CPC price.
A9: FUEL BASIS (edit on 'Fuel & Inputs' — every rate recalculates)
A10: CPC/Ceypetco effective 29-Jun-2026: Auto Diesel Rs.382/L • Petrol 92 Rs.414/L. (Super Diesel Rs.478, Petrol 95 Rs.495, Kerosene Rs.285 — eff. 30-May-2026, reference only.)
A11: 2026 context: Middle-East conflict (Feb-26) + LKR depreciation pushed Auto Diesel from Rs.286 (Jan) to Rs.407 (30-May peak); cut back to Rs.382 on 29-Jun-26. Previous workbook v7 used Rs.478 — that is the SUPER Diesel price; corrected here.
A12: Because Auto Diesel Rs.382 equals the March-2026 engineering basis, the engineering cost floors behind the fleet WET card remain valid at today's pump price.
A14: BILLING RULES
A15: Fleet: hourly card. Daily = hourly x 4 hrs min x 0.95 (5% volume disc). Monthly = hourly x 120 hrs min x 0.85 (15% disc). Extra hours at hourly rate.
... A24: SHEETS: Fuel & Inputs (editable drivers) • Fleet Price Sheet (29 categories x 3 tiers, hourly/daily/monthly) • Machinery Price Sheet (76 items, 5 groups, capacities+efficiency+fuel) • Market Analysis (SL market position & findings).

Sheet Fuel & Inputs
A1: GLOBAL INPUTS — edit BLUE cells; all rates in the workbook recalculate
A3: FUEL PRICES (CPC/Ceypetco pump prices)
A4: Auto Diesel (Rs./litre) | C4: 382 | D4: CPC effective 29-Jun-2026 (cut of Rs.25)
A5: Petrol 92 Octane (Rs./litre) | C5: 414 | D5: CPC effective 29-Jun-2026 (cut of Rs.20)
A6: Super Diesel Euro-4 (Rs./litre) | C6: 478 | D6: Reference — eff. 30-May-2026
A7: Petrol 95 Octane (Rs./litre) | C7: 495 | D7: Reference — eff. 30-May-2026
A8: Kerosene (Rs./litre) | C8: 285 | D8: Reference — eff. 30-May-2026
A10: OPERATOR / DRIVER
A11: Fleet operator/driver cost (Rs./hour) | C11: 650 | D11: Management input, Apr-2026
A12: Loading on operator (EPF/ETF, meals, admin) | C12: 1.23 | D12: 23% loading -> charge-out
A13: Fleet operator charge-out (Rs./hour) | C13: =MROUND(C11*C12,50) -> 800 | D13: cost x loading, rounded to 50
A14: Machinery operator (Rs./day, 8-hr) | C14: 3500 | D14: Semi-skilled plant operator, SL 2026
A15: Skilled welder / gas cutter (Rs./day) | C15: 5000 | D15: For welding plant & gas cutting sets
A17: BILLING FACTORS
A18: Machinery standard working day (hrs) | C18: 8 | D18: Duty hrs per item set on Machinery sheet
A19: Fleet daily minimum (hrs) | C19: 4
A20: Fleet monthly minimum (hrs) | C20: 120
A21: Daily volume factor | C21: 0.95 | D21: 5% discount on hourly x 4
A22: Monthly volume factor | C22: 0.85 | D22: 15% discount on hourly x 120
A23: VAT (add on all rates) | C23: 0.18 | D23: Standard SL rate 2026

Sheet Fleet Price Sheet
A1: FLEET PRICE SHEET 2026 — DRY / DRY + OPERATOR / WET (Rs., excl. 18% VAT)
A2: WET = machine+operator+fuel+maintenance (market-engineered card). DRY+OPERATOR = DRY + operator charge-out (Fuel & Inputs C13). Fuel Rs./hr at CPC Auto Diesel eff. 29-Jun-2026 (motorcycle: Petrol 92). Daily = hourly x 4 x 0.95 • Monthly = hourly x 120 x 0.85. Apply per-unit age factors.
A4: # | B4: Category | C4: Fuel L/hr (typ) | D4: Fuel cost Rs./hr | E4: DRY Rs./hr | F4: DRY+OPERATOR Rs./hr | G4: WET Rs./hr | H4: Fuel recovery in WET (Rs./hr) | I4: Margin check | J4: DRY Rs./day (4h) | K4: DRY+OP Rs./day (4h) | L4: WET Rs./day (4h) | M4: DRY Rs./month (120h) | N4: DRY+OP Rs./month (120h) | O4: WET Rs./month (120h) | P4: Market basis (LOW • HIGH source)
A5: 1 | B5: Backhoe Loader | C5: 5.5 | D5: =MROUND(C5*'Fuel & Inputs'!$C$4,10) -> 2100 | E5: 2000 | F5: =MROUND(E5+'Fuel & Inputs'!$C$13,50) -> 2800 | G5: 4150 | H5: =G5-F5 -> 1350 | I5: =IF(C5=0,"n/a",IF(H5>=D5,"OK","THIN")) -> THIN | J5: =MROUND(E5*'Fuel & Inputs'!$C$19*'Fuel & Inputs'!$C$21,100) -> 7600 | K5: =MROUND(F5*'Fuel & Inputs'!$C$19*'Fuel & Inputs'!$C$21,100) -> 10600 | L5: =MROUND(G5*'Fuel & Inputs'!$C$19*'Fuel & Inputs'!$C$21,100) -> 15800 | M5: =MROUND(E5*'Fuel & Inputs'!$C$20*'Fuel & Inputs'!$C$22,500) -> 204000 | N5: =MROUND(F5*'Fuel & Inputs'!$C$20*'Fuel & Inputs'!$C$22,500) -> 285500 | O5: =MROUND(G5*'Fuel & Inputs'!$C$20*'Fuel & Inputs'!$C$22,500) -> 423500 | P5: LOW: small private/Wedabima • HIGH: SLLDC JCB 3CX
A6: 2 | B6: Wheel Loader | C6: 13 | D6: =MROUND(C6*'Fuel & Inputs'!$C$4,10) -> 4970 | E6: 3800 | F6: =MROUND(E6+'Fuel & Inputs'!$C$13,50) -> 4600 | G6: 8450 | H6: =G6-F6 -> 3850 | I6: =IF(C6=0,"n/a",IF(H6>=D6,"OK","THIN")) -> THIN | J6: =MROUND(E6*'Fuel & Inputs'!$C$19*'Fuel & Inputs'!$C$21,100) -> 14400 | K6: =MROUND(F6*'Fuel & Inputs'!$C$19*'Fuel & Inputs'!$C$21,100) -> 17500 | L6: =MROUND(G6*'Fuel & Inputs'!$C$19*'Fuel & Inputs'!$C$21,100) -> 32100 | M6: =MROUND(E6*'Fuel & Inputs'!$C$20*'Fuel & Inputs'!$C$22,500) -> 387500 | N6: =MROUND(F6*'Fuel & Inputs'!$C$20*'Fuel & Inputs'!$C$22,500) -> 469000 | O6: =MROUND(G6*'Fuel & Inputs'!$C$20*'Fuel & Inputs'!$C$22,500) -> 862000 | P6: LOW: used private • HIGH: SLLDC Doosan Mega 250
A7: 3 | B7: Truck Mixer | C7: 7 | D7: =MROUND(C7*'Fuel & Inputs'!$C$4,10) -> 2670 | E7: 2450 | F7: =MROUND(E7+'Fuel & Inputs'!$C$13,50) -> 3250 | G7: 4850 | H7: =G7-F7 -> 1600 | I7: =IF(C7=0,"n/a",IF(H7>=D7,"OK","THIN")) -> THIN | J7: =MROUND(E7*'Fuel & Inputs'!$C$19*'Fuel & Inputs'!$C$21,100) -> 9300 | K7: =MROUND(F7*'Fuel & Inputs'!$C$19*'Fuel & Inputs'!$C$21,100) -> 12400 | L7: =MROUND(G7*'Fuel & Inputs'!$C$19*'Fuel & Inputs'!$C$21,100) -> 18400 | M7: =MROUND(E7*'Fuel & Inputs'!$C$20*'Fuel & Inputs'!$C$22,500) -> 250000 | N7: =MROUND(F7*'Fuel & Inputs'!$C$20*'Fuel & Inputs'!$C$22,500) -> 331500 | O7: =MROUND(G7*'Fuel & Inputs'!$C$20*'Fuel & Inputs'!$C$22,500) -> 494500 | P7: LOW: TATA mixer private • HIGH: large operators
A8: 4 | B8: Self Loader Mixer | C8: 8 | D8: =MROUND(C8*'Fuel & Inputs'!$C$4,10) -> 3060 | E8: 2650 | F8: =MROUND(E8+'Fuel & Inputs'!$C$13,50) -> 3450 | G8: 5300 | H8: =G8-F8 -> 1850 | I8: =IF(C8=0,"n/a",IF(H8>=D8,"OK","THIN")) -> THIN | J8: =MROUND(E8*'Fuel & Inputs'!$C$19*'Fuel & Inputs'!$C$21,100) -> 10100 | K8: =MROUND(F8*'Fuel & Inputs'!$C$19*'Fuel & Inputs'!$C$21,100) -> 13100 | L8: =MROUND(G8*'Fuel & Inputs'!$C$19*'Fuel & Inputs'!$C$21,100) -> 20100 | M8: =MROUND(E8*'Fuel & Inputs'!$C$20*'Fuel & Inputs'!$C$22,500) -> 270500 | N8: =MROUND(F8*'Fuel & Inputs'!$C$20*'Fuel & Inputs'!$C$22,500) -> 352000 | O8: =MROUND(G8*'Fuel & Inputs'!$C$20*'Fuel & Inputs'!$C$22,500) -> 540500 | P8: LOW: FIORI/Ajax private • HIGH: large operators
A9: 5 | B9: Static Roller | C9: 8 | D9: =MROUND(C9*'Fuel & Inputs'!$C$4,10) -> 3060 | E9: 2300 | F9: =MROUND(E9+'Fuel & Inputs'!$C$13,50) -> 3100 | G9: 4600 | H9: =G9-F9 -> 1500 | I9: =IF(C9=0,"n/a",IF(H9>=D9,"OK","THIN")) -> THIN | J9: =MROUND(E9*'Fuel & Inputs'!$C$19*'Fuel & Inputs'!$C$21,100) -> 8700 | K9: =MROUND(F9*'Fuel & Inputs'!$C$19*'Fuel & Inputs'!$C$21,100) -> 11800 | L9: =MROUND(G9*'Fuel & Inputs'!$C$19*'Fuel & Inputs'!$C$21,100) -> 17500 | M9: =MROUND(E9*'Fuel & Inputs'!$C$20*'Fuel & Inputs'!$C$22,500) -> 234500 | N9: =MROUND(F9*'Fuel & Inputs'!$C$20*'Fuel & Inputs'!$C$22,500) -> 316000 | O9: =MROUND(G9*'Fuel & Inputs'!$C$20*'Fuel & Inputs'!$C$22,500) -> 469000 | P9: LOW: private 10T • HIGH: SLLDC HAMM HD12vv
A10: 6 | B10: Vibrating Roller | C10: 5 | D10: =MROUND(C10*'Fuel & Inputs'!$C$4,10) -> 1910 | E10: 1950 | F10: =MROUND(E10+'Fuel & Inputs'!$C$13,50) -> 2750 | G10: 3900 | H10: =G10-F10 -> 1150 | I10: =IF(C10=0,"n/a",IF(H10>=D10,"OK","THIN")) -> THIN | J10: =MROUND(E10*'Fuel & Inputs'!$C$19*'Fuel & Inputs'!$C$21,100) -> 7400 | K10: =MROUND(F10*'Fuel & Inputs'!$C$19*'Fuel & Inputs'!$C$21,100) -> 10500 | L10: =MROUND(G10*'Fuel & Inputs'!$C$19*'Fuel & Inputs'!$C$21,100) -> 14800 | M10: =MROUND(E10*'Fuel & Inputs'!$C$20*'Fuel & Inputs'!$C$22,500) -> 199000 | N10: =MROUND(F10*'Fuel & Inputs'!$C$20*'Fuel & Inputs'!$C$22,500) -> 280500 | O10: =MROUND(G10*'Fuel & Inputs'!$C$20*'Fuel & Inputs'!$C$22,500) -> 398000 | P10: LOW: BOMAG private • HIGH: large private 10T
A11: 7 | B11: Pneumatic Roller | C11: 7 | D11: =MROUND(C11*'Fuel & Inputs'!$C$4,10) -> 2670 | E11: 2000 | F11: =MROUND(E11+'Fuel & Inputs'!$C$13,50) -> 2800 | G11: 3950 | H11: =G11-F11 -> 1150 | I11: =IF(C11=0,"n/a",IF(H11>=D11,"OK","THIN")) -> THIN | J11: =MROUND(E11*'Fuel & Inputs'!$C$19*'Fuel & Inputs'!$C$21,100) -> 7600 | K11: =MROUND(F11*'Fuel & Inputs'!$C$19*'Fuel & Inputs'!$C$21,100) -> 10600 | L11: =MROUND(G11*'Fuel & Inputs'!$C$19*'Fuel & Inputs'!$C$21,100) -> 15000 | M11: =MROUND(E11*'Fuel & Inputs'!$C$20*'Fuel & Inputs'!$C$22,500) -> 204000 | N11: =MROUND(F11*'Fuel & Inputs'!$C$20*'Fuel & Inputs'!$C$22,500) -> 285500 | O11: =MROUND(G11*'Fuel & Inputs'!$C$20*'Fuel & Inputs'!$C$22,500) -> 403000 | P11: LOW: Sakai/Dynapac private • HIGH: premium
A12: 8 | B12: Motor Grader | C12: 15 | D12: =MROUND(C12*'Fuel & Inputs'!$C$4,10) -> 5730 | E12: 4350 | F12: =MROUND(E12+'Fuel & Inputs'!$C$13,50) -> 5150 | G12: 9650 | H12: =G12-F12 -> 4500 | I12: =IF(C12=0,"n/a",IF(H12>=D12,"OK","THIN")) -> THIN | J12: =MROUND(E12*'Fuel & Inputs'!$C$19*'Fuel & Inputs'!$C$21,100) -> 16500 | K12: =MROUND(F12*'Fuel & Inputs'!$C$19*'Fuel & Inputs'!$C$21,100) -> 19600 | L12: =MROUND(G12*'Fuel & Inputs'!$C$19*'Fuel & Inputs'!$C$21,100) -> 36700 | M12: =MROUND(E12*'Fuel & Inputs'!$C$20*'Fuel & Inputs'!$C$22,500) -> 443500 | N12: =MROUND(F12*'Fuel & Inputs'!$C$20*'Fuel & Inputs'!$C$22,500) -> 525500 | O12: =MROUND(G12*'Fuel & Inputs'!$C$20*'Fuel & Inputs'!$C$22,500) -> 984500 | P12: LOW: used CAT private • HIGH: premium/SLLDC class
A13: 9 | B13: Skid Steer | C13: 4.5 | D13: =MROUND(C13*'Fuel & Inputs'!$C$4,10) -> 1720 | E13: 1350 | F13: =MROUND(E13+'Fuel & Inputs'!$C$13,50) -> 2150 | G13: 2700 | H13: =G13-F13 -> 550 | I13: =IF(C13=0,"n/a",IF(H13>=D13,"OK","THIN")) -> THIN | J13: =MROUND(E13*'Fuel & Inputs'!$C$19*'Fuel & Inputs'!$C$21,100) -> 5100 | K13: =MROUND(F13*'Fuel & Inputs'!$C$19*'Fuel & Inputs'!$C$21,100) -> 8200 | L13: =MROUND(G13*'Fuel & Inputs'!$C$19*'Fuel & Inputs'!$C$21,100) -> 10300 | M13: =MROUND(E13*'Fuel & Inputs'!$C$20*'Fuel & Inputs'!$C$22,500) -> 137500 | N13: =MROUND(F13*'Fuel & Inputs'!$C$20*'Fuel & Inputs'!$C$22,500) -> 219500 | O13: =MROUND(G13*'Fuel & Inputs'!$C$20*'Fuel & Inputs'!$C$22,500) -> 275500 | P13: LOW: small private • HIGH: SLLDC Bobcat
A14: 10 | B14: Asphalt Paver | C14: 12 | D14: =MROUND(C14*'Fuel & Inputs'!$C$4,10) -> 4580 | E14: 3600 | F14: =MROUND(E14+'Fuel & Inputs'!$C$13,50) -> 4400 | G14: 8050 | H14: =G14-F14 -> 3650 | I14: =IF(C14=0,"n/a",IF(H14>=D14,"OK","THIN")) -> THIN | J14: =MROUND(E14*'Fuel & Inputs'!$C$19*'Fuel & Inputs'!$C$21,100) -> 13700 | K14: =MROUND(F14*'Fuel & Inputs'!$C$19*'Fuel & Inputs'!$C$21,100) -> 16700 | L14: =MROUND(G14*'Fuel & Inputs'!$C$19*'Fuel & Inputs'!$C$21,100) -> 30600 | M14: =MROUND(E14*'Fuel & Inputs'!$C$20*'Fuel & Inputs'!$C$22,500) -> 367000 | N14: =MROUND(F14*'Fuel & Inputs'!$C$20*'Fuel & Inputs'!$C$22,500) -> 449000 | O14: =MROUND(G14*'Fuel & Inputs'!$C$20*'Fuel & Inputs'!$C$22,500) -> 821000 | P14: LOW: SUMITOMO private • HIGH: VOLVO premium
A15: 11 | B15: Bitumen Bowser | C15: 6.5 | D15: =MROUND(C15*'Fuel & Inputs'!$C$4,10) -> 2480 | E15: 1750 | F15: =MROUND(E15+'Fuel & Inputs'!$C$13,50) -> 2550 | G15: 3500 | H15: =G15-F15 -> 950 | I15: =IF(C15=0,"n/a",IF(H15>=D15,"OK","THIN")) -> THIN | J15: =MROUND(E15*'Fuel & Inputs'!$C$19*'Fuel & Inputs'!$C$21,100) -> 6700 | K15: =MROUND(F15*'Fuel & Inputs'!$C$19*'Fuel & Inputs'!$C$21,100) -> 9700 | L15: =MROUND(G15*'Fuel & Inputs'!$C$19*'Fuel & Inputs'!$C$21,100) -> 13300 | M15: =MROUND(E15*'Fuel & Inputs'!$C$20*'Fuel & Inputs'!$C$22,500) -> 178500 | N15: =MROUND(F15*'Fuel & Inputs'!$C$20*'Fuel & Inputs'!$C$22,500) -> 260000 | O15: =MROUND(G15*'Fuel & Inputs'!$C$20*'Fuel & Inputs'!$C$22,500) -> 357000 | P15: LOW: private 4-cu • HIGH: large insulated
A16: 12 | B16: Mobile Crane | C16: 10 | D16: =MROUND(C16*'Fuel & Inputs'!$C$4,10) -> 3820 | E16: 4400 | F16: =MROUND(E16+'Fuel & Inputs'!$C$13,50) -> 5200 | G16: 8800 | H16: =G16-F16 -> 3600 | I16: =IF(C16=0,"n/a",IF(H16>=D16,"OK","THIN")) -> THIN | J16: =MROUND(E16*'Fuel & Inputs'!$C$19*'Fuel & Inputs'!$C$21,100) -> 16700 | K16: =MROUND(F16*'Fuel & Inputs'!$C$19*'Fuel & Inputs'!$C$21,100) -> 19800 | L16: =MROUND(G16*'Fuel & Inputs'!$C$19*'Fuel & Inputs'!$C$21,100) -> 33400 | M16: =MROUND(E16*'Fuel & Inputs'!$C$20*'Fuel & Inputs'!$C$22,500) -> 449000 | N16: =MROUND(F16*'Fuel & Inputs'!$C$20*'Fuel & Inputs'!$C$22,500) -> 530500 | O16: =MROUND(G16*'Fuel & Inputs'!$C$20*'Fuel & Inputs'!$C$22,500) -> 897500 | P16: LOW: private 25T • HIGH: SLLDC Kobelco RK250
... A24: 20 | B24: Dump Truck (Tipper) | C24: 7.5 | D24: =MROUND(C24*'Fuel & Inputs'!$C$4,10) -> 2870 | E24: 1550 | F24: =MROUND(E24+'Fuel & Inputs'!$C$13,50) -> 2350 | G24: 3250 | H24: =G24-F24 -> 900 | I24: =IF(C24=0,"n/a",IF(H24>=D24,"OK","THIN")) -> THIN | J24: =MROUND(E24*'Fuel & Inputs'!$C$19*'Fuel & Inputs'!$C$21,100) -> 5900 | K24: =MROUND(F24*'Fuel & Inputs'!$C$19*'Fuel & Inputs'!$C$21,100) -> 8900 | L24: =MROUND(G24*'Fuel & Inputs'!$C$19*'Fuel & Inputs'!$C$21,100) -> 12400 | M24: =MROUND(E24*'Fuel & Inputs'!$C$20*'Fuel & Inputs'!$C$22,500) -> 158000 | N24: =MROUND(F24*'Fuel & Inputs'!$C$20*'Fuel & Inputs'!$C$22,500) -> 239500 | O24: =MROUND(G24*'Fuel & Inputs'!$C$20*'Fuel & Inputs'!$C$22,500) -> 331500 | P24: LOW: ikman monthly • HIGH: premium TATA LPK1618
A25: 21 | B25: Trailer (towed) | C25: 0 | D25: =MROUND(C25*'Fuel & Inputs'!$C$4,10) -> 0 | E25: 1250 | F25: =E25 -> 1250 | G25: 1300 | H25: =G25-F25 -> 50 | I25: =IF(C25=0,"n/a",IF(H25>=D25,"OK","THIN")) -> n/a | J25: =MROUND(E25*'Fuel & Inputs'!$C$19*'Fuel & Inputs'!$C$21,100) -> 4800 | K25: =MROUND(F25*'Fuel & Inputs'!$C$19*'Fuel & Inputs'!$C$21,100) -> 4800 | L25: =MROUND(G25*'Fuel & Inputs'!$C$19*'Fuel & Inputs'!$C$21,100) -> 4900 | M25: =MROUND(E25*'Fuel & Inputs'!$C$20*'Fuel & Inputs'!$C$22,500) -> 127500 | N25: =MROUND(F25*'Fuel & Inputs'!$C$20*'Fuel & Inputs'!$C$22,500) -> 127500 | O25: =MROUND(G25*'Fuel & Inputs'!$C$20*'Fuel & Inputs'!$C$22,500) -> 132500 | P25: LOW: tractor trailer private • HIGH: premium
A26: 22 | B26: Lorry Trailer (towed) | C26: 0 | D26: =MROUND(C26*'Fuel & Inputs'!$C$4,10) -> 0 | E26: 2100 | F26: =E26 -> 2100 | G26: 2200 | H26: =G26-F26 -> 100 | I26: =IF(C26=0,"n/a",IF(H26>=D26,"OK","THIN")) -> n/a | J26: =MROUND(E26*'Fuel & Inputs'!$C$19*'Fuel & Inputs'!$C$21,100) -> 8000 | K26: =MROUND(F26*'Fuel & Inputs'!$C$19*'Fuel & Inputs'!$C$21,100) -> 8000 | L26: =MROUND(G26*'Fuel & Inputs'!$C$19*'Fuel & Inputs'!$C$21,100) -> 8400 | M26: =MROUND(E26*'Fuel & Inputs'!$C$20*'Fuel & Inputs'!$C$22,500) -> 214000 | N26: =MROUND(F26*'Fuel & Inputs'!$C$20*'Fuel & Inputs'!$C$22,500) -> 214000 | O26: =MROUND(G26*'Fuel & Inputs'!$C$20*'Fuel & Inputs'!$C$22,500) -> 224500 | P26: LOW: private Tantri • HIGH: Tantri TFB40
A27: 23 | B27: Diesel Bowser | C27: 3.5 | D27: =MROUND(C27*'Fuel & Inputs'!$C$4,10) -> 1340 | E27: 1350 | F27: =MROUND(E27+'Fuel & Inputs'!$C$13,50) -> 2150 | G27: 2450 | H27: =G27-F27 -> 300 | I27: =IF(C27=0,"n/a",IF(H27>=D27,"OK","THIN")) -> THIN | J27: =MROUND(E27*'Fuel & Inputs'!$C$19*'Fuel & Inputs'!$C$21,100) -> 5100 | K27: =MROUND(F27*'Fuel & Inputs'!$C$19*'Fuel & Inputs'!$C$21,100) -> 8200 | L27: =MROUND(G27*'Fuel & Inputs'!$C$19*'Fuel & Inputs'!$C$21,100) -> 9300 | M27: =MROUND(E27*'Fuel & Inputs'!$C$20*'Fuel & Inputs'!$C$22,500) -> 137500 | N27: =MROUND(F27*'Fuel & Inputs'!$C$20*'Fuel & Inputs'!$C$22,500) -> 219500 | O27: =MROUND(G27*'Fuel & Inputs'!$C$20*'Fuel & Inputs'!$C$22,500) -> 250000 | P27: LOW: private fuel bowser • HIGH: large premium
A28: 24 | B28: Excavator (20T class) | C28: 15 | D28: =MROUND(C28*'Fuel & Inputs'!$C$4,10) -> 5730 | E28: 4300 | F28: =MROUND(E28+'Fuel & Inputs'!$C$13,50) -> 5100 | G28: 9550 | H28: =G28-F28 -> 4450 | I28: =IF(C28=0,"n/a",IF(H28>=D28,"OK","THIN")) -> THIN | J28: =MROUND(E28*'Fuel & Inputs'!$C$19*'Fuel & Inputs'!$C$21,100) -> 16300 | K28: =MROUND(F28*'Fuel & Inputs'!$C$19*'Fuel & Inputs'!$C$21,100) -> 19400 | L28: =MROUND(G28*'Fuel & Inputs'!$C$19*'Fuel & Inputs'!$C$21,100) -> 36300 | M28: =MROUND(E28*'Fuel & Inputs'!$C$20*'Fuel & Inputs'!$C$22,500) -> 438500 | N28: =MROUND(F28*'Fuel & Inputs'!$C$20*'Fuel & Inputs'!$C$22,500) -> 520000 | O28: =MROUND(G28*'Fuel & Inputs'!$C$20*'Fuel & Inputs'!$C$22,500) -> 974000 | P28: LOW: 20T Hyundai private • HIGH: SLLDC Doosan DX200
A29: 25 | B29: Water Bowser | C29: 3.5 | D29: =MROUND(C29*'Fuel & Inputs'!$C$4,10) -> 1340 | E29: 1500 | F29: =MROUND(E29+'Fuel & Inputs'!$C$13,50) -> 2300 | G29: 2950 | H29: =G29-F29 -> 650 | I29: =IF(C29=0,"n/a",IF(H29>=D29,"OK","THIN")) -> THIN | J29: =MROUND(E29*'Fuel & Inputs'!$C$19*'Fuel & Inputs'!$C$21,100) -> 5700 | K29: =MROUND(F29*'Fuel & Inputs'!$C$19*'Fuel & Inputs'!$C$21,100) -> 8700 | L29: =MROUND(G29*'Fuel & Inputs'!$C$19*'Fuel & Inputs'!$C$21,100) -> 11200 | M29: =MROUND(E29*'Fuel & Inputs'!$C$20*'Fuel & Inputs'!$C$22,500) -> 153000 | N29: =MROUND(F29*'Fuel & Inputs'!$C$20*'Fuel & Inputs'!$C$22,500) -> 234500 | O29: =MROUND(G29*'Fuel & Inputs'!$C$20*'Fuel & Inputs'!$C$22,500) -> 301000 | P29: LOW: small private • HIGH: SLLDC 6,000L equiv.
A30: 26 | B30: Farm Tractor | C30: 4 | D30: =MROUND(C30*'Fuel & Inputs'!$C$4,10) -> 1530 | E30: 1150 | F30: =MROUND(E30+'Fuel & Inputs'!$C$13,50) -> 1950 | G30: 2100 | H30: =G30-F30 -> 150 | I30: =IF(C30=0,"n/a",IF(H30>=D30,"OK","THIN")) -> THIN | J30: =MROUND(E30*'Fuel & Inputs'!$C$19*'Fuel & Inputs'!$C$21,100) -> 4400 | K30: =MROUND(F30*'Fuel & Inputs'!$C$19*'Fuel & Inputs'!$C$21,100) -> 7400 | L30: =MROUND(G30*'Fuel & Inputs'!$C$19*'Fuel & Inputs'!$C$21,100) -> 8000 | M30: =MROUND(E30*'Fuel & Inputs'!$C$20*'Fuel & Inputs'!$C$22,500) -> 117500 | N30: =MROUND(F30*'Fuel & Inputs'!$C$20*'Fuel & Inputs'!$C$22,500) -> 199000 | O30: =MROUND(G30*'Fuel & Inputs'!$C$20*'Fuel & Inputs'!$C$22,500) -> 214000 | P30: LOW: MASSEY/TAFE private • HIGH: MAHINDRA premium
A31: 27 | B31: Motor Bicycle (self-ride) | C31: 1.2 | D31: =MROUND(C31*'Fuel & Inputs'!$C$5,10) -> 500 | E31: 300 | F31: =E31 -> 300 | G31: 500 | H31: =G31-F31 -> 200 | I31: =IF(C31=0,"n/a",IF(H31>=D31,"OK","THIN")) -> THIN | J31: =MROUND(E31*'Fuel & Inputs'!$C$19*'Fuel & Inputs'!$C$21,100) -> 1100 | K31: =MROUND(F31*'Fuel & Inputs'!$C$19*'Fuel & Inputs'!$C$21,100) -> 1100 | L31: =MROUND(G31*'Fuel & Inputs'!$C$19*'Fuel & Inputs'!$C$21,100) -> 1900 | M31: =MROUND(E31*'Fuel & Inputs'!$C$20*'Fuel & Inputs'!$C$22,500) -> 30500 | N31: =MROUND(F31*'Fuel & Inputs'!$C$20*'Fuel & Inputs'!$C$22,500) -> 30500 | O31: =MROUND(G31*'Fuel & Inputs'!$C$20*'Fuel & Inputs'!$C$22,500) -> 51000 | P31: LOW: staff rental • HIGH: daily hire
A32: 28 | B32: Tractor Bowser | C32: 4.5 | D32: =MROUND(C32*'Fuel & Inputs'!$C$4,10) -> 1720 | E32: 950 | F32: =MROUND(E32+'Fuel & Inputs'!$C$13,50) -> 1750 | G32: 1750 | H32: =G32-F32 -> 0 | I32: =IF(C32=0,"n/a",IF(H32>=D32,"OK","THIN")) -> THIN | J32: =MROUND(E32*'Fuel & Inputs'!$C$19*'Fuel & Inputs'!$C$21,100) -> 3600 | K32: =MROUND(F32*'Fuel & Inputs'!$C$19*'Fuel & Inputs'!$C$21,100) -> 6700 | L32: =MROUND(G32*'Fuel & Inputs'!$C$19*'Fuel & Inputs'!$C$21,100) -> 6700 | M32: =MROUND(E32*'Fuel & Inputs'!$C$20*'Fuel & Inputs'!$C$22,500) -> 97000 | N32: =MROUND(F32*'Fuel & Inputs'!$C$20*'Fuel & Inputs'!$C$22,500) -> 178500 | O32: =MROUND(G32*'Fuel & Inputs'!$C$20*'Fuel & Inputs'!$C$22,500) -> 178500 | P32: LOW: private combo • HIGH: premium combo
A33: 29 | B33: Forklift (3T) | C33: 3.5 | D33: =MROUND(C33*'Fuel & Inputs'!$C$4,10) -> 1340 | E33: 1550 | F33: =MROUND(E33+'Fuel & Inputs'!$C$13,50) -> 2350 | G33: 3050 | H33: =G33-F33 -> 700 | I33: =IF(C33=0,"n/a",IF(H33>=D33,"OK","THIN")) -> THIN | J33: =MROUND(E33*'Fuel & Inputs'!$C$19*'Fuel & Inputs'!$C$21,100) -> 5900 | K33: =MROUND(F33*'Fuel & Inputs'!$C$19*'Fuel & Inputs'!$C$21,100) -> 8900 | L33: =MROUND(G33*'Fuel & Inputs'!$C$19*'Fuel & Inputs'!$C$21,100) -> 11600 | M33: =MROUND(E33*'Fuel & Inputs'!$C$20*'Fuel & Inputs'!$C$22,500) -> 158000 | N33: =MROUND(F33*'Fuel & Inputs'!$C$20*'Fuel & Inputs'!$C$22,500) -> 239500 | O33: =MROUND(G33*'Fuel & Inputs'!$C$20*'Fuel & Inputs'!$C$22,500) -> 311000 | P33: LOW: private 3T • HIGH: premium/specialist
B35: Notes: trailers are towed (no engine/operator) — DRY+OPERATOR = DRY; motorcycle is self-ride, WET includes Petrol-92 for staff duty use. 'Margin check' = does the WET-vs-DRY+OPERATOR gap cover fuel at today's CPC price? THIN rows: attach the fuel escalation clause (README) and/or bill fuel actuals via the timesheet calculator.

Sheet Fleet — Per Unit
A1: FLEET — UNIT-BY-UNIT PRICE LIST 2026 (518 units) — DRY / DRY + OPERATOR / WET (Rs., excl. 18% VAT)
A2: Per-unit DRY & WET carried over from the engineered Fleet Pricing card (age & size adjusted). DRY+OPERATOR = DRY + operator charge-out (Fuel & Inputs C13; trailers are towed and motorcycles self-ride — no operator added). Per-unit fuel = model-class typical consumption x age factor x CPC price (Auto Diesel Rs.382 / Petrol-92 Rs.414, eff. 29-Jun-2026); road vehicles shown in Rs./km. Daily = hourly x 4 x 0.95 • Monthly = hourly x 120 x 0.85.
A4: # | B4: Category | C4: Brand | D4: Model | E4: Year | F4: E&C No. | G4: Reg No. | H4: Fuel | I4: Cons. (typ) L/hr | km/L | J4: Age factor | K4: Fuel rate | L4: Unit | M4: DRY Rs./hr | N4: DRY+OPERATOR Rs./hr | O4: WET Rs./hr | P4: DRY Rs./day (4h) | Q4: DRY+OP Rs./day (4h) | R4: WET Rs./day (4h) | S4: DRY Rs./mo (120h) | T4: DRY+OP Rs./mo (120h) | U4: WET Rs./mo (120h)
A5: BACKHOE LOADER
A6: 1 | B6: Backhoe Loader | C6: BOB CAT | D6: B760 | E6: 2021 | F6: LB-22 | G6: ZB-2586 | H6: Diesel | I6: 7 | J6: 1.035 | K6: =IF(I6=0,0,IF(L6="Rs./km",MROUND(IF(H6="Petrol",'Fuel & Inputs'!$C$5,'Fuel & Inputs'!$C$4)/I6*J6,1),MROUND(I6*J6*IF(H6="Petrol",'Fuel & Inputs'!$C$5,'Fuel & Inputs'!$C$4),10))) -> 2770 | L6: Rs./hr | M6: 2000 | N6: =MROUND(M6+'Fuel & Inputs'!$C$13,50) -> 2800 | O6: 4150 | P6: =MROUND(M6*'Fuel & Inputs'!$C$19*'Fuel & Inputs'!$C$21,100) -> 7600 | Q6: =MROUND(N6*'Fuel & Inputs'!$C$19*'Fuel & Inputs'!$C$21,100) -> 10600 | R6: =MROUND(O6*'Fuel & Inputs'!$C$19*'Fuel & Inputs'!$C$21,100) -> 15800 | S6: =MROUND(M6*'Fuel & Inputs'!$C$20*'Fuel & Inputs'!$C$22,500) -> 204000 | T6: =MROUND(N6*'Fuel & Inputs'!$C$20*'Fuel & Inputs'!$C$22,500) -> 285500 | U6: =MROUND(O6*'Fuel & Inputs'!$C$20*'Fuel & Inputs'!$C$22,500) -> 423500
A7: 2 | B7: Backhoe Loader | C7: BOB CAT | D7: B760 | E7: 2021 | F7: LB-23 | G7: ZB-2587 | H7: Diesel | I7: 7 | J7: 1.035 | K7: =IF(I7=0,0,IF(L7="Rs./km",MROUND(IF(H7="Petrol",'Fuel & Inputs'!$C$5,'Fuel & Inputs'!$C$4)/I7*J7,1),MROUND(I7*J7*IF(H7="Petrol",'Fuel & Inputs'!$C$5,'Fuel & Inputs'!$C$4),10))) -> 2770 | L7: Rs./hr | M7: 2000 | N7: =MROUND(M7+'Fuel & Inputs'!$C$13,50) -> 2800 | O7: 4150 | P7: =MROUND(M7*'Fuel & Inputs'!$C$19*'Fuel & Inputs'!$C$21,100) -> 7600 | Q7: =MROUND(N7*'Fuel & Inputs'!$C$19*'Fuel & Inputs'!$C$21,100) -> 10600 | R7: =MROUND(O7*'Fuel & Inputs'!$C$19*'Fuel & Inputs'!$C$21,100) -> 15800 | S7: =MROUND(M7*'Fuel & Inputs'!$C$20*'Fuel & Inputs'!$C$22,500) -> 204000 | T7: =MROUND(N7*'Fuel & Inputs'!$C$20*'Fuel & Inputs'!$C$22,500) -> 285500 | U7: =MROUND(O7*'Fuel & Inputs'!$C$20*'Fuel & Inputs'!$C$22,500) -> 423500
A8: 3 | B8: Backhoe Loader | C8: BOB CAT | D8: B760 | E8: 2021 | F8: LB-24 | G8: ZB-2583 | H8: Diesel | I8: 7 | J8: 1.035 | K8: =IF(I8=0,0,IF(L8="Rs./km",MROUND(IF(H8="Petrol",'Fuel & Inputs'!$C$5,'Fuel & Inputs'!$C$4)/I8*J8,1),MROUND(I8*J8*IF(H8="Petrol",'Fuel & Inputs'!$C$5,'Fuel & Inputs'!$C$4),10))) -> 2770 | L8: Rs./hr | M8: 2000 | N8: =MROUND(M8+'Fuel & Inputs'!$C$13,50) -> 2800 | O8: 4150 | P8: =MROUND(M8*'Fuel & Inputs'!$C$19*'Fuel & Inputs'!$C$21,100) -> 7600 | Q8: =MROUND(N8*'Fuel & Inputs'!$C$19*'Fuel & Inputs'!$C$21,100) -> 10600 | R8: =MROUND(O8*'Fuel & Inputs'!$C$19*'Fuel & Inputs'!$C$21,100) -> 15800 | S8: =MROUND(M8*'Fuel & Inputs'!$C$20*'Fuel & Inputs'!$C$22,500) -> 204000 | T8: =MROUND(N8*'Fuel & Inputs'!$C$20*'Fuel & Inputs'!$C$22,500) -> 285500 | U8: =MROUND(O8*'Fuel & Inputs'!$C$20*'Fuel & Inputs'!$C$22,500) -> 423500
A9: 4 | B9: Backhoe Loader | C9: J.C.B | D9: 3DX | E9: 2020 | F9: LB-16 | G9: ZB-1547 | H9: Diesel | I9: 7 | J9: 1.042 | K9: =IF(I9=0,0,IF(L9="Rs./km",MROUND(IF(H9="Petrol",'Fuel & Inputs'!$C$5,'Fuel & Inputs'!$C$4)/I9*J9,1),MROUND(I9*J9*IF(H9="Petrol",'Fuel & Inputs'!$C$5,'Fuel & Inputs'!$C$4),10))) -> 2790 | L9: Rs./hr | M9: 2000 | N9: =MROUND(M9+'Fuel & Inputs'!$C$13,50) -> 2800 | O9: 4150 | P9: =MROUND(M9*'Fuel & Inputs'!$C$19*'Fuel & Inputs'!$C$21,100) -> 7600 | Q9: =MROUND(N9*'Fuel & Inputs'!$C$19*'Fuel & Inputs'!$C$21,100) -> 10600 | R9: =MROUND(O9*'Fuel & Inputs'!$C$19*'Fuel & Inputs'!$C$21,100) -> 15800 | S9: =MROUND(M9*'Fuel & Inputs'!$C$20*'Fuel & Inputs'!$C$22,500) -> 204000 | T9: =MROUND(N9*'Fuel & Inputs'!$C$20*'Fuel & Inputs'!$C$22,500) -> 285500 | U9: =MROUND(O9*'Fuel & Inputs'!$C$20*'Fuel & Inputs'!$C$22,500) -> 423500
A10: 5 | B10: Backhoe Loader | C10: JCB | D10: 3DX | E10: 2012 | F10: LB-02 | G10: ZA-2963 | H10: Diesel | I10: 7 | J10: 1.098 | K10: =IF(I10=0,0,IF(L10="Rs./km",MROUND(IF(H10="Petrol",'Fuel & Inputs'!$C$5,'Fuel & Inputs'!$C$4)/I10*J10,1),MROUND(I10*J10*IF(H10="Petrol",'Fuel & Inputs'!$C$5,'Fuel & Inputs'!$C$4),10))) -> 2940 | L10: Rs./hr | M10: 2000 | N10: =MROUND(M10+'Fuel & Inputs'!$C$13,50) -> 2800 | O10: 4150 | P10: =MROUND(M10*'Fuel & Inputs'!$C$19*'Fuel & Inputs'!$C$21,100) -> 7600 | Q10: =MROUND(N10*'Fuel & Inputs'!$C$19*'Fuel & Inputs'!$C$21,100) -> 10600 | R10: =MROUND(O10*'Fuel & Inputs'!$C$19*'Fuel & Inputs'!$C$21,100) -> 15800 | S10: =MROUND(M10*'Fuel & Inputs'!$C$20*'Fuel & Inputs'!$C$22,500) -> 204000 | T10: =MROUND(N10*'Fuel & Inputs'!$C$20*'Fuel & Inputs'!$C$22,500) -> 285500 | U10: =MROUND(O10*'Fuel & Inputs'!$C$20*'Fuel & Inputs'!$C$22,500) -> 423500
A11: 6 | B11: Backhoe Loader | C11: JCB | D11: 3DX | E11: 2012 | F11: LB-03 | G11: ZA-2964 | H11: Diesel | I11: 7 | J11: 1.098 | K11: =IF(I11=0,0,IF(L11="Rs./km",MROUND(IF(H11="Petrol",'Fuel & Inputs'!$C$5,'Fuel & Inputs'!$C$4)/I11*J11,1),MROUND(I11*J11*IF(H11="Petrol",'Fuel & Inputs'!$C$5,'Fuel & Inputs'!$C$4),10))) -> 2940 | L11: Rs./hr | M11: 2000 | N11: =MROUND(M11+'Fuel & Inputs'!$C$13,50) -> 2800 | O11: 4150 | P11: =MROUND(M11*'Fuel & Inputs'!$C$19*'Fuel & Inputs'!$C$21,100) -> 7600 | Q11: =MROUND(N11*'Fuel & Inputs'!$C$19*'Fuel & Inputs'!$C$21,100) -> 10600 | R11: =MROUND(O11*'Fuel & Inputs'!$C$19*'Fuel & Inputs'!$C$21,100) -> 15800 | S11: =MROUND(M11*'Fuel & Inputs'!$C$20*'Fuel & Inputs'!$C$22,500) -> 204000 | T11: =MROUND(N11*'Fuel & Inputs'!$C$20*'Fuel & Inputs'!$C$22,500) -> 285500 | U11: =MROUND(O11*'Fuel & Inputs'!$C$20*'Fuel & Inputs'!$C$22,500) -> 423500
A12: 7 | B12: Backhoe Loader | C12: JCB | D12: 3DX | E12: 2015 | F12: LB-09 | G12: ZA-6069 | H12: Diesel | I12: 7 | J12: 1.077 | K12: =IF(I12=0,0,IF(L12="Rs./km",MROUND(IF(H12="Petrol",'Fuel & Inputs'!$C$5,'Fuel & Inputs'!$C$4)/I12*J12,1),MROUND(I12*J12*IF(H12="Petrol",'Fuel & Inputs'!$C$5,'Fuel & Inputs'!$C$4),10))) -> 2880 | L12: Rs./hr | M12: 2000 | N12: =MROUND(M12+'Fuel & Inputs'!$C$13,50) -> 2800 | O12: 4150 | P12: =MROUND(M12*'Fuel & Inputs'!$C$19*'Fuel & Inputs'!$C$21,100) -> 7600 | Q12: =MROUND(N12*'Fuel & Inputs'!$C$19*'Fuel & Inputs'!$C$21,100) -> 10600 | R12: =MROUND(O12*'Fuel & Inputs'!$C$19*'Fuel & Inputs'!$C$21,100) -> 15800 | S12: =MROUND(M12*'Fuel & Inputs'!$C$20*'Fuel & Inputs'!$C$22,500) -> 204000 | T12: =MROUND(N12*'Fuel & Inputs'!$C$20*'Fuel & Inputs'!$C$22,500) -> 285500 | U12: =MROUND(O12*'Fuel & Inputs'!$C$20*'Fuel & Inputs'!$C$22,500) -> 423500
A13: 8 | B13: Backhoe Loader | C13: JCB | D13: 3DX | E13: 2016 | F13: LB-11 | G13: ZA-7092 | H13: Diesel | I13: 7 | J13: 1.07 | K13: =IF(I13=0,0,IF(L13="Rs./km",MROUND(IF(H13="Petrol",'Fuel & Inputs'!$C$5,'Fuel & Inputs'!$C$4)/I13*J13,1),MROUND(I13*J13*IF(H13="Petrol",'Fuel & Inputs'!$C$5,'Fuel & Inputs'!$C$4),10))) -> 2860 | L13: Rs./hr | M13: 2000 | N13: =MROUND(M13+'Fuel & Inputs'!$C$13,50) -> 2800 | O13: 4150 | P13: =MROUND(M13*'Fuel & Inputs'!$C$19*'Fuel & Inputs'!$C$21,100) -> 7600 | Q13: =MROUND(N13*'Fuel & Inputs'!$C$19*'Fuel & Inputs'!$C$21,100) -> 10600 | R13: =MROUND(O13*'Fuel & Inputs'!$C$19*'Fuel & Inputs'!$C$21,100) -> 15800 | S13: =MROUND(M13*'Fuel & Inputs'!$C$20*'Fuel & Inputs'!$C$22,500) -> 204000 | T13: =MROUND(N13*'Fuel & Inputs'!$C$20*'Fuel & Inputs'!$C$22,500) -> 285500 | U13: =MROUND(O13*'Fuel & Inputs'!$C$20*'Fuel & Inputs'!$C$22,500) -> 423500
A14: 9 | B14: Backhoe Loader | C14: JCB | D14: 3DX | E14: 2016 | F14: LB-13 | G14: ZA-7965 | H14: Diesel | I14: 7 | J14: 1.07 | K14: =IF(I14=0,0,IF(L14="Rs./km",MROUND(IF(H14="Petrol",'Fuel & Inputs'!$C$5,'Fuel & Inputs'!$C$4)/I14*J14,1),MROUND(I14*J14*IF(H14="Petrol",'Fuel & Inputs'!$C$5,'Fuel & Inputs'!$C$4),10))) -> 2860 | L14: Rs./hr | M14: 2000 | N14: =MROUND(M14+'Fuel & Inputs'!$C$13,50) -> 2800 | O14: 4150 | P14: =MROUND(M14*'Fuel & Inputs'!$C$19*'Fuel & Inputs'!$C$21,100) -> 7600 | Q14: =MROUND(N14*'Fuel & Inputs'!$C$19*'Fuel & Inputs'!$C$21,100) -> 10600 | R14: =MROUND(O14*'Fuel & Inputs'!$C$19*'Fuel & Inputs'!$C$21,100) -> 15800 | S14: =MROUND(M14*'Fuel & Inputs'!$C$20*'Fuel & Inputs'!$C$22,500) -> 204000 | T14: =MROUND(N14*'Fuel & Inputs'!$C$20*'Fuel & Inputs'!$C$22,500) -> 285500 | U14: =MROUND(O14*'Fuel & Inputs'!$C$20*'Fuel & Inputs'!$C$22,500) -> 423500
A15: 10 | B15: Backhoe Loader | C15: J.C.B | D15: 570ST | E15: 2019 | F15: LB-15 | G15: ZB-1047 | H15: Diesel | I15: 7 | J15: 1.049 | K15: =IF(I15=0,0,IF(L15="Rs./km",MROUND(IF(H15="Petrol",'Fuel & Inputs'!$C$5,'Fuel & Inputs'!$C$4)/I15*J15,1),MROUND(I15*J15*IF(H15="Petrol",'Fuel & Inputs'!$C$5,'Fuel & Inputs'!$C$4),10))) -> 2810 | L15: Rs./hr | M15: 1840 | N15: =MROUND(M15+'Fuel & Inputs'!$C$13,50) -> 2650 | O15: 3820 | P15: =MROUND(M15*'Fuel & Inputs'!$C$19*'Fuel & Inputs'!$C$21,100) -> 7000 | Q15: =MROUND(N15*'Fuel & Inputs'!$C$19*'Fuel & Inputs'!$C$21,100) -> 10100 | R15: =MROUND(O15*'Fuel & Inputs'!$C$19*'Fuel & Inputs'!$C$21,100) -> 14500 | S15: =MROUND(M15*'Fuel & Inputs'!$C$20*'Fuel & Inputs'!$C$22,500) -> 187500 | T15: =MROUND(N15*'Fuel & Inputs'!$C$20*'Fuel & Inputs'!$C$22,500) -> 270500 | U15: =MROUND(O15*'Fuel & Inputs'!$C$20*'Fuel & Inputs'!$C$22,500) -> 389500
A16: 11 | B16: Backhoe Loader | C16: JCB | D16: JCB 3DX | E16: 2016 | F16: LB-10 | G16: ZA-7034 | H16: Diesel | I16: 7 | J16: 1.07 | K16: =IF(I16=0,0,IF(L16="Rs./km",MROUND(IF(H16="Petrol",'Fuel & Inputs'!$C$5,'Fuel & Inputs'!$C$4)/I16*J16,1),MROUND(I16*J16*IF(H16="Petrol",'Fuel & Inputs'!$C$5,'Fuel & Inputs'!$C$4),10))) -> 2860 | L16: Rs./hr | M16: 1840 | N16: =MROUND(M16+'Fuel & Inputs'!$C$13,50) -> 2650 | O16: 3820 | P16: =MROUND(M16*'Fuel & Inputs'!$C$19*'Fuel & Inputs'!$C$21,100) -> 7000 | Q16: =MROUND(N16*'Fuel & Inputs'!$C$19*'Fuel & Inputs'!$C$21,100) -> 10100 | R16: =MROUND(O16*'Fuel & Inputs'!$C$19*'Fuel & Inputs'!$C$21,100) -> 14500 | S16: =MROUND(M16*'Fuel & Inputs'!$C$20*'Fuel & Inputs'!$C$22,500) -> 187500 | T16: =MROUND(N16*'Fuel & Inputs'!$C$20*'Fuel & Inputs'!$C$22,500) -> 270500 | U16: =MROUND(O16*'Fuel & Inputs'!$C$20*'Fuel & Inputs'!$C$22,500) -> 389500
A17: 12 | B17: Backhoe Loader | C17: JCB | D17: JCB 3DX | E17: 2016 | F17: LB-14 | G17: ZA-7968 | H17: Diesel | I17: 7 | J17: 1.07 | K17: =IF(I17=0,0,IF(L17="Rs./km",MROUND(IF(H17="Petrol",'Fuel & Inputs'!$C$5,'Fuel & Inputs'!$C$4)/I17*J17,1),MROUND(I17*J17*IF(H17="Petrol",'Fuel & Inputs'!$C$5,'Fuel & Inputs'!$C$4),10))) -> 2860 | L17: Rs./hr | M17: 1840 | N17: =MROUND(M17+'Fuel & Inputs'!$C$13,50) -> 2650 | O17: 3820 | P17: =MROUND(M17*'Fuel & Inputs'!$C$19*'Fuel & Inputs'!$C$21,100) -> 7000 | Q17: =MROUND(N17*'Fuel & Inputs'!$C$19*'Fuel & Inputs'!$C$21,100) -> 10100 | R17: =MROUND(O17*'Fuel & Inputs'!$C$19*'Fuel & Inputs'!$C$21,100) -> 14500 | S17: =MROUND(M17*'Fuel & Inputs'!$C$20*'Fuel & Inputs'!$C$22,500) -> 187500 | T17: =MROUND(N17*'Fuel & Inputs'!$C$20*'Fuel & Inputs'!$C$22,500) -> 270500 | U17: =MROUND(O17*'Fuel & Inputs'!$C$20*'Fuel & Inputs'!$C$22,500) -> 389500
... A29: 24 | B29: Backhoe Loader | C29: JCB | D29: SLP3CX | E29: 1999 | F29: LB-04 | G29: RS-0401 | H29: Diesel | I29: 7 | J29: 1.175 | K29: =IF(I29=0,0,IF(L29="Rs./km",MROUND(IF(H29="Petrol",'Fuel & Inputs'!$C$5,'Fuel & Inputs'!$C$4)/I29*J29,1),MROUND(I29*J29*IF(H29="Petrol",'Fuel & Inputs'!$C$5,'Fuel & Inputs'!$C$4),10))) -> 3140 | L29: Rs./hr | M29: 1160 | N29: =MROUND(M29+'Fuel & Inputs'!$C$13,50) -> 1950 | O29: 2410 | P29: =MROUND(M29*'Fuel & Inputs'!$C$19*'Fuel & Inputs'!$C$21,100) -> 4400 | Q29: =MROUND(N29*'Fuel & Inputs'!$C$19*'Fuel & Inputs'!$C$21,100) -> 7400 | R29: =MROUND(O29*'Fuel & Inputs'!$C$19*'Fuel & Inputs'!$C$21,100) -> 9200 | S29: =MROUND(M29*'Fuel & Inputs'!$C$20*'Fuel & Inputs'!$C$22,500) -> 118500 | T29: =MROUND(N29*'Fuel & Inputs'!$C$20*'Fuel & Inputs'!$C$22,500) -> 199000 | U29: =MROUND(O29*'Fuel & Inputs'!$C$20*'Fuel & Inputs'!$C$22,500) -> 246000
A30: WHEEL LOADER
A31: 25 | B31: Wheel Loader | C31: SHANTUI | D31: SL-50WN | E31: 2020 | F31: LD-09 | G31: — | H31: Diesel | I31: 15 | J31: 1.042 | K31: =IF(I31=0,0,IF(L31="Rs./km",MROUND(IF(H31="Petrol",'Fuel & Inputs'!$C$5,'Fuel & Inputs'!$C$4)/I31*J31,1),MROUND(I31*J31*IF(H31="Petrol",'Fuel & Inputs'!$C$5,'Fuel & Inputs'!$C$4),10))) -> 5970 | L31: Rs./hr | M31: 3800 | N31: =MROUND(M31+'Fuel & Inputs'!$C$13,50) -> 4600 | O31: 8450 | P31: =MROUND(M31*'Fuel & Inputs'!$C$19*'Fuel & Inputs'!$C$21,100) -> 14400 | Q31: =MROUND(N31*'Fuel & Inputs'!$C$19*'Fuel & Inputs'!$C$21,100) -> 17500 | R31: =MROUND(O31*'Fuel & Inputs'!$C$19*'Fuel & Inputs'!$C$21,100) -> 32100 | S31: =MROUND(M31*'Fuel & Inputs'!$C$20*'Fuel & Inputs'!$C$22,500) -> 387500 | T31: =MROUND(N31*'Fuel & Inputs'!$C$20*'Fuel & Inputs'!$C$22,500) -> 469000 | U31: =MROUND(O31*'Fuel & Inputs'!$C$20*'Fuel & Inputs'!$C$22,500) -> 862000
A32: 26 | B32: Wheel Loader | C32: KOMATSU | D32: WA-80SS | E32: 2015 | F32: LD-07 | G32: — | H32: Diesel | I32: 8 | J32: 1.077 | K32: =IF(I32=0,0,IF(L32="Rs./km",MROUND(IF(H32="Petrol",'Fuel & Inputs'!$C$5,'Fuel & Inputs'!$C$4)/I32*J32,1),MROUND(I32*J32*IF(H32="Petrol",'Fuel & Inputs'!$C$5,'Fuel & Inputs'!$C$4),10))) -> 3290 | L32: Rs./hr | M32: 3500 | N32: =MROUND(M32+'Fuel & Inputs'!$C$13,50) -> 4300 | O32: 7770 | P32: =MROUND(M32*'Fuel & Inputs'!$C$19*'Fuel & Inputs'!$C$21,100) -> 13300 | Q32: =MROUND(N32*'Fuel & Inputs'!$C$19*'Fuel & Inputs'!$C$21,100) -> 16300 | R32: =MROUND(O32*'Fuel & Inputs'!$C$19*'Fuel & Inputs'!$C$21,100) -> 29500 | S32: =MROUND(M32*'Fuel & Inputs'!$C$20*'Fuel & Inputs'!$C$22,500) -> 357000 | T32: =MROUND(N32*'Fuel & Inputs'!$C$20*'Fuel & Inputs'!$C$22,500) -> 438500 | U32: =MROUND(O32*'Fuel & Inputs'!$C$20*'Fuel & Inputs'!$C$22,500) -> 792500
A33: 27 | B33: Wheel Loader | C33: KOMATSU | D33: WA150 | E33: 2014 | F33: LD-05 | G33: — | H33: Diesel | I33: 12 | J33: 1.084 | K33: =IF(I33=0,0,IF(L33="Rs./km",MROUND(IF(H33="Petrol",'Fuel & Inputs'!$C$5,'Fuel & Inputs'!$C$4)/I33*J33,1),MROUND(I33*J33*IF(H33="Petrol",'Fuel & Inputs'!$C$5,'Fuel & Inputs'!$C$4),10))) -> 4970 | L33: Rs./hr | M33: 3120 | N33: =MROUND(M33+'Fuel & Inputs'!$C$13,50) -> 3900 | O33: 6930 | P33: =MROUND(M33*'Fuel & Inputs'!$C$19*'Fuel & Inputs'!$C$21,100) -> 11900 | Q33: =MROUND(N33*'Fuel & Inputs'!$C$19*'Fuel & Inputs'!$C$21,100) -> 14800 | R33: =MROUND(O33*'Fuel & Inputs'!$C$19*'Fuel & Inputs'!$C$21,100) -> 26300 | S33: =MROUND(M33*'Fuel & Inputs'!$C$20*'Fuel & Inputs'!$C$22,500) -> 318000 | T33: =MROUND(N33*'Fuel & Inputs'!$C$20*'Fuel & Inputs'!$C$22,500) -> 398000 | U33: =MROUND(O33*'Fuel & Inputs'!$C$20*'Fuel & Inputs'!$C$22,500) -> 707000
A34: 28 | B34: Wheel Loader | C34: SANTUI | D34: SL30W | E34: 2014 | F34: LD-08 | G34: — | H34: Diesel | I34: 9 | J34: 1.084 | K34: =IF(I34=0,0,IF(L34="Rs./km",MROUND(IF(H34="Petrol",'Fuel & Inputs'!$C$5,'Fuel & Inputs'!$C$4)/I34*J34,1),MROUND(I34*J34*IF(H34="Petrol",'Fuel & Inputs'!$C$5,'Fuel & Inputs'!$C$4),10))) -> 3730 | L34: Rs./hr | M34: 3120 | N34: =MROUND(M34+'Fuel & Inputs'!$C$13,50) -> 3900 | O34: 6930 | P34: =MROUND(M34*'Fuel & Inputs'!$C$19*'Fuel & Inputs'!$C$21,100) -> 11900 | Q34: =MROUND(N34*'Fuel & Inputs'!$C$19*'Fuel & Inputs'!$C$21,100) -> 14800 | R34: =MROUND(O34*'Fuel & Inputs'!$C$19*'Fuel & Inputs'!$C$21,100) -> 26300 | S34: =MROUND(M34*'Fuel & Inputs'!$C$20*'Fuel & Inputs'!$C$22,500) -> 318000 | T34: =MROUND(N34*'Fuel & Inputs'!$C$20*'Fuel & Inputs'!$C$22,500) -> 398000 | U34: =MROUND(O34*'Fuel & Inputs'!$C$20*'Fuel & Inputs'!$C$22,500) -> 707000
A35: 29 | B35: Wheel Loader | C35: KOMATSU | D35: 924F | E35: 2013 | F35: LD-04 | G35: — | H35: Diesel | I35: 12 | J35: 1.091 | K35: =IF(I35=0,0,IF(L35="Rs./km",MROUND(IF(H35="Petrol",'Fuel & Inputs'!$C$5,'Fuel & Inputs'!$C$4)/I35*J35,1),MROUND(I35*J35*IF(H35="Petrol",'Fuel & Inputs'!$C$5,'Fuel & Inputs'!$C$4),10))) -> 5000 | L35: Rs./hr | M35: 3120 | N35: =MROUND(M35+'Fuel & Inputs'!$C$13,50) -> 3900 | O35: 6930 | P35: =MROUND(M35*'Fuel & Inputs'!$C$19*'Fuel & Inputs'!$C$21,100) -> 11900 | Q35: =MROUND(N35*'Fuel & Inputs'!$C$19*'Fuel & Inputs'!$C$21,100) -> 14800 | R35: =MROUND(O35*'Fuel & Inputs'!$C$19*'Fuel & Inputs'!$C$21,100) -> 26300 | S35: =MROUND(M35*'Fuel & Inputs'!$C$20*'Fuel & Inputs'!$C$22,500) -> 318000 | T35: =MROUND(N35*'Fuel & Inputs'!$C$20*'Fuel & Inputs'!$C$22,500) -> 398000 | U35: =MROUND(O35*'Fuel & Inputs'!$C$20*'Fuel & Inputs'!$C$22,500) -> 707000
A36: 30 | B36: Wheel Loader | C36: KOMATSU | D36: 510 | E36: 2013 | F36: LD-06 | G36: ZA-3116 | H36: Diesel | I36: 11 | J36: 1.091 | K36: =IF(I36=0,0,IF(L36="Rs./km",MROUND(IF(H36="Petrol",'Fuel & Inputs'!$C$5,'Fuel & Inputs'!$C$4)/I36*J36,1),MROUND(I36*J36*IF(H36="Petrol",'Fuel & Inputs'!$C$5,'Fuel & Inputs'!$C$4),10))) -> 4580 | L36: Rs./hr | M36: 3120 | N36: =MROUND(M36+'Fuel & Inputs'!$C$13,50) -> 3900 | O36: 6930 | P36: =MROUND(M36*'Fuel & Inputs'!$C$19*'Fuel & Inputs'!$C$21,100) -> 11900 | Q36: =MROUND(N36*'Fuel & Inputs'!$C$19*'Fuel & Inputs'!$C$21,100) -> 14800 | R36: =MROUND(O36*'Fuel & Inputs'!$C$19*'Fuel & Inputs'!$C$21,100) -> 26300 | S36: =MROUND(M36*'Fuel & Inputs'!$C$20*'Fuel & Inputs'!$C$22,500) -> 318000 | T36: =MROUND(N36*'Fuel & Inputs'!$C$20*'Fuel & Inputs'!$C$22,500) -> 398000 | U36: =MROUND(O36*'Fuel & Inputs'!$C$20*'Fuel & Inputs'!$C$22,500) -> 707000
A37: 31 | B37: Wheel Loader | C37: KOMATSU | D37: WA100 | E37: 2012 | F37: LD-03 | G37: — | H37: Diesel | I37: 9 | J37: 1.098 | K37: =IF(I37=0,0,IF(L37="Rs./km",MROUND(IF(H37="Petrol",'Fuel & Inputs'!$C$5,'Fuel & Inputs'!$C$4)/I37*J37,1),MROUND(I37*J37*IF(H37="Petrol",'Fuel & Inputs'!$C$5,'Fuel & Inputs'!$C$4),10))) -> 3770 | L37: Rs./hr | M37: 3120 | N37: =MROUND(M37+'Fuel & Inputs'!$C$13,50) -> 3900 | O37: 6930 | P37: =MROUND(M37*'Fuel & Inputs'!$C$19*'Fuel & Inputs'!$C$21,100) -> 11900 | Q37: =MROUND(N37*'Fuel & Inputs'!$C$19*'Fuel & Inputs'!$C$21,100) -> 14800 | R37: =MROUND(O37*'Fuel & Inputs'!$C$19*'Fuel & Inputs'!$C$21,100) -> 26300 | S37: =MROUND(M37*'Fuel & Inputs'!$C$20*'Fuel & Inputs'!$C$22,500) -> 318000 | T37: =MROUND(N37*'Fuel & Inputs'!$C$20*'Fuel & Inputs'!$C$22,500) -> 398000 | U37: =MROUND(O37*'Fuel & Inputs'!$C$20*'Fuel & Inputs'!$C$22,500) -> 707000
A38: 32 | B38: Wheel Loader | C38: CAT | D38: CAT910 | E38: 2010 | F38: LD-02 | G38: — | H38: Diesel | I38: 10 | J38: 1.112 | K38: =IF(I38=0,0,IF(L38="Rs./km",MROUND(IF(H38="Petrol",'Fuel & Inputs'!$C$5,'Fuel & Inputs'!$C$4)/I38*J38,1),MROUND(I38*J38*IF(H38="Petrol",'Fuel & Inputs'!$C$5,'Fuel & Inputs'!$C$4),10))) -> 4250 | L38: Rs./hr | M38: 3120 | N38: =MROUND(M38+'Fuel & Inputs'!$C$13,50) -> 3900 | O38: 6930 | P38: =MROUND(M38*'Fuel & Inputs'!$C$19*'Fuel & Inputs'!$C$21,100) -> 11900 | Q38: =MROUND(N38*'Fuel & Inputs'!$C$19*'Fuel & Inputs'!$C$21,100) -> 14800 | R38: =MROUND(O38*'Fuel & Inputs'!$C$19*'Fuel & Inputs'!$C$21,100) -> 26300 | S38: =MROUND(M38*'Fuel & Inputs'!$C$20*'Fuel & Inputs'!$C$22,500) -> 318000 | T38: =MROUND(N38*'Fuel & Inputs'!$C$20*'Fuel & Inputs'!$C$22,500) -> 398000 | U38: =MROUND(O38*'Fuel & Inputs'!$C$20*'Fuel & Inputs'!$C$22,500) -> 707000
A39: 33 | B39: Wheel Loader | C39: CAT | D39: 910E | E39: 2009 | F39: LD-01 | G39: — | H39: Diesel | I39: 10 | J39: 1.119 | K39: =IF(I39=0,0,IF(L39="Rs./km",MROUND(IF(H39="Petrol",'Fuel & Inputs'!$C$5,'Fuel & Inputs'!$C$4)/I39*J39,1),MROUND(I39*J39*IF(H39="Petrol",'Fuel & Inputs'!$C$5,'Fuel & Inputs'!$C$4),10))) -> 4270 | L39: Rs./hr | M39: 2740 | N39: =MROUND(M39+'Fuel & Inputs'!$C$13,50) -> 3550 | O39: 6080 | P39: =MROUND(M39*'Fuel & Inputs'!$C$19*'Fuel & Inputs'!$C$21,100) -> 10400 | Q39: =MROUND(N39*'Fuel & Inputs'!$C$19*'Fuel & Inputs'!$C$21,100) -> 13500 | R39: =MROUND(O39*'Fuel & Inputs'!$C$19*'Fuel & Inputs'!$C$21,100) -> 23100 | S39: =MROUND(M39*'Fuel & Inputs'!$C$20*'Fuel & Inputs'!$C$22,500) -> 279500 | T39: =MROUND(N39*'Fuel & Inputs'!$C$20*'Fuel & Inputs'!$C$22,500) -> 362000 | U39: =MROUND(O39*'Fuel & Inputs'!$C$20*'Fuel & Inputs'!$C$22,500) -> 620000
A40: TRUCK MIXER
A41: 34 | B41: Truck Mixer | C41: TATA | D41: LPK 1618 | E41: 2017 | F41: TM-18 | G41: ZA-8511 | H41: Diesel | I41: 11 | J41: 1.063 | K41: =IF(I41=0,0,IF(L41="Rs./km",MROUND(IF(H41="Petrol",'Fuel & Inputs'!$C$5,'Fuel & Inputs'!$C$4)/I41*J41,1),MROUND(I41*J41*IF(H41="Petrol",'Fuel & Inputs'!$C$5,'Fuel & Inputs'!$C$4),10))) -> 4470 | L41: Rs./hr | M41: 2250 | N41: =MROUND(M41+'Fuel & Inputs'!$C$13,50) -> 3050 | O41: 4460 | P41: =MROUND(M41*'Fuel & Inputs'!$C$19*'Fuel & Inputs'!$C$21,100) -> 8600 | Q41: =MROUND(N41*'Fuel & Inputs'!$C$19*'Fuel & Inputs'!$C$21,100) -> 11600 | R41: =MROUND(O41*'Fuel & Inputs'!$C$19*'Fuel & Inputs'!$C$21,100) -> 16900 | S41: =MROUND(M41*'Fuel & Inputs'!$C$20*'Fuel & Inputs'!$C$22,500) -> 229500 | T41: =MROUND(N41*'Fuel & Inputs'!$C$20*'Fuel & Inputs'!$C$22,500) -> 311000 | U41: =MROUND(O41*'Fuel & Inputs'!$C$20*'Fuel & Inputs'!$C$22,500) -> 455000
A42: 35 | B42: Truck Mixer | C42: TATA | D42: LPK 2518 | E42: 2017 | F42: TM-19 | G42: ZA-8445 | H42: Diesel | I42: 13 | J42: 1.063 | K42: =IF(I42=0,0,IF(L42="Rs./km",MROUND(IF(H42="Petrol",'Fuel & Inputs'!$C$5,'Fuel & Inputs'!$C$4)/I42*J42,1),MROUND(I42*J42*IF(H42="Petrol",'Fuel & Inputs'!$C$5,'Fuel & Inputs'!$C$4),10))) -> 5280 | L42: Rs./hr | M42: 2250 | N42: =MROUND(M42+'Fuel & Inputs'!$C$13,50) -> 3050 | O42: 4460 | P42: =MROUND(M42*'Fuel & Inputs'!$C$19*'Fuel & Inputs'!$C$21,100) -> 8600 | Q42: =MROUND(N42*'Fuel & Inputs'!$C$19*'Fuel & Inputs'!$C$21,100) -> 11600 | R42: =MROUND(O42*'Fuel & Inputs'!$C$19*'Fuel & Inputs'!$C$21,100) -> 16900 | S42: =MROUND(M42*'Fuel & Inputs'!$C$20*'Fuel & Inputs'!$C$22,500) -> 229500 | T42: =MROUND(N42*'Fuel & Inputs'!$C$20*'Fuel & Inputs'!$C$22,500) -> 311000 | U42: =MROUND(O42*'Fuel & Inputs'!$C$20*'Fuel & Inputs'!$C$22,500) -> 455000
A43: 36 | B43: Truck Mixer | C43: TATA | D43: LPK 1618 | E43: 2016 | F43: TM-15 | G43: ZA-7925 | H43: Diesel | I43: 11 | J43: 1.07 | K43: =IF(I43=0,0,IF(L43="Rs./km",MROUND(IF(H43="Petrol",'Fuel & Inputs'!$C$5,'Fuel & Inputs'!$C$4)/I43*J43,1),MROUND(I43*J43*IF(H43="Petrol",'Fuel & Inputs'!$C$5,'Fuel & Inputs'!$C$4),10))) -> 4500 | L43: Rs./hr | M43: 2250 | N43: =MROUND(M43+'Fuel & Inputs'!$C$13,50) -> 3050 | O43: 4460 | P43: =MROUND(M43*'Fuel & Inputs'!$C$19*'Fuel & Inputs'!$C$21,100) -> 8600 | Q43: =MROUND(N43*'Fuel & Inputs'!$C$19*'Fuel & Inputs'!$C$21,100) -> 11600 | R43: =MROUND(O43*'Fuel & Inputs'!$C$19*'Fuel & Inputs'!$C$21,100) -> 16900 | S43: =MROUND(M43*'Fuel & Inputs'!$C$20*'Fuel & Inputs'!$C$22,500) -> 229500 | T43: =MROUND(N43*'Fuel & Inputs'!$C$20*'Fuel & Inputs'!$C$22,500) -> 311000 | U43: =MROUND(O43*'Fuel & Inputs'!$C$20*'Fuel & Inputs'!$C$22,500) -> 455000
A44: 37 | B44: Truck Mixer | C44: ELCHER | D44: TERRA 16 | E44: 2016 | F44: TM-11 | G44: ZA-7291 | H44: Diesel | I44: 11 | J44: 1.07 | K44: =IF(I44=0,0,IF(L44="Rs./km",MROUND(IF(H44="Petrol",'Fuel & Inputs'!$C$5,'Fuel & Inputs'!$C$4)/I44*J44,1),MROUND(I44*J44*IF(H44="Petrol",'Fuel & Inputs'!$C$5,'Fuel & Inputs'!$C$4),10))) -> 4500 | L44: Rs./hr | M44: 2250 | N44: =MROUND(M44+'Fuel & Inputs'!$C$13,50) -> 3050 | O44: 4460 | P44: =MROUND(M44*'Fuel & Inputs'!$C$19*'Fuel & Inputs'!$C$21,100) -> 8600 | Q44: =MROUND(N44*'Fuel & Inputs'!$C$19*'Fuel & Inputs'!$C$21,100) -> 11600 | R44: =MROUND(O44*'Fuel & Inputs'!$C$19*'Fuel & Inputs'!$C$21,100) -> 16900 | S44: =MROUND(M44*'Fuel & Inputs'!$C$20*'Fuel & Inputs'!$C$22,500) -> 229500 | T44: =MROUND(N44*'Fuel & Inputs'!$C$20*'Fuel & Inputs'!$C$22,500) -> 311000 | U44: =MROUND(O44*'Fuel & Inputs'!$C$20*'Fuel & Inputs'!$C$22,500) -> 455000
A45: 38 | B45: Truck Mixer | C45: ELCHER | D45: TERRA 16 | E45: 2016 | F45: TM-12 | G45: ZA-7290 | H45: Diesel | I45: 11 | J45: 1.07 | K45: =IF(I45=0,0,IF(L45="Rs./km",MROUND(IF(H45="Petrol",'Fuel & Inputs'!$C$5,'Fuel & Inputs'!$C$4)/I45*J45,1),MROUND(I45*J45*IF(H45="Petrol",'Fuel & Inputs'!$C$5,'Fuel & Inputs'!$C$4),10))) -> 4500 | L45: Rs./hr | M45: 2250 | N45: =MROUND(M45+'Fuel & Inputs'!$C$13,50) -> 3050 | O45: 4460 | P45: =MROUND(M45*'Fuel & Inputs'!$C$19*'Fuel & Inputs'!$C$21,100) -> 8600 | Q45: =MROUND(N45*'Fuel & Inputs'!$C$19*'Fuel & Inputs'!$C$21,100) -> 11600 | R45: =MROUND(O45*'Fuel & Inputs'!$C$19*'Fuel & Inputs'!$C$21,100) -> 16900 | S45: =MROUND(M45*'Fuel & Inputs'!$C$20*'Fuel & Inputs'!$C$22,500) -> 229500 | T45: =MROUND(N45*'Fuel & Inputs'!$C$20*'Fuel & Inputs'!$C$22,500) -> 311000 | U45: =MROUND(O45*'Fuel & Inputs'!$C$20*'Fuel & Inputs'!$C$22,500) -> 455000
A46: 39 | B46: Truck Mixer | C46: TATA | D46: LPK 2518 | E46: 2016 | F46: TM-14 | G46: ZA-7810 | H46: Diesel | I46: 13 | J46: 1.07 | K46: =IF(I46=0,0,IF(L46="Rs./km",MROUND(IF(H46="Petrol",'Fuel & Inputs'!$C$5,'Fuel & Inputs'!$C$4)/I46*J46,1),MROUND(I46*J46*IF(H46="Petrol",'Fuel & Inputs'!$C$5,'Fuel & Inputs'!$C$4),10))) -> 5310 | L46: Rs./hr | M46: 2250 | N46: =MROUND(M46+'Fuel & Inputs'!$C$13,50) -> 3050 | O46: 4460 | P46: =MROUND(M46*'Fuel & Inputs'!$C$19*'Fuel & Inputs'!$C$21,100) -> 8600 | Q46: =MROUND(N46*'Fuel & Inputs'!$C$19*'Fuel & Inputs'!$C$21,100) -> 11600 | R46: =MROUND(O46*'Fuel & Inputs'!$C$19*'Fuel & Inputs'!$C$21,100) -> 16900 | S46: =MROUND(M46*'Fuel & Inputs'!$C$20*'Fuel & Inputs'!$C$22,500) -> 229500 | T46: =MROUND(N46*'Fuel & Inputs'!$C$20*'Fuel & Inputs'!$C$22,500) -> 311000 | U46: =MROUND(O46*'Fuel & Inputs'!$C$20*'Fuel & Inputs'!$C$22,500) -> 455000
A47: 40 | B47: Truck Mixer | C47: TATA | D47: LPK 2518 | E47: 2016 | F47: TM-16 | G47: ZA-8033 | H47: Diesel | I47: 13 | J47: 1.07 | K47: =IF(I47=0,0,IF(L47="Rs./km",MROUND(IF(H47="Petrol",'Fuel & Inputs'!$C$5,'Fuel & Inputs'!$C$4)/I47*J47,1),MROUND(I47*J47*IF(H47="Petrol",'Fuel & Inputs'!$C$5,'Fuel & Inputs'!$C$4),10))) -> 5310 | L47: Rs./hr | M47: 2250 | N47: =MROUND(M47+'Fuel & Inputs'!$C$13,50) -> 3050 | O47: 4460 | P47: =MROUND(M47*'Fuel & Inputs'!$C$19*'Fuel & Inputs'!$C$21,100) -> 8600 | Q47: =MROUND(N47*'Fuel & Inputs'!$C$19*'Fuel & Inputs'!$C$21,100) -> 11600 | R47: =MROUND(O47*'Fuel & Inputs'!$C$19*'Fuel & Inputs'!$C$21,100) -> 16900 | S47: =MROUND(M47*'Fuel & Inputs'!$C$20*'Fuel & Inputs'!$C$22,500) -> 229500 | T47: =MROUND(N47*'Fuel & Inputs'!$C$20*'Fuel & Inputs'!$C$22,500) -> 311000 | U47: =MROUND(O47*'Fuel & Inputs'!$C$20*'Fuel & Inputs'!$C$22,500) -> 455000
A48: 41 | B48: Truck Mixer | C48: TATA | D48: LPK 2518 | E48: 2017 | F48: TM-21 | G48: ZA-0050 | H48: Diesel | I48: 13 | J48: 1.063 | K48: =IF(I48=0,0,IF(L48="Rs./km",MROUND(IF(H48="Petrol",'Fuel & Inputs'!$C$5,'Fuel & Inputs'!$C$4)/I48*J48,1),MROUND(I48*J48*IF(H48="Petrol",'Fuel & Inputs'!$C$5,'Fuel & Inputs'!$C$4),10))) -> 5280 | L48: Rs./hr | M48: 2250 | N48: =MROUND(M48+'Fuel & Inputs'!$C$13,50) -> 3050 | O48: 4460 | P48: =MROUND(M48*'Fuel & Inputs'!$C$19*'Fuel & Inputs'!$C$21,100) -> 8600 | Q48: =MROUND(N48*'Fuel & Inputs'!$C$19*'Fuel & Inputs'!$C$21,100) -> 11600 | R48: =MROUND(O48*'Fuel & Inputs'!$C$19*'Fuel & Inputs'!$C$21,100) -> 16900 | S48: =MROUND(M48*'Fuel & Inputs'!$C$20*'Fuel & Inputs'!$C$22,500) -> 229500 | T48: =MROUND(N48*'Fuel & Inputs'!$C$20*'Fuel & Inputs'!$C$22,500) -> 311000 | U48: =MROUND(O48*'Fuel & Inputs'!$C$20*'Fuel & Inputs'!$C$22,500) -> 455000
A49: 42 | B49: Truck Mixer | C49: ASHOK LEYLAND | D49: TUSKER SUPER 1613 | E49: 2015 | F49: TM-10 | G49: ZA-6395 | H49: Diesel | I49: 11 | J49: 1.077 | K49: =IF(I49=0,0,IF(L49="Rs./km",MROUND(IF(H49="Petrol",'Fuel & Inputs'!$C$5,'Fuel & Inputs'!$C$4)/I49*J49,1),MROUND(I49*J49*IF(H49="Petrol",'Fuel & Inputs'!$C$5,'Fuel & Inputs'!$C$4),10))) -> 4530 | L49: Rs./hr | M49: 2250 | N49: =MROUND(M49+'Fuel & Inputs'!$C$13,50) -> 3050 | O49: 4460 | P49: =MROUND(M49*'Fuel & Inputs'!$C$19*'Fuel & Inputs'!$C$21,100) -> 8600 | Q49: =MROUND(N49*'Fuel & Inputs'!$C$19*'Fuel & Inputs'!$C$21,100) -> 11600 | R49: =MROUND(O49*'Fuel & Inputs'!$C$19*'Fuel & Inputs'!$C$21,100) -> 16900 | S49: =MROUND(M49*'Fuel & Inputs'!$C$20*'Fuel & Inputs'!$C$22,500) -> 229500 | T49: =MROUND(N49*'Fuel & Inputs'!$C$20*'Fuel & Inputs'!$C$22,500) -> 311000 | U49: =MROUND(O49*'Fuel & Inputs'!$C$20*'Fuel & Inputs'!$C$22,500) -> 455000
A50: 43 | B50: Truck Mixer | C50: MITSUBISHI | D50: KK-FE73EB CANTER | E50: 2003 | F50: TM-09 | G50: ZA-6255 | H50: Diesel | I50: 8 | J50: 1.161 | K50: =IF(I50=0,0,IF(L50="Rs./km",MROUND(IF(H50="Petrol",'Fuel & Inputs'!$C$5,'Fuel & Inputs'!$C$4)/I50*J50,1),MROUND(I50*J50*IF(H50="Petrol",'Fuel & Inputs'!$C$5,'Fuel & Inputs'!$C$4),10))) -> 3550 | L50: Rs./hr | M50: 1590 | N50: =MROUND(M50+'Fuel & Inputs'!$C$13,50) -> 2400 | O50: 3150 | P50: =MROUND(M50*'Fuel & Inputs'!$C$19*'Fuel & Inputs'!$C$21,100) -> 6000 | Q50: =MROUND(N50*'Fuel & Inputs'!$C$19*'Fuel & Inputs'!$C$21,100) -> 9100 | R50: =MROUND(O50*'Fuel & Inputs'!$C$19*'Fuel & Inputs'!$C$21,100) -> 12000 | S50: =MROUND(M50*'Fuel & Inputs'!$C$20*'Fuel & Inputs'!$C$22,500) -> 162000 | T50: =MROUND(N50*'Fuel & Inputs'!$C$20*'Fuel & Inputs'!$C$22,500) -> 245000 | U50: =MROUND(O50*'Fuel & Inputs'!$C$20*'Fuel & Inputs'!$C$22,500) -> 321500
A51: 44 | B51: Truck Mixer | C51: ISUZU | D51: KK-NRR35C4 FORWARD | E51: 2000 | F51: TM-04 | G51: LL-0690 | H51: Diesel | I51: 8 | J51: 1.175 | K51: =IF(I51=0,0,IF(L51="Rs./km",MROUND(IF(H51="Petrol",'Fuel & Inputs'!$C$5,'Fuel & Inputs'!$C$4)/I51*J51,1),MROUND(I51*J51*IF(H51="Petrol",'Fuel & Inputs'!$C$5,'Fuel & Inputs'!$C$4),10))) -> 3590 | L51: Rs./hr | M51: 1590 | N51: =MROUND(M51+'Fuel & Inputs'!$C$13,50) -> 2400 | O51: 3150 | P51: =MROUND(M51*'Fuel & Inputs'!$C$19*'Fuel & Inputs'!$C$21,100) -> 6000 | Q51: =MROUND(N51*'Fuel & Inputs'!$C$19*'Fuel & Inputs'!$C$21,100) -> 9100 | R51: =MROUND(O51*'Fuel & Inputs'!$C$19*'Fuel & Inputs'!$C$21,100) -> 12000 | S51: =MROUND(M51*'Fuel & Inputs'!$C$20*'Fuel & Inputs'!$C$22,500) -> 162000 | T51: =MROUND(N51*'Fuel & Inputs'!$C$20*'Fuel & Inputs'!$C$22,500) -> 245000 | U51: =MROUND(O51*'Fuel & Inputs'!$C$20*'Fuel & Inputs'!$C$22,500) -> 321500
A52: 45 | B52: Truck Mixer | C52: ISUZU | D52: KC-NRR33C20 | E52: 1996 | F52: TM-03 | G52: LK-5047 | H52: Diesel | I52: 8 | J52: 1.175 | K52: =IF(I52=0,0,IF(L52="Rs./km",MROUND(IF(H52="Petrol",'Fuel & Inputs'!$C$5,'Fuel & Inputs'!$C$4)/I52*J52,1),MROUND(I52*J52*IF(H52="Petrol",'Fuel & Inputs'!$C$5,'Fuel & Inputs'!$C$4),10))) -> 3590 | L52: Rs./hr | M52: 1420 | N52: =MROUND(M52+'Fuel & Inputs'!$C$13,50) -> 2200 | O52: 2810 | P52: =MROUND(M52*'Fuel & Inputs'!$C$19*'Fuel & Inputs'!$C$21,100) -> 5400 | Q52: =MROUND(N52*'Fuel & Inputs'!$C$19*'Fuel & Inputs'!$C$21,100) -> 8400 | R52: =MROUND(O52*'Fuel & Inputs'!$C$19*'Fuel & Inputs'!$C$21,100) -> 10700 | S52: =MROUND(M52*'Fuel & Inputs'!$C$20*'Fuel & Inputs'!$C$22,500) -> 145000 | T52: =MROUND(N52*'Fuel & Inputs'!$C$20*'Fuel & Inputs'!$C$22,500) -> 224500 | U52: =MROUND(O52*'Fuel & Inputs'!$C$20*'Fuel & Inputs'!$C$22,500) -> 286500
... A56: 49 | B56: Truck Mixer | C56: MITSUBISHI | D56: U.FE315BN | E56: 1991 | F56: TM-06 | G56: LH-5475 | H56: Diesel | I56: 8 | J56: 1.175 | K56: =IF(I56=0,0,IF(L56="Rs./km",MROUND(IF(H56="Petrol",'Fuel & Inputs'!$C$5,'Fuel & Inputs'!$C$4)/I56*J56,1),MROUND(I56*J56*IF(H56="Petrol",'Fuel & Inputs'!$C$5,'Fuel & Inputs'!$C$4),10))) -> 3590 | L56: Rs./hr | M56: 1420 | N56: =MROUND(M56+'Fuel & Inputs'!$C$13,50) -> 2200 | O56: 2810 | P56: =MROUND(M56*'Fuel & Inputs'!$C$19*'Fuel & Inputs'!$C$21,100) -> 5400 | Q56: =MROUND(N56*'Fuel & Inputs'!$C$19*'Fuel & Inputs'!$C$21,100) -> 8400 | R56: =MROUND(O56*'Fuel & Inputs'!$C$19*'Fuel & Inputs'!$C$21,100) -> 10700 | S56: =MROUND(M56*'Fuel & Inputs'!$C$20*'Fuel & Inputs'!$C$22,500) -> 145000 | T56: =MROUND(N56*'Fuel & Inputs'!$C$20*'Fuel & Inputs'!$C$22,500) -> 224500 | U56: =MROUND(O56*'Fuel & Inputs'!$C$20*'Fuel & Inputs'!$C$22,500) -> 286500
A57: SELF LOADER MIXER
A58: 50 | B58: Self Loader Mixer | C58: FIORI | D58: BF08H01307 | E58: 2018 | F58: TM-20 | G58: Fiori | H58: Diesel | I58: 11 | J58: 1.056 | K58: =IF(I58=0,0,IF(L58="Rs./km",MROUND(IF(H58="Petrol",'Fuel & Inputs'!$C$5,'Fuel & Inputs'!$C$4)/I58*J58,1),MROUND(I58*J58*IF(H58="Petrol",'Fuel & Inputs'!$C$5,'Fuel & Inputs'!$C$4),10))) -> 4440 | L58: Rs./hr | M58: 2440 | N58: =MROUND(M58+'Fuel & Inputs'!$C$13,50) -> 3250 | O58: 4880 | P58: =MROUND(M58*'Fuel & Inputs'!$C$19*'Fuel & Inputs'!$C$21,100) -> 9300 | Q58: =MROUND(N58*'Fuel & Inputs'!$C$19*'Fuel & Inputs'!$C$21,100) -> 12400 | R58: =MROUND(O58*'Fuel & Inputs'!$C$19*'Fuel & Inputs'!$C$21,100) -> 18500 | S58: =MROUND(M58*'Fuel & Inputs'!$C$20*'Fuel & Inputs'!$C$22,500) -> 249000 | T58: =MROUND(N58*'Fuel & Inputs'!$C$20*'Fuel & Inputs'!$C$22,500) -> 331500 | U58: =MROUND(O58*'Fuel & Inputs'!$C$20*'Fuel & Inputs'!$C$22,500) -> 498000
A59: 51 | B59: Self Loader Mixer | C59: FIORI | D59: 8FO8H01246 | E59: 2017 | F59: TM-13 | G59: Fiori | H59: Diesel | I59: 11 | J59: 1.063 | K59: =IF(I59=0,0,IF(L59="Rs./km",MROUND(IF(H59="Petrol",'Fuel & Inputs'!$C$5,'Fuel & Inputs'!$C$4)/I59*J59,1),MROUND(I59*J59*IF(H59="Petrol",'Fuel & Inputs'!$C$5,'Fuel & Inputs'!$C$4),10))) -> 4470 | L59: Rs./hr | M59: 2440 | N59: =MROUND(M59+'Fuel & Inputs'!$C$13,50) -> 3250 | O59: 4880 | P59: =MROUND(M59*'Fuel & Inputs'!$C$19*'Fuel & Inputs'!$C$21,100) -> 9300 | Q59: =MROUND(N59*'Fuel & Inputs'!$C$19*'Fuel & Inputs'!$C$21,100) -> 12400 | R59: =MROUND(O59*'Fuel & Inputs'!$C$19*'Fuel & Inputs'!$C$21,100) -> 18500 | S59: =MROUND(M59*'Fuel & Inputs'!$C$20*'Fuel & Inputs'!$C$22,500) -> 249000 | T59: =MROUND(N59*'Fuel & Inputs'!$C$20*'Fuel & Inputs'!$C$22,500) -> 331500 | U59: =MROUND(O59*'Fuel & Inputs'!$C$20*'Fuel & Inputs'!$C$22,500) -> 498000
A60: 52 | B60: Self Loader Mixer | C60: FIORI | D60: 8FO8H01252 | E60: 2017 | F60: TM-17 | G60: Fiori | H60: Diesel | I60: 11 | J60: 1.063 | K60: =IF(I60=0,0,IF(L60="Rs./km",MROUND(IF(H60="Petrol",'Fuel & Inputs'!$C$5,'Fuel & Inputs'!$C$4)/I60*J60,1),MROUND(I60*J60*IF(H60="Petrol",'Fuel & Inputs'!$C$5,'Fuel & Inputs'!$C$4),10))) -> 4470 | L60: Rs./hr | M60: 2440 | N60: =MROUND(M60+'Fuel & Inputs'!$C$13,50) -> 3250 | O60: 4880 | P60: =MROUND(M60*'Fuel & Inputs'!$C$19*'Fuel & Inputs'!$C$21,100) -> 9300 | Q60: =MROUND(N60*'Fuel & Inputs'!$C$19*'Fuel & Inputs'!$C$21,100) -> 12400 | R60: =MROUND(O60*'Fuel & Inputs'!$C$19*'Fuel & Inputs'!$C$21,100) -> 18500 | S60: =MROUND(M60*'Fuel & Inputs'!$C$20*'Fuel & Inputs'!$C$22,500) -> 249000 | T60: =MROUND(N60*'Fuel & Inputs'!$C$20*'Fuel & Inputs'!$C$22,500) -> 331500 | U60: =MROUND(O60*'Fuel & Inputs'!$C$20*'Fuel & Inputs'!$C$22,500) -> 498000
A61: STATIC ROLLER
A62: 53 | B62: Static Roller | C62: DYNAPAC | D62: CC425 | E62: 2021 | F62: SR-17 | G62: — | H62: Diesel | I62: 6 | J62: 1.035 | K62: =IF(I62=0,0,IF(L62="Rs./km",MROUND(IF(H62="Petrol",'Fuel & Inputs'!$C$5,'Fuel & Inputs'!$C$4)/I62*J62,1),MROUND(I62*J62*IF(H62="Petrol",'Fuel & Inputs'!$C$5,'Fuel & Inputs'!$C$4),10))) -> 2370 | L62: Rs./hr | M62: 2300 | N62: =MROUND(M62+'Fuel & Inputs'!$C$13,50) -> 3100 | O62: 4600 | P62: =MROUND(M62*'Fuel & Inputs'!$C$19*'Fuel & Inputs'!$C$21,100) -> 8700 | Q62: =MROUND(N62*'Fuel & Inputs'!$C$19*'Fuel & Inputs'!$C$21,100) -> 11800 | R62: =MROUND(O62*'Fuel & Inputs'!$C$19*'Fuel & Inputs'!$C$21,100) -> 17500 | S62: =MROUND(M62*'Fuel & Inputs'!$C$20*'Fuel & Inputs'!$C$22,500) -> 234500 | T62: =MROUND(N62*'Fuel & Inputs'!$C$20*'Fuel & Inputs'!$C$22,500) -> 316000 | U62: =MROUND(O62*'Fuel & Inputs'!$C$20*'Fuel & Inputs'!$C$22,500) -> 469000
A63: 54 | B63: Static Roller | C63: DYNAPAC | D63: CA30D | E63: 2021 | F63: SR-18 | G63: — | H63: Diesel | I63: 6 | J63: 1.035 | K63: =IF(I63=0,0,IF(L63="Rs./km",MROUND(IF(H63="Petrol",'Fuel & Inputs'!$C$5,'Fuel & Inputs'!$C$4)/I63*J63,1),MROUND(I63*J63*IF(H63="Petrol",'Fuel & Inputs'!$C$5,'Fuel & Inputs'!$C$4),10))) -> 2370 | L63: Rs./hr | M63: 2300 | N63: =MROUND(M63+'Fuel & Inputs'!$C$13,50) -> 3100 | O63: 4600 | P63: =MROUND(M63*'Fuel & Inputs'!$C$19*'Fuel & Inputs'!$C$21,100) -> 8700 | Q63: =MROUND(N63*'Fuel & Inputs'!$C$19*'Fuel & Inputs'!$C$21,100) -> 11800 | R63: =MROUND(O63*'Fuel & Inputs'!$C$19*'Fuel & Inputs'!$C$21,100) -> 17500 | S63: =MROUND(M63*'Fuel & Inputs'!$C$20*'Fuel & Inputs'!$C$22,500) -> 234500 | T63: =MROUND(N63*'Fuel & Inputs'!$C$20*'Fuel & Inputs'!$C$22,500) -> 316000 | U63: =MROUND(O63*'Fuel & Inputs'!$C$20*'Fuel & Inputs'!$C$22,500) -> 469000
A64: 55 | B64: Static Roller | C64: DYNAPAC | D64: CA30D | E64: 2021 | F64: SR-19 | G64: — | H64: Diesel | I64: 6 | J64: 1.035 | K64: =IF(I64=0,0,IF(L64="Rs./km",MROUND(IF(H64="Petrol",'Fuel & Inputs'!$C$5,'Fuel & Inputs'!$C$4)/I64*J64,1),MROUND(I64*J64*IF(H64="Petrol",'Fuel & Inputs'!$C$5,'Fuel & Inputs'!$C$4),10))) -> 2370 | L64: Rs./hr | M64: 2300 | N64: =MROUND(M64+'Fuel & Inputs'!$C$13,50) -> 3100 | O64: 4600 | P64: =MROUND(M64*'Fuel & Inputs'!$C$19*'Fuel & Inputs'!$C$21,100) -> 8700 | Q64: =MROUND(N64*'Fuel & Inputs'!$C$19*'Fuel & Inputs'!$C$21,100) -> 11800 | R64: =MROUND(O64*'Fuel & Inputs'!$C$19*'Fuel & Inputs'!$C$21,100) -> 17500 | S64: =MROUND(M64*'Fuel & Inputs'!$C$20*'Fuel & Inputs'!$C$22,500) -> 234500 | T64: =MROUND(N64*'Fuel & Inputs'!$C$20*'Fuel & Inputs'!$C$22,500) -> 316000 | U64: =MROUND(O64*'Fuel & Inputs'!$C$20*'Fuel & Inputs'!$C$22,500) -> 469000
A65: 56 | B65: Static Roller | C65: CASE | D65: 1107EXD | E65: 2017 | F65: SR-08 | G65: — | H65: Diesel | I65: 6 | J65: 1.063 | K65: =IF(I65=0,0,IF(L65="Rs./km",MROUND(IF(H65="Petrol",'Fuel & Inputs'!$C$5,'Fuel & Inputs'!$C$4)/I65*J65,1),MROUND(I65*J65*IF(H65="Petrol",'Fuel & Inputs'!$C$5,'Fuel & Inputs'!$C$4),10))) -> 2440 | L65: Rs./hr | M65: 2120 | N65: =MROUND(M65+'Fuel & Inputs'!$C$13,50) -> 2900 | O65: 4230 | P65: =MROUND(M65*'Fuel & Inputs'!$C$19*'Fuel & Inputs'!$C$21,100) -> 8100 | Q65: =MROUND(N65*'Fuel & Inputs'!$C$19*'Fuel & Inputs'!$C$21,100) -> 11000 | R65: =MROUND(O65*'Fuel & Inputs'!$C$19*'Fuel & Inputs'!$C$21,100) -> 16100 | S65: =MROUND(M65*'Fuel & Inputs'!$C$20*'Fuel & Inputs'!$C$22,500) -> 216000 | T65: =MROUND(N65*'Fuel & Inputs'!$C$20*'Fuel & Inputs'!$C$22,500) -> 296000 | U65: =MROUND(O65*'Fuel & Inputs'!$C$20*'Fuel & Inputs'!$C$22,500) -> 431500
A66: 57 | B66: Static Roller | C66: MACADAM | D66: 1107EXD | E66: 2017 | F66: SR-15 | G66: — | H66: Diesel | I66: 6 | J66: 1.063 | K66: =IF(I66=0,0,IF(L66="Rs./km",MROUND(IF(H66="Petrol",'Fuel & Inputs'!$C$5,'Fuel & Inputs'!$C$4)/I66*J66,1),MROUND(I66*J66*IF(H66="Petrol",'Fuel & Inputs'!$C$5,'Fuel & Inputs'!$C$4),10))) -> 2440 | L66: Rs./hr | M66: 2120 | N66: =MROUND(M66+'Fuel & Inputs'!$C$13,50) -> 2900 | O66: 4230 | P66: =MROUND(M66*'Fuel & Inputs'!$C$19*'Fuel & Inputs'!$C$21,100) -> 8100 | Q66: =MROUND(N66*'Fuel & Inputs'!$C$19*'Fuel & Inputs'!$C$21,100) -> 11000 | R66: =MROUND(O66*'Fuel & Inputs'!$C$19*'Fuel & Inputs'!$C$21,100) -> 16100 | S66: =MROUND(M66*'Fuel & Inputs'!$C$20*'Fuel & Inputs'!$C$22,500) -> 216000 | T66: =MROUND(N66*'Fuel & Inputs'!$C$20*'Fuel & Inputs'!$C$22,500) -> 296000 | U66: =MROUND(O66*'Fuel & Inputs'!$C$20*'Fuel & Inputs'!$C$22,500) -> 431500
A67: 58 | B67: Static Roller | C67: HAMM | D67: HAMM 311D | E67: 2016 | F67: SR-12 | G67: — | H67: Diesel | I67: 6 | J67: 1.07 | K67: =IF(I67=0,0,IF(L67="Rs./km",MROUND(IF(H67="Petrol",'Fuel & Inputs'!$C$5,'Fuel & Inputs'!$C$4)/I67*J67,1),MROUND(I67*J67*IF(H67="Petrol",'Fuel & Inputs'!$C$5,'Fuel & Inputs'!$C$4),10))) -> 2450 | L67: Rs./hr | M67: 2120 | N67: =MROUND(M67+'Fuel & Inputs'!$C$13,50) -> 2900 | O67: 4230 | P67: =MROUND(M67*'Fuel & Inputs'!$C$19*'Fuel & Inputs'!$C$21,100) -> 8100 | Q67: =MROUND(N67*'Fuel & Inputs'!$C$19*'Fuel & Inputs'!$C$21,100) -> 11000 | R67: =MROUND(O67*'Fuel & Inputs'!$C$19*'Fuel & Inputs'!$C$21,100) -> 16100 | S67: =MROUND(M67*'Fuel & Inputs'!$C$20*'Fuel & Inputs'!$C$22,500) -> 216000 | T67: =MROUND(N67*'Fuel & Inputs'!$C$20*'Fuel & Inputs'!$C$22,500) -> 296000 | U67: =MROUND(O67*'Fuel & Inputs'!$C$20*'Fuel & Inputs'!$C$22,500) -> 431500
A68: 59 | B68: Static Roller | C68: CASE | D68: — | E68: 2012 | F68: SR-01 | G68: — | H68: Diesel | I68: 6 | J68: 1.098 | K68: =IF(I68=0,0,IF(L68="Rs./km",MROUND(IF(H68="Petrol",'Fuel & Inputs'!$C$5,'Fuel & Inputs'!$C$4)/I68*J68,1),MROUND(I68*J68*IF(H68="Petrol",'Fuel & Inputs'!$C$5,'Fuel & Inputs'!$C$4),10))) -> 2520 | L68: Rs./hr | M68: 1890 | N68: =MROUND(M68+'Fuel & Inputs'!$C$13,50) -> 2700 | O68: 3770 | P68: =MROUND(M68*'Fuel & Inputs'!$C$19*'Fuel & Inputs'!$C$21,100) -> 7200 | Q68: =MROUND(N68*'Fuel & Inputs'!$C$19*'Fuel & Inputs'!$C$21,100) -> 10300 | R68: =MROUND(O68*'Fuel & Inputs'!$C$19*'Fuel & Inputs'!$C$21,100) -> 14300 | S68: =MROUND(M68*'Fuel & Inputs'!$C$20*'Fuel & Inputs'!$C$22,500) -> 193000 | T68: =MROUND(N68*'Fuel & Inputs'!$C$20*'Fuel & Inputs'!$C$22,500) -> 275500 | U68: =MROUND(O68*'Fuel & Inputs'!$C$20*'Fuel & Inputs'!$C$22,500) -> 384500
A69: 60 | B69: Static Roller | C69: SAKAI | D69: SW-900 | E69: 2014 | F69: SR-05 | G69: — | H69: Diesel | I69: 6 | J69: 1.084 | K69: =IF(I69=0,0,IF(L69="Rs./km",MROUND(IF(H69="Petrol",'Fuel & Inputs'!$C$5,'Fuel & Inputs'!$C$4)/I69*J69,1),MROUND(I69*J69*IF(H69="Petrol",'Fuel & Inputs'!$C$5,'Fuel & Inputs'!$C$4),10))) -> 2480 | L69: Rs./hr | M69: 1890 | N69: =MROUND(M69+'Fuel & Inputs'!$C$13,50) -> 2700 | O69: 3770 | P69: =MROUND(M69*'Fuel & Inputs'!$C$19*'Fuel & Inputs'!$C$21,100) -> 7200 | Q69: =MROUND(N69*'Fuel & Inputs'!$C$19*'Fuel & Inputs'!$C$21,100) -> 10300 | R69: =MROUND(O69*'Fuel & Inputs'!$C$19*'Fuel & Inputs'!$C$21,100) -> 14300 | S69: =MROUND(M69*'Fuel & Inputs'!$C$20*'Fuel & Inputs'!$C$22,500) -> 193000 | T69: =MROUND(N69*'Fuel & Inputs'!$C$20*'Fuel & Inputs'!$C$22,500) -> 275500 | U69: =MROUND(O69*'Fuel & Inputs'!$C$20*'Fuel & Inputs'!$C$22,500) -> 384500
A70: 61 | B70: Static Roller | C70: (Unknown) | D70: R12 | E70: 2009 | F70: SR-02 | G70: — | H70: Diesel | I70: 6 | J70: 1.119 | K70: =IF(I70=0,0,IF(L70="Rs./km",MROUND(IF(H70="Petrol",'Fuel & Inputs'!$C$5,'Fuel & Inputs'!$C$4)/I70*J70,1),MROUND(I70*J70*IF(H70="Petrol",'Fuel & Inputs'!$C$5,'Fuel & Inputs'!$C$4),10))) -> 2560 | L70: Rs./hr | M70: 1890 | N70: =MROUND(M70+'Fuel & Inputs'!$C$13,50) -> 2700 | O70: 3770 | P70: =MROUND(M70*'Fuel & Inputs'!$C$19*'Fuel & Inputs'!$C$21,100) -> 7200 | Q70: =MROUND(N70*'Fuel & Inputs'!$C$19*'Fuel & Inputs'!$C$21,100) -> 10300 | R70: =MROUND(O70*'Fuel & Inputs'!$C$19*'Fuel & Inputs'!$C$21,100) -> 14300 | S70: =MROUND(M70*'Fuel & Inputs'!$C$20*'Fuel & Inputs'!$C$22,500) -> 193000 | T70: =MROUND(N70*'Fuel & Inputs'!$C$20*'Fuel & Inputs'!$C$22,500) -> 275500 | U70: =MROUND(O70*'Fuel & Inputs'!$C$20*'Fuel & Inputs'!$C$22,500) -> 384500
A71: 62 | B71: Static Roller | C71: (Unknown) | D71: — | E71: 2012 | F71: SR-03 | G71: — | H71: Diesel | I71: 6 | J71: 1.098 | K71: =IF(I71=0,0,IF(L71="Rs./km",MROUND(IF(H71="Petrol",'Fuel & Inputs'!$C$5,'Fuel & Inputs'!$C$4)/I71*J71,1),MROUND(I71*J71*IF(H71="Petrol",'Fuel & Inputs'!$C$5,'Fuel & Inputs'!$C$4),10))) -> 2520 | L71: Rs./hr | M71: 1890 | N71: =MROUND(M71+'Fuel & Inputs'!$C$13,50) -> 2700 | O71: 3770 | P71: =MROUND(M71*'Fuel & Inputs'!$C$19*'Fuel & Inputs'!$C$21,100) -> 7200 | Q71: =MROUND(N71*'Fuel & Inputs'!$C$19*'Fuel & Inputs'!$C$21,100) -> 10300 | R71: =MROUND(O71*'Fuel & Inputs'!$C$19*'Fuel & Inputs'!$C$21,100) -> 14300 | S71: =MROUND(M71*'Fuel & Inputs'!$C$20*'Fuel & Inputs'!$C$22,500) -> 193000 | T71: =MROUND(N71*'Fuel & Inputs'!$C$20*'Fuel & Inputs'!$C$22,500) -> 275500 | U71: =MROUND(O71*'Fuel & Inputs'!$C$20*'Fuel & Inputs'!$C$22,500) -> 384500
A72: 63 | B72: Static Roller | C72: (Unknown) | D72: — | E72: 2013 | F72: SR-04 | G72: — | H72: Diesel | I72: 6 | J72: 1.091 | K72: =IF(I72=0,0,IF(L72="Rs./km",MROUND(IF(H72="Petrol",'Fuel & Inputs'!$C$5,'Fuel & Inputs'!$C$4)/I72*J72,1),MROUND(I72*J72*IF(H72="Petrol",'Fuel & Inputs'!$C$5,'Fuel & Inputs'!$C$4),10))) -> 2500 | L72: Rs./hr | M72: 1890 | N72: =MROUND(M72+'Fuel & Inputs'!$C$13,50) -> 2700 | O72: 3770 | P72: =MROUND(M72*'Fuel & Inputs'!$C$19*'Fuel & Inputs'!$C$21,100) -> 7200 | Q72: =MROUND(N72*'Fuel & Inputs'!$C$19*'Fuel & Inputs'!$C$21,100) -> 10300 | R72: =MROUND(O72*'Fuel & Inputs'!$C$19*'Fuel & Inputs'!$C$21,100) -> 14300 | S72: =MROUND(M72*'Fuel & Inputs'!$C$20*'Fuel & Inputs'!$C$22,500) -> 193000 | T72: =MROUND(N72*'Fuel & Inputs'!$C$20*'Fuel & Inputs'!$C$22,500) -> 275500 | U72: =MROUND(O72*'Fuel & Inputs'!$C$20*'Fuel & Inputs'!$C$22,500) -> 384500
A73: 64 | B73: Static Roller | C73: IR | D73: 2860-01 | E73: 2010 | F73: SR-07 | G73: — | H73: Diesel | I73: 6 | J73: 1.112 | K73: =IF(I73=0,0,IF(L73="Rs./km",MROUND(IF(H73="Petrol",'Fuel & Inputs'!$C$5,'Fuel & Inputs'!$C$4)/I73*J73,1),MROUND(I73*J73*IF(H73="Petrol",'Fuel & Inputs'!$C$5,'Fuel & Inputs'!$C$4),10))) -> 2550 | L73: Rs./hr | M73: 1890 | N73: =MROUND(M73+'Fuel & Inputs'!$C$13,50) -> 2700 | O73: 3770 | P73: =MROUND(M73*'Fuel & Inputs'!$C$19*'Fuel & Inputs'!$C$21,100) -> 7200 | Q73: =MROUND(N73*'Fuel & Inputs'!$C$19*'Fuel & Inputs'!$C$21,100) -> 10300 | R73: =MROUND(O73*'Fuel & Inputs'!$C$19*'Fuel & Inputs'!$C$21,100) -> 14300 | S73: =MROUND(M73*'Fuel & Inputs'!$C$20*'Fuel & Inputs'!$C$22,500) -> 193000 | T73: =MROUND(N73*'Fuel & Inputs'!$C$20*'Fuel & Inputs'!$C$22,500) -> 275500 | U73: =MROUND(O73*'Fuel & Inputs'!$C$20*'Fuel & Inputs'!$C$22,500) -> 384500
... A80: 71 | B80: Static Roller | C80: SAKAI | D80: R2V | E80: — | F80: SR-14 | G80: — | H80: Diesel | I80: 6 | J80: 1 | K80: =IF(I80=0,0,IF(L80="Rs./km",MROUND(IF(H80="Petrol",'Fuel & Inputs'!$C$5,'Fuel & Inputs'!$C$4)/I80*J80,1),MROUND(I80*J80*IF(H80="Petrol",'Fuel & Inputs'!$C$5,'Fuel & Inputs'!$C$4),10))) -> 2290 | L80: Rs./hr | M80: 1330 | N80: =MROUND(M80+'Fuel & Inputs'!$C$13,50) -> 2150 | O80: 2670 | P80: =MROUND(M80*'Fuel & Inputs'!$C$19*'Fuel & Inputs'!$C$21,100) -> 5100 | Q80: =MROUND(N80*'Fuel & Inputs'!$C$19*'Fuel & Inputs'!$C$21,100) -> 8200 | R80: =MROUND(O80*'Fuel & Inputs'!$C$19*'Fuel & Inputs'!$C$21,100) -> 10100 | S80: =MROUND(M80*'Fuel & Inputs'!$C$20*'Fuel & Inputs'!$C$22,500) -> 135500 | T80: =MROUND(N80*'Fuel & Inputs'!$C$20*'Fuel & Inputs'!$C$22,500) -> 219500 | U80: =MROUND(O80*'Fuel & Inputs'!$C$20*'Fuel & Inputs'!$C$22,500) -> 272500
A81: VIBRATING ROLLER
A82: 72 | B82: Vibrating Roller | C82: (Unknown) | D82: — | E82: 2010 | F82: VR-01 | G82: — | H82: Diesel | I82: 10 | J82: 1.112 | K82: =IF(I82=0,0,IF(L82="Rs./km",MROUND(IF(H82="Petrol",'Fuel & Inputs'!$C$5,'Fuel & Inputs'!$C$4)/I82*J82,1),MROUND(I82*J82*IF(H82="Petrol",'Fuel & Inputs'!$C$5,'Fuel & Inputs'!$C$4),10))) -> 4250 | L82: Rs./hr | M82: 1790 | N82: =MROUND(M82+'Fuel & Inputs'!$C$13,50) -> 2600 | O82: 3590 | P82: =MROUND(M82*'Fuel & Inputs'!$C$19*'Fuel & Inputs'!$C$21,100) -> 6800 | Q82: =MROUND(N82*'Fuel & Inputs'!$C$19*'Fuel & Inputs'!$C$21,100) -> 9900 | R82: =MROUND(O82*'Fuel & Inputs'!$C$19*'Fuel & Inputs'!$C$21,100) -> 13600 | S82: =MROUND(M82*'Fuel & Inputs'!$C$20*'Fuel & Inputs'!$C$22,500) -> 182500 | T82: =MROUND(N82*'Fuel & Inputs'!$C$20*'Fuel & Inputs'!$C$22,500) -> 265000 | U82: =MROUND(O82*'Fuel & Inputs'!$C$20*'Fuel & Inputs'!$C$22,500) -> 366000
A83: 73 | B83: Vibrating Roller | C83: KOMATSU | D83: SL203468 | E83: 2012 | F83: VR-02 | G83: — | H83: Diesel | I83: 10 | J83: 1.098 | K83: =IF(I83=0,0,IF(L83="Rs./km",MROUND(IF(H83="Petrol",'Fuel & Inputs'!$C$5,'Fuel & Inputs'!$C$4)/I83*J83,1),MROUND(I83*J83*IF(H83="Petrol",'Fuel & Inputs'!$C$5,'Fuel & Inputs'!$C$4),10))) -> 4190 | L83: Rs./hr | M83: 1790 | N83: =MROUND(M83+'Fuel & Inputs'!$C$13,50) -> 2600 | O83: 3590 | P83: =MROUND(M83*'Fuel & Inputs'!$C$19*'Fuel & Inputs'!$C$21,100) -> 6800 | Q83: =MROUND(N83*'Fuel & Inputs'!$C$19*'Fuel & Inputs'!$C$21,100) -> 9900 | R83: =MROUND(O83*'Fuel & Inputs'!$C$19*'Fuel & Inputs'!$C$21,100) -> 13600 | S83: =MROUND(M83*'Fuel & Inputs'!$C$20*'Fuel & Inputs'!$C$22,500) -> 182500 | T83: =MROUND(N83*'Fuel & Inputs'!$C$20*'Fuel & Inputs'!$C$22,500) -> 265000 | U83: =MROUND(O83*'Fuel & Inputs'!$C$20*'Fuel & Inputs'!$C$22,500) -> 366000
A84: 74 | B84: Vibrating Roller | C84: (Unknown) | D84: — | E84: 2013 | F84: VR-03 | G84: — | H84: Diesel | I84: 10 | J84: 1.091 | K84: =IF(I84=0,0,IF(L84="Rs./km",MROUND(IF(H84="Petrol",'Fuel & Inputs'!$C$5,'Fuel & Inputs'!$C$4)/I84*J84,1),MROUND(I84*J84*IF(H84="Petrol",'Fuel & Inputs'!$C$5,'Fuel & Inputs'!$C$4),10))) -> 4170 | L84: Rs./hr | M84: 1790 | N84: =MROUND(M84+'Fuel & Inputs'!$C$13,50) -> 2600 | O84: 3590 | P84: =MROUND(M84*'Fuel & Inputs'!$C$19*'Fuel & Inputs'!$C$21,100) -> 6800 | Q84: =MROUND(N84*'Fuel & Inputs'!$C$19*'Fuel & Inputs'!$C$21,100) -> 9900 | R84: =MROUND(O84*'Fuel & Inputs'!$C$19*'Fuel & Inputs'!$C$21,100) -> 13600 | S84: =MROUND(M84*'Fuel & Inputs'!$C$20*'Fuel & Inputs'!$C$22,500) -> 182500 | T84: =MROUND(N84*'Fuel & Inputs'!$C$20*'Fuel & Inputs'!$C$22,500) -> 265000 | U84: =MROUND(O84*'Fuel & Inputs'!$C$20*'Fuel & Inputs'!$C$22,500) -> 366000
A85: 75 | B85: Vibrating Roller | C85: BOMAG | D85: BW-138 AD | E85: 2016 | F85: VR-14 | G85: — | H85: Diesel | I85: 10 | J85: 1.07 | K85: =IF(I85=0,0,IF(L85="Rs./km",MROUND(IF(H85="Petrol",'Fuel & Inputs'!$C$5,'Fuel & Inputs'!$C$4)/I85*J85,1),MROUND(I85*J85*IF(H85="Petrol",'Fuel & Inputs'!$C$5,'Fuel & Inputs'!$C$4),10))) -> 4090 | L85: Rs./hr | M85: 1790 | N85: =MROUND(M85+'Fuel & Inputs'!$C$13,50) -> 2600 | O85: 3590 | P85: =MROUND(M85*'Fuel & Inputs'!$C$19*'Fuel & Inputs'!$C$21,100) -> 6800 | Q85: =MROUND(N85*'Fuel & Inputs'!$C$19*'Fuel & Inputs'!$C$21,100) -> 9900 | R85: =MROUND(O85*'Fuel & Inputs'!$C$19*'Fuel & Inputs'!$C$21,100) -> 13600 | S85: =MROUND(M85*'Fuel & Inputs'!$C$20*'Fuel & Inputs'!$C$22,500) -> 182500 | T85: =MROUND(N85*'Fuel & Inputs'!$C$20*'Fuel & Inputs'!$C$22,500) -> 265000 | U85: =MROUND(O85*'Fuel & Inputs'!$C$20*'Fuel & Inputs'!$C$22,500) -> 366000
A86: 76 | B86: Vibrating Roller | C86: BOMAG | D86: SA-00-350 | E86: 2016 | F86: VR-18 | G86: — | H86: Diesel | I86: 10 | J86: 1.07 | K86: =IF(I86=0,0,IF(L86="Rs./km",MROUND(IF(H86="Petrol",'Fuel & Inputs'!$C$5,'Fuel & Inputs'!$C$4)/I86*J86,1),MROUND(I86*J86*IF(H86="Petrol",'Fuel & Inputs'!$C$5,'Fuel & Inputs'!$C$4),10))) -> 4090 | L86: Rs./hr | M86: 1790 | N86: =MROUND(M86+'Fuel & Inputs'!$C$13,50) -> 2600 | O86: 3590 | P86: =MROUND(M86*'Fuel & Inputs'!$C$19*'Fuel & Inputs'!$C$21,100) -> 6800 | Q86: =MROUND(N86*'Fuel & Inputs'!$C$19*'Fuel & Inputs'!$C$21,100) -> 9900 | R86: =MROUND(O86*'Fuel & Inputs'!$C$19*'Fuel & Inputs'!$C$21,100) -> 13600 | S86: =MROUND(M86*'Fuel & Inputs'!$C$20*'Fuel & Inputs'!$C$22,500) -> 182500 | T86: =MROUND(N86*'Fuel & Inputs'!$C$20*'Fuel & Inputs'!$C$22,500) -> 265000 | U86: =MROUND(O86*'Fuel & Inputs'!$C$20*'Fuel & Inputs'!$C$22,500) -> 366000
A87: 77 | B87: Vibrating Roller | C87: BOMAG | D87: BW 75 H | E87: 2016 | F87: VR-31 | G87: — | H87: Diesel | I87: 10 | J87: 1.07 | K87: =IF(I87=0,0,IF(L87="Rs./km",MROUND(IF(H87="Petrol",'Fuel & Inputs'!$C$5,'Fuel & Inputs'!$C$4)/I87*J87,1),MROUND(I87*J87*IF(H87="Petrol",'Fuel & Inputs'!$C$5,'Fuel & Inputs'!$C$4),10))) -> 4090 | L87: Rs./hr | M87: 1790 | N87: =MROUND(M87+'Fuel & Inputs'!$C$13,50) -> 2600 | O87: 3590 | P87: =MROUND(M87*'Fuel & Inputs'!$C$19*'Fuel & Inputs'!$C$21,100) -> 6800 | Q87: =MROUND(N87*'Fuel & Inputs'!$C$19*'Fuel & Inputs'!$C$21,100) -> 9900 | R87: =MROUND(O87*'Fuel & Inputs'!$C$19*'Fuel & Inputs'!$C$21,100) -> 13600 | S87: =MROUND(M87*'Fuel & Inputs'!$C$20*'Fuel & Inputs'!$C$22,500) -> 182500 | T87: =MROUND(N87*'Fuel & Inputs'!$C$20*'Fuel & Inputs'!$C$22,500) -> 265000 | U87: =MROUND(O87*'Fuel & Inputs'!$C$20*'Fuel & Inputs'!$C$22,500) -> 366000
A88: 78 | B88: Vibrating Roller | C88: TACOM | D88: TFR60TDS | E88: 2016 | F88: VR-30 | G88: — | H88: Diesel | I88: 10 | J88: 1.07 | K88: =IF(I88=0,0,IF(L88="Rs./km",MROUND(IF(H88="Petrol",'Fuel & Inputs'!$C$5,'Fuel & Inputs'!$C$4)/I88*J88,1),MROUND(I88*J88*IF(H88="Petrol",'Fuel & Inputs'!$C$5,'Fuel & Inputs'!$C$4),10))) -> 4090 | L88: Rs./hr | M88: 1790 | N88: =MROUND(M88+'Fuel & Inputs'!$C$13,50) -> 2600 | O88: 3590 | P88: =MROUND(M88*'Fuel & Inputs'!$C$19*'Fuel & Inputs'!$C$21,100) -> 6800 | Q88: =MROUND(N88*'Fuel & Inputs'!$C$19*'Fuel & Inputs'!$C$21,100) -> 9900 | R88: =MROUND(O88*'Fuel & Inputs'!$C$19*'Fuel & Inputs'!$C$21,100) -> 13600 | S88: =MROUND(M88*'Fuel & Inputs'!$C$20*'Fuel & Inputs'!$C$22,500) -> 182500 | T88: =MROUND(N88*'Fuel & Inputs'!$C$20*'Fuel & Inputs'!$C$22,500) -> 265000 | U88: =MROUND(O88*'Fuel & Inputs'!$C$20*'Fuel & Inputs'!$C$22,500) -> 366000
A89: 79 | B89: Vibrating Roller | C89: TACOM | D89: BW 75 H | E89: 2016 | F89: VR-32 | G89: — | H89: Diesel | I89: 10 | J89: 1.07 | K89: =IF(I89=0,0,IF(L89="Rs./km",MROUND(IF(H89="Petrol",'Fuel & Inputs'!$C$5,'Fuel & Inputs'!$C$4)/I89*J89,1),MROUND(I89*J89*IF(H89="Petrol",'Fuel & Inputs'!$C$5,'Fuel & Inputs'!$C$4),10))) -> 4090 | L89: Rs./hr | M89: 1790 | N89: =MROUND(M89+'Fuel & Inputs'!$C$13,50) -> 2600 | O89: 3590 | P89: =MROUND(M89*'Fuel & Inputs'!$C$19*'Fuel & Inputs'!$C$21,100) -> 6800 | Q89: =MROUND(N89*'Fuel & Inputs'!$C$19*'Fuel & Inputs'!$C$21,100) -> 9900 | R89: =MROUND(O89*'Fuel & Inputs'!$C$19*'Fuel & Inputs'!$C$21,100) -> 13600 | S89: =MROUND(M89*'Fuel & Inputs'!$C$20*'Fuel & Inputs'!$C$22,500) -> 182500 | T89: =MROUND(N89*'Fuel & Inputs'!$C$20*'Fuel & Inputs'!$C$22,500) -> 265000 | U89: =MROUND(O89*'Fuel & Inputs'!$C$20*'Fuel & Inputs'!$C$22,500) -> 366000
A90: 80 | B90: Vibrating Roller | C90: TACOM | D90: BW 75 H | E90: 2016 | F90: VR-69 | G90: — | H90: Diesel | I90: 10 | J90: 1.07 | K90: =IF(I90=0,0,IF(L90="Rs./km",MROUND(IF(H90="Petrol",'Fuel & Inputs'!$C$5,'Fuel & Inputs'!$C$4)/I90*J90,1),MROUND(I90*J90*IF(H90="Petrol",'Fuel & Inputs'!$C$5,'Fuel & Inputs'!$C$4),10))) -> 4090 | L90: Rs./hr | M90: 1790 | N90: =MROUND(M90+'Fuel & Inputs'!$C$13,50) -> 2600 | O90: 3590 | P90: =MROUND(M90*'Fuel & Inputs'!$C$19*'Fuel & Inputs'!$C$21,100) -> 6800 | Q90: =MROUND(N90*'Fuel & Inputs'!$C$19*'Fuel & Inputs'!$C$21,100) -> 9900 | R90: =MROUND(O90*'Fuel & Inputs'!$C$19*'Fuel & Inputs'!$C$21,100) -> 13600 | S90: =MROUND(M90*'Fuel & Inputs'!$C$20*'Fuel & Inputs'!$C$22,500) -> 182500 | T90: =MROUND(N90*'Fuel & Inputs'!$C$20*'Fuel & Inputs'!$C$22,500) -> 265000 | U90: =MROUND(O90*'Fuel & Inputs'!$C$20*'Fuel & Inputs'!$C$22,500) -> 366000
A91: 81 | B91: Vibrating Roller | C91: (Unknown) | D91: — | E91: 2010 | F91: VR-04 | G91: — | H91: Diesel | I91: 10 | J91: 1.112 | K91: =IF(I91=0,0,IF(L91="Rs./km",MROUND(IF(H91="Petrol",'Fuel & Inputs'!$C$5,'Fuel & Inputs'!$C$4)/I91*J91,1),MROUND(I91*J91*IF(H91="Petrol",'Fuel & Inputs'!$C$5,'Fuel & Inputs'!$C$4),10))) -> 4250 | L91: Rs./hr | M91: 1790 | N91: =MROUND(M91+'Fuel & Inputs'!$C$13,50) -> 2600 | O91: 3590 | P91: =MROUND(M91*'Fuel & Inputs'!$C$19*'Fuel & Inputs'!$C$21,100) -> 6800 | Q91: =MROUND(N91*'Fuel & Inputs'!$C$19*'Fuel & Inputs'!$C$21,100) -> 9900 | R91: =MROUND(O91*'Fuel & Inputs'!$C$19*'Fuel & Inputs'!$C$21,100) -> 13600 | S91: =MROUND(M91*'Fuel & Inputs'!$C$20*'Fuel & Inputs'!$C$22,500) -> 182500 | T91: =MROUND(N91*'Fuel & Inputs'!$C$20*'Fuel & Inputs'!$C$22,500) -> 265000 | U91: =MROUND(O91*'Fuel & Inputs'!$C$20*'Fuel & Inputs'!$C$22,500) -> 366000
A92: 82 | B92: Vibrating Roller | C92: BOMAG | D92: BW 75 H | E92: 2015 | F92: VR-28 | G92: — | H92: Diesel | I92: 10 | J92: 1.077 | K92: =IF(I92=0,0,IF(L92="Rs./km",MROUND(IF(H92="Petrol",'Fuel & Inputs'!$C$5,'Fuel & Inputs'!$C$4)/I92*J92,1),MROUND(I92*J92*IF(H92="Petrol",'Fuel & Inputs'!$C$5,'Fuel & Inputs'!$C$4),10))) -> 4110 | L92: Rs./hr | M92: 1790 | N92: =MROUND(M92+'Fuel & Inputs'!$C$13,50) -> 2600 | O92: 3590 | P92: =MROUND(M92*'Fuel & Inputs'!$C$19*'Fuel & Inputs'!$C$21,100) -> 6800 | Q92: =MROUND(N92*'Fuel & Inputs'!$C$19*'Fuel & Inputs'!$C$21,100) -> 9900 | R92: =MROUND(O92*'Fuel & Inputs'!$C$19*'Fuel & Inputs'!$C$21,100) -> 13600 | S92: =MROUND(M92*'Fuel & Inputs'!$C$20*'Fuel & Inputs'!$C$22,500) -> 182500 | T92: =MROUND(N92*'Fuel & Inputs'!$C$20*'Fuel & Inputs'!$C$22,500) -> 265000 | U92: =MROUND(O92*'Fuel & Inputs'!$C$20*'Fuel & Inputs'!$C$22,500) -> 366000
A93: 83 | B93: Vibrating Roller | C93: TACOM | D93: TFR60TDS | E93: 2015 | F93: VR-29 | G93: — | H93: Diesel | I93: 10 | J93: 1.077 | K93: =IF(I93=0,0,IF(L93="Rs./km",MROUND(IF(H93="Petrol",'Fuel & Inputs'!$C$5,'Fuel & Inputs'!$C$4)/I93*J93,1),MROUND(I93*J93*IF(H93="Petrol",'Fuel & Inputs'!$C$5,'Fuel & Inputs'!$C$4),10))) -> 4110 | L93: Rs./hr | M93: 1790 | N93: =MROUND(M93+'Fuel & Inputs'!$C$13,50) -> 2600 | O93: 3590 | P93: =MROUND(M93*'Fuel & Inputs'!$C$19*'Fuel & Inputs'!$C$21,100) -> 6800 | Q93: =MROUND(N93*'Fuel & Inputs'!$C$19*'Fuel & Inputs'!$C$21,100) -> 9900 | R93: =MROUND(O93*'Fuel & Inputs'!$C$19*'Fuel & Inputs'!$C$21,100) -> 13600 | S93: =MROUND(M93*'Fuel & Inputs'!$C$20*'Fuel & Inputs'!$C$22,500) -> 182500 | T93: =MROUND(N93*'Fuel & Inputs'!$C$20*'Fuel & Inputs'!$C$22,500) -> 265000 | U93: =MROUND(O93*'Fuel & Inputs'!$C$20*'Fuel & Inputs'!$C$22,500) -> 366000
... A153: 143 | B153: Vibrating Roller | C153: SAKAI | D153: TW-41 | E153: — | F153: VR-45 | G153: — | H153: Diesel | I153: 10 | J153: 1 | K153: =IF(I153=0,0,IF(L153="Rs./km",MROUND(IF(H153="Petrol",'Fuel & Inputs'!$C$5,'Fuel & Inputs'!$C$4)/I153*J153,1),MROUND(I153*J153*IF(H153="Petrol",'Fuel & Inputs'!$C$5,'Fuel & Inputs'!$C$4),10))) -> 3820 | L153: Rs./hr | M153: 1130 | N153: =MROUND(M153+'Fuel & Inputs'!$C$13,50) -> 1950 | O153: 2260 | P153: =MROUND(M153*'Fuel & Inputs'!$C$19*'Fuel & Inputs'!$C$21,100) -> 4300 | Q153: =MROUND(N153*'Fuel & Inputs'!$C$19*'Fuel & Inputs'!$C$21,100) -> 7400 | R153: =MROUND(O153*'Fuel & Inputs'!$C$19*'Fuel & Inputs'!$C$21,100) -> 8600 | S153: =MROUND(M153*'Fuel & Inputs'!$C$20*'Fuel & Inputs'!$C$22,500) -> 115500 | T153: =MROUND(N153*'Fuel & Inputs'!$C$20*'Fuel & Inputs'!$C$22,500) -> 199000 | U153: =MROUND(O153*'Fuel & Inputs'!$C$20*'Fuel & Inputs'!$C$22,500) -> 230500
A154: PNEUMATIC ROLLER
A155: 144 | B155: Pneumatic Roller | C155: (Unknown) | D155: — | E155: 2012 | F155: PTR-03 | G155: — | H155: Diesel | I155: 9 | J155: 1.098 | K155: =IF(I155=0,0,IF(L155="Rs./km",MROUND(IF(H155="Petrol",'Fuel & Inputs'!$C$5,'Fuel & Inputs'!$C$4)/I155*J155,1),MROUND(I155*J155*IF(H155="Petrol",'Fuel & Inputs'!$C$5,'Fuel & Inputs'!$C$4),10))) -> 3770 | L155: Rs./hr | M155: 1640 | N155: =MROUND(M155+'Fuel & Inputs'!$C$13,50) -> 2450 | O155: 3240 | P155: =MROUND(M155*'Fuel & Inputs'!$C$19*'Fuel & Inputs'!$C$21,100) -> 6200 | Q155: =MROUND(N155*'Fuel & Inputs'!$C$19*'Fuel & Inputs'!$C$21,100) -> 9300 | R155: =MROUND(O155*'Fuel & Inputs'!$C$19*'Fuel & Inputs'!$C$21,100) -> 12300 | S155: =MROUND(M155*'Fuel & Inputs'!$C$20*'Fuel & Inputs'!$C$22,500) -> 167500 | T155: =MROUND(N155*'Fuel & Inputs'!$C$20*'Fuel & Inputs'!$C$22,500) -> 250000 | U155: =MROUND(O155*'Fuel & Inputs'!$C$20*'Fuel & Inputs'!$C$22,500) -> 330500
A156: 145 | B156: Pneumatic Roller | C156: DYNAPAC | D156: CP-201W | E156: 2012 | F156: PTR-04 | G156: — | H156: Diesel | I156: 9 | J156: 1.098 | K156: =IF(I156=0,0,IF(L156="Rs./km",MROUND(IF(H156="Petrol",'Fuel & Inputs'!$C$5,'Fuel & Inputs'!$C$4)/I156*J156,1),MROUND(I156*J156*IF(H156="Petrol",'Fuel & Inputs'!$C$5,'Fuel & Inputs'!$C$4),10))) -> 3770 | L156: Rs./hr | M156: 1640 | N156: =MROUND(M156+'Fuel & Inputs'!$C$13,50) -> 2450 | O156: 3240 | P156: =MROUND(M156*'Fuel & Inputs'!$C$19*'Fuel & Inputs'!$C$21,100) -> 6200 | Q156: =MROUND(N156*'Fuel & Inputs'!$C$19*'Fuel & Inputs'!$C$21,100) -> 9300 | R156: =MROUND(O156*'Fuel & Inputs'!$C$19*'Fuel & Inputs'!$C$21,100) -> 12300 | S156: =MROUND(M156*'Fuel & Inputs'!$C$20*'Fuel & Inputs'!$C$22,500) -> 167500 | T156: =MROUND(N156*'Fuel & Inputs'!$C$20*'Fuel & Inputs'!$C$22,500) -> 250000 | U156: =MROUND(O156*'Fuel & Inputs'!$C$20*'Fuel & Inputs'!$C$22,500) -> 330500
A157: 146 | B157: Pneumatic Roller | C157: DYNAPAC | D157: CP-201W | E157: 2012 | F157: PTR-05 | G157: — | H157: Diesel | I157: 9 | J157: 1.098 | K157: =IF(I157=0,0,IF(L157="Rs./km",MROUND(IF(H157="Petrol",'Fuel & Inputs'!$C$5,'Fuel & Inputs'!$C$4)/I157*J157,1),MROUND(I157*J157*IF(H157="Petrol",'Fuel & Inputs'!$C$5,'Fuel & Inputs'!$C$4),10))) -> 3770 | L157: Rs./hr | M157: 1640 | N157: =MROUND(M157+'Fuel & Inputs'!$C$13,50) -> 2450 | O157: 3240 | P157: =MROUND(M157*'Fuel & Inputs'!$C$19*'Fuel & Inputs'!$C$21,100) -> 6200 | Q157: =MROUND(N157*'Fuel & Inputs'!$C$19*'Fuel & Inputs'!$C$21,100) -> 9300 | R157: =MROUND(O157*'Fuel & Inputs'!$C$19*'Fuel & Inputs'!$C$21,100) -> 12300 | S157: =MROUND(M157*'Fuel & Inputs'!$C$20*'Fuel & Inputs'!$C$22,500) -> 167500 | T157: =MROUND(N157*'Fuel & Inputs'!$C$20*'Fuel & Inputs'!$C$22,500) -> 250000 | U157: =MROUND(O157*'Fuel & Inputs'!$C$20*'Fuel & Inputs'!$C$22,500) -> 330500
A158: 147 | B158: Pneumatic Roller | C158: FURUKAWA | D158: FT-20W | E158: 2012 | F158: PTR-07 | G158: — | H158: Diesel | I158: 9 | J158: 1.098 | K158: =IF(I158=0,0,IF(L158="Rs./km",MROUND(IF(H158="Petrol",'Fuel & Inputs'!$C$5,'Fuel & Inputs'!$C$4)/I158*J158,1),MROUND(I158*J158*IF(H158="Petrol",'Fuel & Inputs'!$C$5,'Fuel & Inputs'!$C$4),10))) -> 3770 | L158: Rs./hr | M158: 1640 | N158: =MROUND(M158+'Fuel & Inputs'!$C$13,50) -> 2450 | O158: 3240 | P158: =MROUND(M158*'Fuel & Inputs'!$C$19*'Fuel & Inputs'!$C$21,100) -> 6200 | Q158: =MROUND(N158*'Fuel & Inputs'!$C$19*'Fuel & Inputs'!$C$21,100) -> 9300 | R158: =MROUND(O158*'Fuel & Inputs'!$C$19*'Fuel & Inputs'!$C$21,100) -> 12300 | S158: =MROUND(M158*'Fuel & Inputs'!$C$20*'Fuel & Inputs'!$C$22,500) -> 167500 | T158: =MROUND(N158*'Fuel & Inputs'!$C$20*'Fuel & Inputs'!$C$22,500) -> 250000 | U158: =MROUND(O158*'Fuel & Inputs'!$C$20*'Fuel & Inputs'!$C$22,500) -> 330500
A159: 148 | B159: Pneumatic Roller | C159: KAWASAKI | D159: KR-20 D | E159: 2012 | F159: PTR-01 | G159: — | H159: Diesel | I159: 9 | J159: 1.098 | K159: =IF(I159=0,0,IF(L159="Rs./km",MROUND(IF(H159="Petrol",'Fuel & Inputs'!$C$5,'Fuel & Inputs'!$C$4)/I159*J159,1),MROUND(I159*J159*IF(H159="Petrol",'Fuel & Inputs'!$C$5,'Fuel & Inputs'!$C$4),10))) -> 3770 | L159: Rs./hr | M159: 1640 | N159: =MROUND(M159+'Fuel & Inputs'!$C$13,50) -> 2450 | O159: 3240 | P159: =MROUND(M159*'Fuel & Inputs'!$C$19*'Fuel & Inputs'!$C$21,100) -> 6200 | Q159: =MROUND(N159*'Fuel & Inputs'!$C$19*'Fuel & Inputs'!$C$21,100) -> 9300 | R159: =MROUND(O159*'Fuel & Inputs'!$C$19*'Fuel & Inputs'!$C$21,100) -> 12300 | S159: =MROUND(M159*'Fuel & Inputs'!$C$20*'Fuel & Inputs'!$C$22,500) -> 167500 | T159: =MROUND(N159*'Fuel & Inputs'!$C$20*'Fuel & Inputs'!$C$22,500) -> 250000 | U159: =MROUND(O159*'Fuel & Inputs'!$C$20*'Fuel & Inputs'!$C$22,500) -> 330500
A160: 149 | B160: Pneumatic Roller | C160: KTDTO | D160: RT-200W | E160: 2012 | F160: PTR-06 | G160: — | H160: Diesel | I160: 9 | J160: 1.098 | K160: =IF(I160=0,0,IF(L160="Rs./km",MROUND(IF(H160="Petrol",'Fuel & Inputs'!$C$5,'Fuel & Inputs'!$C$4)/I160*J160,1),MROUND(I160*J160*IF(H160="Petrol",'Fuel & Inputs'!$C$5,'Fuel & Inputs'!$C$4),10))) -> 3770 | L160: Rs./hr | M160: 1640 | N160: =MROUND(M160+'Fuel & Inputs'!$C$13,50) -> 2450 | O160: 3240 | P160: =MROUND(M160*'Fuel & Inputs'!$C$19*'Fuel & Inputs'!$C$21,100) -> 6200 | Q160: =MROUND(N160*'Fuel & Inputs'!$C$19*'Fuel & Inputs'!$C$21,100) -> 9300 | R160: =MROUND(O160*'Fuel & Inputs'!$C$19*'Fuel & Inputs'!$C$21,100) -> 12300 | S160: =MROUND(M160*'Fuel & Inputs'!$C$20*'Fuel & Inputs'!$C$22,500) -> 167500 | T160: =MROUND(N160*'Fuel & Inputs'!$C$20*'Fuel & Inputs'!$C$22,500) -> 250000 | U160: =MROUND(O160*'Fuel & Inputs'!$C$20*'Fuel & Inputs'!$C$22,500) -> 330500
A161: 150 | B161: Pneumatic Roller | C161: SAKAI | D161: 6BD1LJ-01 | E161: 2012 | F161: PTR-02 | G161: — | H161: Diesel | I161: 9 | J161: 1.098 | K161: =IF(I161=0,0,IF(L161="Rs./km",MROUND(IF(H161="Petrol",'Fuel & Inputs'!$C$5,'Fuel & Inputs'!$C$4)/I161*J161,1),MROUND(I161*J161*IF(H161="Petrol",'Fuel & Inputs'!$C$5,'Fuel & Inputs'!$C$4),10))) -> 3770 | L161: Rs./hr | M161: 1640 | N161: =MROUND(M161+'Fuel & Inputs'!$C$13,50) -> 2450 | O161: 3240 | P161: =MROUND(M161*'Fuel & Inputs'!$C$19*'Fuel & Inputs'!$C$21,100) -> 6200 | Q161: =MROUND(N161*'Fuel & Inputs'!$C$19*'Fuel & Inputs'!$C$21,100) -> 9300 | R161: =MROUND(O161*'Fuel & Inputs'!$C$19*'Fuel & Inputs'!$C$21,100) -> 12300 | S161: =MROUND(M161*'Fuel & Inputs'!$C$20*'Fuel & Inputs'!$C$22,500) -> 167500 | T161: =MROUND(N161*'Fuel & Inputs'!$C$20*'Fuel & Inputs'!$C$22,500) -> 250000 | U161: =MROUND(O161*'Fuel & Inputs'!$C$20*'Fuel & Inputs'!$C$22,500) -> 330500
A162: 151 | B162: Pneumatic Roller | C162: SAKAI | D162: C200 | E162: 2000 | F162: PTR-09 | G162: — | H162: Diesel | I162: 9 | J162: 1.175 | K162: =IF(I162=0,0,IF(L162="Rs./km",MROUND(IF(H162="Petrol",'Fuel & Inputs'!$C$5,'Fuel & Inputs'!$C$4)/I162*J162,1),MROUND(I162*J162*IF(H162="Petrol",'Fuel & Inputs'!$C$5,'Fuel & Inputs'!$C$4),10))) -> 4040 | L162: Rs./hr | M162: 1300 | N162: =MROUND(M162+'Fuel & Inputs'!$C$13,50) -> 2100 | O162: 2570 | P162: =MROUND(M162*'Fuel & Inputs'!$C$19*'Fuel & Inputs'!$C$21,100) -> 4900 | Q162: =MROUND(N162*'Fuel & Inputs'!$C$19*'Fuel & Inputs'!$C$21,100) -> 8000 | R162: =MROUND(O162*'Fuel & Inputs'!$C$19*'Fuel & Inputs'!$C$21,100) -> 9800 | S162: =MROUND(M162*'Fuel & Inputs'!$C$20*'Fuel & Inputs'!$C$22,500) -> 132500 | T162: =MROUND(N162*'Fuel & Inputs'!$C$20*'Fuel & Inputs'!$C$22,500) -> 214000 | U162: =MROUND(O162*'Fuel & Inputs'!$C$20*'Fuel & Inputs'!$C$22,500) -> 262000
A163: 152 | B163: Pneumatic Roller | C163: SAKAI | D163: TS200 | E163: 1990 | F163: PTR-10 | G163: — | H163: Diesel | I163: 9 | J163: 1.175 | K163: =IF(I163=0,0,IF(L163="Rs./km",MROUND(IF(H163="Petrol",'Fuel & Inputs'!$C$5,'Fuel & Inputs'!$C$4)/I163*J163,1),MROUND(I163*J163*IF(H163="Petrol",'Fuel & Inputs'!$C$5,'Fuel & Inputs'!$C$4),10))) -> 4040 | L163: Rs./hr | M163: 1160 | N163: =MROUND(M163+'Fuel & Inputs'!$C$13,50) -> 1950 | O163: 2290 | P163: =MROUND(M163*'Fuel & Inputs'!$C$19*'Fuel & Inputs'!$C$21,100) -> 4400 | Q163: =MROUND(N163*'Fuel & Inputs'!$C$19*'Fuel & Inputs'!$C$21,100) -> 7400 | R163: =MROUND(O163*'Fuel & Inputs'!$C$19*'Fuel & Inputs'!$C$21,100) -> 8700 | S163: =MROUND(M163*'Fuel & Inputs'!$C$20*'Fuel & Inputs'!$C$22,500) -> 118500 | T163: =MROUND(N163*'Fuel & Inputs'!$C$20*'Fuel & Inputs'!$C$22,500) -> 199000 | U163: =MROUND(O163*'Fuel & Inputs'!$C$20*'Fuel & Inputs'!$C$22,500) -> 233500
A164: 153 | B164: Pneumatic Roller | C164: KOMATSU | D164: J.W 200 | E164: — | F164: PTR-08 | G164: — | H164: Diesel | I164: 9 | J164: 1 | K164: =IF(I164=0,0,IF(L164="Rs./km",MROUND(IF(H164="Petrol",'Fuel & Inputs'!$C$5,'Fuel & Inputs'!$C$4)/I164*J164,1),MROUND(I164*J164*IF(H164="Petrol",'Fuel & Inputs'!$C$5,'Fuel & Inputs'!$C$4),10))) -> 3440 | L164: Rs./hr | M164: 1160 | N164: =MROUND(M164+'Fuel & Inputs'!$C$13,50) -> 1950 | O164: 2290 | P164: =MROUND(M164*'Fuel & Inputs'!$C$19*'Fuel & Inputs'!$C$21,100) -> 4400 | Q164: =MROUND(N164*'Fuel & Inputs'!$C$19*'Fuel & Inputs'!$C$21,100) -> 7400 | R164: =MROUND(O164*'Fuel & Inputs'!$C$19*'Fuel & Inputs'!$C$21,100) -> 8700 | S164: =MROUND(M164*'Fuel & Inputs'!$C$20*'Fuel & Inputs'!$C$22,500) -> 118500 | T164: =MROUND(N164*'Fuel & Inputs'!$C$20*'Fuel & Inputs'!$C$22,500) -> 199000 | U164: =MROUND(O164*'Fuel & Inputs'!$C$20*'Fuel & Inputs'!$C$22,500) -> 233500
A165: MOTOR GRADER
A166: 154 | B166: Motor Grader | C166: SANY | D166: STG170C-8 | E166: 2021 | F166: MG-12 | G166: ZB-2564 | H166: Diesel | I166: 18 | J166: 1.035 | K166: =IF(I166=0,0,IF(L166="Rs./km",MROUND(IF(H166="Petrol",'Fuel & Inputs'!$C$5,'Fuel & Inputs'!$C$4)/I166*J166,1),MROUND(I166*J166*IF(H166="Petrol",'Fuel & Inputs'!$C$5,'Fuel & Inputs'!$C$4),10))) -> 7120 | L166: Rs./hr | M166: 4350 | N166: =MROUND(M166+'Fuel & Inputs'!$C$13,50) -> 5150 | O166: 9650 | P166: =MROUND(M166*'Fuel & Inputs'!$C$19*'Fuel & Inputs'!$C$21,100) -> 16500 | Q166: =MROUND(N166*'Fuel & Inputs'!$C$19*'Fuel & Inputs'!$C$21,100) -> 19600 | R166: =MROUND(O166*'Fuel & Inputs'!$C$19*'Fuel & Inputs'!$C$21,100) -> 36700 | S166: =MROUND(M166*'Fuel & Inputs'!$C$20*'Fuel & Inputs'!$C$22,500) -> 443500 | T166: =MROUND(N166*'Fuel & Inputs'!$C$20*'Fuel & Inputs'!$C$22,500) -> 525500 | U166: =MROUND(O166*'Fuel & Inputs'!$C$20*'Fuel & Inputs'!$C$22,500) -> 984500
A167: 155 | B167: Motor Grader | C167: SANY | D167: STG170C-9 | E167: 2021 | F167: MG-13 | G167: ZB-2585 | H167: Diesel | I167: 18 | J167: 1.035 | K167: =IF(I167=0,0,IF(L167="Rs./km",MROUND(IF(H167="Petrol",'Fuel & Inputs'!$C$5,'Fuel & Inputs'!$C$4)/I167*J167,1),MROUND(I167*J167*IF(H167="Petrol",'Fuel & Inputs'!$C$5,'Fuel & Inputs'!$C$4),10))) -> 7120 | L167: Rs./hr | M167: 4350 | N167: =MROUND(M167+'Fuel & Inputs'!$C$13,50) -> 5150 | O167: 9650 | P167: =MROUND(M167*'Fuel & Inputs'!$C$19*'Fuel & Inputs'!$C$21,100) -> 16500 | Q167: =MROUND(N167*'Fuel & Inputs'!$C$19*'Fuel & Inputs'!$C$21,100) -> 19600 | R167: =MROUND(O167*'Fuel & Inputs'!$C$19*'Fuel & Inputs'!$C$21,100) -> 36700 | S167: =MROUND(M167*'Fuel & Inputs'!$C$20*'Fuel & Inputs'!$C$22,500) -> 443500 | T167: =MROUND(N167*'Fuel & Inputs'!$C$20*'Fuel & Inputs'!$C$22,500) -> 525500 | U167: =MROUND(O167*'Fuel & Inputs'!$C$20*'Fuel & Inputs'!$C$22,500) -> 984500
A168: 156 | B168: Motor Grader | C168: SANY | D168: STG170C-8 | E168: 2020 | F168: MG-09 | G168: ZB-2562 | H168: Diesel | I168: 18 | J168: 1.042 | K168: =IF(I168=0,0,IF(L168="Rs./km",MROUND(IF(H168="Petrol",'Fuel & Inputs'!$C$5,'Fuel & Inputs'!$C$4)/I168*J168,1),MROUND(I168*J168*IF(H168="Petrol",'Fuel & Inputs'!$C$5,'Fuel & Inputs'!$C$4),10))) -> 7160 | L168: Rs./hr | M168: 4350 | N168: =MROUND(M168+'Fuel & Inputs'!$C$13,50) -> 5150 | O168: 9650 | P168: =MROUND(M168*'Fuel & Inputs'!$C$19*'Fuel & Inputs'!$C$21,100) -> 16500 | Q168: =MROUND(N168*'Fuel & Inputs'!$C$19*'Fuel & Inputs'!$C$21,100) -> 19600 | R168: =MROUND(O168*'Fuel & Inputs'!$C$19*'Fuel & Inputs'!$C$21,100) -> 36700 | S168: =MROUND(M168*'Fuel & Inputs'!$C$20*'Fuel & Inputs'!$C$22,500) -> 443500 | T168: =MROUND(N168*'Fuel & Inputs'!$C$20*'Fuel & Inputs'!$C$22,500) -> 525500 | U168: =MROUND(O168*'Fuel & Inputs'!$C$20*'Fuel & Inputs'!$C$22,500) -> 984500
A169: 157 | B169: Motor Grader | C169: SANY | D169: STG170C-8 | E169: 2020 | F169: MG-08 | G169: ZB-2561 | H169: Diesel | I169: 18 | J169: 1.042 | K169: =IF(I169=0,0,IF(L169="Rs./km",MROUND(IF(H169="Petrol",'Fuel & Inputs'!$C$5,'Fuel & Inputs'!$C$4)/I169*J169,1),MROUND(I169*J169*IF(H169="Petrol",'Fuel & Inputs'!$C$5,'Fuel & Inputs'!$C$4),10))) -> 7160 | L169: Rs./hr | M169: 4350 | N169: =MROUND(M169+'Fuel & Inputs'!$C$13,50) -> 5150 | O169: 9650 | P169: =MROUND(M169*'Fuel & Inputs'!$C$19*'Fuel & Inputs'!$C$21,100) -> 16500 | Q169: =MROUND(N169*'Fuel & Inputs'!$C$19*'Fuel & Inputs'!$C$21,100) -> 19600 | R169: =MROUND(O169*'Fuel & Inputs'!$C$19*'Fuel & Inputs'!$C$21,100) -> 36700 | S169: =MROUND(M169*'Fuel & Inputs'!$C$20*'Fuel & Inputs'!$C$22,500) -> 443500 | T169: =MROUND(N169*'Fuel & Inputs'!$C$20*'Fuel & Inputs'!$C$22,500) -> 525500 | U169: =MROUND(O169*'Fuel & Inputs'!$C$20*'Fuel & Inputs'!$C$22,500) -> 984500
A170: 158 | B170: Motor Grader | C170: SANY | D170: STG170C-8 | E170: 2020 | F170: MG-10 | G170: ZB-2559 | H170: Diesel | I170: 18 | J170: 1.042 | K170: =IF(I170=0,0,IF(L170="Rs./km",MROUND(IF(H170="Petrol",'Fuel & Inputs'!$C$5,'Fuel & Inputs'!$C$4)/I170*J170,1),MROUND(I170*J170*IF(H170="Petrol",'Fuel & Inputs'!$C$5,'Fuel & Inputs'!$C$4),10))) -> 7160 | L170: Rs./hr | M170: 4350 | N170: =MROUND(M170+'Fuel & Inputs'!$C$13,50) -> 5150 | O170: 9650 | P170: =MROUND(M170*'Fuel & Inputs'!$C$19*'Fuel & Inputs'!$C$21,100) -> 16500 | Q170: =MROUND(N170*'Fuel & Inputs'!$C$19*'Fuel & Inputs'!$C$21,100) -> 19600 | R170: =MROUND(O170*'Fuel & Inputs'!$C$19*'Fuel & Inputs'!$C$21,100) -> 36700 | S170: =MROUND(M170*'Fuel & Inputs'!$C$20*'Fuel & Inputs'!$C$22,500) -> 443500 | T170: =MROUND(N170*'Fuel & Inputs'!$C$20*'Fuel & Inputs'!$C$22,500) -> 525500 | U170: =MROUND(O170*'Fuel & Inputs'!$C$20*'Fuel & Inputs'!$C$22,500) -> 984500
A171: 159 | B171: Motor Grader | C171: MITSUBISHI | D171: 2GB00258 | E171: 2014 | F171: MG-14 | G171: — | H171: Diesel | I171: 18 | J171: 1.084 | K171: =IF(I171=0,0,IF(L171="Rs./km",MROUND(IF(H171="Petrol",'Fuel & Inputs'!$C$5,'Fuel & Inputs'!$C$4)/I171*J171,1),MROUND(I171*J171*IF(H171="Petrol",'Fuel & Inputs'!$C$5,'Fuel & Inputs'!$C$4),10))) -> 7450 | L171: Rs./hr | M171: 3570 | N171: =MROUND(M171+'Fuel & Inputs'!$C$13,50) -> 4350 | O171: 7910 | P171: =MROUND(M171*'Fuel & Inputs'!$C$19*'Fuel & Inputs'!$C$21,100) -> 13600 | Q171: =MROUND(N171*'Fuel & Inputs'!$C$19*'Fuel & Inputs'!$C$21,100) -> 16500 | R171: =MROUND(O171*'Fuel & Inputs'!$C$19*'Fuel & Inputs'!$C$21,100) -> 30100 | S171: =MROUND(M171*'Fuel & Inputs'!$C$20*'Fuel & Inputs'!$C$22,500) -> 364000 | T171: =MROUND(N171*'Fuel & Inputs'!$C$20*'Fuel & Inputs'!$C$22,500) -> 443500 | U171: =MROUND(O171*'Fuel & Inputs'!$C$20*'Fuel & Inputs'!$C$22,500) -> 807000
A172: 160 | B172: Motor Grader | C172: MITSUBISHI | D172: 2GB01241 | E172: 2008 | F172: MG-15 | G172: — | H172: Diesel | I172: 18 | J172: 1.126 | K172: =IF(I172=0,0,IF(L172="Rs./km",MROUND(IF(H172="Petrol",'Fuel & Inputs'!$C$5,'Fuel & Inputs'!$C$4)/I172*J172,1),MROUND(I172*J172*IF(H172="Petrol",'Fuel & Inputs'!$C$5,'Fuel & Inputs'!$C$4),10))) -> 7740 | L172: Rs./hr | M172: 3130 | N172: =MROUND(M172+'Fuel & Inputs'!$C$13,50) -> 3950 | O172: 6950 | P172: =MROUND(M172*'Fuel & Inputs'!$C$19*'Fuel & Inputs'!$C$21,100) -> 11900 | Q172: =MROUND(N172*'Fuel & Inputs'!$C$19*'Fuel & Inputs'!$C$21,100) -> 15000 | R172: =MROUND(O172*'Fuel & Inputs'!$C$19*'Fuel & Inputs'!$C$21,100) -> 26400 | S172: =MROUND(M172*'Fuel & Inputs'!$C$20*'Fuel & Inputs'!$C$22,500) -> 319500 | T172: =MROUND(N172*'Fuel & Inputs'!$C$20*'Fuel & Inputs'!$C$22,500) -> 403000 | U172: =MROUND(O172*'Fuel & Inputs'!$C$20*'Fuel & Inputs'!$C$22,500) -> 709000
A173: 161 | B173: Motor Grader | C173: KOMATSU | D173: — | E173: — | F173: MG-01 | G173: — | H173: Diesel | I173: 18 | J173: 1 | K173: =IF(I173=0,0,IF(L173="Rs./km",MROUND(IF(H173="Petrol",'Fuel & Inputs'!$C$5,'Fuel & Inputs'!$C$4)/I173*J173,1),MROUND(I173*J173*IF(H173="Petrol",'Fuel & Inputs'!$C$5,'Fuel & Inputs'!$C$4),10))) -> 6880 | L173: Rs./hr | M173: 2520 | N173: =MROUND(M173+'Fuel & Inputs'!$C$13,50) -> 3300 | O173: 5600 | P173: =MROUND(M173*'Fuel & Inputs'!$C$19*'Fuel & Inputs'!$C$21,100) -> 9600 | Q173: =MROUND(N173*'Fuel & Inputs'!$C$19*'Fuel & Inputs'!$C$21,100) -> 12500 | R173: =MROUND(O173*'Fuel & Inputs'!$C$19*'Fuel & Inputs'!$C$21,100) -> 21300 | S173: =MROUND(M173*'Fuel & Inputs'!$C$20*'Fuel & Inputs'!$C$22,500) -> 257000 | T173: =MROUND(N173*'Fuel & Inputs'!$C$20*'Fuel & Inputs'!$C$22,500) -> 336500 | U173: =MROUND(O173*'Fuel & Inputs'!$C$20*'Fuel & Inputs'!$C$22,500) -> 571000
A174: 162 | B174: Motor Grader | C174: (Unknown) | D174: — | E174: — | F174: MG-02 | G174: — | H174: Diesel | I174: 18 | J174: 1 | K174: =IF(I174=0,0,IF(L174="Rs./km",MROUND(IF(H174="Petrol",'Fuel & Inputs'!$C$5,'Fuel & Inputs'!$C$4)/I174*J174,1),MROUND(I174*J174*IF(H174="Petrol",'Fuel & Inputs'!$C$5,'Fuel & Inputs'!$C$4),10))) -> 6880 | L174: Rs./hr | M174: 2520 | N174: =MROUND(M174+'Fuel & Inputs'!$C$13,50) -> 3300 | O174: 5600 | P174: =MROUND(M174*'Fuel & Inputs'!$C$19*'Fuel & Inputs'!$C$21,100) -> 9600 | Q174: =MROUND(N174*'Fuel & Inputs'!$C$19*'Fuel & Inputs'!$C$21,100) -> 12500 | R174: =MROUND(O174*'Fuel & Inputs'!$C$19*'Fuel & Inputs'!$C$21,100) -> 21300 | S174: =MROUND(M174*'Fuel & Inputs'!$C$20*'Fuel & Inputs'!$C$22,500) -> 257000 | T174: =MROUND(N174*'Fuel & Inputs'!$C$20*'Fuel & Inputs'!$C$22,500) -> 336500 | U174: =MROUND(O174*'Fuel & Inputs'!$C$20*'Fuel & Inputs'!$C$22,500) -> 571000
A175: 163 | B175: Motor Grader | C175: CATERPILLER | D175: *CAT0140HC5HM03479* | E175: — | F175: MG-16 | G175: — | H175: Diesel | I175: 18 | J175: 1 | K175: =IF(I175=0,0,IF(L175="Rs./km",MROUND(IF(H175="Petrol",'Fuel & Inputs'!$C$5,'Fuel & Inputs'!$C$4)/I175*J175,1),MROUND(I175*J175*IF(H175="Petrol",'Fuel & Inputs'!$C$5,'Fuel & Inputs'!$C$4),10))) -> 6880 | L175: Rs./hr | M175: 2520 | N175: =MROUND(M175+'Fuel & Inputs'!$C$13,50) -> 3300 | O175: 5600 | P175: =MROUND(M175*'Fuel & Inputs'!$C$19*'Fuel & Inputs'!$C$21,100) -> 9600 | Q175: =MROUND(N175*'Fuel & Inputs'!$C$19*'Fuel & Inputs'!$C$21,100) -> 12500 | R175: =MROUND(O175*'Fuel & Inputs'!$C$19*'Fuel & Inputs'!$C$21,100) -> 21300 | S175: =MROUND(M175*'Fuel & Inputs'!$C$20*'Fuel & Inputs'!$C$22,500) -> 257000 | T175: =MROUND(N175*'Fuel & Inputs'!$C$20*'Fuel & Inputs'!$C$22,500) -> 336500 | U175: =MROUND(O175*'Fuel & Inputs'!$C$20*'Fuel & Inputs'!$C$22,500) -> 571000
A176: 164 | B176: Motor Grader | C176: KOMATSU | D176: — | E176: — | F176: MG-04 | G176: — | H176: Diesel | I176: 18 | J176: 1 | K176: =IF(I176=0,0,IF(L176="Rs./km",MROUND(IF(H176="Petrol",'Fuel & Inputs'!$C$5,'Fuel & Inputs'!$C$4)/I176*J176,1),MROUND(I176*J176*IF(H176="Petrol",'Fuel & Inputs'!$C$5,'Fuel & Inputs'!$C$4),10))) -> 6880 | L176: Rs./hr | M176: 2520 | N176: =MROUND(M176+'Fuel & Inputs'!$C$13,50) -> 3300 | O176: 5600 | P176: =MROUND(M176*'Fuel & Inputs'!$C$19*'Fuel & Inputs'!$C$21,100) -> 9600 | Q176: =MROUND(N176*'Fuel & Inputs'!$C$19*'Fuel & Inputs'!$C$21,100) -> 12500 | R176: =MROUND(O176*'Fuel & Inputs'!$C$19*'Fuel & Inputs'!$C$21,100) -> 21300 | S176: =MROUND(M176*'Fuel & Inputs'!$C$20*'Fuel & Inputs'!$C$22,500) -> 257000 | T176: =MROUND(N176*'Fuel & Inputs'!$C$20*'Fuel & Inputs'!$C$22,500) -> 336500 | U176: =MROUND(O176*'Fuel & Inputs'!$C$20*'Fuel & Inputs'!$C$22,500) -> 571000
A177: 165 | B177: Motor Grader | C177: KOMATSU | D177: 2501 | E177: — | F177: MG-05 | G177: — | H177: Diesel | I177: 18 | J177: 1 | K177: =IF(I177=0,0,IF(L177="Rs./km",MROUND(IF(H177="Petrol",'Fuel & Inputs'!$C$5,'Fuel & Inputs'!$C$4)/I177*J177,1),MROUND(I177*J177*IF(H177="Petrol",'Fuel & Inputs'!$C$5,'Fuel & Inputs'!$C$4),10))) -> 6880 | L177: Rs./hr | M177: 2520 | N177: =MROUND(M177+'Fuel & Inputs'!$C$13,50) -> 3300 | O177: 5600 | P177: =MROUND(M177*'Fuel & Inputs'!$C$19*'Fuel & Inputs'!$C$21,100) -> 9600 | Q177: =MROUND(N177*'Fuel & Inputs'!$C$19*'Fuel & Inputs'!$C$21,100) -> 12500 | R177: =MROUND(O177*'Fuel & Inputs'!$C$19*'Fuel & Inputs'!$C$21,100) -> 21300 | S177: =MROUND(M177*'Fuel & Inputs'!$C$20*'Fuel & Inputs'!$C$22,500) -> 257000 | T177: =MROUND(N177*'Fuel & Inputs'!$C$20*'Fuel & Inputs'!$C$22,500) -> 336500 | U177: =MROUND(O177*'Fuel & Inputs'!$C$20*'Fuel & Inputs'!$C$22,500) -> 571000
... A181: 169 | B181: Motor Grader | C181: MITSUBISHI | D181: 320-11-21GD | E181: — | F181: MG-06 | G181: — | H181: Diesel | I181: 18 | J181: 1 | K181: =IF(I181=0,0,IF(L181="Rs./km",MROUND(IF(H181="Petrol",'Fuel & Inputs'!$C$5,'Fuel & Inputs'!$C$4)/I181*J181,1),MROUND(I181*J181*IF(H181="Petrol",'Fuel & Inputs'!$C$5,'Fuel & Inputs'!$C$4),10))) -> 6880 | L181: Rs./hr | M181: 2520 | N181: =MROUND(M181+'Fuel & Inputs'!$C$13,50) -> 3300 | O181: 5600 | P181: =MROUND(M181*'Fuel & Inputs'!$C$19*'Fuel & Inputs'!$C$21,100) -> 9600 | Q181: =MROUND(N181*'Fuel & Inputs'!$C$19*'Fuel & Inputs'!$C$21,100) -> 12500 | R181: =MROUND(O181*'Fuel & Inputs'!$C$19*'Fuel & Inputs'!$C$21,100) -> 21300 | S181: =MROUND(M181*'Fuel & Inputs'!$C$20*'Fuel & Inputs'!$C$22,500) -> 257000 | T181: =MROUND(N181*'Fuel & Inputs'!$C$20*'Fuel & Inputs'!$C$22,500) -> 336500 | U181: =MROUND(O181*'Fuel & Inputs'!$C$20*'Fuel & Inputs'!$C$22,500) -> 571000
A182: SKID STEER
A183: 170 | B183: Skid Steer | C183: BOB CAT | D183: S-450 | E183: 2021 | F183: SL-21 | G183: — | H183: Diesel | I183: 5 | J183: 1.035 | K183: =IF(I183=0,0,IF(L183="Rs./km",MROUND(IF(H183="Petrol",'Fuel & Inputs'!$C$5,'Fuel & Inputs'!$C$4)/I183*J183,1),MROUND(I183*J183*IF(H183="Petrol",'Fuel & Inputs'!$C$5,'Fuel & Inputs'!$C$4),10))) -> 1980 | L183: Rs./hr | M183: 1350 | N183: =MROUND(M183+'Fuel & Inputs'!$C$13,50) -> 2150 | O183: 2700 | P183: =MROUND(M183*'Fuel & Inputs'!$C$19*'Fuel & Inputs'!$C$21,100) -> 5100 | Q183: =MROUND(N183*'Fuel & Inputs'!$C$19*'Fuel & Inputs'!$C$21,100) -> 8200 | R183: =MROUND(O183*'Fuel & Inputs'!$C$19*'Fuel & Inputs'!$C$21,100) -> 10300 | S183: =MROUND(M183*'Fuel & Inputs'!$C$20*'Fuel & Inputs'!$C$22,500) -> 137500 | T183: =MROUND(N183*'Fuel & Inputs'!$C$20*'Fuel & Inputs'!$C$22,500) -> 219500 | U183: =MROUND(O183*'Fuel & Inputs'!$C$20*'Fuel & Inputs'!$C$22,500) -> 275500
...

Sheet Machinery Price Sheet
A1: MACHINERY / PORTABLE EQUIPMENT PRICE SHEET 2026 — DRY / DRY + OPERATOR / WET (Rs./day, excl. 18% VAT, min. 1 day)
A2: WET = DRY + operator + fuel for the stated duty hrs/day at CPC prices (Diesel Rs.382 / Petrol-92 Rs.414, eff. 29-Jun-2026). Electric items: power by client (fuel = 0) — if we supply a generator, add it as a separate line. Extra running hours billed at L/hr x CPC price. Operator Rs.3,500/day (skilled welder/cutter Rs.5,000/day). Diamond blades & core bits billed per use at cost + 15%.
A4: A — POWER & AIR (generators, air compressors, welding generators, gas cutting)
A5: # | B5: Equipment | C5: Capacity / Size | D5: Power / Fuel | E5: Output & Efficiency | F5: Cons. L/hr | G5: Duty hrs/day | H5: Fuel Rs./day | I5: DRY Rs./day | J5: Operator Rs./day | K5: DRY + OPERATOR Rs./day | L5: WET Rs./day | M5: Market reference (SL, 2026)
A6: 1 | B6: Generator | C6: 3–5 kVA (petrol, 1-ph) | D6: Petrol engine | E6: 2.4–4.0 kW prime, 230 V; ~0.35 L/kWh | F6: 1.4 | G6: 8 | H6: =MROUND(F6*G6*IF(ISNUMBER(SEARCH("Diesel",D6)),'Fuel & Inputs'!$C$4,IF(ISNUMBER(SEARCH("Petrol",D6)),'Fuel & Inputs'!$C$5,0)),10) -> 4640 | I6: 2500 | J6: ='Fuel & Inputs'!$C$14 -> 3500 | K6: =I6+J6 -> 6000 | L6: =MROUND(K6+H6,100) -> 10600 | M6: Peters 2–5 kVA Rs.4,000–5,000/day
A7: 2 | B7: Generator | C7: 10 kVA (diesel, 1-ph) | D7: Diesel engine | E7: 8 kW prime, 230 V; ~0.28 L/kWh | F7: 2.2 | G7: 8 | H7: =MROUND(F7*G7*IF(ISNUMBER(SEARCH("Diesel",D7)),'Fuel & Inputs'!$C$4,IF(ISNUMBER(SEARCH("Petrol",D7)),'Fuel & Inputs'!$C$5,0)),10) -> 6720 | I7: 3500 | J7: ='Fuel & Inputs'!$C$14 -> 3500 | K7: =I7+J7 -> 7000 | L7: =MROUND(K7+H7,100) -> 13700 | M7: Peters 10 kVA Rs.6,000/day
A8: 3 | B8: Generator | C8: 15 kVA (diesel, 3-ph) | D8: Diesel engine | E8: 12 kW prime, 400 V | F8: 2.9 | G8: 8 | H8: =MROUND(F8*G8*IF(ISNUMBER(SEARCH("Diesel",D8)),'Fuel & Inputs'!$C$4,IF(ISNUMBER(SEARCH("Petrol",D8)),'Fuel & Inputs'!$C$5,0)),10) -> 8860 | I8: 4800 | J8: ='Fuel & Inputs'!$C$14 -> 3500 | K8: =I8+J8 -> 8300 | L8: =MROUND(K8+H8,100) -> 17200 | M8: Interpolated SL band
A9: 4 | B9: Generator | C9: 20–25 kVA (diesel, 3-ph) | D9: Diesel engine | E9: 16–20 kW prime, 400 V | F9: 4 | G9: 8 | H9: =MROUND(F9*G9*IF(ISNUMBER(SEARCH("Diesel",D9)),'Fuel & Inputs'!$C$4,IF(ISNUMBER(SEARCH("Petrol",D9)),'Fuel & Inputs'!$C$5,0)),10) -> 12220 | I9: 6000 | J9: ='Fuel & Inputs'!$C$14 -> 3500 | K9: =I9+J9 -> 9500 | L9: =MROUND(K9+H9,100) -> 21700 | M9: Peters 25 kVA Rs.8,000/day
A10: 5 | B10: Generator | C10: 30–50 kVA (diesel, 3-ph) | D10: Diesel engine | E10: 24–40 kW prime | F10: 7.5 | G10: 8 | H10: =MROUND(F10*G10*IF(ISNUMBER(SEARCH("Diesel",D10)),'Fuel & Inputs'!$C$4,IF(ISNUMBER(SEARCH("Petrol",D10)),'Fuel & Inputs'!$C$5,0)),10) -> 22920 | I10: 10000 | J10: ='Fuel & Inputs'!$C$14 -> 3500 | K10: =I10+J10 -> 13500 | L10: =MROUND(K10+H10,100) -> 36400 | M10: Peters 50 kVA Rs.10–12,000/day
A11: 6 | B11: Generator | C11: 60–80 kVA (soundproof) | D11: Diesel engine | E11: 48–64 kW prime, <75 dB@7m | F11: 12 | G11: 8 | H11: =MROUND(F11*G11*IF(ISNUMBER(SEARCH("Diesel",D11)),'Fuel & Inputs'!$C$4,IF(ISNUMBER(SEARCH("Petrol",D11)),'Fuel & Inputs'!$C$5,0)),10) -> 36670 | I11: 15000 | J11: ='Fuel & Inputs'!$C$14 -> 3500 | K11: =I11+J11 -> 18500 | L11: =MROUND(K11+H11,100) -> 55200 | M11: Generators.lk/UTE band
A12: 7 | B12: Generator | C12: 100–125 kVA (soundproof) | D12: Diesel engine | E12: 80–100 kW prime | F12: 19 | G12: 8 | H12: =MROUND(F12*G12*IF(ISNUMBER(SEARCH("Diesel",D12)),'Fuel & Inputs'!$C$4,IF(ISNUMBER(SEARCH("Petrol",D12)),'Fuel & Inputs'!$C$5,0)),10) -> 58060 | I12: 22000 | J12: ='Fuel & Inputs'!$C$14 -> 3500 | K12: =I12+J12 -> 25500 | L12: =MROUND(K12+H12,100) -> 83600 | M12: Generators.lk/UTE band
A13: 8 | B13: Generator | C13: 150 kVA (soundproof) | D13: Diesel engine | E13: 120 kW prime | F13: 24 | G13: 8 | H13: =MROUND(F13*G13*IF(ISNUMBER(SEARCH("Diesel",D13)),'Fuel & Inputs'!$C$4,IF(ISNUMBER(SEARCH("Petrol",D13)),'Fuel & Inputs'!$C$5,0)),10) -> 73340 | I13: 28000 | J13: ='Fuel & Inputs'!$C$14 -> 3500 | K13: =I13+J13 -> 31500 | L13: =MROUND(K13+H13,100) -> 104800 | M13: Generators.lk upper band
A14: 9 | B14: Generator | C14: 250 kVA (soundproof) | D14: Diesel engine | E14: 200 kW prime | F14: 38 | G14: 8 | H14: =MROUND(F14*G14*IF(ISNUMBER(SEARCH("Diesel",D14)),'Fuel & Inputs'!$C$4,IF(ISNUMBER(SEARCH("Petrol",D14)),'Fuel & Inputs'!$C$5,0)),10) -> 116130 | I14: 40000 | J14: ='Fuel & Inputs'!$C$14 -> 3500 | K14: =I14+J14 -> 43500 | L14: =MROUND(K14+H14,100) -> 159600 | M14: Project/event band, Colombo
A15: 10 | B15: Air Compressor | C15: 2–3 HP (portable) | D15: Electric 1.5–2.2 kW | E15: 8–10 cfm @ 8 bar, 50 L tank | F15: 0 | G15: 8 | H15: =MROUND(F15*G15*IF(ISNUMBER(SEARCH("Diesel",D15)),'Fuel & Inputs'!$C$4,IF(ISNUMBER(SEARCH("Petrol",D15)),'Fuel & Inputs'!$C$5,0)),10) -> 0 | I15: 1300 | J15: ='Fuel & Inputs'!$C$14 -> 3500 | K15: =I15+J15 -> 4800 | L15: =MROUND(K15+H15,100) -> 4800 | M15: SL hire-shop day-rate
A16: 11 | B16: Air Compressor | C16: 5–7 HP (belt-drive) | D16: Petrol engine | E16: 16–21 cfm @ 8–10 bar | F16: 1.2 | G16: 6 | H16: =MROUND(F16*G16*IF(ISNUMBER(SEARCH("Diesel",D16)),'Fuel & Inputs'!$C$4,IF(ISNUMBER(SEARCH("Petrol",D16)),'Fuel & Inputs'!$C$5,0)),10) -> 2980 | I16: 2400 | J16: ='Fuel & Inputs'!$C$14 -> 3500 | K16: =I16+J16 -> 5900 | L16: =MROUND(K16+H16,100) -> 8900 | M16: Western-Province hire-shop
A17: 12 | B17: Air Compressor | C17: 10–15 HP (industrial) | D17: Electric 7.5–11 kW | E17: 35–50 cfm @ 10–12 bar | F17: 0 | G17: 8 | H17: =MROUND(F17*G17*IF(ISNUMBER(SEARCH("Diesel",D17)),'Fuel & Inputs'!$C$4,IF(ISNUMBER(SEARCH("Petrol",D17)),'Fuel & Inputs'!$C$5,0)),10) -> 0 | I17: 4500 | J17: ='Fuel & Inputs'!$C$14 -> 3500 | K17: =I17+J17 -> 8000 | L17: =MROUND(K17+H17,100) -> 8000 | M17: Western-Province hire-shop
... A20: 15 | B20: Pneumatic Jack Hammer | C20: 25–30 kg (w/ hoses, excl. compressor) | D20: Pneumatic (via compressor) | E20: ~1,250 bpm; pavement/rock breaking | F20: 0 | G20: 0 | H20: =MROUND(F20*G20*IF(ISNUMBER(SEARCH("Diesel",D20)),'Fuel & Inputs'!$C$4,IF(ISNUMBER(SEARCH("Petrol",D20)),'Fuel & Inputs'!$C$5,0)),10) -> 0 | I20: 4000 | J20: ='Fuel & Inputs'!$C$14 -> 3500 | K20: =I20+J20 -> 7500 | L20: =MROUND(K20+H20,100) -> 7500 | M20: Peters jackhammer pkg Rs.10,000/day (with compressor)
A21: 16 | B21: Welding Inverter | C21: 200 A (MMA/ARC) | D21: Electric 6–8 kVA | E21: 200 A @ 60% duty; rods up to 4.0 mm | F21: 0 | G21: 8 | H21: =MROUND(F21*G21*IF(ISNUMBER(SEARCH("Diesel",D21)),'Fuel & Inputs'!$C$4,IF(ISNUMBER(SEARCH("Petrol",D21)),'Fuel & Inputs'!$C$5,0)),10) -> 0 | I21: 1800 | J21: ='Fuel & Inputs'!$C$15 -> 5000 | K21: =I21+J21 -> 6800 | L21: =MROUND(K21+H21,100) -> 6800 | M21: SL hire-shop day-rate
A22: 17 | B22: Welding Generator | C22: 250 A (petrol) | D22: Petrol engine | E22: 250 A DC @ 60% duty + 3 kW aux power | F22: 1.8 | G22: 5 | H22: =MROUND(F22*G22*IF(ISNUMBER(SEARCH("Diesel",D22)),'Fuel & Inputs'!$C$4,IF(ISNUMBER(SEARCH("Petrol",D22)),'Fuel & Inputs'!$C$5,0)),10) -> 3730 | I22: 5500 | J22: ='Fuel & Inputs'!$C$15 -> 5000 | K22: =I22+J22 -> 10500 | L22: =MROUND(K22+H22,100) -> 14200 | M22: Engine-welder SL band
A23: 18 | B23: Welding Generator | C23: 300 A (diesel) | D23: Diesel engine | E23: 300 A DC @ 60% duty + 5 kW aux power | F23: 2.5 | G23: 5 | H23: =MROUND(F23*G23*IF(ISNUMBER(SEARCH("Diesel",D23)),'Fuel & Inputs'!$C$4,IF(ISNUMBER(SEARCH("Petrol",D23)),'Fuel & Inputs'!$C$5,0)),10) -> 4780 | I23: 6500 | J23: ='Fuel & Inputs'!$C$15 -> 5000 | K23: =I23+J23 -> 11500 | L23: =MROUND(K23+H23,100) -> 16300 | M23: Existing card; SL band
A24: 19 | B24: Welding Generator | C24: 400–500 A (diesel) | D24: Diesel engine | E24: 400–500 A @ 60%; dual-arc capable | F24: 4 | G24: 5 | H24: =MROUND(F24*G24*IF(ISNUMBER(SEARCH("Diesel",D24)),'Fuel & Inputs'!$C$4,IF(ISNUMBER(SEARCH("Petrol",D24)),'Fuel & Inputs'!$C$5,0)),10) -> 7640 | I24: 9000 | J24: ='Fuel & Inputs'!$C$15 -> 5000 | K24: =I24+J24 -> 14000 | L24: =MROUND(K24+H24,100) -> 21600 | M24: Heavy fabrication band
A25: 20 | B25: Gas Cutting Set | C25: Oxy-acetylene (cylinders excl.) | D25: Gas (billed per cylinder) | E25: Cuts MS plate up to 150 mm | F25: 0 | G25: 0 | H25: =MROUND(F25*G25*IF(ISNUMBER(SEARCH("Diesel",D25)),'Fuel & Inputs'!$C$4,IF(ISNUMBER(SEARCH("Petrol",D25)),'Fuel & Inputs'!$C$5,0)),10) -> 0 | I25: 3800 | J25: ='Fuel & Inputs'!$C$15 -> 5000 | K25: =I25+J25 -> 8800 | L25: =MROUND(K25+H25,100) -> 8800 | M25: Peters metal gas cutter Rs.5,500/day
A26: B — CONCRETING & STRUCTURAL (mixers, pokers, bar cutters, bar benders, trowels, breakers)
A27: # | B27: Equipment | C27: Capacity / Size | D27: Power / Fuel | E27: Output & Efficiency | F27: Cons. L/hr | G27: Duty hrs/day | H27: Fuel Rs./day | I27: DRY Rs./day | J27: Operator Rs./day | K27: DRY + OPERATOR Rs./day | L27: WET Rs./day | M27: Market reference (SL, 2026)
A28: 21 | B28: Concrete Mixer | C28: 5/3.5 cu.ft (half-bag) | D28: Petrol engine | E28: ~1.5–2.0 m3/hr output; drum ~20 rpm | F28: 0.9 | G28: 5 | H28: =MROUND(F28*G28*IF(ISNUMBER(SEARCH("Diesel",D28)),'Fuel & Inputs'!$C$4,IF(ISNUMBER(SEARCH("Petrol",D28)),'Fuel & Inputs'!$C$5,0)),10) -> 1860 | I28: 2000 | J28: ='Fuel & Inputs'!$C$14 -> 3500 | K28: =I28+J28 -> 5500 | L28: =MROUND(K28+H28,100) -> 7400 | M28: Existing card; SL hire-shops
A29: 22 | B29: Concrete Mixer | C29: 10/7 cu.ft (one-bag) | D29: Diesel engine | E29: ~3–4 m3/hr; 1 bag/batch, ~18 rpm | F29: 1.3 | G29: 5 | H29: =MROUND(F29*G29*IF(ISNUMBER(SEARCH("Diesel",D29)),'Fuel & Inputs'!$C$4,IF(ISNUMBER(SEARCH("Petrol",D29)),'Fuel & Inputs'!$C$5,0)),10) -> 2480 | I29: 3000 | J29: ='Fuel & Inputs'!$C$14 -> 3500 | K29: =I29+J29 -> 6500 | L29: =MROUND(K29+H29,100) -> 9000 | M29: Existing card; SL hire-shops
A30: 23 | B30: Concrete Mixer | C30: 10/7 cu.ft + hopper/hoist | D30: Diesel engine | E30: ~3.5–4.5 m3/hr; mechanical feed | F30: 1.6 | G30: 5 | H30: =MROUND(F30*G30*IF(ISNUMBER(SEARCH("Diesel",D30)),'Fuel & Inputs'!$C$4,IF(ISNUMBER(SEARCH("Petrol",D30)),'Fuel & Inputs'!$C$5,0)),10) -> 3060 | I30: 4500 | J30: ='Fuel & Inputs'!$C$14 -> 3500 | K30: =I30+J30 -> 8000 | L30: =MROUND(K30+H30,100) -> 11100 | M30: Existing card
A31: 24 | B31: Poker / Concrete Vibrator | C31: Electric drive + 4 m shaft | D31: Electric 2.3 kW | E31: Needle 25–60 mm; compacts ~12–20 m3/hr | F31: 0 | G31: 4 | H31: =MROUND(F31*G31*IF(ISNUMBER(SEARCH("Diesel",D31)),'Fuel & Inputs'!$C$4,IF(ISNUMBER(SEARCH("Petrol",D31)),'Fuel & Inputs'!$C$5,0)),10) -> 0 | I31: 1200 | J31: ='Fuel & Inputs'!$C$14 -> 3500 | K31: =I31+J31 -> 4700 | L31: =MROUND(K31+H31,100) -> 4700 | M31: Existing card; wedabima listings
A32: 25 | B32: Poker / Concrete Vibrator | C32: Petrol drive + 4 m shaft | D32: Petrol engine (GX160) | E32: Compacts ~15–25 m3/hr | F32: 1 | G32: 4 | H32: =MROUND(F32*G32*IF(ISNUMBER(SEARCH("Diesel",D32)),'Fuel & Inputs'!$C$4,IF(ISNUMBER(SEARCH("Petrol",D32)),'Fuel & Inputs'!$C$5,0)),10) -> 1660 | I32: 1700 | J32: ='Fuel & Inputs'!$C$14 -> 3500 | K32: =I32+J32 -> 5200 | L32: =MROUND(K32+H32,100) -> 6900 | M32: Existing card; wedabima listings
A33: 26 | B33: Poker / Concrete Vibrator | C33: Spare needle/shaft 35–60 mm | D33: — | E33: Accessory only | F33: 0 | G33: 0 | H33: =MROUND(F33*G33*IF(ISNUMBER(SEARCH("Diesel",D33)),'Fuel & Inputs'!$C$4,IF(ISNUMBER(SEARCH("Petrol",D33)),'Fuel & Inputs'!$C$5,0)),10) -> 0 | I33: 500 | J33: 0 | K33: =I33+J33 -> 500 | L33: =MROUND(K33+H33,100) -> 500 | M33: Accessory
A34: 27 | B34: Bar Cutter (Heavy) | C34: Up to 25 mm TMT | D34: Electric 2.2 kW | E34: ~2–3 s per cut; ~400–600 cuts/day | F34: 0 | G34: 4 | H34: =MROUND(F34*G34*IF(ISNUMBER(SEARCH("Diesel",D34)),'Fuel & Inputs'!$C$4,IF(ISNUMBER(SEARCH("Petrol",D34)),'Fuel & Inputs'!$C$5,0)),10) -> 0 | I34: 3500 | J34: ='Fuel & Inputs'!$C$14 -> 3500 | K34: =I34+J34 -> 7000 | L34: =MROUND(K34+H34,100) -> 7000 | M34: vs Peters bender Rs.6,000/day class
A35: 28 | B35: Bar Cutter (Heavy) | C35: Up to 32 mm TMT | D35: Electric 3.0 kW | E35: ~3 s per cut; GQ40/RC-32 class | F35: 0 | G35: 4 | H35: =MROUND(F35*G35*IF(ISNUMBER(SEARCH("Diesel",D35)),'Fuel & Inputs'!$C$4,IF(ISNUMBER(SEARCH("Petrol",D35)),'Fuel & Inputs'!$C$5,0)),10) -> 0 | I35: 4500 | J35: ='Fuel & Inputs'!$C$14 -> 3500 | K35: =I35+J35 -> 8000 | L35: =MROUND(K35+H35,100) -> 8000 | M35: SL hire market (wedabima 6–52 mm)
A36: 29 | B36: Bar Cutter (Heavy) | C36: Up to 40 mm TMT | D36: Electric 4.0 kW | E36: Heavy site fabrication; GQ50 class | F36: 0 | G36: 4 | H36: =MROUND(F36*G36*IF(ISNUMBER(SEARCH("Diesel",D36)),'Fuel & Inputs'!$C$4,IF(ISNUMBER(SEARCH("Petrol",D36)),'Fuel & Inputs'!$C$5,0)),10) -> 0 | I36: 6000 | J36: ='Fuel & Inputs'!$C$14 -> 3500 | K36: =I36+J36 -> 9500 | L36: =MROUND(K36+H36,100) -> 9500 | M36: SL hire market
A37: 30 | B37: Rebar Cutter (Portable) | C37: Hydraulic, up to 20 mm | D37: Electric 1.3 kW | E37: Hand-held; 3–4 s per cut | F37: 0 | G37: 4 | H37: =MROUND(F37*G37*IF(ISNUMBER(SEARCH("Diesel",D37)),'Fuel & Inputs'!$C$4,IF(ISNUMBER(SEARCH("Petrol",D37)),'Fuel & Inputs'!$C$5,0)),10) -> 0 | I37: 2500 | J37: ='Fuel & Inputs'!$C$14 -> 3500 | K37: =I37+J37 -> 6000 | L37: =MROUND(K37+H37,100) -> 6000 | M37: SL hire market
A38: 31 | B38: Bar Bender | C38: Up to 25 mm TMT | D38: Electric 2.2 kW | E38: 0–180° bends; multi-bar on small dia | F38: 0 | G38: 4 | H38: =MROUND(F38*G38*IF(ISNUMBER(SEARCH("Diesel",D38)),'Fuel & Inputs'!$C$4,IF(ISNUMBER(SEARCH("Petrol",D38)),'Fuel & Inputs'!$C$5,0)),10) -> 0 | I38: 3500 | J38: ='Fuel & Inputs'!$C$14 -> 3500 | K38: =I38+J38 -> 7000 | L38: =MROUND(K38+H38,100) -> 7000 | M38: vs Peters Rs.6,000/day
A39: 32 | B39: Bar Bender | C39: Up to 32 mm TMT | D39: Electric 3.0 kW | E39: 0–180°, adjustable angle stops | F39: 0 | G39: 4 | H39: =MROUND(F39*G39*IF(ISNUMBER(SEARCH("Diesel",D39)),'Fuel & Inputs'!$C$4,IF(ISNUMBER(SEARCH("Petrol",D39)),'Fuel & Inputs'!$C$5,0)),10) -> 0 | I39: 4500 | J39: ='Fuel & Inputs'!$C$14 -> 3500 | K39: =I39+J39 -> 8000 | L39: =MROUND(K39+H39,100) -> 8000 | M39: Peters bar bender Rs.6,000/day
A40: 33 | B40: Bar Bender | C40: Up to 42 mm TMT | D40: Electric 4.0 kW | E40: GW50 class; heavy cage work | F40: 0 | G40: 4 | H40: =MROUND(F40*G40*IF(ISNUMBER(SEARCH("Diesel",D40)),'Fuel & Inputs'!$C$4,IF(ISNUMBER(SEARCH("Petrol",D40)),'Fuel & Inputs'!$C$5,0)),10) -> 0 | I40: 6000 | J40: ='Fuel & Inputs'!$C$14 -> 3500 | K40: =I40+J40 -> 9500 | L40: =MROUND(K40+H40,100) -> 9500 | M40: SL hire market (wedabima to 52 mm)
A41: 34 | B41: Power Trowel | C41: 36 in (900 mm) blade | D41: Petrol engine (GX160) | E41: 60–115 rpm; finishes ~500–700 m2/day | F41: 1 | G41: 4 | H41: =MROUND(F41*G41*IF(ISNUMBER(SEARCH("Diesel",D41)),'Fuel & Inputs'!$C$4,IF(ISNUMBER(SEARCH("Petrol",D41)),'Fuel & Inputs'!$C$5,0)),10) -> 1660 | I41: 3800 | J41: ='Fuel & Inputs'!$C$14 -> 3500 | K41: =I41+J41 -> 7300 | L41: =MROUND(K41+H41,100) -> 9000 | M41: Existing card
A42: 35 | B42: Rotary Hammer | C42: 2–4 kg (SDS-plus) | D42: Electric 0.8 kW | E42: Drills concrete up to 26 mm | F42: 0 | G42: 4 | H42: =MROUND(F42*G42*IF(ISNUMBER(SEARCH("Diesel",D42)),'Fuel & Inputs'!$C$4,IF(ISNUMBER(SEARCH("Petrol",D42)),'Fuel & Inputs'!$C$5,0)),10) -> 0 | I42: 1000 | J42: 0 | K42: =I42+J42 -> 1000 | L42: =MROUND(K42+H42,100) -> 1000 | M42: Peters SDS Rs.3,000/day
A43: 36 | B43: Rotary Hammer | C43: 5–7 kg (SDS-max) | D43: Electric 1.3 kW | E43: Up to 40 mm; light chiselling | F43: 0 | G43: 4 | H43: =MROUND(F43*G43*IF(ISNUMBER(SEARCH("Diesel",D43)),'Fuel & Inputs'!$C$4,IF(ISNUMBER(SEARCH("Petrol",D43)),'Fuel & Inputs'!$C$5,0)),10) -> 0 | I43: 1500 | J43: 0 | K43: =I43+J43 -> 1500 | L43: =MROUND(K43+H43,100) -> 1500 | M43: SL hire market
A44: 37 | B44: Demolition Breaker | C44: 10–16 kg | D44: Electric 1.7 kW | E44: 25–45 J impact; wall/slab demolition | F44: 0 | G44: 4 | H44: =MROUND(F44*G44*IF(ISNUMBER(SEARCH("Diesel",D44)),'Fuel & Inputs'!$C$4,IF(ISNUMBER(SEARCH("Petrol",D44)),'Fuel & Inputs'!$C$5,0)),10) -> 0 | I44: 2700 | J44: ='Fuel & Inputs'!$C$14 -> 3500 | K44: =I44+J44 -> 6200 | L44: =MROUND(K44+H44,100) -> 6200 | M44: Peters breaker Rs.4,000/day
A45: 38 | B45: Cut-off Saw (bench) | C45: 14 in metal chop saw | D45: Electric 2.4 kW | E45: Cuts bar/section up to ~120 mm | F45: 0 | G45: 4 | H45: =MROUND(F45*G45*IF(ISNUMBER(SEARCH("Diesel",D45)),'Fuel & Inputs'!$C$4,IF(ISNUMBER(SEARCH("Petrol",D45)),'Fuel & Inputs'!$C$5,0)),10) -> 0 | I45: 2600 | J45: 0 | K45: =I45+J45 -> 2600 | L45: =MROUND(K45+H45,100) -> 2600 | M45: Existing card; Peters metal saw
A46: C — ROADWORK & COMPACTION (asphalt cutters, core cutters, wackers/rammers, compactors, rollers)
A47: # | B47: Equipment | C47: Capacity / Size | D47: Power / Fuel | E47: Output & Efficiency | F47: Cons. L/hr | G47: Duty hrs/day | H47: Fuel Rs./day | I47: DRY Rs./day | J47: Operator Rs./day | K47: DRY + OPERATOR Rs./day | L47: WET Rs./day | M47: Market reference (SL, 2026)
A48: 39 | B48: Asphalt Cutter (floor saw) | C48: 12 in blade | D48: Petrol engine 13 HP | E48: Cut depth to 100 mm; water-cooled | F48: 1.8 | G48: 3 | H48: =MROUND(F48*G48*IF(ISNUMBER(SEARCH("Diesel",D48)),'Fuel & Inputs'!$C$4,IF(ISNUMBER(SEARCH("Petrol",D48)),'Fuel & Inputs'!$C$5,0)),10) -> 2240 | I48: 4500 | J48: ='Fuel & Inputs'!$C$14 -> 3500 | K48: =I48+J48 -> 8000 | L48: =MROUND(K48+H48,100) -> 10200 | M48: SL road-contractor band
A49: 40 | B49: Asphalt Cutter (floor saw) | C49: 14 in blade | D49: Petrol engine 13 HP | E49: Cut depth to 120 mm; 25 L water tank | F49: 2 | G49: 3 | H49: =MROUND(F49*G49*IF(ISNUMBER(SEARCH("Diesel",D49)),'Fuel & Inputs'!$C$4,IF(ISNUMBER(SEARCH("Petrol",D49)),'Fuel & Inputs'!$C$5,0)),10) -> 2480 | I49: 5500 | J49: ='Fuel & Inputs'!$C$14 -> 3500 | K49: =I49+J49 -> 9000 | L49: =MROUND(K49+H49,100) -> 11500 | M49: SL road-contractor band
A50: 41 | B50: Asphalt Cutter (floor saw) | C50: 16–18 in blade | D50: Diesel engine | E50: Cut depth 150–175 mm; highway joints | F50: 2.5 | G50: 3 | H50: =MROUND(F50*G50*IF(ISNUMBER(SEARCH("Diesel",D50)),'Fuel & Inputs'!$C$4,IF(ISNUMBER(SEARCH("Petrol",D50)),'Fuel & Inputs'!$C$5,0)),10) -> 2870 | I50: 7500 | J50: ='Fuel & Inputs'!$C$14 -> 3500 | K50: =I50+J50 -> 11000 | L50: =MROUND(K50+H50,100) -> 13900 | M50: SL road-contractor band
A51: 42 | B51: Hand Cut-off Saw | C51: 12–14 in (petrol, hand-held) | D51: Petrol engine | E51: Free-hand cuts to 100–125 mm | F51: 1.5 | G51: 3 | H51: =MROUND(F51*G51*IF(ISNUMBER(SEARCH("Diesel",D51)),'Fuel & Inputs'!$C$4,IF(ISNUMBER(SEARCH("Petrol",D51)),'Fuel & Inputs'!$C$5,0)),10) -> 1860 | I51: 3500 | J51: ='Fuel & Inputs'!$C$14 -> 3500 | K51: =I51+J51 -> 7000 | L51: =MROUND(K51+H51,100) -> 8900 | M51: Stihl TS-class hire band
A52: 43 | B52: Asphalt/Concrete Core Cutter | C52: Up to 4 in (102 mm) | D52: Electric 2.5 kW | E52: Diamond cores 25–102 mm; wet drilling | F52: 0 | G52: 2 | H52: =MROUND(F52*G52*IF(ISNUMBER(SEARCH("Diesel",D52)),'Fuel & Inputs'!$C$4,IF(ISNUMBER(SEARCH("Petrol",D52)),'Fuel & Inputs'!$C$5,0)),10) -> 0 | I52: 3000 | J52: ='Fuel & Inputs'!$C$14 -> 3500 | K52: =I52+J52 -> 6500 | L52: =MROUND(K52+H52,100) -> 6500 | M52: Hi-Q/SL hire market
A53: 44 | B53: Asphalt/Concrete Core Cutter | C53: Up to 6 in (152 mm), w/ stand | D53: Electric 3.3 kW | E53: Wet drilling; anchor/vacuum stand | F53: 0 | G53: 2 | H53: =MROUND(F53*G53*IF(ISNUMBER(SEARCH("Diesel",D53)),'Fuel & Inputs'!$C$4,IF(ISNUMBER(SEARCH("Petrol",D53)),'Fuel & Inputs'!$C$5,0)),10) -> 0 | I53: 4500 | J53: ='Fuel & Inputs'!$C$14 -> 3500 | K53: =I53+J53 -> 8000 | L53: =MROUND(K53+H53,100) -> 8000 | M53: Hi-Q/SL hire market
A54: 45 | B54: Asphalt/Concrete Core Cutter | C54: Up to 10 in (254 mm), heavy | D54: Electric 5+ kW | E54: Deep cores; services penetrations | F54: 0 | G54: 2 | H54: =MROUND(F54*G54*IF(ISNUMBER(SEARCH("Diesel",D54)),'Fuel & Inputs'!$C$4,IF(ISNUMBER(SEARCH("Petrol",D54)),'Fuel & Inputs'!$C$5,0)),10) -> 0 | I54: 7000 | J54: ='Fuel & Inputs'!$C$14 -> 3500 | K54: =I54+J54 -> 10500 | L54: =MROUND(K54+H54,100) -> 10500 | M54: SL hire market
A55: 46 | B55: Road Core Cutter (petrol) | C55: 100/150 mm pavement cores | D55: Petrol engine | E55: QC cores on asphalt/ABC; trolley-mounted | F55: 1.2 | G55: 2 | H55: =MROUND(F55*G55*IF(ISNUMBER(SEARCH("Diesel",D55)),'Fuel & Inputs'!$C$4,IF(ISNUMBER(SEARCH("Petrol",D55)),'Fuel & Inputs'!$C$5,0)),10) -> 990 | I55: 5500 | J55: ='Fuel & Inputs'!$C$14 -> 3500 | K55: =I55+J55 -> 9000 | L55: =MROUND(K55+H55,100) -> 10000 | M55: Road-lab practice; bits at cost+15%
A56: 47 | B56: Wacker / Tamping Rammer | C56: 60–80 kg | D56: Petrol engine (GX120) | E56: 10–14 kN impact, ~650 bpm; trench compaction | F56: 1.2 | G56: 4 | H56: =MROUND(F56*G56*IF(ISNUMBER(SEARCH("Diesel",D56)),'Fuel & Inputs'!$C$4,IF(ISNUMBER(SEARCH("Petrol",D56)),'Fuel & Inputs'!$C$5,0)),10) -> 1990 | I56: 2500 | J56: ='Fuel & Inputs'!$C$14 -> 3500 | K56: =I56+J56 -> 6000 | L56: =MROUND(K56+H56,100) -> 8000 | M56: Peters rammer Rs.3,500/day
A57: 48 | B57: Plate Compactor (forward) | C57: 60–90 kg | D57: Petrol engine | E57: 10–15 kN; compacts ~400–600 m2/day | F57: 1 | G57: 4 | H57: =MROUND(F57*G57*IF(ISNUMBER(SEARCH("Diesel",D57)),'Fuel & Inputs'!$C$4,IF(ISNUMBER(SEARCH("Petrol",D57)),'Fuel & Inputs'!$C$5,0)),10) -> 1660 | I57: 3500 | J57: ='Fuel & Inputs'!$C$14 -> 3500 | K57: =I57+J57 -> 7000 | L57: =MROUND(K57+H57,100) -> 8700 | M57: Existing card; Peters
A58: 49 | B58: Plate Compactor (reversible) | C58: 160–250 kg | D58: Diesel engine | E58: 30–38 kN; deep-lift ABC/backfill | F58: 1.5 | G58: 4 | H58: =MROUND(F58*G58*IF(ISNUMBER(SEARCH("Diesel",D58)),'Fuel & Inputs'!$C$4,IF(ISNUMBER(SEARCH("Petrol",D58)),'Fuel & Inputs'!$C$5,0)),10) -> 2290 | I58: 6000 | J58: ='Fuel & Inputs'!$C$14 -> 3500 | K58: =I58+J58 -> 9500 | L58: =MROUND(K58+H58,100) -> 11800 | M58: SL hire market
A59: 50 | B59: Walk-behind Roller | C59: 600–1,000 kg (hand-drive) | D59: Diesel engine | E59: 650 mm drum; patch/footpath rolling | F59: 1.8 | G59: 4 | H59: =MROUND(F59*G59*IF(ISNUMBER(SEARCH("Diesel",D59)),'Fuel & Inputs'!$C$4,IF(ISNUMBER(SEARCH("Petrol",D59)),'Fuel & Inputs'!$C$5,0)),10) -> 2750 | I59: 6500 | J59: ='Fuel & Inputs'!$C$14 -> 3500 | K59: =I59+J59 -> 10000 | L59: =MROUND(K59+H59,100) -> 12800 | M59: Peters 1-ton hand-drive roller
A60: D — PUMPS & LIGHTING (engine pumps, submersibles, pressure pumps, light plants)
A61: # | B61: Equipment | C61: Capacity / Size | D61: Power / Fuel | E61: Output & Efficiency | F61: Cons. L/hr | G61: Duty hrs/day | H61: Fuel Rs./day | I61: DRY Rs./day | J61: Operator Rs./day | K61: DRY + OPERATOR Rs./day | L61: WET Rs./day | M61: Market reference (SL, 2026)
A62: 51 | B62: Engine Water Pump | C62: 2 in (petrol, self-priming) | D62: Petrol engine (WB20 class) | E62: 600–700 L/min; head ~30 m | F62: 0.9 | G62: 6 | H62: =MROUND(F62*G62*IF(ISNUMBER(SEARCH("Diesel",D62)),'Fuel & Inputs'!$C$4,IF(ISNUMBER(SEARCH("Petrol",D62)),'Fuel & Inputs'!$C$5,0)),10) -> 2240 | I62: 1800 | J62: ='Fuel & Inputs'!$C$14 -> 3500 | K62: =I62+J62 -> 5300 | L62: =MROUND(K62+H62,100) -> 7500 | M62: Existing card; Honda-type
A63: 52 | B63: Engine Water Pump | C63: 3 in (petrol, self-priming) | D63: Petrol engine (WB30 class) | E63: 1,000–1,100 L/min; head ~27 m | F63: 1.2 | G63: 6 | H63: =MROUND(F63*G63*IF(ISNUMBER(SEARCH("Diesel",D63)),'Fuel & Inputs'!$C$4,IF(ISNUMBER(SEARCH("Petrol",D63)),'Fuel & Inputs'!$C$5,0)),10) -> 2980 | I63: 2600 | J63: ='Fuel & Inputs'!$C$14 -> 3500 | K63: =I63+J63 -> 6100 | L63: =MROUND(K63+H63,100) -> 9100 | M63: Existing card
A64: 53 | B64: Engine Water Pump | C64: 4 in (diesel) | D64: Diesel engine | E64: 1,600–1,800 L/min; site dewatering | F64: 1.6 | G64: 6 | H64: =MROUND(F64*G64*IF(ISNUMBER(SEARCH("Diesel",D64)),'Fuel & Inputs'!$C$4,IF(ISNUMBER(SEARCH("Petrol",D64)),'Fuel & Inputs'!$C$5,0)),10) -> 3670 | I64: 4300 | J64: ='Fuel & Inputs'!$C$14 -> 3500 | K64: =I64+J64 -> 7800 | L64: =MROUND(K64+H64,100) -> 11500 | M64: Existing card
A65: 54 | B65: Engine Water Pump | C65: 6 in (diesel) | D65: Diesel engine | E65: 2,500–3,000 L/min; bulk dewatering | F65: 3 | G65: 6 | H65: =MROUND(F65*G65*IF(ISNUMBER(SEARCH("Diesel",D65)),'Fuel & Inputs'!$C$4,IF(ISNUMBER(SEARCH("Petrol",D65)),'Fuel & Inputs'!$C$5,0)),10) -> 6880 | I65: 6500 | J65: ='Fuel & Inputs'!$C$14 -> 3500 | K65: =I65+J65 -> 10000 | L65: =MROUND(K65+H65,100) -> 16900 | M65: SL project band
A66: 55 | B66: Trash Pump | C66: 3 in solids-handling | D66: Diesel engine | E66: ~1,200 L/min; solids up to 25 mm | F66: 1.4 | G66: 6 | H66: =MROUND(F66*G66*IF(ISNUMBER(SEARCH("Diesel",D66)),'Fuel & Inputs'!$C$4,IF(ISNUMBER(SEARCH("Petrol",D66)),'Fuel & Inputs'!$C$5,0)),10) -> 3210 | I66: 3700 | J66: ='Fuel & Inputs'!$C$14 -> 3500 | K66: =I66+J66 -> 7200 | L66: =MROUND(K66+H66,100) -> 10400 | M66: Existing card
A67: 56 | B67: Submersible Pump | C67: 1 in (electric) | D67: Electric 0.4 kW | E67: 100–150 L/min; head 8–10 m | F67: 0 | G67: 8 | H67: =MROUND(F67*G67*IF(ISNUMBER(SEARCH("Diesel",D67)),'Fuel & Inputs'!$C$4,IF(ISNUMBER(SEARCH("Petrol",D67)),'Fuel & Inputs'!$C$5,0)),10) -> 0 | I67: 800 | J67: 0 | K67: =I67+J67 -> 800 | L67: =MROUND(K67+H67,100) -> 800 | M67: Existing card
A68: 57 | B68: Submersible Pump | C68: 2 in (electric) | D68: Electric 1.1 kW | E68: 250–350 L/min; head 10–12 m | F68: 0 | G68: 8 | H68: =MROUND(F68*G68*IF(ISNUMBER(SEARCH("Diesel",D68)),'Fuel & Inputs'!$C$4,IF(ISNUMBER(SEARCH("Petrol",D68)),'Fuel & Inputs'!$C$5,0)),10) -> 0 | I68: 1300 | J68: 0 | K68: =I68+J68 -> 1300 | L68: =MROUND(K68+H68,100) -> 1300 | M68: Existing card
A69: 58 | B69: Submersible Pump | C69: 3 in (electric) | D69: Electric 2.2 kW | E69: 600–700 L/min; head 12–15 m | F69: 0 | G69: 8 | H69: =MROUND(F69*G69*IF(ISNUMBER(SEARCH("Diesel",D69)),'Fuel & Inputs'!$C$4,IF(ISNUMBER(SEARCH("Petrol",D69)),'Fuel & Inputs'!$C$5,0)),10) -> 0 | I69: 2100 | J69: 0 | K69: =I69+J69 -> 2100 | L69: =MROUND(K69+H69,100) -> 2100 | M69: Existing card
A70: 59 | B70: Submersible Pump | C70: 4 in (electric) | D70: Electric 3.7 kW | E70: 1,000–1,300 L/min | F70: 0 | G70: 8 | H70: =MROUND(F70*G70*IF(ISNUMBER(SEARCH("Diesel",D70)),'Fuel & Inputs'!$C$4,IF(ISNUMBER(SEARCH("Petrol",D70)),'Fuel & Inputs'!$C$5,0)),10) -> 0 | I70: 3300 | J70: 0 | K70: =I70+J70 -> 3300 | L70: =MROUND(K70+H70,100) -> 3300 | M70: Existing card
A71: 60 | B71: Submersible Pump | C71: 6 in (high-volume) | D71: Electric 7.5 kW | E71: 2,500–3,000 L/min | F71: 0 | G71: 8 | H71: =MROUND(F71*G71*IF(ISNUMBER(SEARCH("Diesel",D71)),'Fuel & Inputs'!$C$4,IF(ISNUMBER(SEARCH("Petrol",D71)),'Fuel & Inputs'!$C$5,0)),10) -> 0 | I71: 6000 | J71: ='Fuel & Inputs'!$C$14 -> 3500 | K71: =I71+J71 -> 9500 | L71: =MROUND(K71+H71,100) -> 9500 | M71: Existing card
A72: 61 | B72: Water Pressure Pump | C72: HP washer 100–130 bar | D72: Electric 2.0–2.5 kW | E72: 6–8 L/min; cleaning/curing | F72: 0 | G72: 4 | H72: =MROUND(F72*G72*IF(ISNUMBER(SEARCH("Diesel",D72)),'Fuel & Inputs'!$C$4,IF(ISNUMBER(SEARCH("Petrol",D72)),'Fuel & Inputs'!$C$5,0)),10) -> 0 | I72: 1500 | J72: 0 | K72: =I72+J72 -> 1500 | L72: =MROUND(K72+H72,100) -> 1500 | M72: SL hire market
A73: 62 | B73: Water Pressure Pump | C73: HP washer 150–200 bar | D73: Petrol engine | E73: 12–15 L/min; shutter/plant washing | F73: 0.9 | G73: 4 | H73: =MROUND(F73*G73*IF(ISNUMBER(SEARCH("Diesel",D73)),'Fuel & Inputs'!$C$4,IF(ISNUMBER(SEARCH("Petrol",D73)),'Fuel & Inputs'!$C$5,0)),10) -> 1490 | I73: 3000 | J73: ='Fuel & Inputs'!$C$14 -> 3500 | K73: =I73+J73 -> 6500 | L73: =MROUND(K73+H73,100) -> 8000 | M73: SL hire market
A74: 63 | B74: Water Pressure Pump | C74: HP washer 250 bar industrial | D74: Diesel engine | E74: 15–21 L/min; hydro-cleaning | F74: 1.5 | G74: 4 | H74: =MROUND(F74*G74*IF(ISNUMBER(SEARCH("Diesel",D74)),'Fuel & Inputs'!$C$4,IF(ISNUMBER(SEARCH("Petrol",D74)),'Fuel & Inputs'!$C$5,0)),10) -> 2290 | I74: 5000 | J74: ='Fuel & Inputs'!$C$14 -> 3500 | K74: =I74+J74 -> 8500 | L74: =MROUND(K74+H74,100) -> 10800 | M74: SL hire market
A75: 64 | B75: Water Pressure Pump | C75: Hydrostatic test pump to 60 bar | D75: Electric / manual | E75: Pipeline pressure testing | F75: 0 | G75: 2 | H75: =MROUND(F75*G75*IF(ISNUMBER(SEARCH("Diesel",D75)),'Fuel & Inputs'!$C$4,IF(ISNUMBER(SEARCH("Petrol",D75)),'Fuel & Inputs'!$C$5,0)),10) -> 0 | I75: 1500 | J75: 0 | K75: =I75+J75 -> 1500 | L75: =MROUND(K75+H75,100) -> 1500 | M75: Hi-Q hand test pump class
A76: 65 | B76: Water Pressure Pump | C76: Booster pump 1–2 HP | D76: Electric 0.75–1.5 kW | E76: 30–60 L/min; head 30–40 m | F76: 0 | G76: 8 | H76: =MROUND(F76*G76*IF(ISNUMBER(SEARCH("Diesel",D76)),'Fuel & Inputs'!$C$4,IF(ISNUMBER(SEARCH("Petrol",D76)),'Fuel & Inputs'!$C$5,0)),10) -> 0 | I76: 1200 | J76: 0 | K76: =I76+J76 -> 1200 | L76: =MROUND(K76+H76,100) -> 1200 | M76: SL hire market
A77: 66 | B77: Light Plant | C77: LED tower 4x400 W (mobile) | D77: Diesel engine | E77: Mast 5–9 m; lights ~4,000–5,000 m2; 12-hr night duty | F77: 0.8 | G77: 12 | H77: =MROUND(F77*G77*IF(ISNUMBER(SEARCH("Diesel",D77)),'Fuel & Inputs'!$C$4,IF(ISNUMBER(SEARCH("Petrol",D77)),'Fuel & Inputs'!$C$5,0)),10) -> 3670 | I77: 6000 | J77: ='Fuel & Inputs'!$C$14 -> 3500 | K77: =I77+J77 -> 9500 | L77: =MROUND(K77+H77,100) -> 13200 | M77: Existing card
A78: 67 | B78: Light Plant | C78: Metal-halide tower 4x1,000 W | D78: Diesel engine | E78: Mast 9 m; lights ~6,000 m2; 12-hr night duty | F78: 2 | G78: 12 | H78: =MROUND(F78*G78*IF(ISNUMBER(SEARCH("Diesel",D78)),'Fuel & Inputs'!$C$4,IF(ISNUMBER(SEARCH("Petrol",D78)),'Fuel & Inputs'!$C$5,0)),10) -> 9170 | I78: 8000 | J78: ='Fuel & Inputs'!$C$14 -> 3500 | K78: =I78+J78 -> 11500 | L78: =MROUND(K78+H78,100) -> 20700 | M78: Existing card
A79: 68 | B79: Light Plant | C79: LED work light 2x50 W + tripod | D79: Electric | E79: Task lighting, indoor works | F79: 0 | G79: 12 | H79: =MROUND(F79*G79*IF(ISNUMBER(SEARCH("Diesel",D79)),'Fuel & Inputs'!$C$4,IF(ISNUMBER(SEARCH("Petrol",D79)),'Fuel & Inputs'!$C$5,0)),10) -> 0 | I79: 600 | J79: 0 | K79: =I79+J79 -> 600 | L79: =MROUND(K79+H79,100) -> 600 | M79: SL hire market
A80: E — GENERAL TOOLS (saws, grinders, drills, winches)
A81: # | B81: Equipment | C81: Capacity / Size | D81: Power / Fuel | E81: Output & Efficiency | F81: Cons. L/hr | G81: Duty hrs/day | H81: Fuel Rs./day | I81: DRY Rs./day | J81: Operator Rs./day | K81: DRY + OPERATOR Rs./day | L81: WET Rs./day | M81: Market reference (SL, 2026)
A82: 69 | B82: Circular Saw | C82: 7 in (185 mm) | D82: Electric 1.4 kW | E82: Timber to 60 mm | F82: 0 | G82: 4 | H82: =MROUND(F82*G82*IF(ISNUMBER(SEARCH("Diesel",D82)),'Fuel & Inputs'!$C$4,IF(ISNUMBER(SEARCH("Petrol",D82)),'Fuel & Inputs'!$C$5,0)),10) -> 0 | I82: 800 | J82: 0 | K82: =I82+J82 -> 800 | L82: =MROUND(K82+H82,100) -> 800 | M82: Existing card
A83: 70 | B83: Circular Saw | C83: 9 in (235 mm) | D83: Electric 2.0 kW | E83: Timber to 85 mm | F83: 0 | G83: 4 | H83: =MROUND(F83*G83*IF(ISNUMBER(SEARCH("Diesel",D83)),'Fuel & Inputs'!$C$4,IF(ISNUMBER(SEARCH("Petrol",D83)),'Fuel & Inputs'!$C$5,0)),10) -> 0 | I83: 1100 | J83: 0 | K83: =I83+J83 -> 1100 | L83: =MROUND(K83+H83,100) -> 1100 | M83: Existing card
A84: 71 | B84: Angle Grinder | C84: 4–5 in (100–125 mm) | D84: Electric 0.9 kW | E84: Cutting/grinding steel & masonry | F84: 0 | G84: 4 | H84: =MROUND(F84*G84*IF(ISNUMBER(SEARCH("Diesel",D84)),'Fuel & Inputs'!$C$4,IF(ISNUMBER(SEARCH("Petrol",D84)),'Fuel & Inputs'!$C$5,0)),10) -> 0 | I84: 550 | J84: 0 | K84: =I84+J84 -> 550 | L84: =MROUND(K84+H84,100) -> 600 | M84: Existing card
A85: 72 | B85: Angle Grinder | C85: 7–9 in (180–230 mm) | D85: Electric 2.2 kW | E85: Heavy cutting/grinding | F85: 0 | G85: 4 | H85: =MROUND(F85*G85*IF(ISNUMBER(SEARCH("Diesel",D85)),'Fuel & Inputs'!$C$4,IF(ISNUMBER(SEARCH("Petrol",D85)),'Fuel & Inputs'!$C$5,0)),10) -> 0 | I85: 950 | J85: 0 | K85: =I85+J85 -> 950 | L85: =MROUND(K85+H85,100) -> 1000 | M85: Existing card
A86: 73 | B86: Drill (hand/hammer/impact) | C86: Up to 13 mm | D86: Electric 0.5–0.8 kW | E86: Steel/masonry drilling | F86: 0 | G86: 4 | H86: =MROUND(F86*G86*IF(ISNUMBER(SEARCH("Diesel",D86)),'Fuel & Inputs'!$C$4,IF(ISNUMBER(SEARCH("Petrol",D86)),'Fuel & Inputs'!$C$5,0)),10) -> 0 | I86: 450 | J86: 0 | K86: =I86+J86 -> 450 | L86: =MROUND(K86+H86,100) -> 500 | M86: Peters drills Rs.250–500/day
A87: 74 | B87: Magnetic Drill | C87: Broach to 32 mm | D87: Electric 1.1 kW | E87: Steel fabrication drilling | F87: 0 | G87: 4 | H87: =MROUND(F87*G87*IF(ISNUMBER(SEARCH("Diesel",D87)),'Fuel & Inputs'!$C$4,IF(ISNUMBER(SEARCH("Petrol",D87)),'Fuel & Inputs'!$C$5,0)),10) -> 0 | I87: 4000 | J87: ='Fuel & Inputs'!$C$14 -> 3500 | K87: =I87+J87 -> 7500 | L87: =MROUND(K87+H87,100) -> 7500 | M87: Peters magnetic drill Rs.6,000/day
A88: 75 | B88: Electric Winch | C88: 500 kg – 1 t | D88: Electric | E88: Lifting/pulling with wire rope | F88: 0 | G88: 4 | H88: =MROUND(F88*G88*IF(ISNUMBER(SEARCH("Diesel",D88)),'Fuel & Inputs'!$C$4,IF(ISNUMBER(SEARCH("Petrol",D88)),'Fuel & Inputs'!$C$5,0)),10) -> 0 | I88: 3500 | J88: ='Fuel & Inputs'!$C$14 -> 3500 | K88: =I88+J88 -> 7000 | L88: =MROUND(K88+H88,100) -> 7000 | M88: Peters winch Rs.5,000/day
A89: 76 | B89: Bench Drill | C89: Up to 16 mm | D89: Electric | E89: Workshop precision drilling | F89: 0 | G89: 8 | H89: =MROUND(F89*G89*IF(ISNUMBER(SEARCH("Diesel",D89)),'Fuel & Inputs'!$C$4,IF(ISNUMBER(SEARCH("Petrol",D89)),'Fuel & Inputs'!$C$5,0)),10) -> 0 | I89: 500 | J89: 0 | K89: =I89+J89 -> 500 | L89: =MROUND(K89+H89,100) -> 500 | M89: Peters bench drill Rs.500/day
B91: Operator column = 0 means the item is typically dry-hired (hand tool); a tradesman can be supplied at Rs.3,500–5,000/day on request. Jack hammer & gas-cutting set: consumables (air from compressor / gas cylinders) billed separately — hence duty hrs = 0 in the fuel column.

Sheet Market Analysis
A1: SRI LANKAN RENTAL MARKET ANALYSIS — JULY 2026
A2: Sources: SLLDC official rates (government ceiling), Peters Equipment published day-rates (petersequipment.lk), wedabima.com & ikman.lk listings, Hi-Q Tools, Generators.lk/UTE bands, CPC/Ceypetco fuel notices, Daily Mirror/News1st fuel reporting.
A4: 1. FUEL PRICE CONTEXT (drives every WET rate)
A5: • Feb-2026 Middle-East conflict disrupted the Hormuz route (+~45% global crude) and LKR fell ~5% YTD -> CPC raised prices 3 times: Auto Diesel Rs.286 (Jan) -> 303 (Mar) -> 392 -> 407 (30-May peak). Petrol 92 peaked at Rs.434.
A6: • 29-Jun-2026 revision CUT Auto Diesel by Rs.25 to Rs.382/L and Petrol 92 by Rs.20 to Rs.414/L — the basis used throughout this workbook.
A7: • The old v7 'Fuel Rates' sheet used Rs.478/L — that is the SUPER Diesel (Euro-4) price, not Auto Diesel. All fleet plant runs on Auto Diesel; rates here are corrected to Rs.382.
A8: • CPC subsidy (~Rs.100/L on diesel) is confirmed only until Sep-2026 — quote WET rates with the fuel escalation clause (README). A +Rs.50/L move adds e.g. Rs.750/hr to a 20T excavator (15 L/hr).
A10: 2. FLEET — OUR WET RATE vs MARKET (Rs./hr)
A11: Category | B11: Our WET | C11: Market LOW | D11: Market MID | E11: Market HIGH | F11: % above LOW | G11: % below HIGH | H11: Position
A12: Backhoe Loader | B12: ='Fleet Price Sheet'!G5 -> 4150 | C12: 2500 | D12: 3500 | E12: 6050 | F12: =(B12-C12)/C12 -> 0.66 | G12: =(E12-B12)/E12 -> 0.31404959 | H12: =IF(B12>E12*0.88,"UPPER",IF(B12<C12*1.1,"LOWER","MID-MARKET")) -> MID-MARKET
A13: Wheel Loader | B13: ='Fleet Price Sheet'!G6 -> 8450 | C13: 5000 | D13: 8500 | E13: 15760 | F13: =(B13-C13)/C13 -> 0.69 | G13: =(E13-B13)/E13 -> 0.46383249 | H13: =IF(B13>E13*0.88,"UPPER",IF(B13<C13*1.1,"LOWER","MID-MARKET")) -> MID-MARKET
A14: Truck Mixer | B14: ='Fleet Price Sheet'!G7 -> 4850 | C14: 3500 | D14: 4500 | E14: 5500 | F14: =(B14-C14)/C14 -> 0.38571429 | G14: =(E14-B14)/E14 -> 0.11818182 | H14: =IF(B14>E14*0.88,"UPPER",IF(B14<C14*1.1,"LOWER","MID-MARKET")) -> UPPER
A15: Self Loader Mixer | B15: ='Fleet Price Sheet'!G8 -> 5300 | C15: 4500 | D15: 5200 | E15: 6000 | F15: =(B15-C15)/C15 -> 0.17777778 | G15: =(E15-B15)/E15 -> 0.11666667 | H15: =IF(B15>E15*0.88,"UPPER",IF(B15<C15*1.1,"LOWER","MID-MARKET")) -> UPPER
A16: Static Roller | B16: ='Fleet Price Sheet'!G9 -> 4600 | C16: 2500 | D16: 3500 | E16: 5230 | F16: =(B16-C16)/C16 -> 0.84 | G16: =(E16-B16)/E16 -> 0.12045889 | H16: =IF(B16>E16*0.88,"UPPER",IF(B16<C16*1.1,"LOWER","MID-MARKET")) -> MID-MARKET
A17: Vibrating Roller | B17: ='Fleet Price Sheet'!G10 -> 3900 | C17: 3000 | D17: 4000 | E17: 5000 | F17: =(B17-C17)/C17 -> 0.3 | G17: =(E17-B17)/E17 -> 0.22 | H17: =IF(B17>E17*0.88,"UPPER",IF(B17<C17*1.1,"LOWER","MID-MARKET")) -> MID-MARKET
A18: Pneumatic Roller | B18: ='Fleet Price Sheet'!G11 -> 3950 | C18: 3000 | D18: 3800 | E18: 4500 | F18: =(B18-C18)/C18 -> 0.31666667 | G18: =(E18-B18)/E18 -> 0.12222222 | H18: =IF(B18>E18*0.88,"UPPER",IF(B18<C18*1.1,"LOWER","MID-MARKET")) -> MID-MARKET
A19: Motor Grader | B19: ='Fleet Price Sheet'!G12 -> 9650 | C19: 7000 | D19: 8500 | E19: 11000 | F19: =(B19-C19)/C19 -> 0.37857143 | G19: =(E19-B19)/E19 -> 0.12272727 | H19: =IF(B19>E19*0.88,"UPPER",IF(B19<C19*1.1,"LOWER","MID-MARKET")) -> MID-MARKET
A20: Skid Steer | B20: ='Fleet Price Sheet'!G13 -> 2700 | C20: 2000 | D20: 2500 | E20: 3060 | F20: =(B20-C20)/C20 -> 0.35 | G20: =(E20-B20)/E20 -> 0.11764706 | H20: =IF(B20>E20*0.88,"UPPER",IF(B20<C20*1.1,"LOWER","MID-MARKET")) -> UPPER
A21: Asphalt Paver | B21: ='Fleet Price Sheet'!G14 -> 8050 | C21: 7000 | D21: 8500 | E21: 10000 | F21: =(B21-C21)/C21 -> 0.15 | G21: =(E21-B21)/E21 -> 0.195 | H21: =IF(B21>E21*0.88,"UPPER",IF(B21<C21*1.1,"LOWER","MID-MARKET")) -> MID-MARKET
A22: Bitumen Bowser | B22: ='Fleet Price Sheet'!G15 -> 3500 | C22: 2500 | D22: 3200 | E22: 4000 | F22: =(B22-C22)/C22 -> 0.4 | G22: =(E22-B22)/E22 -> 0.125 | H22: =IF(B22>E22*0.88,"UPPER",IF(B22<C22*1.1,"LOWER","MID-MARKET")) -> MID-MARKET
A23: Mobile Crane | B23: ='Fleet Price Sheet'!G16 -> 8800 | C23: 8000 | D23: 9500 | E23: 11660 | F23: =(B23-C23)/C23 -> 0.1 | G23: =(E23-B23)/E23 -> 0.24528302 | H23: =IF(B23>E23*0.88,"UPPER",IF(B23<C23*1.1,"LOWER","MID-MARKET")) -> MID-MARKET
... A40: Forklift (3T) | B40: ='Fleet Price Sheet'!G33 -> 3050 | C40: 2000 | D40: 3000 | E40: 3800 | F40: =(B40-C40)/C40 -> 0.525 | G40: =(E40-B40)/E40 -> 0.19736842 | H40: =IF(B40>E40*0.88,"UPPER",IF(B40<C40*1.1,"LOWER","MID-MARKET")) -> MID-MARKET
A42: 3. MACHINERY — PUBLISHED SL DAY-RATE ANCHORS vs THIS SHEET
A43: Market item (published) | B43: Published Rs./day | C43: Vendor / basis | D43: Our comparable DRY | E43: Our DRY+OPERATOR | F43: Our fully-WET | G43: Reading
A44: Generator 5 kVA | B44: 4000 | C44: Peters Equipment | G44: Published rate ~ our DRY+attendant; excludes 8-hr fuel (~Rs.4,600 petrol)
A45: Generator 10 kVA diesel | B45: 6000 | C45: Peters Equipment | G45: 8-hr fuel alone = ~Rs.6,700 -> published rate cannot be fully wet
A46: Generator 25 kVA diesel | B46: 8000 | C46: Peters Equipment | G46: 8-hr fuel = ~Rs.12,200; treat market rate as DRY-plus
A47: Generator 50 kVA diesel | B47: 11000 | C47: Peters Equipment | G47: 8-hr fuel = ~Rs.22,900; fully-wet is ~2x the published rate
A48: Bar bending machine | B48: 6000 | C48: Peters Equipment | G48: Sits between our DRY Rs.4,500 and DRY+OP Rs.8,000 (32 mm class)
A49: Tamping rammer | B49: 3500 | C49: Peters Equipment | G49: our dry rs.2,500 + margin; our fully-wet ~rs.8,0 incl. op+fuel
A50: Jack hammer (pkg) | B50: 10000 | C50: Peters Equipment | G50: Package incl. compressor air; our breaker line + 185 cfm covers it
A51: Demolition breaker | B51: 4000 | C51: Peters Equipment | G51: Matches our DRY Rs.2,700 + operator margin
A52: Rotary hammer SDS | B52: 3000 | C52: Peters Equipment | G52: Our DRY Rs.1,000 undercuts; theirs likely incl. bits/attendance
A53: Metal gas cutter set | B53: 5500 | C53: Peters Equipment | G53: Ours Rs.3,800 DRY + welder; gas cylinders billed at cost
A54: Magnetic drill | B54: 6000 | C54: Peters Equipment | G54: Ours Rs.4,000 DRY — competitive
A55: Electric winch | B55: 5000 | C55: Peters Equipment | G55: Ours Rs.3,500 DRY — competitive
A56: Hand drill | B56: 250 | C56: Peters Equipment | G56: Ours Rs.450 DRY incl. hammer/impact class
A57: Bar bender/cutter 6–52 mm | B57: Call | C57: wedabima.com listings | G57: Full diameter range confirmed available for hire in SL
A58: Tamping rammer (regional) | B58: Call | C58: Wayamba Rent-A-All (wedabima) | G58: Regional availability outside Colombo confirmed
A60: 4. KEY FINDINGS & RECOMMENDATIONS
A61: F1 — Fleet WET card sits mid-market: typically 10–75% above the cheapest private quotes and 11–47% below the SLLDC government ceiling. Positioning intact at Diesel Rs.382.
A62: F2 — New DRY+OPERATOR tier = DRY + Rs.800/hr (Rs.650 cost x 1.23 loading). This prices the common 'our operator, your fuel' deal without disturbing the engineered card, and protects us from fuel-price risk on those contracts.
A63: F3 — Margin check (Fleet sheet col H/I): 27 of 29 categories flag THIN, i.e. the price drop from WET to DRY+OPERATOR is larger than the diesel the client takes over. This is a structural feature of the SL market: DRY ratios (0.45–0.55 x WET) price the bare machine at a premium for utilisation/abuse risk. Commercial reading: (a) WET still clears the engineering floor (fuel+operator+20% profit) so keep pushing WET; (b) DRY+OPERATOR contracts fully insulate us from fuel-price risk — favour them while CPC prices are volatile; (c) never quote WET without the escalation clause, because the implied fuel allowance inside WET has no headroom for heavy-duty burn.
A64: F4 — Machinery: published SL 'day rates' (e.g., 10 kVA genset Rs.6,000) behave like DRY / DRY+attendant. A genuine fully-wet 10 kVA day costs ~Rs.13,700 (Rs.3,500 machine + Rs.3,500 operator + ~Rs.6,700 diesel for 8 hrs). The old sheet's 'WET Rs.7,000' under-recovered fuel by ~Rs.6,700/day. This sheet computes WET honestly from duty-hours x L/hr x CPC price — quote it with confidence and show the client the math.
A65: F5 — Duty-hours are the fair-use assumption inside each WET day rate (generators 8 h, pumps 6 h, mixers/pokers/compaction 4–5 h, cutters/cores 2–3 h, light towers 12 h night). Meter/log extra hours and bill at L/hr x CPC price.
A66: F6 — Bar cutters/benders to 40–42 mm, asphalt cutters to 18 in, core cutters to 10 in, wackers, pressure pumps and light towers are all confirmed rentable in the SL market (Peters, wedabima, Hi-Q) — the new lines fill gaps competitors already monetise.
A67: F7 — All rates exclude 18% VAT, transport/mobilisation and operator out-station costs. Review the blue market cells quarterly; review fuel cells at every CPC notice (monthly).
