Workbook

Sheet README
B2: FLEET RENTAL PRICING — 2026 RATE CARD
B3: Market: Sri Lanka | Currency: LKR | Fleet Size: 518 units
B5: Purpose | C5: Internal rate-card workbook used to quote customers for daily / hourly / monthly rental of our machinery fleet.
B6: Pricing strategy | C6: Competitive but not cheapest — positioned ~15–20% below SLLDC official government rates and in line with private operators in Colombo, Gampaha, Kandy, Kurunegala.
B7: Wet rate | C7: INCLUDES fuel + operator + normal maintenance. Recommended for clients without trained operators.
B8: Dry rate | C8: Machine ONLY. Fuel, operator, lubricants, toll and food paid by client. Recommended for contractors with own crew.
B9: Daily rate | C9: Minimum billable 4 working hours per day. Derived as Hourly × 4 × 0.95 (5% volume discount).
B10: Monthly rate | C10: Minimum billable 120 working hours per month. Derived as Hourly × 120 × 0.85 (15% volume discount). Extra hours billed at Hourly rate.
B11: Age adjustment | C11: Rate declines with age: 2020+ = 100%, 2015–19 = 92%, 2010–14 = 82%, 2005–09 = 72%, 2000–04 = 65%, pre-2000 = 58%. Applied on top of base rate.
B12: Excavator size | C12: Separate multiplier by model (e.g. PC30 = 0.55×, PC200 = 1.00×, R330 = 1.30×).
B13: Client extras | C13: Trailer one-way, toll, fines, operator meals & lodging charged at cost. 15-day advance payment standard.
B14: VAT | C14: Add 18% VAT on all rates (standard SL rate 2026).
B16: Workbook sheets
B17: 1. README | C17: This page.
B18: 2. Rate Card | C18: Base hourly Wet/Dry rate per category + age factors (editable inputs in blue).
B19: 3. Fleet Pricing | C19: Every single unit (518) with calculated 2026 Dry/Wet hourly, daily (min 4h), monthly (min 120h) rates.
B20: 4. Market Research | C20: Competitor prices gathered from Sri Lankan & Indian rental portals (SLLDC, wedabima, krearthmovers, petersequipment, ikman).
B21: 5. Summary by Category | C21: Fleet count & average monthly wet revenue potential per category.
B23: Prepared | C23: April 2026 — All prices in LKR, exclusive of VAT.
B25: NEW SHEETS (v2 — engineering)
B26: 6. Engineering Assumptions | C26: All inputs: diesel price, operator rate, fuel consumption per category, PM/repair base costs, new unit prices, service life, age multipliers, consumable prices.
B27: 7. Engineering Cost | C27: Per-unit hourly cost build-up: Fuel + Operator + PM + Major repair + Overhead + 20% profit = suggested WET rate. Compare against current Fleet Pricing.
B28: 8. Maintenance & Repair | C28: Monthly spend forecast per unit (120 hrs): fuel, operator, PM, major repair, totals with overhead.
B29: 9. Replacement Analysis | C29: Every unit scored KEEP / MONITOR / REPLACE based on age, repair-to-revenue ratio, estimated 2026 resale value, and brand-new 2026 price.
B30: 10. Replacement Summary | C30: Category rollup — how many to KEEP / MONITOR / REPLACE, total CAPEX for new equipment, total resale from retiring old units.
B32: Key inputs given (Apr 2026)
B33: Operator rate | C33: Rs. 650 / hour • Minimum monthly salary Rs. 78,000
B34: Gross profit target | C34: 20% on total cost
B35: Overhead | C35: 15% of direct cost (yard, admin, insurance, transport, depreciation recovery)
B36: Diesel (CPC Auto Diesel) | C36: Rs. 382 / litre (March 2026 CPC)
B37: Min working hours | C37: 120 / month • 4 / day
B39: CHANGELOG — v3 rate engineering
B40: Issue identified | C40: Previous rates (v2) sat below engineering cost floor — we were earning less than the 20% target profit on many units.
B41: Fix (v3) | C41: Rate Card now shows Market LOW / MID / HIGH for each category and derives the recommended rate via formula: MAX(Engineering Floor, LOW × 1.10) capped at HIGH × 0.88.
B42: Outcome | C42: New rates sit in the upper-mid of the market — above bottom-feeders, below SLLDC government ceiling. Typical increase +25–40%.
B43: If the cell in column G (Eng. Floor) on Rate Card turns red | C43: It means even the market HIGH price × 0.88 won't cover cost + 20% profit. Either we must run at lower margin for that category, or stop renting it out.
B45: CHANGELOG — v4 portable equipment
B46: New sheet added | C46: "Portable Equipment Rates" (sheet 3) — capacity-wise daily hire rates for generators, air compressors, poker/concrete vibrators, submersible pumps (1"–6"), engine water pumps (2"/3"/4"), rotary hammers, circular saws, angle grinders, plate compactor, power trowel and welding plant.
B47: Basis | C47: WET = fuel/operator/consumables included; DRY = bare hire. Per-day billing, minimum 1 day. 36 line items across 10 categories. Excludes 18% VAT & transport.
B48: Market sources | C48: Sri Lankan rental market, May–Jun 2026: Peters Equipment (petersequipment.lk) published day-rates; surplus.lk and wedabima.com availability. Generators Rs.4,000–12,000/day by kVA; Rotary Hammer SDS Rs.3,000; Demolition Breaker Rs.4,000; Tamping Rammer Rs.3,500; drills Rs.250–500.
B49: Also in app | C49: The same 36 items are loaded into the Machine Rental Calculator (invoice/proforma/quotation tool) under a new "Per-Day" billing mode with a WET/DRY toggle.
B51: CHANGELOG — v7 fuel rates by model class + year
B52: New sheet | C52: "Fuel Rates": per-unit Lowest/Medium/Highest fuel-cost rate for all 518 units, estimated from each machine's MODEL size/engine class and adjusted for AGE via the manufacturing year. Rs./hr machinery, Rs./km road.
B53: Method | C53: Typical consumption is model-specific (e.g. excavators: Mini 4 L/hr / Compact 6.5 / Midi 10 / Standard 16 / Large 22). Econ=0.72x & Heavy=1.35x for machinery; road km/L Econ=1.28x, Heavy=0.80x. Age factor = 1+(years x %/yr, capped); editable base year 2026, 0.7%/yr, cap 25. Rate = consumption x age x fuel price.
B54: Coverage | C54: 29 categories, model-tiered where size varies (excavator, loader, tipper, mixer, crane, skid-steer, prime mover). 411/518 have a year; 107 use x1.00 until filled. Trailers=zero. Only motorcycles petrol.
B55: Examples | C55: Mini excavator (PC60) Rs.1,551/2,140/2,888/hr; Large excavator (Robex330) Rs.7,552/10,516/14,197/hr; Std tipper 16t Rs.139/176/220 per km; Motorcycle Rs.9/11/14 per km. Age: 1995 unit x1.18, 2013 unit x1.09, no-year x1.00.
B56: Note | C56: Bare fuel cost only — excludes operator, lubricants, maintenance, margin. Add on top of a DRY or DRY+Labour rate to build a WET charge.

Sheet Rate Card
A1: 2026 RATE CARD — Engineering-Derived Hourly Rates
A2: Each rate is computed from three drivers: Market LOW, Market HIGH, and Engineering Cost + 20% profit. Recommended Wet = MAX(Engineering Floor, Market LOW × 1.10) capped at Market HIGH × 0.88. Recommended Dry = Wet × Dry ratio (industry convention). Blue cells = editable inputs.
A4: # | B4: Category | C4: Market LOW (wet) | D4: Market MID (wet) | E4: Market HIGH (wet) | F4: Eng. Cost / h (age-5) | G4: Eng. Floor (+20% profit) | H4: Positioning rule | I4: Recommended WET (/h) | J4: Dry ratio (blue = editable) | K4: Recommended DRY (/h) | L4: Wet : Dry ratio | M4: % above LOW | N4: % below HIGH | O4: Source / note
A5: 1 | B5: Backhoe Loader | C5: 2500 | D5: 3500 | E5: 6050 | F5: ='Engineering Assumptions'!$C$18*'Engineering Assumptions'!$B$5+'Engineering Assumptions'!$B$8+'Engineering Assumptions'!$D$18*1+'Engineering Assumptions'!$E$18*0.3 -> 2997 | G5: =F5*(1+'Engineering Assumptions'!$B$10)*(1+'Engineering Assumptions'!$B$11) -> 4135.86 | H5: MAX(Eng. Floor, LOW×1.10) capped at HIGH×0.88 | I5: =MROUND(MIN(MAX(G5,C5*1.1),E5*0.88),50) -> 4150 | J5: 0.48 | K5: =MROUND(I5*J5,50) -> 2000 | L5: =K5/I5 -> 0.48192771 | M5: =(I5-C5)/C5 -> 0.66 | N5: =(E5-I5)/E5 -> 0.31404959 | O5: LOW: Small private, Wedabima • HIGH: SLLDC JCB 3CX wet
A6: 2 | B6: Wheel Loader | C6: 5000 | D6: 8500 | E6: 15760 | F6: ='Engineering Assumptions'!$C$19*'Engineering Assumptions'!$B$5+'Engineering Assumptions'!$B$8+'Engineering Assumptions'!$D$19*1+'Engineering Assumptions'!$E$19*0.3 -> 6110 | G6: =F6*(1+'Engineering Assumptions'!$B$10)*(1+'Engineering Assumptions'!$B$11) -> 8431.8 | H6: MAX(Eng. Floor, LOW×1.10) capped at HIGH×0.88 | I6: =MROUND(MIN(MAX(G6,C6*1.1),E6*0.88),50) -> 8450 | J6: 0.45 | K6: =MROUND(I6*J6,50) -> 3800 | L6: =K6/I6 -> 0.44970414 | M6: =(I6-C6)/C6 -> 0.69 | N6: =(E6-I6)/E6 -> 0.46383249 | O6: LOW: Used private • HIGH: SLLDC Doosan Mega 250
A7: 3 | B7: Truck Mixer | C7: 3500 | D7: 4500 | E7: 5500 | F7: ='Engineering Assumptions'!$C$20*'Engineering Assumptions'!$B$5+'Engineering Assumptions'!$B$8+'Engineering Assumptions'!$D$20*1+'Engineering Assumptions'!$E$20*0.3 -> 3628 | G7: =F7*(1+'Engineering Assumptions'!$B$10)*(1+'Engineering Assumptions'!$B$11) -> 5006.64 | H7: MAX(Eng. Floor, LOW×1.10) capped at HIGH×0.88 | I7: =MROUND(MIN(MAX(G7,C7*1.1),E7*0.88),50) -> 4850 | J7: 0.5 | K7: =MROUND(I7*J7,50) -> 2450 | L7: =K7/I7 -> 0.50515464 | M7: =(I7-C7)/C7 -> 0.38571429 | N7: =(E7-I7)/E7 -> 0.11818182 | O7: LOW: TATA mixer private • HIGH: Large private operators
A8: 4 | B8: Self Loader Mixer | C8: 4500 | D8: 5200 | E8: 6000 | F8: ='Engineering Assumptions'!$C$21*'Engineering Assumptions'!$B$5+'Engineering Assumptions'!$B$8+'Engineering Assumptions'!$D$21*1+'Engineering Assumptions'!$E$21*0.3 -> 4062 | G8: =F8*(1+'Engineering Assumptions'!$B$10)*(1+'Engineering Assumptions'!$B$11) -> 5605.56 | H8: MAX(Eng. Floor, LOW×1.10) capped at HIGH×0.88 | I8: =MROUND(MIN(MAX(G8,C8*1.1),E8*0.88),50) -> 5300 | J8: 0.5 | K8: =MROUND(I8*J8,50) -> 2650 | L8: =K8/I8 -> 0.5 | M8: =(I8-C8)/C8 -> 0.17777778 | N8: =(E8-I8)/E8 -> 0.11666667 | O8: LOW: FIORI/Ajax private • HIGH: Large operators
A9: 5 | B9: Static Roller | C9: 2500 | D9: 3500 | E9: 5230 | F9: ='Engineering Assumptions'!$C$22*'Engineering Assumptions'!$B$5+'Engineering Assumptions'!$B$8+'Engineering Assumptions'!$D$22*1+'Engineering Assumptions'!$E$22*0.3 -> 4029 | G9: =F9*(1+'Engineering Assumptions'!$B$10)*(1+'Engineering Assumptions'!$B$11) -> 5560.02 | H9: MAX(Eng. Floor, LOW×1.10) capped at HIGH×0.88 | I9: =MROUND(MIN(MAX(G9,C9*1.1),E9*0.88),50) -> 4600 | J9: 0.5 | K9: =MROUND(I9*J9,50) -> 2300 | L9: =K9/I9 -> 0.5 | M9: =(I9-C9)/C9 -> 0.84 | N9: =(E9-I9)/E9 -> 0.12045889 | O9: LOW: Private 10T • HIGH: SLLDC HAMM HD12vv
A10: 6 | B10: Vibrating Roller | C10: 3000 | D10: 4000 | E10: 5000 | F10: ='Engineering Assumptions'!$C$23*'Engineering Assumptions'!$B$5+'Engineering Assumptions'!$B$8+'Engineering Assumptions'!$D$23*1+'Engineering Assumptions'!$E$23*0.3 -> 2812 | G10: =F10*(1+'Engineering Assumptions'!$B$10)*(1+'Engineering Assumptions'!$B$11) -> 3880.56 | H10: MAX(Eng. Floor, LOW×1.10) capped at HIGH×0.88 | I10: =MROUND(MIN(MAX(G10,C10*1.1),E10*0.88),50) -> 3900 | J10: 0.5 | K10: =MROUND(I10*J10,50) -> 1950 | L10: =K10/I10 -> 0.5 | M10: =(I10-C10)/C10 -> 0.3 | N10: =(E10-I10)/E10 -> 0.22 | O10: LOW: BOMAG private • HIGH: Large private 10T
A11: 7 | B11: Pneumatic Roller | C11: 3000 | D11: 3800 | E11: 4500 | F11: ='Engineering Assumptions'!$C$24*'Engineering Assumptions'!$B$5+'Engineering Assumptions'!$B$8+'Engineering Assumptions'!$D$24*1+'Engineering Assumptions'!$E$24*0.3 -> 3605 | G11: =F11*(1+'Engineering Assumptions'!$B$10)*(1+'Engineering Assumptions'!$B$11) -> 4974.9 | H11: MAX(Eng. Floor, LOW×1.10) capped at HIGH×0.88 | I11: =MROUND(MIN(MAX(G11,C11*1.1),E11*0.88),50) -> 3950 | J11: 0.5 | K11: =MROUND(I11*J11,50) -> 2000 | L11: =K11/I11 -> 0.50632911 | M11: =(I11-C11)/C11 -> 0.31666667 | N11: =(E11-I11)/E11 -> 0.12222222 | O11: LOW: Private Sakai/Dynapac • HIGH: Premium operators
A12: 8 | B12: Motor Grader | C12: 7000 | D12: 8500 | E12: 11000 | F12: ='Engineering Assumptions'!$C$25*'Engineering Assumptions'!$B$5+'Engineering Assumptions'!$B$8+'Engineering Assumptions'!$D$25*1+'Engineering Assumptions'!$E$25*0.3 -> 6980 | G12: =F12*(1+'Engineering Assumptions'!$B$10)*(1+'Engineering Assumptions'!$B$11) -> 9632.4 | H12: MAX(Eng. Floor, LOW×1.10) capped at HIGH×0.88 | I12: =MROUND(MIN(MAX(G12,C12*1.1),E12*0.88),50) -> 9650 | J12: 0.45 | K12: =MROUND(I12*J12,50) -> 4350 | L12: =K12/I12 -> 0.4507772 | M12: =(I12-C12)/C12 -> 0.37857143 | N12: =(E12-I12)/E12 -> 0.12272727 | O12: LOW: Private used CAT • HIGH: Premium/SLLDC class
A13: 9 | B13: Skid Steer | C13: 2000 | D13: 2500 | E13: 3060 | F13: ='Engineering Assumptions'!$C$26*'Engineering Assumptions'!$B$5+'Engineering Assumptions'!$B$8+'Engineering Assumptions'!$D$26*1+'Engineering Assumptions'!$E$26*0.3 -> 2589 | G13: =F13*(1+'Engineering Assumptions'!$B$10)*(1+'Engineering Assumptions'!$B$11) -> 3572.82 | H13: MAX(Eng. Floor, LOW×1.10) capped at HIGH×0.88 | I13: =MROUND(MIN(MAX(G13,C13*1.1),E13*0.88),50) -> 2700 | J13: 0.5 | K13: =MROUND(I13*J13,50) -> 1350 | L13: =K13/I13 -> 0.5 | M13: =(I13-C13)/C13 -> 0.35 | N13: =(E13-I13)/E13 -> 0.11764706 | O13: LOW: Small private • HIGH: SLLDC Bobcat
A14: 10 | B14: Asphalt Paver | C14: 7000 | D14: 8500 | E14: 10000 | F14: ='Engineering Assumptions'!$C$27*'Engineering Assumptions'!$B$5+'Engineering Assumptions'!$B$8+'Engineering Assumptions'!$D$27*1+'Engineering Assumptions'!$E$27*0.3 -> 5822 | G14: =F14*(1+'Engineering Assumptions'!$B$10)*(1+'Engineering Assumptions'!$B$11) -> 8034.36 | H14: MAX(Eng. Floor, LOW×1.10) capped at HIGH×0.88 | I14: =MROUND(MIN(MAX(G14,C14*1.1),E14*0.88),50) -> 8050 | J14: 0.45 | K14: =MROUND(I14*J14,50) -> 3600 | L14: =K14/I14 -> 0.44720497 | M14: =(I14-C14)/C14 -> 0.15 | N14: =(E14-I14)/E14 -> 0.195 | O14: LOW: SUMITOMO private • HIGH: VOLVO premium
A15: 11 | B15: Bitumen Bowser | C15: 2500 | D15: 3200 | E15: 4000 | F15: ='Engineering Assumptions'!$C$28*'Engineering Assumptions'!$B$5+'Engineering Assumptions'!$B$8+'Engineering Assumptions'!$D$28*1+'Engineering Assumptions'!$E$28*0.3 -> 3366 | G15: =F15*(1+'Engineering Assumptions'!$B$10)*(1+'Engineering Assumptions'!$B$11) -> 4645.08 | H15: MAX(Eng. Floor, LOW×1.10) capped at HIGH×0.88 | I15: =MROUND(MIN(MAX(G15,C15*1.1),E15*0.88),50) -> 3500 | J15: 0.5 | K15: =MROUND(I15*J15,50) -> 1750 | L15: =K15/I15 -> 0.5 | M15: =(I15-C15)/C15 -> 0.4 | N15: =(E15-I15)/E15 -> 0.125 | O15: LOW: Private 4-cu • HIGH: Large insulated bowser
A16: 12 | B16: Mobile Crane | C16: 8000 | D16: 9500 | E16: 11660 | F16: ='Engineering Assumptions'!$C$29*'Engineering Assumptions'!$B$5+'Engineering Assumptions'!$B$8+'Engineering Assumptions'!$D$29*1+'Engineering Assumptions'!$E$29*0.3 -> 4954 | G16: =F16*(1+'Engineering Assumptions'!$B$10)*(1+'Engineering Assumptions'!$B$11) -> 6836.52 | H16: MAX(Eng. Floor, LOW×1.10) capped at HIGH×0.88 | I16: =MROUND(MIN(MAX(G16,C16*1.1),E16*0.88),50) -> 8800 | J16: 0.5 | K16: =MROUND(I16*J16,50) -> 4400 | L16: =K16/I16 -> 0.5 | M16: =(I16-C16)/C16 -> 0.1 | N16: =(E16-I16)/E16 -> 0.24528302 | O16: LOW: Private 25T • HIGH: SLLDC Kobelco RK250
A17: 13 | B17: Boom Truck | C17: 4000 | D17: 5000 | E17: 6610 | F17: ='Engineering Assumptions'!$C$30*'Engineering Assumptions'!$B$5+'Engineering Assumptions'!$B$8+'Engineering Assumptions'!$D$30*1+'Engineering Assumptions'!$E$30*0.3 -> 3628 | G17: =F17*(1+'Engineering Assumptions'!$B$10)*(1+'Engineering Assumptions'!$B$11) -> 5006.64 | H17: MAX(Eng. Floor, LOW×1.10) capped at HIGH×0.88 | I17: =MROUND(MIN(MAX(G17,C17*1.1),E17*0.88),50) -> 5000 | J17: 0.5 | K17: =MROUND(I17*J17,50) -> 2500 | L17: =K17/I17 -> 0.5 | M17: =(I17-C17)/C17 -> 0.25 | N17: =(E17-I17)/E17 -> 0.24357035 | O17: LOW: Califolink private • HIGH: SLLDC 17T 3T-crane
A18: 14 | B18: Prime Mover / Bed | C18: 3500 | D18: 4500 | E18: 5500 | F18: ='Engineering Assumptions'!$C$31*'Engineering Assumptions'!$B$5+'Engineering Assumptions'!$B$8+'Engineering Assumptions'!$D$31*1+'Engineering Assumptions'!$E$31*0.3 -> 6363 | G18: =F18*(1+'Engineering Assumptions'!$B$10)*(1+'Engineering Assumptions'!$B$11) -> 8780.94 | H18: MAX(Eng. Floor, LOW×1.10) capped at HIGH×0.88 | I18: =MROUND(MIN(MAX(G18,C18*1.1),E18*0.88),50) -> 4850 | J18: 0.5 | K18: =MROUND(I18*J18,50) -> 2450 | L18: =K18/I18 -> 0.50515464 | M18: =(I18-C18)/C18 -> 0.38571429 | N18: =(E18-I18)/E18 -> 0.11818182 | O18: LOW: Private HINO/TATA • HIGH: Premium lowbed operators
A19: 15 | B19: Pump Truck (Concrete) | C19: 8500 | D19: 10000 | E19: 11000 | F19: ='Engineering Assumptions'!$C$32*'Engineering Assumptions'!$B$5+'Engineering Assumptions'!$B$8+'Engineering Assumptions'!$D$32*1+'Engineering Assumptions'!$E$32*0.3 -> 6242 | G19: =F19*(1+'Engineering Assumptions'!$B$10)*(1+'Engineering Assumptions'!$B$11) -> 8613.96 | H19: MAX(Eng. Floor, LOW×1.10) capped at HIGH×0.88 | I19: =MROUND(MIN(MAX(G19,C19*1.1),E19*0.88),50) -> 9350 | J19: 0.45 | K19: =MROUND(I19*J19,50) -> 4200 | L19: =K19/I19 -> 0.44919786 | M19: =(I19-C19)/C19 -> 0.1 | N19: =(E19-I19)/E19 -> 0.15 | O19: LOW: Private Sany pump • HIGH: Premium operators
A20: 16 | B20: Double Cab (Pickup) | C20: 1200 | D20: 1500 | E20: 2000 | F20: ='Engineering Assumptions'!$C$33*'Engineering Assumptions'!$B$5+'Engineering Assumptions'!$B$8+'Engineering Assumptions'!$D$33*1+'Engineering Assumptions'!$E$33*0.3 -> 1919 | G20: =F20*(1+'Engineering Assumptions'!$B$10)*(1+'Engineering Assumptions'!$B$11) -> 2648.22 | H20: MAX(Eng. Floor, LOW×1.10) capped at HIGH×0.88 | I20: =MROUND(MIN(MAX(G20,C20*1.1),E20*0.88),50) -> 1750 | J20: 0.55 | K20: =MROUND(I20*J20,50) -> 950 | L20: =K20/I20 -> 0.54285714 | M20: =(I20-C20)/C20 -> 0.45833333 | N20: =(E20-I20)/E20 -> 0.125 | O20: LOW: Hilux long-term private • HIGH: Malkey/Lanka Rent premium
A21: 17 | B21: Van | C21: 950 | D21: 1300 | E21: 1800 | F21: ='Engineering Assumptions'!$C$34*'Engineering Assumptions'!$B$5+'Engineering Assumptions'!$B$8+'Engineering Assumptions'!$D$34*1+'Engineering Assumptions'!$E$34*0.3 -> 1702 | G21: =F21*(1+'Engineering Assumptions'!$B$10)*(1+'Engineering Assumptions'!$B$11) -> 2348.76 | H21: MAX(Eng. Floor, LOW×1.10) capped at HIGH×0.88 | I21: =MROUND(MIN(MAX(G21,C21*1.1),E21*0.88),50) -> 1600 | J21: 0.55 | K21: =MROUND(I21*J21,50) -> 900 | L21: =K21/I21 -> 0.5625 | M21: =(I21-C21)/C21 -> 0.68421053 | N21: =(E21-I21)/E21 -> 0.11111111 | O21: LOW: Liteace private • HIGH: KDH200 premium
A22: 18 | B22: Crew Cab | C22: 900 | D22: 1200 | E22: 1600 | F22: ='Engineering Assumptions'!$C$35*'Engineering Assumptions'!$B$5+'Engineering Assumptions'!$B$8+'Engineering Assumptions'!$D$35*1+'Engineering Assumptions'!$E$35*0.3 -> 1906 | G22: =F22*(1+'Engineering Assumptions'!$B$10)*(1+'Engineering Assumptions'!$B$11) -> 2630.28 | H22: MAX(Eng. Floor, LOW×1.10) capped at HIGH×0.88 | I22: =MROUND(MIN(MAX(G22,C22*1.1),E22*0.88),50) -> 1400 | J22: 0.55 | K22: =MROUND(I22*J22,50) -> 750 | L22: =K22/I22 -> 0.53571429 | M22: =(I22-C22)/C22 -> 0.55555556 | N22: =(E22-I22)/E22 -> 0.125 | O22: LOW: JMC private • HIGH: ISUZU premium
A23: 19 | B23: Single Cab | C23: 700 | D23: 1000 | E23: 1300 | F23: ='Engineering Assumptions'!$C$36*'Engineering Assumptions'!$B$5+'Engineering Assumptions'!$B$8+'Engineering Assumptions'!$D$36*1+'Engineering Assumptions'!$E$36*0.3 -> 1702 | G23: =F23*(1+'Engineering Assumptions'!$B$10)*(1+'Engineering Assumptions'!$B$11) -> 2348.76 | H23: MAX(Eng. Floor, LOW×1.10) capped at HIGH×0.88 | I23: =MROUND(MIN(MAX(G23,C23*1.1),E23*0.88),50) -> 1150 | J23: 0.55 | K23: =MROUND(I23*J23,50) -> 650 | L23: =K23/I23 -> 0.56521739 | M23: =(I23-C23)/C23 -> 0.64285714 | N23: =(E23-I23)/E23 -> 0.11538462 | O23: LOW: Tata Ace small • HIGH: Mahindra BMT premium
A24: 20 | B24: Dump Truck (Tipper) | C24: 2000 | D24: 2800 | E24: 3700 | F24: ='Engineering Assumptions'!$C$37*'Engineering Assumptions'!$B$5+'Engineering Assumptions'!$B$8+'Engineering Assumptions'!$D$37*1+'Engineering Assumptions'!$E$37*0.3 -> 3838 | G24: =F24*(1+'Engineering Assumptions'!$B$10)*(1+'Engineering Assumptions'!$B$11) -> 5296.44 | H24: MAX(Eng. Floor, LOW×1.10) capped at HIGH×0.88 | I24: =MROUND(MIN(MAX(G24,C24*1.1),E24*0.88),50) -> 3250 | J24: 0.48 | K24: =MROUND(I24*J24,50) -> 1550 | L24: =K24/I24 -> 0.47692308 | M24: =(I24-C24)/C24 -> 0.625 | N24: =(E24-I24)/E24 -> 0.12162162 | O24: LOW: Ikman monthly low • HIGH: Premium Tata LPK1618
A25: 21 | B25: Trailer | C25: 1200 | D25: 1700 | E25: 2200 | F25: ='Engineering Assumptions'!$C$38*'Engineering Assumptions'!$B$5+0+'Engineering Assumptions'!$D$38*1+'Engineering Assumptions'!$E$38*0.3 -> 71 | G25: =F25*(1+'Engineering Assumptions'!$B$10)*(1+'Engineering Assumptions'!$B$11) -> 97.98 | H25: MAX(Eng. Floor, LOW×1.10) capped at HIGH×0.88 | I25: =MROUND(MIN(MAX(G25,C25*1.1),E25*0.88),50) -> 1300 | J25: 0.95 | K25: =MROUND(I25*J25,50) -> 1250 | L25: =K25/I25 -> 0.96153846 | M25: =(I25-C25)/C25 -> 0.083333333 | N25: =(E25-I25)/E25 -> 0.40909091 | O25: LOW: Private tractor trailer • HIGH: Premium operators
A26: 22 | B26: Lorry Trailer | C26: 2000 | D26: 2600 | E26: 3200 | F26: ='Engineering Assumptions'!$C$39*'Engineering Assumptions'!$B$5+0+'Engineering Assumptions'!$D$39*1+'Engineering Assumptions'!$E$39*0.3 -> 84 | G26: =F26*(1+'Engineering Assumptions'!$B$10)*(1+'Engineering Assumptions'!$B$11) -> 115.92 | H26: MAX(Eng. Floor, LOW×1.10) capped at HIGH×0.88 | I26: =MROUND(MIN(MAX(G26,C26*1.1),E26*0.88),50) -> 2200 | J26: 0.95 | K26: =MROUND(I26*J26,50) -> 2100 | L26: =K26/I26 -> 0.95454545 | M26: =(I26-C26)/C26 -> 0.1 | N26: =(E26-I26)/E26 -> 0.3125 | O26: LOW: Private Tantri • HIGH: Premium Tantri TFB40
A27: 23 | B27: Diesel Bowser | C27: 1500 | D27: 2200 | E27: 2800 | F27: ='Engineering Assumptions'!$C$40*'Engineering Assumptions'!$B$5+'Engineering Assumptions'!$B$8+'Engineering Assumptions'!$D$40*1+'Engineering Assumptions'!$E$40*0.3 -> 2139 | G27: =F27*(1+'Engineering Assumptions'!$B$10)*(1+'Engineering Assumptions'!$B$11) -> 2951.82 | H27: MAX(Eng. Floor, LOW×1.10) capped at HIGH×0.88 | I27: =MROUND(MIN(MAX(G27,C27*1.1),E27*0.88),50) -> 2450 | J27: 0.55 | K27: =MROUND(I27*J27,50) -> 1350 | L27: =K27/I27 -> 0.55102041 | M27: =(I27-C27)/C27 -> 0.63333333 | N27: =(E27-I27)/E27 -> 0.125 | O27: LOW: Private fuel bowser • HIGH: Premium large bowser
A28: 24 | B28: Excavator | C28: 5500 | D28: 7500 | E28: 12100 | F28: ='Engineering Assumptions'!$C$41*'Engineering Assumptions'!$B$5+'Engineering Assumptions'!$B$8+'Engineering Assumptions'!$D$41*1+'Engineering Assumptions'!$E$41*0.3 -> 6916 | G28: =F28*(1+'Engineering Assumptions'!$B$10)*(1+'Engineering Assumptions'!$B$11) -> 9544.08 | H28: MAX(Eng. Floor, LOW×1.10) capped at HIGH×0.88 | I28: =MROUND(MIN(MAX(G28,C28*1.1),E28*0.88),50) -> 9550 | J28: 0.45 | K28: =MROUND(I28*J28,50) -> 4300 | L28: =K28/I28 -> 0.45026178 | M28: =(I28-C28)/C28 -> 0.73636364 | N28: =(E28-I28)/E28 -> 0.2107438 | O28: LOW: Private 20T Hyundai • HIGH: SLLDC Doosan DX200
A29: 25 | B29: Water Bowser | C29: 1800 | D29: 2300 | E29: 4940 | F29: ='Engineering Assumptions'!$C$42*'Engineering Assumptions'!$B$5+'Engineering Assumptions'!$B$8+'Engineering Assumptions'!$D$42*1+'Engineering Assumptions'!$E$42*0.3 -> 2152 | G29: =F29*(1+'Engineering Assumptions'!$B$10)*(1+'Engineering Assumptions'!$B$11) -> 2969.76 | H29: MAX(Eng. Floor, LOW×1.10) capped at HIGH×0.88 | I29: =MROUND(MIN(MAX(G29,C29*1.1),E29*0.88),50) -> 2950 | J29: 0.5 | K29: =MROUND(I29*J29,50) -> 1500 | L29: =K29/I29 -> 0.50847458 | M29: =(I29-C29)/C29 -> 0.63888889 | N29: =(E29-I29)/E29 -> 0.40283401 | O29: LOW: Private small • HIGH: SLLDC 6,000L equiv.
A30: 26 | B30: Farm Tractor | C30: 1200 | D30: 1800 | E30: 2400 | F30: ='Engineering Assumptions'!$C$43*'Engineering Assumptions'!$B$5+'Engineering Assumptions'!$B$8+'Engineering Assumptions'!$D$43*1+'Engineering Assumptions'!$E$43*0.3 -> 2330 | G30: =F30*(1+'Engineering Assumptions'!$B$10)*(1+'Engineering Assumptions'!$B$11) -> 3215.4 | H30: MAX(Eng. Floor, LOW×1.10) capped at HIGH×0.88 | I30: =MROUND(MIN(MAX(G30,C30*1.1),E30*0.88),50) -> 2100 | J30: 0.55 | K30: =MROUND(I30*J30,50) -> 1150 | L30: =K30/I30 -> 0.54761905 | M30: =(I30-C30)/C30 -> 0.75 | N30: =(E30-I30)/E30 -> 0.125 | O30: LOW: MASSEY/TAFE private • HIGH: MAHINDRA premium
A31: 27 | B31: Motor Bicycle | C31: 250 | D31: 350 | E31: 550 | F31: ='Engineering Assumptions'!$C$44*'Engineering Assumptions'!$B$5+0+'Engineering Assumptions'!$D$44*1+'Engineering Assumptions'!$E$44*0.3 -> 493.9 | G31: =F31*(1+'Engineering Assumptions'!$B$10)*(1+'Engineering Assumptions'!$B$11) -> 681.582 | H31: MAX(Eng. Floor, LOW×1.10) capped at HIGH×0.88 | I31: =MROUND(MIN(MAX(G31,C31*1.1),E31*0.88),50) -> 500 | J31: 0.6 | K31: =MROUND(I31*J31,50) -> 300 | L31: =K31/I31 -> 0.6 | M31: =(I31-C31)/C31 -> 1 | N31: =(E31-I31)/E31 -> 0.090909091 | O31: LOW: Staff rental private • HIGH: Daily hire
A32: 28 | B32: Tractor Bowser | C32: 1200 | D32: 1600 | E32: 2000 | F32: ='Engineering Assumptions'!$C$45*'Engineering Assumptions'!$B$5+'Engineering Assumptions'!$B$8+'Engineering Assumptions'!$D$45*1+'Engineering Assumptions'!$E$45*0.3 -> 2521 | G32: =F32*(1+'Engineering Assumptions'!$B$10)*(1+'Engineering Assumptions'!$B$11) -> 3478.98 | H32: MAX(Eng. Floor, LOW×1.10) capped at HIGH×0.88 | I32: =MROUND(MIN(MAX(G32,C32*1.1),E32*0.88),50) -> 1750 | J32: 0.55 | K32: =MROUND(I32*J32,50) -> 950 | L32: =K32/I32 -> 0.54285714 | M32: =(I32-C32)/C32 -> 0.45833333 | N32: =(E32-I32)/E32 -> 0.125 | O32: LOW: Private combo • HIGH: Premium combo
A33: 29 | B33: Forklift | C33: 2000 | D33: 3000 | E33: 3800 | F33: ='Engineering Assumptions'!$C$46*'Engineering Assumptions'!$B$5+'Engineering Assumptions'!$B$8+'Engineering Assumptions'!$D$46*1+'Engineering Assumptions'!$E$46*0.3 -> 2210 | G33: =F33*(1+'Engineering Assumptions'!$B$10)*(1+'Engineering Assumptions'!$B$11) -> 3049.8 | H33: MAX(Eng. Floor, LOW×1.10) capped at HIGH×0.88 | I33: =MROUND(MIN(MAX(G33,C33*1.1),E33*0.88),50) -> 3050 | J33: 0.5 | K33: =MROUND(I33*J33,50) -> 1550 | L33: =K33/I33 -> 0.50819672 | M33: =(I33-C33)/C33 -> 0.525 | N33: =(E33-I33)/E33 -> 0.19736842 | O33: LOW: Private 3T • HIGH: Premium insulated/specialist
A36: AGE DEPRECIATION APPLIED TO FLEET UNITS
A37: Year of manufacture | B37: Age factor | C37: % of base rate | D37: Rationale
A38: 2020 and newer | B38: 1 | C38: =B38 -> 1 | D38: Same as new — no discount
A39: 2015 – 2019 | B39: 0.92 | C39: =B39 -> 0.92 | D39: Light depreciation
A40: 2010 – 2014 | B40: 0.82 | C40: =B40 -> 0.82 | D40: Used but serviceable
A41: 2005 – 2009 | B41: 0.72 | C41: =B41 -> 0.72 | D41: Older unit — customer expects discount
A42: 2000 – 2004 | B42: 0.65 | C42: =B42 -> 0.65 | D42: Legacy — only for budget-sensitive clients
A43: Before 2000 / Unknown | B43: 0.58 | C43: =B43 -> 0.58 | D43: End-of-life — last resort only
A46: VOLUME DISCOUNT APPLIED TO FLEET UNITS
A47: Daily (≥ 4 hrs) | B47: 0.95 | C47: 5% off hourly × 4
A48: Monthly (≥ 120 hrs) | B48: 0.85 | C48: 15% off hourly × 120

Sheet Portable Equipment Rates
A1: 2026 PORTABLE EQUIPMENT RATES — Day-Hire, Sri Lankan Market
A2: Capacity-wise daily hire rates (Rs./day) for portable plant, surveyed from the Sri Lankan rental market (May–Jun 2026). WET = with fuel/operator/consumables; DRY = bare machine hire only. Min. billing 1 day. Rates exclude 18% VAT and transport.
A4: # | B4: Category | C4: Capacity / Size | D4: WET Rs./day | E4: DRY Rs./day | F4: Billing | G4: Min. | H4: Source / basis note
A5: 1 | B5: Generator | C5: 3–5 kVA (petrol, 1-ph) | D5: 5000 | E5: 2500 | F5: Per day | G5: 1 day | H5: Peters Equipment: 5kVA Rs.4,000 / 2-3kVA Rs.5,000 per day
A6: 2 | B6: Generator | C6: 10 kVA (diesel, 1-ph) | D6: 7000 | E6: 3500 | F6: Per day | G6: 1 day | H6: Peters Equipment 10kVA diesel Rs.6,000/day (op w/fuel basis)
A7: 3 | B7: Generator | C7: 20–25 kVA (diesel, 3-ph) | D7: 12000 | E7: 6000 | F7: Per day | G7: 1 day | H7: Peters Equipment 25kVA diesel Rs.8,000/day
A8: 4 | B8: Generator | C8: 30–50 kVA (diesel, 3-ph) | D8: 18000 | E8: 10000 | F8: Per day | G8: 1 day | H8: Peters Equipment 50kVA diesel Rs.10-12,000/day
A9: 5 | B9: Generator | C9: 60–80 kVA (soundproof) | D9: 26000 | E9: 15000 | F9: Per day | G9: 1 day | H9: Interpolated from 50kVA card + UTE/Generators.lk band
A10: 6 | B10: Generator | C10: 100–125 kVA (soundproof) | D10: 38000 | E10: 22000 | F10: Per day | G10: 1 day | H10: Generators.lk / UTE long-term construction band
A11: 7 | B11: Generator | C11: 150 kVA (soundproof) | D11: 48000 | E11: 28000 | F11: Per day | G11: 1 day | H11: Generators.lk 150kVA upper rental band
A12: 8 | B12: Air Compressor | C12: 2–3 HP (portable, electric) | D12: 2200 | E12: 1300 | F12: Per day | G12: 1 day | H12: SL hire-shop day-rate; surplus.lk "any capacity per day"
A13: 9 | B13: Air Compressor | C13: 5–7 HP (belt-drive, petrol) | D13: 3800 | E13: 2400 | F13: Per day | G13: 1 day | H13: Competitive Western-Province hire-shop day-rate
A14: 10 | B14: Air Compressor | C14: 10–15 HP (industrial) | D14: 6500 | E14: 4500 | F14: Per day | G14: 1 day | H14: Competitive Western-Province hire-shop day-rate
A15: 11 | B15: Air Compressor | C15: 185 cfm (towable diesel) | D15: 16000 | E15: 11000 | F15: Per day | G15: 1 day | H15: Towable jackhammer-feed compressor; project day-rate
A16: 12 | B16: Air Compressor | C16: 375 cfm (towable diesel) | D16: 26000 | E16: 18000 | F16: Per day | G16: 1 day | H16: Large towable diesel; project day-rate
... A40: 36 | B40: Welding Plant | C40: 300 A diesel (engine-driven) | D40: 9500 | E40: 6500 | F40: Per day | G40: 1 day | H40: Engine-driven welder day-hire
A42: Methodology & sources
A43: • WET rate = machine + fuel/power + operator + routine consumables (bits, oil, nozzles). DRY rate = bare equipment hire; customer supplies fuel, power and operator.
A44: • Anchored to published Sri Lankan rental day-rates from Peters Equipment (petersequipment.lk, 2026): generators Rs.4,000–12,000/day by kVA; Rotary Hammer SDS Rs.3,000; Jack Hammer Rs.10,000; Demolition Breaker Rs.4,000; Tamping Rammer Rs.3,500; drills Rs.250–500/day.
A45: • Air compressors, poker/concrete vibrators, submersible & engine water pumps, circular saws and angle grinders are confirmed available for daily hire in the Sri Lankan market (surplus.lk, wedabima.com); where a vendor lists "call for price", the rate shown is a competitive Colombo / Western-Province hire-shop day-rate.
A46: • Rates are indicative for quotation/proforma use and exclude 18% VAT, transport/mobilisation, and any operator overtime. Minimum billing is one (1) day unless agreed otherwise.
A47: • Review the WET/DRY cells (blue/green) each quarter against current market quotes; they are hardcoded inputs, not formulas.

Sheet Fuel Rates
A1: FLEET FUEL RATES — estimated by model size-class & manufacturing year (518 units)
A2: Per-unit fuel-cost rate at three duty scenarios (Lowest / Medium / Highest). Typical consumption is set from each machine's model size/engine class, then adjusted for age via the manufacturing year. Machinery Rs./hr, road vehicles Rs./km. Edit the blue cells (fuel prices, age factor, or any vehicle's consumption) and rates recalculate. SL prices, Jun 2026.
A4: FUEL PRICE & AGE INPUTS (edit to update every rate)
A5: Auto Diesel (Rs./litre) | D5: 478 | E5: ← Ceypetco/LIOC 01-Jun-2026
A6: Petrol 92 Octane (Rs./litre) | D6: 434
A8: Base year (new = no penalty) | D8: 2026
A9: Extra fuel % per year of age | D9: 0.007 | E9: ← older engines burn more (e.g. 0.7%/yr)
A10: Cap age (years) | D10: 25
A11: PER-VEHICLE FUEL RATES (518 units) — by model class & year
A12: # | B12: E&C No | C12: Reg No | D12: Category | E12: Model | F12: Year | G12: Fuel | H12: Basis | I12: Size / Engine Class | J12: Unit | K12: Cons Econ | L12: Cons Typ | M12: Cons Heavy | N12: Age × | O12: Lowest Rate | P12: Medium Rate | Q12: Highest Rate | R12: Rate Unit
A13: 1 | B13: AP-01 | C13: — | D13: Asphalt Paver | E13: Sumitomo Ha45C-2065 | F13: 2012 | G13: Diesel | H13: Hour | I13: Standard (class avg) | J13: L/hr | K13: 10.1 | L13: 14 | M13: 18.9 | N13: =1+MIN(MAX($D$8-F13,0),$D$10)*$D$9 -> 1.098 | O13: =IF(H13="None",0,IF(H13="KM",IF(G13="Petrol",$D$6,$D$5)*N13/K13,K13*N13*IF(G13="Petrol",$D$6,$D$5))) -> 5300.9244 | P13: =IF(H13="None",0,IF(H13="KM",IF(G13="Petrol",$D$6,$D$5)*N13/L13,L13*N13*IF(G13="Petrol",$D$6,$D$5))) -> 7347.816 | Q13: =IF(H13="None",0,IF(H13="KM",IF(G13="Petrol",$D$6,$D$5)*N13/M13,M13*N13*IF(G13="Petrol",$D$6,$D$5))) -> 9919.5516 | R13: =IF(H13="None","—",IF(H13="KM","Rs./km","Rs./hr")) -> Rs./hr
A14: 2 | B14: AP-02 | C14: — | D14: Asphalt Paver | E14: Mitsubishi Mf40Wh | F14: 2013 | G14: Diesel | H14: Hour | I14: Standard (class avg) | J14: L/hr | K14: 10.1 | L14: 14 | M14: 18.9 | N14: =1+MIN(MAX($D$8-F14,0),$D$10)*$D$9 -> 1.091 | O14: =IF(H14="None",0,IF(H14="KM",IF(G14="Petrol",$D$6,$D$5)*N14/K14,K14*N14*IF(G14="Petrol",$D$6,$D$5))) -> 5267.1298 | P14: =IF(H14="None",0,IF(H14="KM",IF(G14="Petrol",$D$6,$D$5)*N14/L14,L14*N14*IF(G14="Petrol",$D$6,$D$5))) -> 7300.972 | Q14: =IF(H14="None",0,IF(H14="KM",IF(G14="Petrol",$D$6,$D$5)*N14/M14,M14*N14*IF(G14="Petrol",$D$6,$D$5))) -> 9856.3122 | R14: =IF(H14="None","—",IF(H14="KM","Rs./km","Rs./hr")) -> Rs./hr
A15: 3 | B15: AP-03 | C15: — | D15: Asphalt Paver | E15: Mitsubishi Mf-55Wh | F15: 2014 | G15: Diesel | H15: Hour | I15: Standard (class avg) | J15: L/hr | K15: 10.1 | L15: 14 | M15: 18.9 | N15: =1+MIN(MAX($D$8-F15,0),$D$10)*$D$9 -> 1.084 | O15: =IF(H15="None",0,IF(H15="KM",IF(G15="Petrol",$D$6,$D$5)*N15/K15,K15*N15*IF(G15="Petrol",$D$6,$D$5))) -> 5233.3352 | P15: =IF(H15="None",0,IF(H15="KM",IF(G15="Petrol",$D$6,$D$5)*N15/L15,L15*N15*IF(G15="Petrol",$D$6,$D$5))) -> 7254.128 | Q15: =IF(H15="None",0,IF(H15="KM",IF(G15="Petrol",$D$6,$D$5)*N15/M15,M15*N15*IF(G15="Petrol",$D$6,$D$5))) -> 9793.0728 | R15: =IF(H15="None","—",IF(H15="KM","Rs./km","Rs./hr")) -> Rs./hr
A16: 4 | B16: AP-04 | C16: — | D16: Asphalt Paver | E16: Mitsubishi Mf60Wd | F16: 2014 | G16: Diesel | H16: Hour | I16: Standard (class avg) | J16: L/hr | K16: 10.1 | L16: 14 | M16: 18.9 | N16: =1+MIN(MAX($D$8-F16,0),$D$10)*$D$9 -> 1.084 | O16: =IF(H16="None",0,IF(H16="KM",IF(G16="Petrol",$D$6,$D$5)*N16/K16,K16*N16*IF(G16="Petrol",$D$6,$D$5))) -> 5233.3352 | P16: =IF(H16="None",0,IF(H16="KM",IF(G16="Petrol",$D$6,$D$5)*N16/L16,L16*N16*IF(G16="Petrol",$D$6,$D$5))) -> 7254.128 | Q16: =IF(H16="None",0,IF(H16="KM",IF(G16="Petrol",$D$6,$D$5)*N16/M16,M16*N16*IF(G16="Petrol",$D$6,$D$5))) -> 9793.0728 | R16: =IF(H16="None","—",IF(H16="KM","Rs./km","Rs./hr")) -> Rs./hr
A17: 5 | B17: AP-05 | C17: — | D17: Asphalt Paver | E17: Nigata — | F17: 2012 | G17: Diesel | H17: Hour | I17: Standard (class avg) | J17: L/hr | K17: 10.1 | L17: 14 | M17: 18.9 | N17: =1+MIN(MAX($D$8-F17,0),$D$10)*$D$9 -> 1.098 | O17: =IF(H17="None",0,IF(H17="KM",IF(G17="Petrol",$D$6,$D$5)*N17/K17,K17*N17*IF(G17="Petrol",$D$6,$D$5))) -> 5300.9244 | P17: =IF(H17="None",0,IF(H17="KM",IF(G17="Petrol",$D$6,$D$5)*N17/L17,L17*N17*IF(G17="Petrol",$D$6,$D$5))) -> 7347.816 | Q17: =IF(H17="None",0,IF(H17="KM",IF(G17="Petrol",$D$6,$D$5)*N17/M17,M17*N17*IF(G17="Petrol",$D$6,$D$5))) -> 9919.5516 | R17: =IF(H17="None","—",IF(H17="KM","Rs./km","Rs./hr")) -> Rs./hr
A18: 6 | B18: AP-06 | C18: — | D18: Asphalt Paver | E18: (Unknown) — | F18: — | G18: Diesel | H18: Hour | I18: Standard (class avg) | J18: L/hr | K18: 10.1 | L18: 14 | M18: 18.9 | N18: =1 -> 1 | O18: =IF(H18="None",0,IF(H18="KM",IF(G18="Petrol",$D$6,$D$5)*N18/K18,K18*N18*IF(G18="Petrol",$D$6,$D$5))) -> 4827.8 | P18: =IF(H18="None",0,IF(H18="KM",IF(G18="Petrol",$D$6,$D$5)*N18/L18,L18*N18*IF(G18="Petrol",$D$6,$D$5))) -> 6692 | Q18: =IF(H18="None",0,IF(H18="KM",IF(G18="Petrol",$D$6,$D$5)*N18/M18,M18*N18*IF(G18="Petrol",$D$6,$D$5))) -> 9034.2 | R18: =IF(H18="None","—",IF(H18="KM","Rs./km","Rs./hr")) -> Rs./hr
A19: 7 | B19: AP-07 | C19: — | D19: Asphalt Paver | E19: (Unknown) — | F19: — | G19: Diesel | H19: Hour | I19: Standard (class avg) | J19: L/hr | K19: 10.1 | L19: 14 | M19: 18.9 | N19: =1 -> 1 | O19: =IF(H19="None",0,IF(H19="KM",IF(G19="Petrol",$D$6,$D$5)*N19/K19,K19*N19*IF(G19="Petrol",$D$6,$D$5))) -> 4827.8 | P19: =IF(H19="None",0,IF(H19="KM",IF(G19="Petrol",$D$6,$D$5)*N19/L19,L19*N19*IF(G19="Petrol",$D$6,$D$5))) -> 6692 | Q19: =IF(H19="None",0,IF(H19="KM",IF(G19="Petrol",$D$6,$D$5)*N19/M19,M19*N19*IF(G19="Petrol",$D$6,$D$5))) -> 9034.2 | R19: =IF(H19="None","—",IF(H19="KM","Rs./km","Rs./hr")) -> Rs./hr
A20: 8 | B20: AP-08 | C20: — | D20: Asphalt Paver | E20: Volvo P6820C | F20: 2019 | G20: Diesel | H20: Hour | I20: Standard (class avg) | J20: L/hr | K20: 10.1 | L20: 14 | M20: 18.9 | N20: =1+MIN(MAX($D$8-F20,0),$D$10)*$D$9 -> 1.049 | O20: =IF(H20="None",0,IF(H20="KM",IF(G20="Petrol",$D$6,$D$5)*N20/K20,K20*N20*IF(G20="Petrol",$D$6,$D$5))) -> 5064.3622 | P20: =IF(H20="None",0,IF(H20="KM",IF(G20="Petrol",$D$6,$D$5)*N20/L20,L20*N20*IF(G20="Petrol",$D$6,$D$5))) -> 7019.908 | Q20: =IF(H20="None",0,IF(H20="KM",IF(G20="Petrol",$D$6,$D$5)*N20/M20,M20*N20*IF(G20="Petrol",$D$6,$D$5))) -> 9476.8758 | R20: =IF(H20="None","—",IF(H20="KM","Rs./km","Rs./hr")) -> Rs./hr
A21: 9 | B21: AP-09 | C21: — | D21: Asphalt Paver | E21: Sumitomo Ha60W-7 | F21: 2012 | G21: Diesel | H21: Hour | I21: Standard (class avg) | J21: L/hr | K21: 10.1 | L21: 14 | M21: 18.9 | N21: =1+MIN(MAX($D$8-F21,0),$D$10)*$D$9 -> 1.098 | O21: =IF(H21="None",0,IF(H21="KM",IF(G21="Petrol",$D$6,$D$5)*N21/K21,K21*N21*IF(G21="Petrol",$D$6,$D$5))) -> 5300.9244 | P21: =IF(H21="None",0,IF(H21="KM",IF(G21="Petrol",$D$6,$D$5)*N21/L21,L21*N21*IF(G21="Petrol",$D$6,$D$5))) -> 7347.816 | Q21: =IF(H21="None",0,IF(H21="KM",IF(G21="Petrol",$D$6,$D$5)*N21/M21,M21*N21*IF(G21="Petrol",$D$6,$D$5))) -> 9919.5516 | R21: =IF(H21="None","—",IF(H21="KM","Rs./km","Rs./hr")) -> Rs./hr
A22: 10 | B22: AP-10 | C22: — | D22: Asphalt Paver | E22: Dynapac Sd2500C | F22: 2020 | G22: Diesel | H22: Hour | I22: Standard (class avg) | J22: L/hr | K22: 10.1 | L22: 14 | M22: 18.9 | N22: =1+MIN(MAX($D$8-F22,0),$D$10)*$D$9 -> 1.042 | O22: =IF(H22="None",0,IF(H22="KM",IF(G22="Petrol",$D$6,$D$5)*N22/K22,K22*N22*IF(G22="Petrol",$D$6,$D$5))) -> 5030.5676 | P22: =IF(H22="None",0,IF(H22="KM",IF(G22="Petrol",$D$6,$D$5)*N22/L22,L22*N22*IF(G22="Petrol",$D$6,$D$5))) -> 6973.064 | Q22: =IF(H22="None",0,IF(H22="KM",IF(G22="Petrol",$D$6,$D$5)*N22/M22,M22*N22*IF(G22="Petrol",$D$6,$D$5))) -> 9413.6364 | R22: =IF(H22="None","—",IF(H22="KM","Rs./km","Rs./hr")) -> Rs./hr
A23: 11 | B23: AP-11 | C23: — | D23: Asphalt Paver | E23: Sumitomo Ha60W-5 | F23: 2006 | G23: Diesel | H23: Hour | I23: Standard (class avg) | J23: L/hr | K23: 10.1 | L23: 14 | M23: 18.9 | N23: =1+MIN(MAX($D$8-F23,0),$D$10)*$D$9 -> 1.14 | O23: =IF(H23="None",0,IF(H23="KM",IF(G23="Petrol",$D$6,$D$5)*N23/K23,K23*N23*IF(G23="Petrol",$D$6,$D$5))) -> 5503.692 | P23: =IF(H23="None",0,IF(H23="KM",IF(G23="Petrol",$D$6,$D$5)*N23/L23,L23*N23*IF(G23="Petrol",$D$6,$D$5))) -> 7628.88 | Q23: =IF(H23="None",0,IF(H23="KM",IF(G23="Petrol",$D$6,$D$5)*N23/M23,M23*N23*IF(G23="Petrol",$D$6,$D$5))) -> 10298.988 | R23: =IF(H23="None","—",IF(H23="KM","Rs./km","Rs./hr")) -> Rs./hr
A24: 12 | B24: LB-01 | C24: ZA-2609 | D24: Backhoe Loader | E24: Jcb 3Dx | F24: 2012 | G24: Diesel | H24: Hour | I24: Standard (class avg) | J24: L/hr | K24: 5 | L24: 7 | M24: 9.5 | N24: =1+MIN(MAX($D$8-F24,0),$D$10)*$D$9 -> 1.098 | O24: =IF(H24="None",0,IF(H24="KM",IF(G24="Petrol",$D$6,$D$5)*N24/K24,K24*N24*IF(G24="Petrol",$D$6,$D$5))) -> 2624.22 | P24: =IF(H24="None",0,IF(H24="KM",IF(G24="Petrol",$D$6,$D$5)*N24/L24,L24*N24*IF(G24="Petrol",$D$6,$D$5))) -> 3673.908 | Q24: =IF(H24="None",0,IF(H24="KM",IF(G24="Petrol",$D$6,$D$5)*N24/M24,M24*N24*IF(G24="Petrol",$D$6,$D$5))) -> 4986.018 | R24: =IF(H24="None","—",IF(H24="KM","Rs./km","Rs./hr")) -> Rs./hr
A25: 13 | B25: LB-02 | C25: ZA-2963 | D25: Backhoe Loader | E25: Jcb 3Dx | F25: 2012 | G25: Diesel | H25: Hour | I25: Standard (class avg) | J25: L/hr | K25: 5 | L25: 7 | M25: 9.5 | N25: =1+MIN(MAX($D$8-F25,0),$D$10)*$D$9 -> 1.098 | O25: =IF(H25="None",0,IF(H25="KM",IF(G25="Petrol",$D$6,$D$5)*N25/K25,K25*N25*IF(G25="Petrol",$D$6,$D$5))) -> 2624.22 | P25: =IF(H25="None",0,IF(H25="KM",IF(G25="Petrol",$D$6,$D$5)*N25/L25,L25*N25*IF(G25="Petrol",$D$6,$D$5))) -> 3673.908 | Q25: =IF(H25="None",0,IF(H25="KM",IF(G25="Petrol",$D$6,$D$5)*N25/M25,M25*N25*IF(G25="Petrol",$D$6,$D$5))) -> 4986.018 | R25: =IF(H25="None","—",IF(H25="KM","Rs./km","Rs./hr")) -> Rs./hr
A26: 14 | B26: LB-03 | C26: ZA-2964 | D26: Backhoe Loader | E26: Jcb 3Dx | F26: 2012 | G26: Diesel | H26: Hour | I26: Standard (class avg) | J26: L/hr | K26: 5 | L26: 7 | M26: 9.5 | N26: =1+MIN(MAX($D$8-F26,0),$D$10)*$D$9 -> 1.098 | O26: =IF(H26="None",0,IF(H26="KM",IF(G26="Petrol",$D$6,$D$5)*N26/K26,K26*N26*IF(G26="Petrol",$D$6,$D$5))) -> 2624.22 | P26: =IF(H26="None",0,IF(H26="KM",IF(G26="Petrol",$D$6,$D$5)*N26/L26,L26*N26*IF(G26="Petrol",$D$6,$D$5))) -> 3673.908 | Q26: =IF(H26="None",0,IF(H26="KM",IF(G26="Petrol",$D$6,$D$5)*N26/M26,M26*N26*IF(G26="Petrol",$D$6,$D$5))) -> 4986.018 | R26: =IF(H26="None","—",IF(H26="KM","Rs./km","Rs./hr")) -> Rs./hr
A27: 15 | B27: LB-04 | C27: RS-0401 | D27: Backhoe Loader | E27: Jcb Slp3Cx | F27: 1999 | G27: Diesel | H27: Hour | I27: Standard (class avg) | J27: L/hr | K27: 5 | L27: 7 | M27: 9.5 | N27: =1+MIN(MAX($D$8-F27,0),$D$10)*$D$9 -> 1.175 | O27: =IF(H27="None",0,IF(H27="KM",IF(G27="Petrol",$D$6,$D$5)*N27/K27,K27*N27*IF(G27="Petrol",$D$6,$D$5))) -> 2808.25 | P27: =IF(H27="None",0,IF(H27="KM",IF(G27="Petrol",$D$6,$D$5)*N27/L27,L27*N27*IF(G27="Petrol",$D$6,$D$5))) -> 3931.55 | Q27: =IF(H27="None",0,IF(H27="KM",IF(G27="Petrol",$D$6,$D$5)*N27/M27,M27*N27*IF(G27="Petrol",$D$6,$D$5))) -> 5335.675 | R27: =IF(H27="None","—",IF(H27="KM","Rs./km","Rs./hr")) -> Rs./hr
A28: 16 | B28: LB-05 | C28: RS-0483 | D28: Backhoe Loader | E28: Jcb 3Dx | F28: 2006 | G28: Diesel | H28: Hour | I28: Standard (class avg) | J28: L/hr | K28: 5 | L28: 7 | M28: 9.5 | N28: =1+MIN(MAX($D$8-F28,0),$D$10)*$D$9 -> 1.14 | O28: =IF(H28="None",0,IF(H28="KM",IF(G28="Petrol",$D$6,$D$5)*N28/K28,K28*N28*IF(G28="Petrol",$D$6,$D$5))) -> 2724.6 | P28: =IF(H28="None",0,IF(H28="KM",IF(G28="Petrol",$D$6,$D$5)*N28/L28,L28*N28*IF(G28="Petrol",$D$6,$D$5))) -> 3814.44 | Q28: =IF(H28="None",0,IF(H28="KM",IF(G28="Petrol",$D$6,$D$5)*N28/M28,M28*N28*IF(G28="Petrol",$D$6,$D$5))) -> 5176.74 | R28: =IF(H28="None","—",IF(H28="KM","Rs./km","Rs./hr")) -> Rs./hr
A29: 17 | B29: LB-06 | C29: ZA-0447 | D29: Backhoe Loader | E29: Jcb 3Cx | F29: 2002 | G29: Diesel | H29: Hour | I29: Standard (class avg) | J29: L/hr | K29: 5 | L29: 7 | M29: 9.5 | N29: =1+MIN(MAX($D$8-F29,0),$D$10)*$D$9 -> 1.168 | O29: =IF(H29="None",0,IF(H29="KM",IF(G29="Petrol",$D$6,$D$5)*N29/K29,K29*N29*IF(G29="Petrol",$D$6,$D$5))) -> 2791.52 | P29: =IF(H29="None",0,IF(H29="KM",IF(G29="Petrol",$D$6,$D$5)*N29/L29,L29*N29*IF(G29="Petrol",$D$6,$D$5))) -> 3908.128 | Q29: =IF(H29="None",0,IF(H29="KM",IF(G29="Petrol",$D$6,$D$5)*N29/M29,M29*N29*IF(G29="Petrol",$D$6,$D$5))) -> 5303.888 | R29: =IF(H29="None","—",IF(H29="KM","Rs./km","Rs./hr")) -> Rs./hr
A30: 18 | B30: LB-07 | C30: ZA-2608 | D30: Backhoe Loader | E30: Jcb Jcb 3Cx | F30: 2004 | G30: Diesel | H30: Hour | I30: Standard (class avg) | J30: L/hr | K30: 5 | L30: 7 | M30: 9.5 | N30: =1+MIN(MAX($D$8-F30,0),$D$10)*$D$9 -> 1.154 | O30: =IF(H30="None",0,IF(H30="KM",IF(G30="Petrol",$D$6,$D$5)*N30/K30,K30*N30*IF(G30="Petrol",$D$6,$D$5))) -> 2758.06 | P30: =IF(H30="None",0,IF(H30="KM",IF(G30="Petrol",$D$6,$D$5)*N30/L30,L30*N30*IF(G30="Petrol",$D$6,$D$5))) -> 3861.284 | Q30: =IF(H30="None",0,IF(H30="KM",IF(G30="Petrol",$D$6,$D$5)*N30/M30,M30*N30*IF(G30="Petrol",$D$6,$D$5))) -> 5240.314 | R30: =IF(H30="None","—",IF(H30="KM","Rs./km","Rs./hr")) -> Rs./hr
A31: 19 | B31: LB-08 | C31: ZA-6068 | D31: Backhoe Loader | E31: Jcb Jcb 3Dx | F31: 2015 | G31: Diesel | H31: Hour | I31: Standard (class avg) | J31: L/hr | K31: 5 | L31: 7 | M31: 9.5 | N31: =1+MIN(MAX($D$8-F31,0),$D$10)*$D$9 -> 1.077 | O31: =IF(H31="None",0,IF(H31="KM",IF(G31="Petrol",$D$6,$D$5)*N31/K31,K31*N31*IF(G31="Petrol",$D$6,$D$5))) -> 2574.03 | P31: =IF(H31="None",0,IF(H31="KM",IF(G31="Petrol",$D$6,$D$5)*N31/L31,L31*N31*IF(G31="Petrol",$D$6,$D$5))) -> 3603.642 | Q31: =IF(H31="None",0,IF(H31="KM",IF(G31="Petrol",$D$6,$D$5)*N31/M31,M31*N31*IF(G31="Petrol",$D$6,$D$5))) -> 4890.657 | R31: =IF(H31="None","—",IF(H31="KM","Rs./km","Rs./hr")) -> Rs./hr
... A68: 56 | B68: DB-02 | C68: 68-5115 | D68: Diesel Bowser | E68: Isuzu 207 Di | F68: 1990 | G68: Diesel | H68: Hour | I68: Standard (class avg) | J68: L/hr | K68: 5 | L68: 7 | M68: 9.5 | N68: =1+MIN(MAX($D$8-F68,0),$D$10)*$D$9 -> 1.175 | O68: =IF(H68="None",0,IF(H68="KM",IF(G68="Petrol",$D$6,$D$5)*N68/K68,K68*N68*IF(G68="Petrol",$D$6,$D$5))) -> 2808.25 | P68: =IF(H68="None",0,IF(H68="KM",IF(G68="Petrol",$D$6,$D$5)*N68/L68,L68*N68*IF(G68="Petrol",$D$6,$D$5))) -> 3931.55 | Q68: =IF(H68="None",0,IF(H68="KM",IF(G68="Petrol",$D$6,$D$5)*N68/M68,M68*N68*IF(G68="Petrol",$D$6,$D$5))) -> 5335.675 | R68: =IF(H68="None","—",IF(H68="KM","Rs./km","Rs./hr")) -> Rs./hr
A69: 57 | B69: DB-03 | C69: 40-2955 | D69: Diesel Bowser | E69: Nissan Atlas | F69: — | G69: Diesel | H69: Hour | I69: Standard (class avg) | J69: L/hr | K69: 5 | L69: 7 | M69: 9.5 | N69: =1 -> 1 | O69: =IF(H69="None",0,IF(H69="KM",IF(G69="Petrol",$D$6,$D$5)*N69/K69,K69*N69*IF(G69="Petrol",$D$6,$D$5))) -> 2390 | P69: =IF(H69="None",0,IF(H69="KM",IF(G69="Petrol",$D$6,$D$5)*N69/L69,L69*N69*IF(G69="Petrol",$D$6,$D$5))) -> 3346 | Q69: =IF(H69="None",0,IF(H69="KM",IF(G69="Petrol",$D$6,$D$5)*N69/M69,M69*N69*IF(G69="Petrol",$D$6,$D$5))) -> 4541 | R69: =IF(H69="None","—",IF(H69="KM","Rs./km","Rs./hr")) -> Rs./hr
A70: 58 | B70: DB-04 | C70: 41-1130 | D70: Diesel Bowser | E70: Isuzu — | F70: 2005 | G70: Diesel | H70: Hour | I70: Standard (class avg) | J70: L/hr | K70: 5 | L70: 7 | M70: 9.5 | N70: =1+MIN(MAX($D$8-F70,0),$D$10)*$D$9 -> 1.147 | O70: =IF(H70="None",0,IF(H70="KM",IF(G70="Petrol",$D$6,$D$5)*N70/K70,K70*N70*IF(G70="Petrol",$D$6,$D$5))) -> 2741.33 | P70: =IF(H70="None",0,IF(H70="KM",IF(G70="Petrol",$D$6,$D$5)*N70/L70,L70*N70*IF(G70="Petrol",$D$6,$D$5))) -> 3837.862 | Q70: =IF(H70="None",0,IF(H70="KM",IF(G70="Petrol",$D$6,$D$5)*N70/M70,M70*N70*IF(G70="Petrol",$D$6,$D$5))) -> 5208.527 | R70: =IF(H70="None","—",IF(H70="KM","Rs./km","Rs./hr")) -> Rs./hr
A71: 59 | B71: DB-05 | C71: LA-1359 | D71: Diesel Bowser | E71: Tata — | F71: 1990 | G71: Diesel | H71: Hour | I71: Standard (class avg) | J71: L/hr | K71: 5 | L71: 7 | M71: 9.5 | N71: =1+MIN(MAX($D$8-F71,0),$D$10)*$D$9 -> 1.175 | O71: =IF(H71="None",0,IF(H71="KM",IF(G71="Petrol",$D$6,$D$5)*N71/K71,K71*N71*IF(G71="Petrol",$D$6,$D$5))) -> 2808.25 | P71: =IF(H71="None",0,IF(H71="KM",IF(G71="Petrol",$D$6,$D$5)*N71/L71,L71*N71*IF(G71="Petrol",$D$6,$D$5))) -> 3931.55 | Q71: =IF(H71="None",0,IF(H71="KM",IF(G71="Petrol",$D$6,$D$5)*N71/M71,M71*N71*IF(G71="Petrol",$D$6,$D$5))) -> 5335.675 | R71: =IF(H71="None","—",IF(H71="KM","Rs./km","Rs./hr")) -> Rs./hr
A72: 60 | B72: — | C72: — | D72: Diesel Bowser | E72: Tata — | F72: — | G72: Diesel | H72: Hour | I72: Standard (class avg) | J72: L/hr | K72: 5 | L72: 7 | M72: 9.5 | N72: =1 -> 1 | O72: =IF(H72="None",0,IF(H72="KM",IF(G72="Petrol",$D$6,$D$5)*N72/K72,K72*N72*IF(G72="Petrol",$D$6,$D$5))) -> 2390 | P72: =IF(H72="None",0,IF(H72="KM",IF(G72="Petrol",$D$6,$D$5)*N72/L72,L72*N72*IF(G72="Petrol",$D$6,$D$5))) -> 3346 | Q72: =IF(H72="None",0,IF(H72="KM",IF(G72="Petrol",$D$6,$D$5)*N72/M72,M72*N72*IF(G72="Petrol",$D$6,$D$5))) -> 4541 | R72: =IF(H72="None","—",IF(H72="KM","Rs./km","Rs./hr")) -> Rs./hr
A73: 61 | B73: DC-06 | C73: PA-4193 | D73: Double Cab (Pickup) | E73: Toyota Hilux | F73: 2005 | G73: Diesel | H73: KM | I73: Standard (class avg) | J73: km/L | K73: 12.8 | L73: 10 | M73: 8 | N73: =1+MIN(MAX($D$8-F73,0),$D$10)*$D$9 -> 1.147 | O73: =IF(H73="None",0,IF(H73="KM",IF(G73="Petrol",$D$6,$D$5)*N73/K73,K73*N73*IF(G73="Petrol",$D$6,$D$5))) -> 42.833281 | P73: =IF(H73="None",0,IF(H73="KM",IF(G73="Petrol",$D$6,$D$5)*N73/L73,L73*N73*IF(G73="Petrol",$D$6,$D$5))) -> 54.8266 | Q73: =IF(H73="None",0,IF(H73="KM",IF(G73="Petrol",$D$6,$D$5)*N73/M73,M73*N73*IF(G73="Petrol",$D$6,$D$5))) -> 68.53325 | R73: =IF(H73="None","—",IF(H73="KM","Rs./km","Rs./hr")) -> Rs./km
A74: 62 | B74: DC-07 | C74: 51-8083 | D74: Double Cab (Pickup) | E74: Datzen Motor Pic-Up | F74: — | G74: Diesel | H74: KM | I74: Standard (class avg) | J74: km/L | K74: 12.8 | L74: 10 | M74: 8 | N74: =1 -> 1 | O74: =IF(H74="None",0,IF(H74="KM",IF(G74="Petrol",$D$6,$D$5)*N74/K74,K74*N74*IF(G74="Petrol",$D$6,$D$5))) -> 37.34375 | P74: =IF(H74="None",0,IF(H74="KM",IF(G74="Petrol",$D$6,$D$5)*N74/L74,L74*N74*IF(G74="Petrol",$D$6,$D$5))) -> 47.8 | Q74: =IF(H74="None",0,IF(H74="KM",IF(G74="Petrol",$D$6,$D$5)*N74/M74,M74*N74*IF(G74="Petrol",$D$6,$D$5))) -> 59.75 | R74: =IF(H74="None","—",IF(H74="KM","Rs./km","Rs./hr")) -> Rs./km
A75: 63 | B75: DC-08 | C75: 59-5421 | D75: Double Cab (Pickup) | E75: Isuzu Motor Pic-Up | F75: 1997 | G75: Diesel | H75: KM | I75: Standard (class avg) | J75: km/L | K75: 12.8 | L75: 10 | M75: 8 | N75: =1+MIN(MAX($D$8-F75,0),$D$10)*$D$9 -> 1.175 | O75: =IF(H75="None",0,IF(H75="KM",IF(G75="Petrol",$D$6,$D$5)*N75/K75,K75*N75*IF(G75="Petrol",$D$6,$D$5))) -> 43.878906 | P75: =IF(H75="None",0,IF(H75="KM",IF(G75="Petrol",$D$6,$D$5)*N75/L75,L75*N75*IF(G75="Petrol",$D$6,$D$5))) -> 56.165 | Q75: =IF(H75="None",0,IF(H75="KM",IF(G75="Petrol",$D$6,$D$5)*N75/M75,M75*N75*IF(G75="Petrol",$D$6,$D$5))) -> 70.20625 | R75: =IF(H75="None","—",IF(H75="KM","Rs./km","Rs./hr")) -> Rs./km
A76: 64 | B76: DC-10 | C76: 28-4314 | D76: Double Cab (Pickup) | E76: Datzen Motor Pic-Up | F76: 1985 | G76: Diesel | H76: KM | I76: Standard (class avg) | J76: km/L | K76: 12.8 | L76: 10 | M76: 8 | N76: =1+MIN(MAX($D$8-F76,0),$D$10)*$D$9 -> 1.175 | O76: =IF(H76="None",0,IF(H76="KM",IF(G76="Petrol",$D$6,$D$5)*N76/K76,K76*N76*IF(G76="Petrol",$D$6,$D$5))) -> 43.878906 | P76: =IF(H76="None",0,IF(H76="KM",IF(G76="Petrol",$D$6,$D$5)*N76/L76,L76*N76*IF(G76="Petrol",$D$6,$D$5))) -> 56.165 | Q76: =IF(H76="None",0,IF(H76="KM",IF(G76="Petrol",$D$6,$D$5)*N76/M76,M76*N76*IF(G76="Petrol",$D$6,$D$5))) -> 70.20625 | R76: =IF(H76="None","—",IF(H76="KM","Rs./km","Rs./hr")) -> Rs./km
A77: 65 | B77: DC-11 | C77: HU-5097 | D77: Double Cab (Pickup) | E77: Mitsubishi L 200 | F77: 2003 | G77: Diesel | H77: KM | I77: Standard (class avg) | J77: km/L | K77: 12.8 | L77: 10 | M77: 8 | N77: =1+MIN(MAX($D$8-F77,0),$D$10)*$D$9 -> 1.161 | O77: =IF(H77="None",0,IF(H77="KM",IF(G77="Petrol",$D$6,$D$5)*N77/K77,K77*N77*IF(G77="Petrol",$D$6,$D$5))) -> 43.356094 | P77: =IF(H77="None",0,IF(H77="KM",IF(G77="Petrol",$D$6,$D$5)*N77/L77,L77*N77*IF(G77="Petrol",$D$6,$D$5))) -> 55.4958 | Q77: =IF(H77="None",0,IF(H77="KM",IF(G77="Petrol",$D$6,$D$5)*N77/M77,M77*N77*IF(G77="Petrol",$D$6,$D$5))) -> 69.36975 | R77: =IF(H77="None","—",IF(H77="KM","Rs./km","Rs./hr")) -> Rs./km
A78: 66 | B78: DC-12 | C78: 253-2574 | D78: Double Cab (Pickup) | E78: Mitsubishi Motor Pic-Up | F78: 1999 | G78: Diesel | H78: KM | I78: Standard (class avg) | J78: km/L | K78: 12.8 | L78: 10 | M78: 8 | N78: =1+MIN(MAX($D$8-F78,0),$D$10)*$D$9 -> 1.175 | O78: =IF(H78="None",0,IF(H78="KM",IF(G78="Petrol",$D$6,$D$5)*N78/K78,K78*N78*IF(G78="Petrol",$D$6,$D$5))) -> 43.878906 | P78: =IF(H78="None",0,IF(H78="KM",IF(G78="Petrol",$D$6,$D$5)*N78/L78,L78*N78*IF(G78="Petrol",$D$6,$D$5))) -> 56.165 | Q78: =IF(H78="None",0,IF(H78="KM",IF(G78="Petrol",$D$6,$D$5)*N78/M78,M78*N78*IF(G78="Petrol",$D$6,$D$5))) -> 70.20625 | R78: =IF(H78="None","—",IF(H78="KM","Rs./km","Rs./hr")) -> Rs./km
A79: 67 | B79: DC-14 | C79: PD-6917 | D79: Double Cab (Pickup) | E79: Mahindra Bolero Camper Gold | F79: 2011 | G79: Diesel | H79: KM | I79: Standard (class avg) | J79: km/L | K79: 12.8 | L79: 10 | M79: 8 | N79: =1+MIN(MAX($D$8-F79,0),$D$10)*$D$9 -> 1.105 | O79: =IF(H79="None",0,IF(H79="KM",IF(G79="Petrol",$D$6,$D$5)*N79/K79,K79*N79*IF(G79="Petrol",$D$6,$D$5))) -> 41.264844 | P79: =IF(H79="None",0,IF(H79="KM",IF(G79="Petrol",$D$6,$D$5)*N79/L79,L79*N79*IF(G79="Petrol",$D$6,$D$5))) -> 52.819 | Q79: =IF(H79="None",0,IF(H79="KM",IF(G79="Petrol",$D$6,$D$5)*N79/M79,M79*N79*IF(G79="Petrol",$D$6,$D$5))) -> 66.02375 | R79: =IF(H79="None","—",IF(H79="KM","Rs./km","Rs./hr")) -> Rs./km
A80: 68 | B80: DC-15 | C80: PE-6582 | D80: Double Cab (Pickup) | E80: Mitsubishi L 200 | F80: 2008 | G80: Diesel | H80: KM | I80: Standard (class avg) | J80: km/L | K80: 12.8 | L80: 10 | M80: 8 | N80: =1+MIN(MAX($D$8-F80,0),$D$10)*$D$9 -> 1.126 | O80: =IF(H80="None",0,IF(H80="KM",IF(G80="Petrol",$D$6,$D$5)*N80/K80,K80*N80*IF(G80="Petrol",$D$6,$D$5))) -> 42.049062 | P80: =IF(H80="None",0,IF(H80="KM",IF(G80="Petrol",$D$6,$D$5)*N80/L80,L80*N80*IF(G80="Petrol",$D$6,$D$5))) -> 53.8228 | Q80: =IF(H80="None",0,IF(H80="KM",IF(G80="Petrol",$D$6,$D$5)*N80/M80,M80*N80*IF(G80="Petrol",$D$6,$D$5))) -> 67.2785 | R80: =IF(H80="None","—",IF(H80="KM","Rs./km","Rs./hr")) -> Rs./km
A81: 69 | B81: DC-16 | C81: PA-4102 | D81: Double Cab (Pickup) | E81: Volkswagon T5 Transporter | F81: 2005 | G81: Diesel | H81: KM | I81: Standard (class avg) | J81: km/L | K81: 12.8 | L81: 10 | M81: 8 | N81: =1+MIN(MAX($D$8-F81,0),$D$10)*$D$9 -> 1.147 | O81: =IF(H81="None",0,IF(H81="KM",IF(G81="Petrol",$D$6,$D$5)*N81/K81,K81*N81*IF(G81="Petrol",$D$6,$D$5))) -> 42.833281 | P81: =IF(H81="None",0,IF(H81="KM",IF(G81="Petrol",$D$6,$D$5)*N81/L81,L81*N81*IF(G81="Petrol",$D$6,$D$5))) -> 54.8266 | Q81: =IF(H81="None",0,IF(H81="KM",IF(G81="Petrol",$D$6,$D$5)*N81/M81,M81*N81*IF(G81="Petrol",$D$6,$D$5))) -> 68.53325 | R81: =IF(H81="None","—",IF(H81="KM","Rs./km","Rs./hr")) -> Rs./km
A82: 70 | B82: DC-18 | C82: PE-5879 | D82: Double Cab (Pickup) | E82: Toyota Hilux Vigo | F82: 2008 | G82: Diesel | H82: KM | I82: Standard (class avg) | J82: km/L | K82: 12.8 | L82: 10 | M82: 8 | N82: =1+MIN(MAX($D$8-F82,0),$D$10)*$D$9 -> 1.126 | O82: =IF(H82="None",0,IF(H82="KM",IF(G82="Petrol",$D$6,$D$5)*N82/K82,K82*N82*IF(G82="Petrol",$D$6,$D$5))) -> 42.049062 | P82: =IF(H82="None",0,IF(H82="KM",IF(G82="Petrol",$D$6,$D$5)*N82/L82,L82*N82*IF(G82="Petrol",$D$6,$D$5))) -> 53.8228 | Q82: =IF(H82="None",0,IF(H82="KM",IF(G82="Petrol",$D$6,$D$5)*N82/M82,M82*N82*IF(G82="Petrol",$D$6,$D$5))) -> 67.2785 | R82: =IF(H82="None","—",IF(H82="KM","Rs./km","Rs./hr")) -> Rs./km
A83: 71 | B83: DC-19 | C83: PD-8451 | D83: Double Cab (Pickup) | E83: Toyota Hilux Vigo | F83: 2007 | G83: Diesel | H83: KM | I83: Standard (class avg) | J83: km/L | K83: 12.8 | L83: 10 | M83: 8 | N83: =1+MIN(MAX($D$8-F83,0),$D$10)*$D$9 -> 1.133 | O83: =IF(H83="None",0,IF(H83="KM",IF(G83="Petrol",$D$6,$D$5)*N83/K83,K83*N83*IF(G83="Petrol",$D$6,$D$5))) -> 42.310469 | P83: =IF(H83="None",0,IF(H83="KM",IF(G83="Petrol",$D$6,$D$5)*N83/L83,L83*N83*IF(G83="Petrol",$D$6,$D$5))) -> 54.1574 | Q83: =IF(H83="None",0,IF(H83="KM",IF(G83="Petrol",$D$6,$D$5)*N83/M83,M83*N83*IF(G83="Petrol",$D$6,$D$5))) -> 67.69675 | R83: =IF(H83="None","—",IF(H83="KM","Rs./km","Rs./hr")) -> Rs./km
A84: 72 | B84: DC-20 | C84: PH-0765 | D84: Double Cab (Pickup) | E84: Mahindra Bolero Camper Gold | F84: 2015 | G84: Diesel | H84: KM | I84: Standard (class avg) | J84: km/L | K84: 12.8 | L84: 10 | M84: 8 | N84: =1+MIN(MAX($D$8-F84,0),$D$10)*$D$9 -> 1.077 | O84: =IF(H84="None",0,IF(H84="KM",IF(G84="Petrol",$D$6,$D$5)*N84/K84,K84*N84*IF(G84="Petrol",$D$6,$D$5))) -> 40.219219 | P84: =IF(H84="None",0,IF(H84="KM",IF(G84="Petrol",$D$6,$D$5)*N84/L84,L84*N84*IF(G84="Petrol",$D$6,$D$5))) -> 51.4806 | Q84: =IF(H84="None",0,IF(H84="KM",IF(G84="Petrol",$D$6,$D$5)*N84/M84,M84*N84*IF(G84="Petrol",$D$6,$D$5))) -> 64.35075 | R84: =IF(H84="None","—",IF(H84="KM","Rs./km","Rs./hr")) -> Rs./km
A85: 73 | B85: DC-21 | C85: PH-3945 | D85: Double Cab (Pickup) | E85: Mahindra Imperio Dcvx | F85: 2016 | G85: Diesel | H85: KM | I85: Standard (class avg) | J85: km/L | K85: 12.8 | L85: 10 | M85: 8 | N85: =1+MIN(MAX($D$8-F85,0),$D$10)*$D$9 -> 1.07 | O85: =IF(H85="None",0,IF(H85="KM",IF(G85="Petrol",$D$6,$D$5)*N85/K85,K85*N85*IF(G85="Petrol",$D$6,$D$5))) -> 39.957813 | P85: =IF(H85="None",0,IF(H85="KM",IF(G85="Petrol",$D$6,$D$5)*N85/L85,L85*N85*IF(G85="Petrol",$D$6,$D$5))) -> 51.146 | Q85: =IF(H85="None",0,IF(H85="KM",IF(G85="Petrol",$D$6,$D$5)*N85/M85,M85*N85*IF(G85="Petrol",$D$6,$D$5))) -> 63.9325 | R85: =IF(H85="None","—",IF(H85="KM","Rs./km","Rs./hr")) -> Rs./km
A86: 74 | B86: DC-22 | C86: PE-3911 | D86: Double Cab (Pickup) | E86: Toyota Hilux | F86: 2012 | G86: Diesel | H86: KM | I86: Standard (class avg) | J86: km/L | K86: 12.8 | L86: 10 | M86: 8 | N86: =1+MIN(MAX($D$8-F86,0),$D$10)*$D$9 -> 1.098 | O86: =IF(H86="None",0,IF(H86="KM",IF(G86="Petrol",$D$6,$D$5)*N86/K86,K86*N86*IF(G86="Petrol",$D$6,$D$5))) -> 41.003438 | P86: =IF(H86="None",0,IF(H86="KM",IF(G86="Petrol",$D$6,$D$5)*N86/L86,L86*N86*IF(G86="Petrol",$D$6,$D$5))) -> 52.4844 | Q86: =IF(H86="None",0,IF(H86="KM",IF(G86="Petrol",$D$6,$D$5)*N86/M86,M86*N86*IF(G86="Petrol",$D$6,$D$5))) -> 65.6055 | R86: =IF(H86="None","—",IF(H86="KM","Rs./km","Rs./hr")) -> Rs./km
... A96: 84 | B96: DC-32 | C96: PH-9072 | D96: Double Cab (Pickup) | E96: Toyota Hilux | F96: 2017 | G96: Diesel | H96: KM | I96: Standard (class avg) | J96: km/L | K96: 12.8 | L96: 10 | M96: 8 | N96: =1+MIN(MAX($D$8-F96,0),$D$10)*$D$9 -> 1.063 | O96: =IF(H96="None",0,IF(H96="KM",IF(G96="Petrol",$D$6,$D$5)*N96/K96,K96*N96*IF(G96="Petrol",$D$6,$D$5))) -> 39.696406 | P96: =IF(H96="None",0,IF(H96="KM",IF(G96="Petrol",$D$6,$D$5)*N96/L96,L96*N96*IF(G96="Petrol",$D$6,$D$5))) -> 50.8114 | Q96: =IF(H96="None",0,IF(H96="KM",IF(G96="Petrol",$D$6,$D$5)*N96/M96,M96*N96*IF(G96="Petrol",$D$6,$D$5))) -> 63.51425 | R96: =IF(H96="None","—",IF(H96="KM","Rs./km","Rs./hr")) -> Rs./km
A97: 85 | B97: — | C97: PJ-7604 | D97: Double Cab (Pickup) | E97: Toyota — | F97: — | G97: Diesel | H97: KM | I97: Standard (class avg) | J97: km/L | K97: 12.8 | L97: 10 | M97: 8 | N97: =1 -> 1 | O97: =IF(H97="None",0,IF(H97="KM",IF(G97="Petrol",$D$6,$D$5)*N97/K97,K97*N97*IF(G97="Petrol",$D$6,$D$5))) -> 37.34375 | P97: =IF(H97="None",0,IF(H97="KM",IF(G97="Petrol",$D$6,$D$5)*N97/L97,L97*N97*IF(G97="Petrol",$D$6,$D$5))) -> 47.8 | Q97: =IF(H97="None",0,IF(H97="KM",IF(G97="Petrol",$D$6,$D$5)*N97/M97,M97*N97*IF(G97="Petrol",$D$6,$D$5))) -> 59.75 | R97: =IF(H97="None","—",IF(H97="KM","Rs./km","Rs./hr")) -> Rs./km
A98: 86 | B98: DT-01 | C98: LB-9496 | D98: Dump Truck (Tipper) | E98: Ashok Leland Comet | F98: 2006 | G98: Diesel | H98: KM | I98: Standard ~16t | J98: km/L | K98: 3.8 | L98: 3 | M98: 2.4 | N98: =1+MIN(MAX($D$8-F98,0),$D$10)*$D$9 -> 1.14 | O98: =IF(H98="None",0,IF(H98="KM",IF(G98="Petrol",$D$6,$D$5)*N98/K98,K98*N98*IF(G98="Petrol",$D$6,$D$5))) -> 143.4 | P98: =IF(H98="None",0,IF(H98="KM",IF(G98="Petrol",$D$6,$D$5)*N98/L98,L98*N98*IF(G98="Petrol",$D$6,$D$5))) -> 181.64 | Q98: =IF(H98="None",0,IF(H98="KM",IF(G98="Petrol",$D$6,$D$5)*N98/M98,M98*N98*IF(G98="Petrol",$D$6,$D$5))) -> 227.05 | R98: =IF(H98="None","—",IF(H98="KM","Rs./km","Rs./hr")) -> Rs./km
A99: 87 | B99: DT-02 | C99: LL-0920 | D99: Dump Truck (Tipper) | E99: Tata Lpk 407 | F99: 2013 | G99: Diesel | H99: KM | I99: Light 4t | J99: km/L | K99: 6.4 | L99: 5 | M99: 4 | N99: =1+MIN(MAX($D$8-F99,0),$D$10)*$D$9 -> 1.091 | O99: =IF(H99="None",0,IF(H99="KM",IF(G99="Petrol",$D$6,$D$5)*N99/K99,K99*N99*IF(G99="Petrol",$D$6,$D$5))) -> 81.484062 | P99: =IF(H99="None",0,IF(H99="KM",IF(G99="Petrol",$D$6,$D$5)*N99/L99,L99*N99*IF(G99="Petrol",$D$6,$D$5))) -> 104.2996 | Q99: =IF(H99="None",0,IF(H99="KM",IF(G99="Petrol",$D$6,$D$5)*N99/M99,M99*N99*IF(G99="Petrol",$D$6,$D$5))) -> 130.3745 | R99: =IF(H99="None","—",IF(H99="KM","Rs./km","Rs./hr")) -> Rs./km
A100: 88 | B100: DT-03 | C100: LK-4057 | D100: Dump Truck (Tipper) | E100: Ashok Leland Commet Tipper 1613 | F100: 2012 | G100: Diesel | H100: KM | I100: Standard 16t | J100: km/L | K100: 3.8 | L100: 3 | M100: 2.4 | N100: =1+MIN(MAX($D$8-F100,0),$D$10)*$D$9 -> 1.098 | O100: =IF(H100="None",0,IF(H100="KM",IF(G100="Petrol",$D$6,$D$5)*N100/K100,K100*N100*IF(G100="Petrol",$D$6,$D$5))) -> 138.11684 | P100: =IF(H100="None",0,IF(H100="KM",IF(G100="Petrol",$D$6,$D$5)*N100/L100,L100*N100*IF(G100="Petrol",$D$6,$D$5))) -> 174.948 | Q100: =IF(H100="None",0,IF(H100="KM",IF(G100="Petrol",$D$6,$D$5)*N100/M100,M100*N100*IF(G100="Petrol",$D$6,$D$5))) -> 218.685 | R100: =IF(H100="None","—",IF(H100="KM","Rs./km","Rs./hr")) -> Rs./km
A101: 89 | B101: DT-04 | C101: HS-1794 | D101: Dump Truck (Tipper) | E101: Ashok Leland Comet | F101: 2003 | G101: Diesel | H101: KM | I101: Standard ~16t | J101: km/L | K101: 3.8 | L101: 3 | M101: 2.4 | N101: =1+MIN(MAX($D$8-F101,0),$D$10)*$D$9 -> 1.161 | O101: =IF(H101="None",0,IF(H101="KM",IF(G101="Petrol",$D$6,$D$5)*N101/K101,K101*N101*IF(G101="Petrol",$D$6,$D$5))) -> 146.04158 | P101: =IF(H101="None",0,IF(H101="KM",IF(G101="Petrol",$D$6,$D$5)*N101/L101,L101*N101*IF(G101="Petrol",$D$6,$D$5))) -> 184.986 | Q101: =IF(H101="None",0,IF(H101="KM",IF(G101="Petrol",$D$6,$D$5)*N101/M101,M101*N101*IF(G101="Petrol",$D$6,$D$5))) -> 231.2325 | R101: =IF(H101="None","—",IF(H101="KM","Rs./km","Rs./hr")) -> Rs./km
A102: 90 | B102: DT-05 | C102: HS-1773 | D102: Dump Truck (Tipper) | E102: Ashok Leland Commet Tipper 1613 | F102: 2003 | G102: Diesel | H102: KM | I102: Standard 16t | J102: km/L | K102: 3.8 | L102: 3 | M102: 2.4 | N102: =1+MIN(MAX($D$8-F102,0),$D$10)*$D$9 -> 1.161 | O102: =IF(H102="None",0,IF(H102="KM",IF(G102="Petrol",$D$6,$D$5)*N102/K102,K102*N102*IF(G102="Petrol",$D$6,$D$5))) -> 146.04158 | P102: =IF(H102="None",0,IF(H102="KM",IF(G102="Petrol",$D$6,$D$5)*N102/L102,L102*N102*IF(G102="Petrol",$D$6,$D$5))) -> 184.986 | Q102: =IF(H102="None",0,IF(H102="KM",IF(G102="Petrol",$D$6,$D$5)*N102/M102,M102*N102*IF(G102="Petrol",$D$6,$D$5))) -> 231.2325 | R102: =IF(H102="None","—",IF(H102="KM","Rs./km","Rs./hr")) -> Rs./km
A103: 91 | B103: DT-07 | C103: LI-7618 | D103: Dump Truck (Tipper) | E103: Tata Lpk 1615 | F103: 2011 | G103: Diesel | H103: KM | I103: Standard 16t | J103: km/L | K103: 3.8 | L103: 3 | M103: 2.4 | N103: =1+MIN(MAX($D$8-F103,0),$D$10)*$D$9 -> 1.105 | O103: =IF(H103="None",0,IF(H103="KM",IF(G103="Petrol",$D$6,$D$5)*N103/K103,K103*N103*IF(G103="Petrol",$D$6,$D$5))) -> 138.99737 | P103: =IF(H103="None",0,IF(H103="KM",IF(G103="Petrol",$D$6,$D$5)*N103/L103,L103*N103*IF(G103="Petrol",$D$6,$D$5))) -> 176.06333 | Q103: =IF(H103="None",0,IF(H103="KM",IF(G103="Petrol",$D$6,$D$5)*N103/M103,M103*N103*IF(G103="Petrol",$D$6,$D$5))) -> 220.07917 | R103: =IF(H103="None","—",IF(H103="KM","Rs./km","Rs./hr")) -> Rs./km
A104: 92 | B104: DT-08 | C104: LI-7620 | D104: Dump Truck (Tipper) | E104: Tata Lpk1618 | F104: 2011 | G104: Diesel | H104: KM | I104: Standard 16t | J104: km/L | K104: 3.8 | L104: 3 | M104: 2.4 | N104: =1+MIN(MAX($D$8-F104,0),$D$10)*$D$9 -> 1.105 | O104: =IF(H104="None",0,IF(H104="KM",IF(G104="Petrol",$D$6,$D$5)*N104/K104,K104*N104*IF(G104="Petrol",$D$6,$D$5))) -> 138.99737 | P104: =IF(H104="None",0,IF(H104="KM",IF(G104="Petrol",$D$6,$D$5)*N104/L104,L104*N104*IF(G104="Petrol",$D$6,$D$5))) -> 176.06333 | Q104: =IF(H104="None",0,IF(H104="KM",IF(G104="Petrol",$D$6,$D$5)*N104/M104,M104*N104*IF(G104="Petrol",$D$6,$D$5))) -> 220.07917 | R104: =IF(H104="None","—",IF(H104="KM","Rs./km","Rs./hr")) -> Rs./km
A105: 93 | B105: DT-09 | C105: LI-7701 | D105: Dump Truck (Tipper) | E105: Tata Lpk1618 | F105: 2011 | G105: Diesel | H105: KM | I105: Standard 16t | J105: km/L | K105: 3.8 | L105: 3 | M105: 2.4 | N105: =1+MIN(MAX($D$8-F105,0),$D$10)*$D$9 -> 1.105 | O105: =IF(H105="None",0,IF(H105="KM",IF(G105="Petrol",$D$6,$D$5)*N105/K105,K105*N105*IF(G105="Petrol",$D$6,$D$5))) -> 138.99737 | P105: =IF(H105="None",0,IF(H105="KM",IF(G105="Petrol",$D$6,$D$5)*N105/L105,L105*N105*IF(G105="Petrol",$D$6,$D$5))) -> 176.06333 | Q105: =IF(H105="None",0,IF(H105="KM",IF(G105="Petrol",$D$6,$D$5)*N105/M105,M105*N105*IF(G105="Petrol",$D$6,$D$5))) -> 220.07917 | R105: =IF(H105="None","—",IF(H105="KM","Rs./km","Rs./hr")) -> Rs./km
A106: 94 | B106: DT-10 | C106: LK-6740 | D106: Dump Truck (Tipper) | E106: Tata Lpk 407 | F106: 2012 | G106: Diesel | H106: KM | I106: Light 4t | J106: km/L | K106: 6.4 | L106: 5 | M106: 4 | N106: =1+MIN(MAX($D$8-F106,0),$D$10)*$D$9 -> 1.098 | O106: =IF(H106="None",0,IF(H106="KM",IF(G106="Petrol",$D$6,$D$5)*N106/K106,K106*N106*IF(G106="Petrol",$D$6,$D$5))) -> 82.006875 | P106: =IF(H106="None",0,IF(H106="KM",IF(G106="Petrol",$D$6,$D$5)*N106/L106,L106*N106*IF(G106="Petrol",$D$6,$D$5))) -> 104.9688 | Q106: =IF(H106="None",0,IF(H106="KM",IF(G106="Petrol",$D$6,$D$5)*N106/M106,M106*N106*IF(G106="Petrol",$D$6,$D$5))) -> 131.211 | R106: =IF(H106="None","—",IF(H106="KM","Rs./km","Rs./hr")) -> Rs./km
A107: 95 | B107: DT-11 | C107: LK-6738 | D107: Dump Truck (Tipper) | E107: Tata Lpk1618 | F107: 2012 | G107: Diesel | H107: KM | I107: Standard 16t | J107: km/L | K107: 3.8 | L107: 3 | M107: 2.4 | N107: =1+MIN(MAX($D$8-F107,0),$D$10)*$D$9 -> 1.098 | O107: =IF(H107="None",0,IF(H107="KM",IF(G107="Petrol",$D$6,$D$5)*N107/K107,K107*N107*IF(G107="Petrol",$D$6,$D$5))) -> 138.11684 | P107: =IF(H107="None",0,IF(H107="KM",IF(G107="Petrol",$D$6,$D$5)*N107/L107,L107*N107*IF(G107="Petrol",$D$6,$D$5))) -> 174.948 | Q107: =IF(H107="None",0,IF(H107="KM",IF(G107="Petrol",$D$6,$D$5)*N107/M107,M107*N107*IF(G107="Petrol",$D$6,$D$5))) -> 218.685 | R107: =IF(H107="None","—",IF(H107="KM","Rs./km","Rs./hr")) -> Rs./km
A108: 96 | B108: DT-12 | C108: LK-2276 | D108: Dump Truck (Tipper) | E108: Tata Lpk 909 | F108: 2012 | G108: Diesel | H108: KM | I108: Medium 9t | J108: km/L | K108: 4.9 | L108: 3.8 | M108: 3 | N108: =1+MIN(MAX($D$8-F108,0),$D$10)*$D$9 -> 1.098 | O108: =IF(H108="None",0,IF(H108="KM",IF(G108="Petrol",$D$6,$D$5)*N108/K108,K108*N108*IF(G108="Petrol",$D$6,$D$5))) -> 107.11102 | P108: =IF(H108="None",0,IF(H108="KM",IF(G108="Petrol",$D$6,$D$5)*N108/L108,L108*N108*IF(G108="Petrol",$D$6,$D$5))) -> 138.11684 | Q108: =IF(H108="None",0,IF(H108="KM",IF(G108="Petrol",$D$6,$D$5)*N108/M108,M108*N108*IF(G108="Petrol",$D$6,$D$5))) -> 174.948 | R108: =IF(H108="None","—",IF(H108="KM","Rs./km","Rs./hr")) -> Rs./km
A109: 97 | B109: DT-13 | C109: LK-2366 | D109: Dump Truck (Tipper) | E109: Tata Lpk1618 | F109: 2012 | G109: Diesel | H109: KM | I109: Standard 16t | J109: km/L | K109: 3.8 | L109: 3 | M109: 2.4 | N109: =1+MIN(MAX($D$8-F109,0),$D$10)*$D$9 -> 1.098 | O109: =IF(H109="None",0,IF(H109="KM",IF(G109="Petrol",$D$6,$D$5)*N109/K109,K109*N109*IF(G109="Petrol",$D$6,$D$5))) -> 138.11684 | P109: =IF(H109="None",0,IF(H109="KM",IF(G109="Petrol",$D$6,$D$5)*N109/L109,L109*N109*IF(G109="Petrol",$D$6,$D$5))) -> 174.948 | Q109: =IF(H109="None",0,IF(H109="KM",IF(G109="Petrol",$D$6,$D$5)*N109/M109,M109*N109*IF(G109="Petrol",$D$6,$D$5))) -> 218.685 | R109: =IF(H109="None","—",IF(H109="KM","Rs./km","Rs./hr")) -> Rs./km
... A193: 181 | B193: HEX-09 | C193: — | D193: Excavator | E193: Komatsu Pc27R-8 | F193: 2009 | G193: Diesel | H193: Hour | I193: Mini 2.7t | J193: L/hr | K193: 2.9 | L193: 4 | M193: 5.4 | N193: =1+MIN(MAX($D$8-F193,0),$D$10)*$D$9 -> 1.119 | O193: =IF(H193="None",0,IF(H193="KM",IF(G193="Petrol",$D$6,$D$5)*N193/K193,K193*N193*IF(G193="Petrol",$D$6,$D$5))) -> 1551.1578 | P193: =IF(H193="None",0,IF(H193="KM",IF(G193="Petrol",$D$6,$D$5)*N193/L193,L193*N193*IF(G193="Petrol",$D$6,$D$5))) -> 2139.528 | Q193: =IF(H193="None",0,IF(H193="KM",IF(G193="Petrol",$D$6,$D$5)*N193/M193,M193*N193*IF(G193="Petrol",$D$6,$D$5))) -> 2888.3628 | R193: =IF(H193="None","—",IF(H193="KM","Rs./km","Rs./hr")) -> Rs./hr
A194: 182 | B194: HEX-12 | C194: — | D194: Excavator | E194: (Unknown) — | F194: — | G194: Diesel | H194: Hour | I194: Standard (assumed) | J194: L/hr | K194: 11.5 | L194: 16 | M194: 21.6 | N194: =1 -> 1 | O194: =IF(H194="None",0,IF(H194="KM",IF(G194="Petrol",$D$6,$D$5)*N194/K194,K194*N194*IF(G194="Petrol",$D$6,$D$5))) -> 5497 | P194: =IF(H194="None",0,IF(H194="KM",IF(G194="Petrol",$D$6,$D$5)*N194/L194,L194*N194*IF(G194="Petrol",$D$6,$D$5))) -> 7648 | Q194: =IF(H194="None",0,IF(H194="KM",IF(G194="Petrol",$D$6,$D$5)*N194/M194,M194*N194*IF(G194="Petrol",$D$6,$D$5))) -> 10324.8 | R194: =IF(H194="None","—",IF(H194="KM","Rs./km","Rs./hr")) -> Rs./hr
A195: 183 | B195: HEX-13 | C195: — | D195: Excavator | E195: Kubota U-25-35 | F195: 2010 | G195: Diesel | H195: Hour | I195: Mini 2.5t | J195: L/hr | K195: 2.9 | L195: 4 | M195: 5.4 | N195: =1+MIN(MAX($D$8-F195,0),$D$10)*$D$9 -> 1.112 | O195: =IF(H195="None",0,IF(H195="KM",IF(G195="Petrol",$D$6,$D$5)*N195/K195,K195*N195*IF(G195="Petrol",$D$6,$D$5))) -> 1541.4544 | P195: =IF(H195="None",0,IF(H195="KM",IF(G195="Petrol",$D$6,$D$5)*N195/L195,L195*N195*IF(G195="Petrol",$D$6,$D$5))) -> 2126.144 | Q195: =IF(H195="None",0,IF(H195="KM",IF(G195="Petrol",$D$6,$D$5)*N195/M195,M195*N195*IF(G195="Petrol",$D$6,$D$5))) -> 2870.2944 | R195: =IF(H195="None","—",IF(H195="KM","Rs./km","Rs./hr")) -> Rs./hr
A196: 184 | B196: HEX-14 | C196: — | D196: Excavator | E196: Cat 303 Cr | F196: 2014 | G196: Diesel | H196: Hour | I196: Mini 3t | J196: L/hr | K196: 2.9 | L196: 4 | M196: 5.4 | N196: =1+MIN(MAX($D$8-F196,0),$D$10)*$D$9 -> 1.084 | O196: =IF(H196="None",0,IF(H196="KM",IF(G196="Petrol",$D$6,$D$5)*N196/K196,K196*N196*IF(G196="Petrol",$D$6,$D$5))) -> 1502.6408 | P196: =IF(H196="None",0,IF(H196="KM",IF(G196="Petrol",$D$6,$D$5)*N196/L196,L196*N196*IF(G196="Petrol",$D$6,$D$5))) -> 2072.608 | Q196: =IF(H196="None",0,IF(H196="KM",IF(G196="Petrol",$D$6,$D$5)*N196/M196,M196*N196*IF(G196="Petrol",$D$6,$D$5))) -> 2798.0208 | R196: =IF(H196="None","—",IF(H196="KM","Rs./km","Rs./hr")) -> Rs./hr
A197: 185 | B197: HEX-15 | C197: — | D197: Excavator | E197: Kubota Kx-040 | F197: 2013 | G197: Diesel | H197: Hour | I197: Mini 4t | J197: L/hr | K197: 2.9 | L197: 4 | M197: 5.4 | N197: =1+MIN(MAX($D$8-F197,0),$D$10)*$D$9 -> 1.091 | O197: =IF(H197="None",0,IF(H197="KM",IF(G197="Petrol",$D$6,$D$5)*N197/K197,K197*N197*IF(G197="Petrol",$D$6,$D$5))) -> 1512.3442 | P197: =IF(H197="None",0,IF(H197="KM",IF(G197="Petrol",$D$6,$D$5)*N197/L197,L197*N197*IF(G197="Petrol",$D$6,$D$5))) -> 2085.992 | Q197: =IF(H197="None",0,IF(H197="KM",IF(G197="Petrol",$D$6,$D$5)*N197/M197,M197*N197*IF(G197="Petrol",$D$6,$D$5))) -> 2816.0892 | R197: =IF(H197="None","—",IF(H197="KM","Rs./km","Rs./hr")) -> Rs./hr
A198: 186 | B198: HEX-17 | C198: — | D198: Excavator | E198: Hyundai 0Bex220Lc-9S | F198: — | G198: Diesel | H198: Hour | I198: Standard 22t | J198: L/hr | K198: 11.5 | L198: 16 | M198: 21.6 | N198: =1 -> 1 | O198: =IF(H198="None",0,IF(H198="KM",IF(G198="Petrol",$D$6,$D$5)*N198/K198,K198*N198*IF(G198="Petrol",$D$6,$D$5))) -> 5497 | P198: =IF(H198="None",0,IF(H198="KM",IF(G198="Petrol",$D$6,$D$5)*N198/L198,L198*N198*IF(G198="Petrol",$D$6,$D$5))) -> 7648 | Q198: =IF(H198="None",0,IF(H198="KM",IF(G198="Petrol",$D$6,$D$5)*N198/M198,M198*N198*IF(G198="Petrol",$D$6,$D$5))) -> 10324.8 | R198: =IF(H198="None","—",IF(H198="KM","Rs./km","Rs./hr")) -> Rs./hr
A199: 187 | B199: HEX-18 | C199: — | D199: Excavator | E199: Hithachi Ex75Ur-3 | F199: 2014 | G199: Diesel | H199: Hour | I199: Compact 7.5t | J199: L/hr | K199: 4.7 | L199: 6.5 | M199: 8.8 | N199: =1+MIN(MAX($D$8-F199,0),$D$10)*$D$9 -> 1.084 | O199: =IF(H199="None",0,IF(H199="KM",IF(G199="Petrol",$D$6,$D$5)*N199/K199,K199*N199*IF(G199="Petrol",$D$6,$D$5))) -> 2435.3144 | P199: =IF(H199="None",0,IF(H199="KM",IF(G199="Petrol",$D$6,$D$5)*N199/L199,L199*N199*IF(G199="Petrol",$D$6,$D$5))) -> 3367.988 | Q199: =IF(H199="None",0,IF(H199="KM",IF(G199="Petrol",$D$6,$D$5)*N199/M199,M199*N199*IF(G199="Petrol",$D$6,$D$5))) -> 4559.7376 | R199: =IF(H199="None","—",IF(H199="KM","Rs./km","Rs./hr")) -> Rs./hr
A200: 188 | B200: HEX-19 | C200: — | D200: Excavator | E200: Komatsu Pc-120-6Eo | F200: 2009 | G200: Diesel | H200: Hour | I200: Midi 12t | J200: L/hr | K200: 7.2 | L200: 10 | M200: 13.5 | N200: =1+MIN(MAX($D$8-F200,0),$D$10)*$D$9 -> 1.119 | O200: =IF(H200="None",0,IF(H200="KM",IF(G200="Petrol",$D$6,$D$5)*N200/K200,K200*N200*IF(G200="Petrol",$D$6,$D$5))) -> 3851.1504 | P200: =IF(H200="None",0,IF(H200="KM",IF(G200="Petrol",$D$6,$D$5)*N200/L200,L200*N200*IF(G200="Petrol",$D$6,$D$5))) -> 5348.82 | Q200: =IF(H200="None",0,IF(H200="KM",IF(G200="Petrol",$D$6,$D$5)*N200/M200,M200*N200*IF(G200="Petrol",$D$6,$D$5))) -> 7220.907 | R200: =IF(H200="None","—",IF(H200="KM","Rs./km","Rs./hr")) -> Rs./hr
A201: 189 | B201: HEX-20 | C201: — | D201: Excavator | E201: Komatsu Pc-40Mr-02 | F201: 2009 | G201: Diesel | H201: Hour | I201: Mini 4t | J201: L/hr | K201: 2.9 | L201: 4 | M201: 5.4 | N201: =1+MIN(MAX($D$8-F201,0),$D$10)*$D$9 -> 1.119 | O201: =IF(H201="None",0,IF(H201="KM",IF(G201="Petrol",$D$6,$D$5)*N201/K201,K201*N201*IF(G201="Petrol",$D$6,$D$5))) -> 1551.1578 | P201: =IF(H201="None",0,IF(H201="KM",IF(G201="Petrol",$D$6,$D$5)*N201/L201,L201*N201*IF(G201="Petrol",$D$6,$D$5))) -> 2139.528 | Q201: =IF(H201="None",0,IF(H201="KM",IF(G201="Petrol",$D$6,$D$5)*N201/M201,M201*N201*IF(G201="Petrol",$D$6,$D$5))) -> 2888.3628 | R201: =IF(H201="None","—",IF(H201="KM","Rs./km","Rs./hr")) -> Rs./hr
A202: 190 | B202: HEX-21 | C202: — | D202: Excavator | E202: Kobelko Sk115Sr | F202: 2012 | G202: Diesel | H202: Hour | I202: Midi 11.5t | J202: L/hr | K202: 7.2 | L202: 10 | M202: 13.5 | N202: =1+MIN(MAX($D$8-F202,0),$D$10)*$D$9 -> 1.098 | O202: =IF(H202="None",0,IF(H202="KM",IF(G202="Petrol",$D$6,$D$5)*N202/K202,K202*N202*IF(G202="Petrol",$D$6,$D$5))) -> 3778.8768 | P202: =IF(H202="None",0,IF(H202="KM",IF(G202="Petrol",$D$6,$D$5)*N202/L202,L202*N202*IF(G202="Petrol",$D$6,$D$5))) -> 5248.44 | Q202: =IF(H202="None",0,IF(H202="KM",IF(G202="Petrol",$D$6,$D$5)*N202/M202,M202*N202*IF(G202="Petrol",$D$6,$D$5))) -> 7085.394 | R202: =IF(H202="None","—",IF(H202="KM","Rs./km","Rs./hr")) -> Rs./hr
A203: 191 | B203: HEX-22 | C203: — | D203: Excavator | E203: Catapillar 314C | F203: 2014 | G203: Diesel | H203: Hour | I203: Midi 14t | J203: L/hr | K203: 7.2 | L203: 10 | M203: 13.5 | N203: =1+MIN(MAX($D$8-F203,0),$D$10)*$D$9 -> 1.084 | O203: =IF(H203="None",0,IF(H203="KM",IF(G203="Petrol",$D$6,$D$5)*N203/K203,K203*N203*IF(G203="Petrol",$D$6,$D$5))) -> 3730.6944 | P203: =IF(H203="None",0,IF(H203="KM",IF(G203="Petrol",$D$6,$D$5)*N203/L203,L203*N203*IF(G203="Petrol",$D$6,$D$5))) -> 5181.52 | Q203: =IF(H203="None",0,IF(H203="KM",IF(G203="Petrol",$D$6,$D$5)*N203/M203,M203*N203*IF(G203="Petrol",$D$6,$D$5))) -> 6995.052 | R203: =IF(H203="None","—",IF(H203="KM","Rs./km","Rs./hr")) -> Rs./hr
A204: 192 | B204: HEX-23 | C204: — | D204: Excavator | E204: Kobelko 200 | F204: 2015 | G204: Diesel | H204: Hour | I204: Standard 20t | J204: L/hr | K204: 11.5 | L204: 16 | M204: 21.6 | N204: =1+MIN(MAX($D$8-F204,0),$D$10)*$D$9 -> 1.077 | O204: =IF(H204="None",0,IF(H204="KM",IF(G204="Petrol",$D$6,$D$5)*N204/K204,K204*N204*IF(G204="Petrol",$D$6,$D$5))) -> 5920.269 | P204: =IF(H204="None",0,IF(H204="KM",IF(G204="Petrol",$D$6,$D$5)*N204/L204,L204*N204*IF(G204="Petrol",$D$6,$D$5))) -> 8236.896 | Q204: =IF(H204="None",0,IF(H204="KM",IF(G204="Petrol",$D$6,$D$5)*N204/M204,M204*N204*IF(G204="Petrol",$D$6,$D$5))) -> 11119.81 | R204: =IF(H204="None","—",IF(H204="KM","Rs./km","Rs./hr")) -> Rs./hr
A205: 193 | B205: HEX-24 | C205: — | D205: Excavator | E205: Komatsu Pc-40Mr-1 | F205: 2012 | G205: Diesel | H205: Hour | I205: Mini 4t | J205: L/hr | K205: 2.9 | L205: 4 | M205: 5.4 | N205: =1+MIN(MAX($D$8-F205,0),$D$10)*$D$9 -> 1.098 | O205: =IF(H205="None",0,IF(H205="KM",IF(G205="Petrol",$D$6,$D$5)*N205/K205,K205*N205*IF(G205="Petrol",$D$6,$D$5))) -> 1522.0476 | P205: =IF(H205="None",0,IF(H205="KM",IF(G205="Petrol",$D$6,$D$5)*N205/L205,L205*N205*IF(G205="Petrol",$D$6,$D$5))) -> 2099.376 | Q205: =IF(H205="None",0,IF(H205="KM",IF(G205="Petrol",$D$6,$D$5)*N205/M205,M205*N205*IF(G205="Petrol",$D$6,$D$5))) -> 2834.1576 | R205: =IF(H205="None","—",IF(H205="KM","Rs./km","Rs./hr")) -> Rs./hr
A206: 194 | B206: HEX-25 | C206: 14160 | D206: Excavator | E206: Hyundai R230Lm | F206: 2017 | G206: Diesel | H206: Hour | I206: Standard 20-23t | J206: L/hr | K206: 11.5 | L206: 16 | M206: 21.6 | N206: =1+MIN(MAX($D$8-F206,0),$D$10)*$D$9 -> 1.063 | O206: =IF(H206="None",0,IF(H206="KM",IF(G206="Petrol",$D$6,$D$5)*N206/K206,K206*N206*IF(G206="Petrol",$D$6,$D$5))) -> 5843.311 | P206: =IF(H206="None",0,IF(H206="KM",IF(G206="Petrol",$D$6,$D$5)*N206/L206,L206*N206*IF(G206="Petrol",$D$6,$D$5))) -> 8129.824 | Q206: =IF(H206="None",0,IF(H206="KM",IF(G206="Petrol",$D$6,$D$5)*N206/M206,M206*N206*IF(G206="Petrol",$D$6,$D$5))) -> 10975.262 | R206: =IF(H206="None","—",IF(H206="KM","Rs./km","Rs./hr")) -> Rs./hr
A207: 195 | B207: HEX-26 | C207: — | D207: Excavator | E207: Hyundai Robex330Lc-9S | F207: — | G207: Diesel | H207: Hour | I207: Large 33t | J207: L/hr | K207: 15.8 | L207: 22 | M207: 29.7 | N207: =1 -> 1 | O207: =IF(H207="None",0,IF(H207="KM",IF(G207="Petrol",$D$6,$D$5)*N207/K207,K207*N207*IF(G207="Petrol",$D$6,$D$5))) -> 7552.4 | P207: =IF(H207="None",0,IF(H207="KM",IF(G207="Petrol",$D$6,$D$5)*N207/L207,L207*N207*IF(G207="Petrol",$D$6,$D$5))) -> 10516 | Q207: =IF(H207="None",0,IF(H207="KM",IF(G207="Petrol",$D$6,$D$5)*N207/M207,M207*N207*IF(G207="Petrol",$D$6,$D$5))) -> 14196.6 | R207: =IF(H207="None","—",IF(H207="KM","Rs./km","Rs./hr")) -> Rs./hr
A208: 196 | B208: HEX-27 | C208: — | D208: Excavator | E208: Hyundai E55W | F208: — | G208: Diesel | H208: Hour | I208: Mini 5.5t | J208: L/hr | K208: 2.9 | L208: 4 | M208: 5.4 | N208: =1 -> 1 | O208: =IF(H208="None",0,IF(H208="KM",IF(G208="Petrol",$D$6,$D$5)*N208/K208,K208*N208*IF(G208="Petrol",$D$6,$D$5))) -> 1386.2 | P208: =IF(H208="None",0,IF(H208="KM",IF(G208="Petrol",$D$6,$D$5)*N208/L208,L208*N208*IF(G208="Petrol",$D$6,$D$5))) -> 1912 | Q208: =IF(H208="None",0,IF(H208="KM",IF(G208="Petrol",$D$6,$D$5)*N208/M208,M208*N208*IF(G208="Petrol",$D$6,$D$5))) -> 2581.2 | R208: =IF(H208="None","—",IF(H208="KM","Rs./km","Rs./hr")) -> Rs./hr
A209: 197 | B209: HEX-28 | C209: — | D209: Excavator | E209: Komatsu Pc-60-6 | F209: 2012 | G209: Diesel | H209: Hour | I209: Mini 6t | J209: L/hr | K209: 2.9 | L209: 4 | M209: 5.4 | N209: =1+MIN(MAX($D$8-F209,0),$D$10)*$D$9 -> 1.098 | O209: =IF(H209="None",0,IF(H209="KM",IF(G209="Petrol",$D$6,$D$5)*N209/K209,K209*N209*IF(G209="Petrol",$D$6,$D$5))) -> 1522.0476 | P209: =IF(H209="None",0,IF(H209="KM",IF(G209="Petrol",$D$6,$D$5)*N209/L209,L209*N209*IF(G209="Petrol",$D$6,$D$5))) -> 2099.376 | Q209: =IF(H209="None",0,IF(H209="KM",IF(G209="Petrol",$D$6,$D$5)*N209/M209,M209*N209*IF(G209="Petrol",$D$6,$D$5))) -> 2834.1576 | R209: =IF(H209="None","—",IF(H209="KM","Rs./km","Rs./hr")) -> Rs./hr
A210: 198 | B210: HEX-29 | C210: — | D210: Excavator | E210: Cat Cat308Ccr | F210: 2013 | G210: Diesel | H210: Hour | I210: Compact 8t | J210: L/hr | K210: 4.7 | L210: 6.5 | M210: 8.8 | N210: =1+MIN(MAX($D$8-F210,0),$D$10)*$D$9 -> 1.091 | O210: =IF(H210="None",0,IF(H210="KM",IF(G210="Petrol",$D$6,$D$5)*N210/K210,K210*N210*IF(G210="Petrol",$D$6,$D$5))) -> 2451.0406 | P210: =IF(H210="None",0,IF(H210="KM",IF(G210="Petrol",$D$6,$D$5)*N210/L210,L210*N210*IF(G210="Petrol",$D$6,$D$5))) -> 3389.737 | Q210: =IF(H210="None",0,IF(H210="KM",IF(G210="Petrol",$D$6,$D$5)*N210/M210,M210*N210*IF(G210="Petrol",$D$6,$D$5))) -> 4589.1824 | R210: =IF(H210="None","—",IF(H210="KM","Rs./km","Rs./hr")) -> Rs./hr
A211: 199 | B211: HEX-31 | C211: — | D211: Excavator | E211: Komatsu Pc-30 | F211: 2014 | G211: Diesel | H211: Hour | I211: Mini 3t | J211: L/hr | K211: 2.9 | L211: 4 | M211: 5.4 | N211: =1+MIN(MAX($D$8-F211,0),$D$10)*$D$9 -> 1.084 | O211: =IF(H211="None",0,IF(H211="KM",IF(G211="Petrol",$D$6,$D$5)*N211/K211,K211*N211*IF(G211="Petrol",$D$6,$D$5))) -> 1502.6408 | P211: =IF(H211="None",0,IF(H211="KM",IF(G211="Petrol",$D$6,$D$5)*N211/L211,L211*N211*IF(G211="Petrol",$D$6,$D$5))) -> 2072.608 | Q211: =IF(H211="None",0,IF(H211="KM",IF(G211="Petrol",$D$6,$D$5)*N211/M211,M211*N211*IF(G211="Petrol",$D$6,$D$5))) -> 2798.0208 | R211: =IF(H211="None","—",IF(H211="KM","Rs./km","Rs./hr")) -> Rs./hr
A212: 200 | B212: HEX-32 | C212: 14160 | D212: Excavator | E212: Hyundai R230Lm | F212: 2017 | G212: Diesel | H212: Hour | I212: Standard 20-23t | J212: L/hr | K212: 11.5 | L212: 16 | M212: 21.6 | N212: =1+MIN(MAX($D$8-F212,0),$D$10)*$D$9 -> 1.063 | O212: =IF(H212="None",0,IF(H212="KM",IF(G212="Petrol",$D$6,$D$5)*N212/K212,K212*N212*IF(G212="Petrol",$D$6,$D$5))) -> 5843.311 | P212: =IF(H212="None",0,IF(H212="KM",IF(G212="Petrol",$D$6,$D$5)*N212/L212,L212*N212*IF(G212="Petrol",$D$6,$D$5))) -> 8129.824 | Q212: =IF(H212="None",0,IF(H212="KM",IF(G212="Petrol",$D$6,$D$5)*N212/M212,M212*N212*IF(G212="Petrol",$D$6,$D$5))) -> 10975.262 | R212: =IF(H212="None","—",IF(H212="KM","Rs./km","Rs./hr")) -> Rs./hr
A213: 201 | B213: HEX-33 | C213: 14160 | D213: Excavator | E213: Hyundai R230Lm | F213: 2017 | G213: Diesel | H213: Hour | I213: Standard 20-23t | J213: L/hr | K213: 11.5 | L213: 16 | M213: 21.6 | N213: =1+MIN(MAX($D$8-F213,0),$D$10)*$D$9 -> 1.063 | O213: =IF(H213="None",0,IF(H213="KM",IF(G213="Petrol",$D$6,$D$5)*N213/K213,K213*N213*IF(G213="Petrol",$D$6,$D$5))) -> 5843.311 | P213: =IF(H213="None",0,IF(H213="KM",IF(G213="Petrol",$D$6,$D$5)*N213/L213,L213*N213*IF(G213="Petrol",$D$6,$D$5))) -> 8129.824 | Q213: =IF(H213="None",0,IF(H213="KM",IF(G213="Petrol",$D$6,$D$5)*N213/M213,M213*N213*IF(G213="Petrol",$D$6,$D$5))) -> 10975.262 | R213: =IF(H213="None","—",IF(H213="KM","Rs./km","Rs./hr")) -> Rs./hr
A214: 202 | B214: HEX-34 | C214: — | D214: Excavator | E214: Hyundai R220Lc-9S | F214: 2017 | G214: Diesel | H214: Hour | I214: Standard 22t | J214: L/hr | K214: 11.5 | L214: 16 | M214: 21.6 | N214: =1+MIN(MAX($D$8-F214,0),$D$10)*$D$9 -> 1.063 | O214: =IF(H214="None",0,IF(H214="KM",IF(G214="Petrol",$D$6,$D$5)*N214/K214,K214*N214*IF(G214="Petrol",$D$6,$D$5))) -> 5843.311 | P214: =IF(H214="None",0,IF(H214="KM",IF(G214="Petrol",$D$6,$D$5)*N214/L214,L214*N214*IF(G214="Petrol",$D$6,$D$5))) -> 8129.824 | Q214: =IF(H214="None",0,IF(H214="KM",IF(G214="Petrol",$D$6,$D$5)*N214/M214,M214*N214*IF(G214="Petrol",$D$6,$D$5))) -> 10975.262 | R214: =IF(H214="None","—",IF(H214="KM","Rs./km","Rs./hr")) -> Rs./hr
A215: 203 | B215: HEX-35 | C215: 14160 | D215: Excavator | E215: Hyundai R230Lm | F215: 2017 | G215: Diesel | H215: Hour | I215: Standard 20-23t | J215: L/hr | K215: 11.5 | L215: 16 | M215: 21.6 | N215: =1+MIN(MAX($D$8-F215,0),$D$10)*$D$9 -> 1.063 | O215: =IF(H215="None",0,IF(H215="KM",IF(G215="Petrol",$D$6,$D$5)*N215/K215,K215*N215*IF(G215="Petrol",$D$6,$D$5))) -> 5843.311 | P215: =IF(H215="None",0,IF(H215="KM",IF(G215="Petrol",$D$6,$D$5)*N215/L215,L215*N215*IF(G215="Petrol",$D$6,$D$5))) -> 8129.824 | Q215: =IF(H215="None",0,IF(H215="KM",IF(G215="Petrol",$D$6,$D$5)*N215/M215,M215*N215*IF(G215="Petrol",$D$6,$D$5))) -> 10975.262 | R215: =IF(H215="None","—",IF(H215="KM","Rs./km","Rs./hr")) -> Rs./hr
A216: 204 | B216: HEX-36 | C216: — | D216: Excavator | E216: Hyundai E55W | F216: 2018 | G216: Diesel | H216: Hour | I216: Mini 5.5t | J216: L/hr | K216: 2.9 | L216: 4 | M216: 5.4 | N216: =1+MIN(MAX($D$8-F216,0),$D$10)*$D$9 -> 1.056 | O216: =IF(H216="None",0,IF(H216="KM",IF(G216="Petrol",$D$6,$D$5)*N216/K216,K216*N216*IF(G216="Petrol",$D$6,$D$5))) -> 1463.8272 | P216: =IF(H216="None",0,IF(H216="KM",IF(G216="Petrol",$D$6,$D$5)*N216/L216,L216*N216*IF(G216="Petrol",$D$6,$D$5))) -> 2019.072 | Q216: =IF(H216="None",0,IF(H216="KM",IF(G216="Petrol",$D$6,$D$5)*N216/M216,M216*N216*IF(G216="Petrol",$D$6,$D$5))) -> 2725.7472 | R216: =IF(H216="None","—",IF(H216="KM","Rs./km","Rs./hr")) -> Rs./hr
A217: 205 | B217: HEX-37 | C217: — | D217: Excavator | E217: Hyundai (Robex330Lc-96) | F217: — | G217: Diesel | H217: Hour | I217: Large 33t | J217: L/hr | K217: 15.8 | L217: 22 | M217: 29.7 | N217: =1 -> 1 | O217: =IF(H217="None",0,IF(H217="KM",IF(G217="Petrol",$D$6,$D$5)*N217/K217,K217*N217*IF(G217="Petrol",$D$6,$D$5))) -> 7552.4 | P217: =IF(H217="None",0,IF(H217="KM",IF(G217="Petrol",$D$6,$D$5)*N217/L217,L217*N217*IF(G217="Petrol",$D$6,$D$5))) -> 10516 | Q217: =IF(H217="None",0,IF(H217="KM",IF(G217="Petrol",$D$6,$D$5)*N217/M217,M217*N217*IF(G217="Petrol",$D$6,$D$5))) -> 14196.6 | R217: =IF(H217="None","—",IF(H217="KM","Rs./km","Rs./hr")) -> Rs./hr
A218: 206 | B218: HEX-38 | C218: 14160 | D218: Excavator | E218: Hyundai R230Lm | F218: 2017 | G218: Diesel | H218: Hour | I218: Standard 20-23t | J218: L/hr | K218: 11.5 | L218: 16 | M218: 21.6 | N218: =1+MIN(MAX($D$8-F218,0),$D$10)*$D$9 -> 1.063 | O218: =IF(H218="None",0,IF(H218="KM",IF(G218="Petrol",$D$6,$D$5)*N218/K218,K218*N218*IF(G218="Petrol",$D$6,$D$5))) -> 5843.311 | P218: =IF(H218="None",0,IF(H218="KM",IF(G218="Petrol",$D$6,$D$5)*N218/L218,L218*N218*IF(G218="Petrol",$D$6,$D$5))) -> 8129.824 | Q218: =IF(H218="None",0,IF(H218="KM",IF(G218="Petrol",$D$6,$D$5)*N218/M218,M218*N218*IF(G218="Petrol",$D$6,$D$5))) -> 10975.262 | R218: =IF(H218="None","—",IF(H218="KM","Rs./km","Rs./hr")) -> Rs./hr
A219: 207 | B219: HEX-39 | C219: — | D219: Excavator | E219: Hyundai R220Lc-9S | F219: 2017 | G219: Diesel | H219: Hour | I219: Standard 22t | J219: L/hr | K219: 11.5 | L219: 16 | M219: 21.6 | N219: =1+MIN(MAX($D$8-F219,0),$D$10)*$D$9 -> 1.063 | O219: =IF(H219="None",0,IF(H219="KM",IF(G219="Petrol",$D$6,$D$5)*N219/K219,K219*N219*IF(G219="Petrol",$D$6,$D$5))) -> 5843.311 | P219: =IF(H219="None",0,IF(H219="KM",IF(G219="Petrol",$D$6,$D$5)*N219/L219,L219*N219*IF(G219="Petrol",$D$6,$D$5))) -> 8129.824 | Q219: =IF(H219="None",0,IF(H219="KM",IF(G219="Petrol",$D$6,$D$5)*N219/M219,M219*N219*IF(G219="Petrol",$D$6,$D$5))) -> 10975.262 | R219: =IF(H219="None","—",IF(H219="KM","Rs./km","Rs./hr")) -> Rs./hr
A220: 208 | B220: HEX-40 | C220: — | D220: Excavator | E220: Santui Se210 | F220: — | G220: Diesel | H220: Hour | I220: Standard 21t | J220: L/hr | K220: 11.5 | L220: 16 | M220: 21.6 | N220: =1 -> 1 | O220: =IF(H220="None",0,IF(H220="KM",IF(G220="Petrol",$D$6,$D$5)*N220/K220,K220*N220*IF(G220="Petrol",$D$6,$D$5))) -> 5497 | P220: =IF(H220="None",0,IF(H220="KM",IF(G220="Petrol",$D$6,$D$5)*N220/L220,L220*N220*IF(G220="Petrol",$D$6,$D$5))) -> 7648 | Q220: =IF(H220="None",0,IF(H220="KM",IF(G220="Petrol",$D$6,$D$5)*N220/M220,M220*N220*IF(G220="Petrol",$D$6,$D$5))) -> 10324.8 | R220: =IF(H220="None","—",IF(H220="KM","Rs./km","Rs./hr")) -> Rs./hr
A221: 209 | B221: HEX-41 | C221: — | D221: Excavator | E221: Hyundai 220Lc-7 | F221: — | G221: Diesel | H221: Hour | I221: Standard 22t | J221: L/hr | K221: 11.5 | L221: 16 | M221: 21.6 | N221: =1 -> 1 | O221: =IF(H221="None",0,IF(H221="KM",IF(G221="Petrol",$D$6,$D$5)*N221/K221,K221*N221*IF(G221="Petrol",$D$6,$D$5))) -> 5497 | P221: =IF(H221="None",0,IF(H221="KM",IF(G221="Petrol",$D$6,$D$5)*N221/L221,L221*N221*IF(G221="Petrol",$D$6,$D$5))) -> 7648 | Q221: =IF(H221="None",0,IF(H221="KM",IF(G221="Petrol",$D$6,$D$5)*N221/M221,M221*N221*IF(G221="Petrol",$D$6,$D$5))) -> 10324.8 | R221: =IF(H221="None","—",IF(H221="KM","Rs./km","Rs./hr")) -> Rs./hr
A222: 210 | B222: HEX-42 | C222: — | D222: Excavator | E222: Case Cx220C Lc Hd | F222: 2021 | G222: Diesel | H222: Hour | I222: Standard 22t | J222: L/hr | K222: 11.5 | L222: 16 | M222: 21.6 | N222: =1+MIN(MAX($D$8-F222,0),$D$10)*$D$9 -> 1.035 | O222: =IF(H222="None",0,IF(H222="KM",IF(G222="Petrol",$D$6,$D$5)*N222/K222,K222*N222*IF(G222="Petrol",$D$6,$D$5))) -> 5689.395 | P222: =IF(H222="None",0,IF(H222="KM",IF(G222="Petrol",$D$6,$D$5)*N222/L222,L222*N222*IF(G222="Petrol",$D$6,$D$5))) -> 7915.68 | Q222: =IF(H222="None",0,IF(H222="KM",IF(G222="Petrol",$D$6,$D$5)*N222/M222,M222*N222*IF(G222="Petrol",$D$6,$D$5))) -> 10686.168 | R222: =IF(H222="None","—",IF(H222="KM","Rs./km","Rs./hr")) -> Rs./hr
A223: 211 | B223: HEX-43 | C223: — | D223: Excavator | E223: Case Cx220C Lc Hd | F223: 2021 | G223: Diesel | H223: Hour | I223: Standard 22t | J223: L/hr | K223: 11.5 | L223: 16 | M223: 21.6 | N223: =1+MIN(MAX($D$8-F223,0),$D$10)*$D$9 -> 1.035 | O223: =IF(H223="None",0,IF(H223="KM",IF(G223="Petrol",$D$6,$D$5)*N223/K223,K223*N223*IF(G223="Petrol",$D$6,$D$5))) -> 5689.395 | P223: =IF(H223="None",0,IF(H223="KM",IF(G223="Petrol",$D$6,$D$5)*N223/L223,L223*N223*IF(G223="Petrol",$D$6,$D$5))) -> 7915.68 | Q223: =IF(H223="None",0,IF(H223="KM",IF(G223="Petrol",$D$6,$D$5)*N223/M223,M223*N223*IF(G223="Petrol",$D$6,$D$5))) -> 10686.168 | R223: =IF(H223="None","—",IF(H223="KM","Rs./km","Rs./hr")) -> Rs./hr
A224: 212 | B224: HEX-44 | C224: — | D224: Excavator | E224: Kobelco Sx 120 | F224: — | G224: Diesel | H224: Hour | I224: Midi 12t | J224: L/hr | K224: 7.2 | L224: 10 | M224: 13.5 | N224: =1 -> 1 | O224: =IF(H224="None",0,IF(H224="KM",IF(G224="Petrol",$D$6,$D$5)*N224/K224,K224*N224*IF(G224="Petrol",$D$6,$D$5))) -> 3441.6 | P224: =IF(H224="None",0,IF(H224="KM",IF(G224="Petrol",$D$6,$D$5)*N224/L224,L224*N224*IF(G224="Petrol",$D$6,$D$5))) -> 4780 | Q224: =IF(H224="None",0,IF(H224="KM",IF(G224="Petrol",$D$6,$D$5)*N224/M224,M224*N224*IF(G224="Petrol",$D$6,$D$5))) -> 6453 | R224: =IF(H224="None","—",IF(H224="KM","Rs./km","Rs./hr")) -> Rs./hr
A225: 213 | B225: HEX-45 | C225: — | D225: Excavator | E225: Case Cx220C Lc Hd | F225: 2021 | G225: Diesel | H225: Hour | I225: Standard 22t | J225: L/hr | K225: 11.5 | L225: 16 | M225: 21.6 | N225: =1+MIN(MAX($D$8-F225,0),$D$10)*$D$9 -> 1.035 | O225: =IF(H225="None",0,IF(H225="KM",IF(G225="Petrol",$D$6,$D$5)*N225/K225,K225*N225*IF(G225="Petrol",$D$6,$D$5))) -> 5689.395 | P225: =IF(H225="None",0,IF(H225="KM",IF(G225="Petrol",$D$6,$D$5)*N225/L225,L225*N225*IF(G225="Petrol",$D$6,$D$5))) -> 7915.68 | Q225: =IF(H225="None",0,IF(H225="KM",IF(G225="Petrol",$D$6,$D$5)*N225/M225,M225*N225*IF(G225="Petrol",$D$6,$D$5))) -> 10686.168 | R225: =IF(H225="None","—",IF(H225="KM","Rs./km","Rs./hr")) -> Rs./hr
A226: 214 | B226: HEX-46 | C226: — | D226: Excavator | E226: Case Cx220C Lc Hd | F226: 2021 | G226: Diesel | H226: Hour | I226: Standard 22t | J226: L/hr | K226: 11.5 | L226: 16 | M226: 21.6 | N226: =1+MIN(MAX($D$8-F226,0),$D$10)*$D$9 -> 1.035 | O226: =IF(H226="None",0,IF(H226="KM",IF(G226="Petrol",$D$6,$D$5)*N226/K226,K226*N226*IF(G226="Petrol",$D$6,$D$5))) -> 5689.395 | P226: =IF(H226="None",0,IF(H226="KM",IF(G226="Petrol",$D$6,$D$5)*N226/L226,L226*N226*IF(G226="Petrol",$D$6,$D$5))) -> 7915.68 | Q226: =IF(H226="None",0,IF(H226="KM",IF(G226="Petrol",$D$6,$D$5)*N226/M226,M226*N226*IF(G226="Petrol",$D$6,$D$5))) -> 10686.168 | R226: =IF(H226="None","—",IF(H226="KM","Rs./km","Rs./hr")) -> Rs./hr
A227: 215 | B227: FT-02 | C227: 49-2289 | D227: Farm Tractor | E227: Massey Furguson 135 | F227: 1974 | G227: Diesel | H227: Hour | I227: Standard (class avg) | J227: L/hr | K227: 4.3 | L227: 6 | M227: 8.1 | N227: =1+MIN(MAX($D$8-F227,0),$D$10)*$D$9 -> 1.175 | O227: =IF(H227="None",0,IF(H227="KM",IF(G227="Petrol",$D$6,$D$5)*N227/K227,K227*N227*IF(G227="Petrol",$D$6,$D$5))) -> 2415.095 | P227: =IF(H227="None",0,IF(H227="KM",IF(G227="Petrol",$D$6,$D$5)*N227/L227,L227*N227*IF(G227="Petrol",$D$6,$D$5))) -> 3369.9 | Q227: =IF(H227="None",0,IF(H227="KM",IF(G227="Petrol",$D$6,$D$5)*N227/M227,M227*N227*IF(G227="Petrol",$D$6,$D$5))) -> 4549.365 | R227: =IF(H227="None","—",IF(H227="KM","Rs./km","Rs./hr")) -> Rs./hr
A228: 216 | B228: FT-03 | C228: RA-3051 | D228: Farm Tractor | E228: Tafe 45Di | F228: 2005 | G228: Diesel | H228: Hour | I228: Standard (class avg) | J228: L/hr | K228: 4.3 | L228: 6 | M228: 8.1 | N228: =1+MIN(MAX($D$8-F228,0),$D$10)*$D$9 -> 1.147 | O228: =IF(H228="None",0,IF(H228="KM",IF(G228="Petrol",$D$6,$D$5)*N228/K228,K228*N228*IF(G228="Petrol",$D$6,$D$5))) -> 2357.5438 | P228: =IF(H228="None",0,IF(H228="KM",IF(G228="Petrol",$D$6,$D$5)*N228/L228,L228*N228*IF(G228="Petrol",$D$6,$D$5))) -> 3289.596 | Q228: =IF(H228="None",0,IF(H228="KM",IF(G228="Petrol",$D$6,$D$5)*N228/M228,M228*N228*IF(G228="Petrol",$D$6,$D$5))) -> 4440.9546 | R228: =IF(H228="None","—",IF(H228="KM","Rs./km","Rs./hr")) -> Rs./hr
A229: 217 | B229: FT-04 | C229: RA-3052 | D229: Farm Tractor | E229: Tafe 45Di | F229: 2005 | G229: Diesel | H229: Hour | I229: Standard (class avg) | J229: L/hr | K229: 4.3 | L229: 6 | M229: 8.1 | N229: =1+MIN(MAX($D$8-F229,0),$D$10)*$D$9 -> 1.147 | O229: =IF(H229="None",0,IF(H229="KM",IF(G229="Petrol",$D$6,$D$5)*N229/K229,K229*N229*IF(G229="Petrol",$D$6,$D$5))) -> 2357.5438 | P229: =IF(H229="None",0,IF(H229="KM",IF(G229="Petrol",$D$6,$D$5)*N229/L229,L229*N229*IF(G229="Petrol",$D$6,$D$5))) -> 3289.596 | Q229: =IF(H229="None",0,IF(H229="KM",IF(G229="Petrol",$D$6,$D$5)*N229/M229,M229*N229*IF(G229="Petrol",$D$6,$D$5))) -> 4440.9546 | R229: =IF(H229="None","—",IF(H229="KM","Rs./km","Rs./hr")) -> Rs./hr
A230: 218 | B230: FT-05 | C230: RF-0748 | D230: Farm Tractor | E230: Massey Ferouson Mf 240 | F230: — | G230: Diesel | H230: Hour | I230: Standard (class avg) | J230: L/hr | K230: 4.3 | L230: 6 | M230: 8.1 | N230: =1 -> 1 | O230: =IF(H230="None",0,IF(H230="KM",IF(G230="Petrol",$D$6,$D$5)*N230/K230,K230*N230*IF(G230="Petrol",$D$6,$D$5))) -> 2055.4 | P230: =IF(H230="None",0,IF(H230="KM",IF(G230="Petrol",$D$6,$D$5)*N230/L230,L230*N230*IF(G230="Petrol",$D$6,$D$5))) -> 2868 | Q230: =IF(H230="None",0,IF(H230="KM",IF(G230="Petrol",$D$6,$D$5)*N230/M230,M230*N230*IF(G230="Petrol",$D$6,$D$5))) -> 3871.8 | R230: =IF(H230="None","—",IF(H230="KM","Rs./km","Rs./hr")) -> Rs./hr
...

Sheet Summary
A1: FLEET SUMMARY — Counts & Monthly Revenue Potential
A2: Monthly potential = unit count × average monthly WET rate (120 hrs, 85% volume discount) if every machine deployed 1 full month.
A4: # | B4: Category | C4: Unit count | D4: Avg. Hourly WET | E4: Avg. Monthly WET (120h) | F4: Category Monthly Revenue Potential
A5: 1 | B5: Backhoe Loader | C5: 24 | D5: =IFERROR(AVERAGEIF('Fleet Pricing'!B:B,B5,'Fleet Pricing'!H:H),0) -> 3704.5833 | E5: =IFERROR(AVERAGEIF('Fleet Pricing'!B:B,B5,'Fleet Pricing'!L:L),0) -> 377937.5 | F5: =C5*E5 -> 9070500
A6: 2 | B6: Wheel Loader | C6: 9 | D6: =IFERROR(AVERAGEIF('Fleet Pricing'!B:B,B6,'Fleet Pricing'!H:H),0) -> 7097.7778 | E6: =IFERROR(AVERAGEIF('Fleet Pricing'!B:B,B6,'Fleet Pricing'!L:L),0) -> 724055.56 | F6: =C6*E6 -> 6516500
A7: 3 | B7: Truck Mixer | C7: 16 | D7: =IFERROR(AVERAGEIF('Fleet Pricing'!B:B,B7,'Fleet Pricing'!H:H),0) -> 3780.625 | E7: =IFERROR(AVERAGEIF('Fleet Pricing'!B:B,B7,'Fleet Pricing'!L:L),0) -> 385656.25 | F7: =C7*E7 -> 6170500
A8: 4 | B8: Self Loader Mixer | C8: 3 | D8: =IFERROR(AVERAGEIF('Fleet Pricing'!B:B,B8,'Fleet Pricing'!H:H),0) -> 4880 | E8: =IFERROR(AVERAGEIF('Fleet Pricing'!B:B,B8,'Fleet Pricing'!L:L),0) -> 498000 | F8: =C8*E8 -> 1494000
A9: 5 | B9: Static Roller | C9: 19 | D9: =IFERROR(AVERAGEIF('Fleet Pricing'!B:B,B9,'Fleet Pricing'!H:H),0) -> 3602.1053 | E9: =IFERROR(AVERAGEIF('Fleet Pricing'!B:B,B9,'Fleet Pricing'!L:L),0) -> 367421.05 | F9: =C9*E9 -> 6981000
A10: 6 | B10: Vibrating Roller | C10: 72 | D10: =IFERROR(AVERAGEIF('Fleet Pricing'!B:B,B10,'Fleet Pricing'!H:H),0) -> 2716.6667 | E10: =IFERROR(AVERAGEIF('Fleet Pricing'!B:B,B10,'Fleet Pricing'!L:L),0) -> 277083.33 | F10: =C10*E10 -> 19950000
A11: 7 | B11: Pneumatic Roller | C11: 10 | D11: =IFERROR(AVERAGEIF('Fleet Pricing'!B:B,B11,'Fleet Pricing'!H:H),0) -> 2983 | E11: =IFERROR(AVERAGEIF('Fleet Pricing'!B:B,B11,'Fleet Pricing'!L:L),0) -> 304250 | F11: =C11*E11 -> 3042500
A12: 8 | B12: Motor Grader | C12: 16 | D12: =IFERROR(AVERAGEIF('Fleet Pricing'!B:B,B12,'Fleet Pricing'!H:H),0) -> 7094.375 | E12: =IFERROR(AVERAGEIF('Fleet Pricing'!B:B,B12,'Fleet Pricing'!L:L),0) -> 723593.75 | F12: =C12*E12 -> 11577500
A13: 9 | B13: Skid Steer | C13: 25 | D13: =IFERROR(AVERAGEIF('Fleet Pricing'!B:B,B13,'Fleet Pricing'!H:H),0) -> 2489.6 | E13: =IFERROR(AVERAGEIF('Fleet Pricing'!B:B,B13,'Fleet Pricing'!L:L),0) -> 254000 | F13: =C13*E13 -> 6350000
A14: 10 | B14: Asphalt Paver | C14: 11 | D14: =IFERROR(AVERAGEIF('Fleet Pricing'!B:B,B14,'Fleet Pricing'!H:H),0) -> 6381.8182 | E14: =IFERROR(AVERAGEIF('Fleet Pricing'!B:B,B14,'Fleet Pricing'!L:L),0) -> 650863.64 | F14: =C14*E14 -> 7159500
A15: 11 | B15: Bitumen Bowser | C15: 4 | D15: =IFERROR(AVERAGEIF('Fleet Pricing'!B:B,B15,'Fleet Pricing'!H:H),0) -> 2747.5 | E15: =IFERROR(AVERAGEIF('Fleet Pricing'!B:B,B15,'Fleet Pricing'!L:L),0) -> 280125 | F15: =C15*E15 -> 1120500
A16: 12 | B16: Mobile Crane | C16: 2 | D16: =IFERROR(AVERAGEIF('Fleet Pricing'!B:B,B16,'Fleet Pricing'!H:H),0) -> 5100 | E16: =IFERROR(AVERAGEIF('Fleet Pricing'!B:B,B16,'Fleet Pricing'!L:L),0) -> 520000 | F16: =C16*E16 -> 1040000
... A33: 29 | B33: Forklift | C33: 3 | D33: =IFERROR(AVERAGEIF('Fleet Pricing'!B:B,B33,'Fleet Pricing'!H:H),0) -> 1770 | E33: =IFERROR(AVERAGEIF('Fleet Pricing'!B:B,B33,'Fleet Pricing'!L:L),0) -> 180500 | F33: =C33*E33 -> 541500
B34: TOTAL FLEET | C34: =SUM(C5:C33) -> 518 | F34: =SUM(F5:F33) -> 159293500

Sheet Fleet Pricing
A1: FLEET PRICING 2026 — ALL 518 UNITS (engineered rates)
A2: Rates in LKR, excluding 18% VAT. Daily min. 4 hrs • Monthly min. 120 hrs. Driven by Rate Card sheet.
A4: # | B4: Category | C4: Brand | D4: E&C No. | E4: Model | F4: Year | G4: Registration No. | H4: Hourly WET | I4: Hourly DRY | J4: Daily WET (4h) | K4: Daily DRY (4h) | L4: Monthly WET (120h) | M4: Monthly DRY (120h) | N4: Remarks | O4: age_f | P4: size_m
A5: BACKHOE LOADER
A6: 1 | B6: Backhoe Loader | C6: BOB CAT | D6: LB-22 | E6: B760 | F6: 2021 | G6: ZB-2586 | H6: =MROUND('Rate Card'!$I$5*O6*P6,10) -> 4150 | I6: =MROUND('Rate Card'!$K$5*O6*P6,10) -> 2000 | J6: =MROUND(H6*4*'Rate Card'!$B$47,100) -> 15800 | K6: =MROUND(I6*4*'Rate Card'!$B$47,100) -> 7600 | L6: =MROUND(H6*120*'Rate Card'!$B$48,500) -> 423500 | M6: =MROUND(I6*120*'Rate Card'!$B$48,500) -> 204000 | O6: 1 | P6: 1
A7: 2 | B7: Backhoe Loader | C7: BOB CAT | D7: LB-23 | E7: B760 | F7: 2021 | G7: ZB-2587 | H7: =MROUND('Rate Card'!$I$5*O7*P7,10) -> 4150 | I7: =MROUND('Rate Card'!$K$5*O7*P7,10) -> 2000 | J7: =MROUND(H7*4*'Rate Card'!$B$47,100) -> 15800 | K7: =MROUND(I7*4*'Rate Card'!$B$47,100) -> 7600 | L7: =MROUND(H7*120*'Rate Card'!$B$48,500) -> 423500 | M7: =MROUND(I7*120*'Rate Card'!$B$48,500) -> 204000 | O7: 1 | P7: 1
A8: 3 | B8: Backhoe Loader | C8: BOB CAT | D8: LB-24 | E8: B760 | F8: 2021 | G8: ZB-2583 | H8: =MROUND('Rate Card'!$I$5*O8*P8,10) -> 4150 | I8: =MROUND('Rate Card'!$K$5*O8*P8,10) -> 2000 | J8: =MROUND(H8*4*'Rate Card'!$B$47,100) -> 15800 | K8: =MROUND(I8*4*'Rate Card'!$B$47,100) -> 7600 | L8: =MROUND(H8*120*'Rate Card'!$B$48,500) -> 423500 | M8: =MROUND(I8*120*'Rate Card'!$B$48,500) -> 204000 | O8: 1 | P8: 1
A9: 4 | B9: Backhoe Loader | C9: J.C.B | D9: LB-16 | E9: 3DX | F9: 2020 | G9: ZB-1547 | H9: =MROUND('Rate Card'!$I$5*O9*P9,10) -> 4150 | I9: =MROUND('Rate Card'!$K$5*O9*P9,10) -> 2000 | J9: =MROUND(H9*4*'Rate Card'!$B$47,100) -> 15800 | K9: =MROUND(I9*4*'Rate Card'!$B$47,100) -> 7600 | L9: =MROUND(H9*120*'Rate Card'!$B$48,500) -> 423500 | M9: =MROUND(I9*120*'Rate Card'!$B$48,500) -> 204000 | O9: 1 | P9: 1
A10: 5 | B10: Backhoe Loader | C10: JCB | D10: LB-02 | E10: 3DX | F10: 2012 | G10: ZA-2963 | H10: =MROUND('Rate Card'!$I$5*O10*P10,10) -> 4150 | I10: =MROUND('Rate Card'!$K$5*O10*P10,10) -> 2000 | J10: =MROUND(H10*4*'Rate Card'!$B$47,100) -> 15800 | K10: =MROUND(I10*4*'Rate Card'!$B$47,100) -> 7600 | L10: =MROUND(H10*120*'Rate Card'!$B$48,500) -> 423500 | M10: =MROUND(I10*120*'Rate Card'!$B$48,500) -> 204000 | O10: 1 | P10: 1
A11: 6 | B11: Backhoe Loader | C11: JCB | D11: LB-03 | E11: 3DX | F11: 2012 | G11: ZA-2964 | H11: =MROUND('Rate Card'!$I$5*O11*P11,10) -> 4150 | I11: =MROUND('Rate Card'!$K$5*O11*P11,10) -> 2000 | J11: =MROUND(H11*4*'Rate Card'!$B$47,100) -> 15800 | K11: =MROUND(I11*4*'Rate Card'!$B$47,100) -> 7600 | L11: =MROUND(H11*120*'Rate Card'!$B$48,500) -> 423500 | M11: =MROUND(I11*120*'Rate Card'!$B$48,500) -> 204000 | O11: 1 | P11: 1
A12: 7 | B12: Backhoe Loader | C12: JCB | D12: LB-09 | E12: 3DX | F12: 2015 | G12: ZA-6069 | H12: =MROUND('Rate Card'!$I$5*O12*P12,10) -> 4150 | I12: =MROUND('Rate Card'!$K$5*O12*P12,10) -> 2000 | J12: =MROUND(H12*4*'Rate Card'!$B$47,100) -> 15800 | K12: =MROUND(I12*4*'Rate Card'!$B$47,100) -> 7600 | L12: =MROUND(H12*120*'Rate Card'!$B$48,500) -> 423500 | M12: =MROUND(I12*120*'Rate Card'!$B$48,500) -> 204000 | O12: 1 | P12: 1
A13: 8 | B13: Backhoe Loader | C13: JCB | D13: LB-11 | E13: 3DX | F13: 2016 | G13: ZA-7092 | H13: =MROUND('Rate Card'!$I$5*O13*P13,10) -> 4150 | I13: =MROUND('Rate Card'!$K$5*O13*P13,10) -> 2000 | J13: =MROUND(H13*4*'Rate Card'!$B$47,100) -> 15800 | K13: =MROUND(I13*4*'Rate Card'!$B$47,100) -> 7600 | L13: =MROUND(H13*120*'Rate Card'!$B$48,500) -> 423500 | M13: =MROUND(I13*120*'Rate Card'!$B$48,500) -> 204000 | O13: 1 | P13: 1
A14: 9 | B14: Backhoe Loader | C14: JCB | D14: LB-13 | E14: 3DX | F14: 2016 | G14: ZA-7965 | H14: =MROUND('Rate Card'!$I$5*O14*P14,10) -> 4150 | I14: =MROUND('Rate Card'!$K$5*O14*P14,10) -> 2000 | J14: =MROUND(H14*4*'Rate Card'!$B$47,100) -> 15800 | K14: =MROUND(I14*4*'Rate Card'!$B$47,100) -> 7600 | L14: =MROUND(H14*120*'Rate Card'!$B$48,500) -> 423500 | M14: =MROUND(I14*120*'Rate Card'!$B$48,500) -> 204000 | O14: 1 | P14: 1
A15: 10 | B15: Backhoe Loader | C15: J.C.B | D15: LB-15 | E15: 570ST | F15: 2019 | G15: ZB-1047 | H15: =MROUND('Rate Card'!$I$5*O15*P15,10) -> 3820 | I15: =MROUND('Rate Card'!$K$5*O15*P15,10) -> 1840 | J15: =MROUND(H15*4*'Rate Card'!$B$47,100) -> 14500 | K15: =MROUND(I15*4*'Rate Card'!$B$47,100) -> 7000 | L15: =MROUND(H15*120*'Rate Card'!$B$48,500) -> 389500 | M15: =MROUND(I15*120*'Rate Card'!$B$48,500) -> 187500 | O15: 0.92 | P15: 1
A16: 11 | B16: Backhoe Loader | C16: JCB | D16: LB-10 | E16: JCB 3DX | F16: 2016 | G16: ZA-7034 | H16: =MROUND('Rate Card'!$I$5*O16*P16,10) -> 3820 | I16: =MROUND('Rate Card'!$K$5*O16*P16,10) -> 1840 | J16: =MROUND(H16*4*'Rate Card'!$B$47,100) -> 14500 | K16: =MROUND(I16*4*'Rate Card'!$B$47,100) -> 7000 | L16: =MROUND(H16*120*'Rate Card'!$B$48,500) -> 389500 | M16: =MROUND(I16*120*'Rate Card'!$B$48,500) -> 187500 | O16: 0.92 | P16: 1
A17: 12 | B17: Backhoe Loader | C17: JCB | D17: LB-14 | E17: JCB 3DX | F17: 2016 | G17: ZA-7968 | H17: =MROUND('Rate Card'!$I$5*O17*P17,10) -> 3820 | I17: =MROUND('Rate Card'!$K$5*O17*P17,10) -> 1840 | J17: =MROUND(H17*4*'Rate Card'!$B$47,100) -> 14500 | K17: =MROUND(I17*4*'Rate Card'!$B$47,100) -> 7000 | L17: =MROUND(H17*120*'Rate Card'!$B$48,500) -> 389500 | M17: =MROUND(I17*120*'Rate Card'!$B$48,500) -> 187500 | O17: 0.92 | P17: 1
... A25: 20 | B25: Backhoe Loader | C25: J.C.B | D25: LB-21 | E25: 3DX | F25: 2020 | G25: ZB-1980 | H25: =MROUND('Rate Card'!$I$5*O25*P25,10) -> 3400 | I25: =MROUND('Rate Card'!$K$5*O25*P25,10) -> 1640 | J25: =MROUND(H25*4*'Rate Card'!$B$47,100) -> 12900 | K25: =MROUND(I25*4*'Rate Card'!$B$47,100) -> 6200 | L25: =MROUND(H25*120*'Rate Card'!$B$48,500) -> 347000 | M25: =MROUND(I25*120*'Rate Card'!$B$48,500) -> 167500 | O25: 0.82 | P25: 1
A26: 21 | B26: Backhoe Loader | C26: JCB | D26: LB-05 | E26: 3DX | F26: 2006 | G26: RS-0483 | H26: =MROUND('Rate Card'!$I$5*O26*P26,10) -> 2990 | I26: =MROUND('Rate Card'!$K$5*O26*P26,10) -> 1440 | J26: =MROUND(H26*4*'Rate Card'!$B$47,100) -> 11400 | K26: =MROUND(I26*4*'Rate Card'!$B$47,100) -> 5500 | L26: =MROUND(H26*120*'Rate Card'!$B$48,500) -> 305000 | M26: =MROUND(I26*120*'Rate Card'!$B$48,500) -> 147000 | N26: age factor 72% | O26: 0.72 | P26: 1
A27: 22 | B27: Backhoe Loader | C27: JCB | D27: LB-07 | E27: JCB 3CX | F27: 2004 | G27: ZA-2608 | H27: =MROUND('Rate Card'!$I$5*O27*P27,10) -> 2700 | I27: =MROUND('Rate Card'!$K$5*O27*P27,10) -> 1300 | J27: =MROUND(H27*4*'Rate Card'!$B$47,100) -> 10300 | K27: =MROUND(I27*4*'Rate Card'!$B$47,100) -> 4900 | L27: =MROUND(H27*120*'Rate Card'!$B$48,500) -> 275500 | M27: =MROUND(I27*120*'Rate Card'!$B$48,500) -> 132500 | N27: age factor 65% | O27: 0.65 | P27: 1
A28: 23 | B28: Backhoe Loader | C28: JCB | D28: LB-06 | E28: 3CX | F28: 2002 | G28: ZA-0447 | H28: =MROUND('Rate Card'!$I$5*O28*P28,10) -> 2700 | I28: =MROUND('Rate Card'!$K$5*O28*P28,10) -> 1300 | J28: =MROUND(H28*4*'Rate Card'!$B$47,100) -> 10300 | K28: =MROUND(I28*4*'Rate Card'!$B$47,100) -> 4900 | L28: =MROUND(H28*120*'Rate Card'!$B$48,500) -> 275500 | M28: =MROUND(I28*120*'Rate Card'!$B$48,500) -> 132500 | N28: age factor 65% | O28: 0.65 | P28: 1
A29: 24 | B29: Backhoe Loader | C29: JCB | D29: LB-04 | E29: SLP3CX | F29: 1999 | G29: RS-0401 | H29: =MROUND('Rate Card'!$I$5*O29*P29,10) -> 2410 | I29: =MROUND('Rate Card'!$K$5*O29*P29,10) -> 1160 | J29: =MROUND(H29*4*'Rate Card'!$B$47,100) -> 9200 | K29: =MROUND(I29*4*'Rate Card'!$B$47,100) -> 4400 | L29: =MROUND(H29*120*'Rate Card'!$B$48,500) -> 246000 | M29: =MROUND(I29*120*'Rate Card'!$B$48,500) -> 118500 | N29: age factor 57% | O29: 0.58 | P29: 1
A30: WHEEL LOADER
A31: 25 | B31: Wheel Loader | C31: SHANTUI | D31: LD-09 | E31: SL-50WN | F31: 2020 | H31: =MROUND('Rate Card'!$I$6*O31*P31,10) -> 8450 | I31: =MROUND('Rate Card'!$K$6*O31*P31,10) -> 3800 | J31: =MROUND(H31*4*'Rate Card'!$B$47,100) -> 32100 | K31: =MROUND(I31*4*'Rate Card'!$B$47,100) -> 14400 | L31: =MROUND(H31*120*'Rate Card'!$B$48,500) -> 862000 | M31: =MROUND(I31*120*'Rate Card'!$B$48,500) -> 387500 | O31: 1 | P31: 1
A32: 26 | B32: Wheel Loader | C32: KOMATSU | D32: LD-07 | E32: WA-80SS | F32: 2015 | H32: =MROUND('Rate Card'!$I$6*O32*P32,10) -> 7770 | I32: =MROUND('Rate Card'!$K$6*O32*P32,10) -> 3500 | J32: =MROUND(H32*4*'Rate Card'!$B$47,100) -> 29500 | K32: =MROUND(I32*4*'Rate Card'!$B$47,100) -> 13300 | L32: =MROUND(H32*120*'Rate Card'!$B$48,500) -> 792500 | M32: =MROUND(I32*120*'Rate Card'!$B$48,500) -> 357000 | O32: 0.92 | P32: 1
A33: 27 | B33: Wheel Loader | C33: KOMATSU | D33: LD-05 | E33: WA150 | F33: 2014 | H33: =MROUND('Rate Card'!$I$6*O33*P33,10) -> 6930 | I33: =MROUND('Rate Card'!$K$6*O33*P33,10) -> 3120 | J33: =MROUND(H33*4*'Rate Card'!$B$47,100) -> 26300 | K33: =MROUND(I33*4*'Rate Card'!$B$47,100) -> 11900 | L33: =MROUND(H33*120*'Rate Card'!$B$48,500) -> 707000 | M33: =MROUND(I33*120*'Rate Card'!$B$48,500) -> 318000 | O33: 0.82 | P33: 1
A34: 28 | B34: Wheel Loader | C34: SANTUI | D34: LD-08 | E34: SL30W | F34: 2014 | H34: =MROUND('Rate Card'!$I$6*O34*P34,10) -> 6930 | I34: =MROUND('Rate Card'!$K$6*O34*P34,10) -> 3120 | J34: =MROUND(H34*4*'Rate Card'!$B$47,100) -> 26300 | K34: =MROUND(I34*4*'Rate Card'!$B$47,100) -> 11900 | L34: =MROUND(H34*120*'Rate Card'!$B$48,500) -> 707000 | M34: =MROUND(I34*120*'Rate Card'!$B$48,500) -> 318000 | O34: 0.82 | P34: 1
A35: 29 | B35: Wheel Loader | C35: KOMATSU | D35: LD-04 | E35: 924F | F35: 2013 | H35: =MROUND('Rate Card'!$I$6*O35*P35,10) -> 6930 | I35: =MROUND('Rate Card'!$K$6*O35*P35,10) -> 3120 | J35: =MROUND(H35*4*'Rate Card'!$B$47,100) -> 26300 | K35: =MROUND(I35*4*'Rate Card'!$B$47,100) -> 11900 | L35: =MROUND(H35*120*'Rate Card'!$B$48,500) -> 707000 | M35: =MROUND(I35*120*'Rate Card'!$B$48,500) -> 318000 | O35: 0.82 | P35: 1
A36: 30 | B36: Wheel Loader | C36: KOMATSU | D36: LD-06 | E36: 510 | F36: 2013 | G36: ZA-3116 | H36: =MROUND('Rate Card'!$I$6*O36*P36,10) -> 6930 | I36: =MROUND('Rate Card'!$K$6*O36*P36,10) -> 3120 | J36: =MROUND(H36*4*'Rate Card'!$B$47,100) -> 26300 | K36: =MROUND(I36*4*'Rate Card'!$B$47,100) -> 11900 | L36: =MROUND(H36*120*'Rate Card'!$B$48,500) -> 707000 | M36: =MROUND(I36*120*'Rate Card'!$B$48,500) -> 318000 | O36: 0.82 | P36: 1
A37: 31 | B37: Wheel Loader | C37: KOMATSU | D37: LD-03 | E37: WA100 | F37: 2012 | H37: =MROUND('Rate Card'!$I$6*O37*P37,10) -> 6930 | I37: =MROUND('Rate Card'!$K$6*O37*P37,10) -> 3120 | J37: =MROUND(H37*4*'Rate Card'!$B$47,100) -> 26300 | K37: =MROUND(I37*4*'Rate Card'!$B$47,100) -> 11900 | L37: =MROUND(H37*120*'Rate Card'!$B$48,500) -> 707000 | M37: =MROUND(I37*120*'Rate Card'!$B$48,500) -> 318000 | O37: 0.82 | P37: 1
A38: 32 | B38: Wheel Loader | C38: CAT | D38: LD-02 | E38: CAT910 | F38: 2010 | H38: =MROUND('Rate Card'!$I$6*O38*P38,10) -> 6930 | I38: =MROUND('Rate Card'!$K$6*O38*P38,10) -> 3120 | J38: =MROUND(H38*4*'Rate Card'!$B$47,100) -> 26300 | K38: =MROUND(I38*4*'Rate Card'!$B$47,100) -> 11900 | L38: =MROUND(H38*120*'Rate Card'!$B$48,500) -> 707000 | M38: =MROUND(I38*120*'Rate Card'!$B$48,500) -> 318000 | O38: 0.82 | P38: 1
A39: 33 | B39: Wheel Loader | C39: CAT | D39: LD-01 | E39: 910E | F39: 2009 | H39: =MROUND('Rate Card'!$I$6*O39*P39,10) -> 6080 | I39: =MROUND('Rate Card'!$K$6*O39*P39,10) -> 2740 | J39: =MROUND(H39*4*'Rate Card'!$B$47,100) -> 23100 | K39: =MROUND(I39*4*'Rate Card'!$B$47,100) -> 10400 | L39: =MROUND(H39*120*'Rate Card'!$B$48,500) -> 620000 | M39: =MROUND(I39*120*'Rate Card'!$B$48,500) -> 279500 | N39: age factor 72% | O39: 0.72 | P39: 1
A40: TRUCK MIXER
A41: 34 | B41: Truck Mixer | C41: TATA | D41: TM-18 | E41: LPK 1618 | F41: 2017 | G41: ZA-8511 | H41: =MROUND('Rate Card'!$I$7*O41*P41,10) -> 4460 | I41: =MROUND('Rate Card'!$K$7*O41*P41,10) -> 2250 | J41: =MROUND(H41*4*'Rate Card'!$B$47,100) -> 16900 | K41: =MROUND(I41*4*'Rate Card'!$B$47,100) -> 8600 | L41: =MROUND(H41*120*'Rate Card'!$B$48,500) -> 455000 | M41: =MROUND(I41*120*'Rate Card'!$B$48,500) -> 229500 | O41: 0.92 | P41: 1
A42: 35 | B42: Truck Mixer | C42: TATA | D42: TM-19 | E42: LPK 2518 | F42: 2017 | G42: ZA-8445 | H42: =MROUND('Rate Card'!$I$7*O42*P42,10) -> 4460 | I42: =MROUND('Rate Card'!$K$7*O42*P42,10) -> 2250 | J42: =MROUND(H42*4*'Rate Card'!$B$47,100) -> 16900 | K42: =MROUND(I42*4*'Rate Card'!$B$47,100) -> 8600 | L42: =MROUND(H42*120*'Rate Card'!$B$48,500) -> 455000 | M42: =MROUND(I42*120*'Rate Card'!$B$48,500) -> 229500 | O42: 0.92 | P42: 1
A43: 36 | B43: Truck Mixer | C43: TATA | D43: TM-15 | E43: LPK 1618 | F43: 2016 | G43: ZA-7925 | H43: =MROUND('Rate Card'!$I$7*O43*P43,10) -> 4460 | I43: =MROUND('Rate Card'!$K$7*O43*P43,10) -> 2250 | J43: =MROUND(H43*4*'Rate Card'!$B$47,100) -> 16900 | K43: =MROUND(I43*4*'Rate Card'!$B$47,100) -> 8600 | L43: =MROUND(H43*120*'Rate Card'!$B$48,500) -> 455000 | M43: =MROUND(I43*120*'Rate Card'!$B$48,500) -> 229500 | O43: 0.92 | P43: 1
A44: 37 | B44: Truck Mixer | C44: ELCHER | D44: TM-11 | E44: TERRA 16 | F44: 2016 | G44: ZA-7291 | H44: =MROUND('Rate Card'!$I$7*O44*P44,10) -> 4460 | I44: =MROUND('Rate Card'!$K$7*O44*P44,10) -> 2250 | J44: =MROUND(H44*4*'Rate Card'!$B$47,100) -> 16900 | K44: =MROUND(I44*4*'Rate Card'!$B$47,100) -> 8600 | L44: =MROUND(H44*120*'Rate Card'!$B$48,500) -> 455000 | M44: =MROUND(I44*120*'Rate Card'!$B$48,500) -> 229500 | O44: 0.92 | P44: 1
A45: 38 | B45: Truck Mixer | C45: ELCHER | D45: TM-12 | E45: TERRA 16 | F45: 2016 | G45: ZA-7290 | H45: =MROUND('Rate Card'!$I$7*O45*P45,10) -> 4460 | I45: =MROUND('Rate Card'!$K$7*O45*P45,10) -> 2250 | J45: =MROUND(H45*4*'Rate Card'!$B$47,100) -> 16900 | K45: =MROUND(I45*4*'Rate Card'!$B$47,100) -> 8600 | L45: =MROUND(H45*120*'Rate Card'!$B$48,500) -> 455000 | M45: =MROUND(I45*120*'Rate Card'!$B$48,500) -> 229500 | O45: 0.92 | P45: 1
A46: 39 | B46: Truck Mixer | C46: TATA | D46: TM-14 | E46: LPK 2518 | F46: 2016 | G46: ZA-7810 | H46: =MROUND('Rate Card'!$I$7*O46*P46,10) -> 4460 | I46: =MROUND('Rate Card'!$K$7*O46*P46,10) -> 2250 | J46: =MROUND(H46*4*'Rate Card'!$B$47,100) -> 16900 | K46: =MROUND(I46*4*'Rate Card'!$B$47,100) -> 8600 | L46: =MROUND(H46*120*'Rate Card'!$B$48,500) -> 455000 | M46: =MROUND(I46*120*'Rate Card'!$B$48,500) -> 229500 | O46: 0.92 | P46: 1
A47: 40 | B47: Truck Mixer | C47: TATA | D47: TM-16 | E47: LPK 2518 | F47: 2016 | G47: ZA-8033 | H47: =MROUND('Rate Card'!$I$7*O47*P47,10) -> 4460 | I47: =MROUND('Rate Card'!$K$7*O47*P47,10) -> 2250 | J47: =MROUND(H47*4*'Rate Card'!$B$47,100) -> 16900 | K47: =MROUND(I47*4*'Rate Card'!$B$47,100) -> 8600 | L47: =MROUND(H47*120*'Rate Card'!$B$48,500) -> 455000 | M47: =MROUND(I47*120*'Rate Card'!$B$48,500) -> 229500 | O47: 0.92 | P47: 1
A48: 41 | B48: Truck Mixer | C48: TATA | D48: TM-21 | E48: LPK 2518 | F48: 2017 | G48: ZA-0050 | H48: =MROUND('Rate Card'!$I$7*O48*P48,10) -> 4460 | I48: =MROUND('Rate Card'!$K$7*O48*P48,10) -> 2250 | J48: =MROUND(H48*4*'Rate Card'!$B$47,100) -> 16900 | K48: =MROUND(I48*4*'Rate Card'!$B$47,100) -> 8600 | L48: =MROUND(H48*120*'Rate Card'!$B$48,500) -> 455000 | M48: =MROUND(I48*120*'Rate Card'!$B$48,500) -> 229500 | O48: 0.92 | P48: 1
A49: 42 | B49: Truck Mixer | C49: ASHOK LEYLAND | D49: TM-10 | E49: TUSKER SUPER 1613 | F49: 2015 | G49: ZA-6395 | H49: =MROUND('Rate Card'!$I$7*O49*P49,10) -> 4460 | I49: =MROUND('Rate Card'!$K$7*O49*P49,10) -> 2250 | J49: =MROUND(H49*4*'Rate Card'!$B$47,100) -> 16900 | K49: =MROUND(I49*4*'Rate Card'!$B$47,100) -> 8600 | L49: =MROUND(H49*120*'Rate Card'!$B$48,500) -> 455000 | M49: =MROUND(I49*120*'Rate Card'!$B$48,500) -> 229500 | O49: 0.92 | P49: 1
A50: 43 | B50: Truck Mixer | C50: MITSUBISHI | D50: TM-09 | E50: KK-FE73EB CANTER | F50: 2003 | G50: ZA-6255 | H50: =MROUND('Rate Card'!$I$7*O50*P50,10) -> 3150 | I50: =MROUND('Rate Card'!$K$7*O50*P50,10) -> 1590 | J50: =MROUND(H50*4*'Rate Card'!$B$47,100) -> 12000 | K50: =MROUND(I50*4*'Rate Card'!$B$47,100) -> 6000 | L50: =MROUND(H50*120*'Rate Card'!$B$48,500) -> 321500 | M50: =MROUND(I50*120*'Rate Card'!$B$48,500) -> 162000 | N50: age factor 65% | O50: 0.65 | P50: 1
A51: 44 | B51: Truck Mixer | C51: ISUZU | D51: TM-04 | E51: KK-NRR35C4 FORWARD | F51: 2000 | G51: LL-0690 | H51: =MROUND('Rate Card'!$I$7*O51*P51,10) -> 3150 | I51: =MROUND('Rate Card'!$K$7*O51*P51,10) -> 1590 | J51: =MROUND(H51*4*'Rate Card'!$B$47,100) -> 12000 | K51: =MROUND(I51*4*'Rate Card'!$B$47,100) -> 6000 | L51: =MROUND(H51*120*'Rate Card'!$B$48,500) -> 321500 | M51: =MROUND(I51*120*'Rate Card'!$B$48,500) -> 162000 | N51: age factor 65% | O51: 0.65 | P51: 1
A52: 45 | B52: Truck Mixer | C52: ISUZU | D52: TM-03 | E52: KC-NRR33C20 | F52: 1996 | G52: LK-5047 | H52: =MROUND('Rate Card'!$I$7*O52*P52,10) -> 2810 | I52: =MROUND('Rate Card'!$K$7*O52*P52,10) -> 1420 | J52: =MROUND(H52*4*'Rate Card'!$B$47,100) -> 10700 | K52: =MROUND(I52*4*'Rate Card'!$B$47,100) -> 5400 | L52: =MROUND(H52*120*'Rate Card'!$B$48,500) -> 286500 | M52: =MROUND(I52*120*'Rate Card'!$B$48,500) -> 145000 | N52: age factor 57% | O52: 0.58 | P52: 1
A53: 46 | B53: Truck Mixer | C53: ISUZU | D53: TM-08 | E53: KC-NRR33C20 | F53: 1996 | G53: LJ-8055 | H53: =MROUND('Rate Card'!$I$7*O53*P53,10) -> 2810 | I53: =MROUND('Rate Card'!$K$7*O53*P53,10) -> 1420 | J53: =MROUND(H53*4*'Rate Card'!$B$47,100) -> 10700 | K53: =MROUND(I53*4*'Rate Card'!$B$47,100) -> 5400 | L53: =MROUND(H53*120*'Rate Card'!$B$48,500) -> 286500 | M53: =MROUND(I53*120*'Rate Card'!$B$48,500) -> 145000 | N53: age factor 57% | O53: 0.58 | P53: 1
A54: 47 | B54: Truck Mixer | C54: MITSUBISHI | D54: TM-01 | E54: KC-FH217C | F54: 1996 | G54: LK-5048 | H54: =MROUND('Rate Card'!$I$7*O54*P54,10) -> 2810 | I54: =MROUND('Rate Card'!$K$7*O54*P54,10) -> 1420 | J54: =MROUND(H54*4*'Rate Card'!$B$47,100) -> 10700 | K54: =MROUND(I54*4*'Rate Card'!$B$47,100) -> 5400 | L54: =MROUND(H54*120*'Rate Card'!$B$48,500) -> 286500 | M54: =MROUND(I54*120*'Rate Card'!$B$48,500) -> 145000 | N54: age factor 57% | O54: 0.58 | P54: 1
A55: 48 | B55: Truck Mixer | C55: MITSUBISHI | D55: TM-05 | E55: KC-FE517BN | F55: 1996 | G55: LH-5474 | H55: =MROUND('Rate Card'!$I$7*O55*P55,10) -> 2810 | I55: =MROUND('Rate Card'!$K$7*O55*P55,10) -> 1420 | J55: =MROUND(H55*4*'Rate Card'!$B$47,100) -> 10700 | K55: =MROUND(I55*4*'Rate Card'!$B$47,100) -> 5400 | L55: =MROUND(H55*120*'Rate Card'!$B$48,500) -> 286500 | M55: =MROUND(I55*120*'Rate Card'!$B$48,500) -> 145000 | N55: age factor 57% | O55: 0.58 | P55: 1
A56: 49 | B56: Truck Mixer | C56: MITSUBISHI | D56: TM-06 | E56: U.FE315BN | F56: 1991 | G56: LH-5475 | H56: =MROUND('Rate Card'!$I$7*O56*P56,10) -> 2810 | I56: =MROUND('Rate Card'!$K$7*O56*P56,10) -> 1420 | J56: =MROUND(H56*4*'Rate Card'!$B$47,100) -> 10700 | K56: =MROUND(I56*4*'Rate Card'!$B$47,100) -> 5400 | L56: =MROUND(H56*120*'Rate Card'!$B$48,500) -> 286500 | M56: =MROUND(I56*120*'Rate Card'!$B$48,500) -> 145000 | N56: age factor 57% | O56: 0.58 | P56: 1
A57: SELF LOADER MIXER
A58: 50 | B58: Self Loader Mixer | C58: FIORI | D58: TM-20 | E58: BF08H01307 | F58: 2018 | G58: Fiori | H58: =MROUND('Rate Card'!$I$8*O58*P58,10) -> 4880 | I58: =MROUND('Rate Card'!$K$8*O58*P58,10) -> 2440 | J58: =MROUND(H58*4*'Rate Card'!$B$47,100) -> 18500 | K58: =MROUND(I58*4*'Rate Card'!$B$47,100) -> 9300 | L58: =MROUND(H58*120*'Rate Card'!$B$48,500) -> 498000 | M58: =MROUND(I58*120*'Rate Card'!$B$48,500) -> 249000 | O58: 0.92 | P58: 1
A59: 51 | B59: Self Loader Mixer | C59: FIORI | D59: TM-13 | E59: 8FO8H01246 | F59: 2017 | G59: Fiori | H59: =MROUND('Rate Card'!$I$8*O59*P59,10) -> 4880 | I59: =MROUND('Rate Card'!$K$8*O59*P59,10) -> 2440 | J59: =MROUND(H59*4*'Rate Card'!$B$47,100) -> 18500 | K59: =MROUND(I59*4*'Rate Card'!$B$47,100) -> 9300 | L59: =MROUND(H59*120*'Rate Card'!$B$48,500) -> 498000 | M59: =MROUND(I59*120*'Rate Card'!$B$48,500) -> 249000 | O59: 0.92 | P59: 1
A60: 52 | B60: Self Loader Mixer | C60: FIORI | D60: TM-17 | E60: 8FO8H01252 | F60: 2017 | G60: Fiori | H60: =MROUND('Rate Card'!$I$8*O60*P60,10) -> 4880 | I60: =MROUND('Rate Card'!$K$8*O60*P60,10) -> 2440 | J60: =MROUND(H60*4*'Rate Card'!$B$47,100) -> 18500 | K60: =MROUND(I60*4*'Rate Card'!$B$47,100) -> 9300 | L60: =MROUND(H60*120*'Rate Card'!$B$48,500) -> 498000 | M60: =MROUND(I60*120*'Rate Card'!$B$48,500) -> 249000 | O60: 0.92 | P60: 1
A61: STATIC ROLLER
A62: 53 | B62: Static Roller | C62: DYNAPAC | D62: SR-17 | E62: CC425 | F62: 2021 | H62: =MROUND('Rate Card'!$I$9*O62*P62,10) -> 4600 | I62: =MROUND('Rate Card'!$K$9*O62*P62,10) -> 2300 | J62: =MROUND(H62*4*'Rate Card'!$B$47,100) -> 17500 | K62: =MROUND(I62*4*'Rate Card'!$B$47,100) -> 8700 | L62: =MROUND(H62*120*'Rate Card'!$B$48,500) -> 469000 | M62: =MROUND(I62*120*'Rate Card'!$B$48,500) -> 234500 | O62: 1 | P62: 1
A63: 54 | B63: Static Roller | C63: DYNAPAC | D63: SR-18 | E63: CA30D | F63: 2021 | H63: =MROUND('Rate Card'!$I$9*O63*P63,10) -> 4600 | I63: =MROUND('Rate Card'!$K$9*O63*P63,10) -> 2300 | J63: =MROUND(H63*4*'Rate Card'!$B$47,100) -> 17500 | K63: =MROUND(I63*4*'Rate Card'!$B$47,100) -> 8700 | L63: =MROUND(H63*120*'Rate Card'!$B$48,500) -> 469000 | M63: =MROUND(I63*120*'Rate Card'!$B$48,500) -> 234500 | O63: 1 | P63: 1
A64: 55 | B64: Static Roller | C64: DYNAPAC | D64: SR-19 | E64: CA30D | F64: 2021 | H64: =MROUND('Rate Card'!$I$9*O64*P64,10) -> 4600 | I64: =MROUND('Rate Card'!$K$9*O64*P64,10) -> 2300 | J64: =MROUND(H64*4*'Rate Card'!$B$47,100) -> 17500 | K64: =MROUND(I64*4*'Rate Card'!$B$47,100) -> 8700 | L64: =MROUND(H64*120*'Rate Card'!$B$48,500) -> 469000 | M64: =MROUND(I64*120*'Rate Card'!$B$48,500) -> 234500 | O64: 1 | P64: 1
A65: 56 | B65: Static Roller | C65: CASE | D65: SR-08 | E65: 1107EXD | F65: 2017 | H65: =MROUND('Rate Card'!$I$9*O65*P65,10) -> 4230 | I65: =MROUND('Rate Card'!$K$9*O65*P65,10) -> 2120 | J65: =MROUND(H65*4*'Rate Card'!$B$47,100) -> 16100 | K65: =MROUND(I65*4*'Rate Card'!$B$47,100) -> 8100 | L65: =MROUND(H65*120*'Rate Card'!$B$48,500) -> 431500 | M65: =MROUND(I65*120*'Rate Card'!$B$48,500) -> 216000 | O65: 0.92 | P65: 1
A66: 57 | B66: Static Roller | C66: MACADAM | D66: SR-15 | E66: 1107EXD | F66: 2017 | H66: =MROUND('Rate Card'!$I$9*O66*P66,10) -> 4230 | I66: =MROUND('Rate Card'!$K$9*O66*P66,10) -> 2120 | J66: =MROUND(H66*4*'Rate Card'!$B$47,100) -> 16100 | K66: =MROUND(I66*4*'Rate Card'!$B$47,100) -> 8100 | L66: =MROUND(H66*120*'Rate Card'!$B$48,500) -> 431500 | M66: =MROUND(I66*120*'Rate Card'!$B$48,500) -> 216000 | O66: 0.92 | P66: 1
A67: 58 | B67: Static Roller | C67: HAMM | D67: SR-12 | E67: HAMM 311D | F67: 2016 | H67: =MROUND('Rate Card'!$I$9*O67*P67,10) -> 4230 | I67: =MROUND('Rate Card'!$K$9*O67*P67,10) -> 2120 | J67: =MROUND(H67*4*'Rate Card'!$B$47,100) -> 16100 | K67: =MROUND(I67*4*'Rate Card'!$B$47,100) -> 8100 | L67: =MROUND(H67*120*'Rate Card'!$B$48,500) -> 431500 | M67: =MROUND(I67*120*'Rate Card'!$B$48,500) -> 216000 | O67: 0.92 | P67: 1
A68: 59 | B68: Static Roller | C68: CASE | D68: SR-01 | E68: — | F68: 2012 | H68: =MROUND('Rate Card'!$I$9*O68*P68,10) -> 3770 | I68: =MROUND('Rate Card'!$K$9*O68*P68,10) -> 1890 | J68: =MROUND(H68*4*'Rate Card'!$B$47,100) -> 14300 | K68: =MROUND(I68*4*'Rate Card'!$B$47,100) -> 7200 | L68: =MROUND(H68*120*'Rate Card'!$B$48,500) -> 384500 | M68: =MROUND(I68*120*'Rate Card'!$B$48,500) -> 193000 | O68: 0.82 | P68: 1
A69: 60 | B69: Static Roller | C69: SAKAI | D69: SR-05 | E69: SW-900 | F69: 2014 | H69: =MROUND('Rate Card'!$I$9*O69*P69,10) -> 3770 | I69: =MROUND('Rate Card'!$K$9*O69*P69,10) -> 1890 | J69: =MROUND(H69*4*'Rate Card'!$B$47,100) -> 14300 | K69: =MROUND(I69*4*'Rate Card'!$B$47,100) -> 7200 | L69: =MROUND(H69*120*'Rate Card'!$B$48,500) -> 384500 | M69: =MROUND(I69*120*'Rate Card'!$B$48,500) -> 193000 | O69: 0.82 | P69: 1
A70: 61 | B70: Static Roller | C70: (Unknown) | D70: SR-02 | E70: R12 | F70: 2009 | H70: =MROUND('Rate Card'!$I$9*O70*P70,10) -> 3770 | I70: =MROUND('Rate Card'!$K$9*O70*P70,10) -> 1890 | J70: =MROUND(H70*4*'Rate Card'!$B$47,100) -> 14300 | K70: =MROUND(I70*4*'Rate Card'!$B$47,100) -> 7200 | L70: =MROUND(H70*120*'Rate Card'!$B$48,500) -> 384500 | M70: =MROUND(I70*120*'Rate Card'!$B$48,500) -> 193000 | O70: 0.82 | P70: 1
A71: 62 | B71: Static Roller | C71: (Unknown) | D71: SR-03 | E71: — | F71: 2012 | H71: =MROUND('Rate Card'!$I$9*O71*P71,10) -> 3770 | I71: =MROUND('Rate Card'!$K$9*O71*P71,10) -> 1890 | J71: =MROUND(H71*4*'Rate Card'!$B$47,100) -> 14300 | K71: =MROUND(I71*4*'Rate Card'!$B$47,100) -> 7200 | L71: =MROUND(H71*120*'Rate Card'!$B$48,500) -> 384500 | M71: =MROUND(I71*120*'Rate Card'!$B$48,500) -> 193000 | O71: 0.82 | P71: 1
A72: 63 | B72: Static Roller | C72: (Unknown) | D72: SR-04 | E72: — | F72: 2013 | H72: =MROUND('Rate Card'!$I$9*O72*P72,10) -> 3770 | I72: =MROUND('Rate Card'!$K$9*O72*P72,10) -> 1890 | J72: =MROUND(H72*4*'Rate Card'!$B$47,100) -> 14300 | K72: =MROUND(I72*4*'Rate Card'!$B$47,100) -> 7200 | L72: =MROUND(H72*120*'Rate Card'!$B$48,500) -> 384500 | M72: =MROUND(I72*120*'Rate Card'!$B$48,500) -> 193000 | O72: 0.82 | P72: 1
A73: 64 | B73: Static Roller | C73: IR | D73: SR-07 | E73: 2860-01 | F73: 2010 | H73: =MROUND('Rate Card'!$I$9*O73*P73,10) -> 3770 | I73: =MROUND('Rate Card'!$K$9*O73*P73,10) -> 1890 | J73: =MROUND(H73*4*'Rate Card'!$B$47,100) -> 14300 | K73: =MROUND(I73*4*'Rate Card'!$B$47,100) -> 7200 | L73: =MROUND(H73*120*'Rate Card'!$B$48,500) -> 384500 | M73: =MROUND(I73*120*'Rate Card'!$B$48,500) -> 193000 | O73: 0.82 | P73: 1
A74: 65 | B74: Static Roller | C74: CASE | D74: SR-06 | E74: — | F74: 2014 | H74: =MROUND('Rate Card'!$I$9*O74*P74,10) -> 3310 | I74: =MROUND('Rate Card'!$K$9*O74*P74,10) -> 1660 | J74: =MROUND(H74*4*'Rate Card'!$B$47,100) -> 12600 | K74: =MROUND(I74*4*'Rate Card'!$B$47,100) -> 6300 | L74: =MROUND(H74*120*'Rate Card'!$B$48,500) -> 337500 | M74: =MROUND(I74*120*'Rate Card'!$B$48,500) -> 169500 | N74: age factor 72% | O74: 0.72 | P74: 1
A75: 66 | B75: Static Roller | C75: CASE | D75: SR-09 | E75: — | F75: — | H75: =MROUND('Rate Card'!$I$9*O75*P75,10) -> 2670 | I75: =MROUND('Rate Card'!$K$9*O75*P75,10) -> 1330 | J75: =MROUND(H75*4*'Rate Card'!$B$47,100) -> 10100 | K75: =MROUND(I75*4*'Rate Card'!$B$47,100) -> 5100 | L75: =MROUND(H75*120*'Rate Card'!$B$48,500) -> 272500 | M75: =MROUND(I75*120*'Rate Card'!$B$48,500) -> 135500 | N75: year unknown → 58% factor | O75: 0.58 | P75: 1
A76: 67 | B76: Static Roller | C76: DYNAPAC | D76: SR-13 | E76: CA250D | F76: — | H76: =MROUND('Rate Card'!$I$9*O76*P76,10) -> 2670 | I76: =MROUND('Rate Card'!$K$9*O76*P76,10) -> 1330 | J76: =MROUND(H76*4*'Rate Card'!$B$47,100) -> 10100 | K76: =MROUND(I76*4*'Rate Card'!$B$47,100) -> 5100 | L76: =MROUND(H76*120*'Rate Card'!$B$48,500) -> 272500 | M76: =MROUND(I76*120*'Rate Card'!$B$48,500) -> 135500 | N76: year unknown → 58% factor | O76: 0.58 | P76: 1
A77: 68 | B77: Static Roller | C77: DYNAPAC | D77: SR-16 | E77: CA30D | F77: — | H77: =MROUND('Rate Card'!$I$9*O77*P77,10) -> 2670 | I77: =MROUND('Rate Card'!$K$9*O77*P77,10) -> 1330 | J77: =MROUND(H77*4*'Rate Card'!$B$47,100) -> 10100 | K77: =MROUND(I77*4*'Rate Card'!$B$47,100) -> 5100 | L77: =MROUND(H77*120*'Rate Card'!$B$48,500) -> 272500 | M77: =MROUND(I77*120*'Rate Card'!$B$48,500) -> 135500 | N77: year unknown → 58% factor | O77: 0.58 | P77: 1
A78: 69 | B78: Static Roller | C78: HAMM | D78: SR-11 | E78: HAMM 311D | F78: — | H78: =MROUND('Rate Card'!$I$9*O78*P78,10) -> 2670 | I78: =MROUND('Rate Card'!$K$9*O78*P78,10) -> 1330 | J78: =MROUND(H78*4*'Rate Card'!$B$47,100) -> 10100 | K78: =MROUND(I78*4*'Rate Card'!$B$47,100) -> 5100 | L78: =MROUND(H78*120*'Rate Card'!$B$48,500) -> 272500 | M78: =MROUND(I78*120*'Rate Card'!$B$48,500) -> 135500 | N78: year unknown → 58% factor | O78: 0.58 | P78: 1
A79: 70 | B79: Static Roller | C79: MACADAM | D79: SR-10 | E79: — | F79: — | H79: =MROUND('Rate Card'!$I$9*O79*P79,10) -> 2670 | I79: =MROUND('Rate Card'!$K$9*O79*P79,10) -> 1330 | J79: =MROUND(H79*4*'Rate Card'!$B$47,100) -> 10100 | K79: =MROUND(I79*4*'Rate Card'!$B$47,100) -> 5100 | L79: =MROUND(H79*120*'Rate Card'!$B$48,500) -> 272500 | M79: =MROUND(I79*120*'Rate Card'!$B$48,500) -> 135500 | N79: year unknown → 58% factor | O79: 0.58 | P79: 1
A80: 71 | B80: Static Roller | C80: SAKAI | D80: SR-14 | E80: R2V | F80: — | H80: =MROUND('Rate Card'!$I$9*O80*P80,10) -> 2670 | I80: =MROUND('Rate Card'!$K$9*O80*P80,10) -> 1330 | J80: =MROUND(H80*4*'Rate Card'!$B$47,100) -> 10100 | K80: =MROUND(I80*4*'Rate Card'!$B$47,100) -> 5100 | L80: =MROUND(H80*120*'Rate Card'!$B$48,500) -> 272500 | M80: =MROUND(I80*120*'Rate Card'!$B$48,500) -> 135500 | N80: year unknown → 58% factor | O80: 0.58 | P80: 1
A81: VIBRATING ROLLER
A82: 72 | B82: Vibrating Roller | C82: (Unknown) | D82: VR-01 | E82: — | F82: 2010 | H82: =MROUND('Rate Card'!$I$10*O82*P82,10) -> 3590 | I82: =MROUND('Rate Card'!$K$10*O82*P82,10) -> 1790 | J82: =MROUND(H82*4*'Rate Card'!$B$47,100) -> 13600 | K82: =MROUND(I82*4*'Rate Card'!$B$47,100) -> 6800 | L82: =MROUND(H82*120*'Rate Card'!$B$48,500) -> 366000 | M82: =MROUND(I82*120*'Rate Card'!$B$48,500) -> 182500 | O82: 0.92 | P82: 1
A83: 73 | B83: Vibrating Roller | C83: KOMATSU | D83: VR-02 | E83: SL203468 | F83: 2012 | H83: =MROUND('Rate Card'!$I$10*O83*P83,10) -> 3590 | I83: =MROUND('Rate Card'!$K$10*O83*P83,10) -> 1790 | J83: =MROUND(H83*4*'Rate Card'!$B$47,100) -> 13600 | K83: =MROUND(I83*4*'Rate Card'!$B$47,100) -> 6800 | L83: =MROUND(H83*120*'Rate Card'!$B$48,500) -> 366000 | M83: =MROUND(I83*120*'Rate Card'!$B$48,500) -> 182500 | O83: 0.92 | P83: 1
A84: 74 | B84: Vibrating Roller | C84: (Unknown) | D84: VR-03 | E84: — | F84: 2013 | H84: =MROUND('Rate Card'!$I$10*O84*P84,10) -> 3590 | I84: =MROUND('Rate Card'!$K$10*O84*P84,10) -> 1790 | J84: =MROUND(H84*4*'Rate Card'!$B$47,100) -> 13600 | K84: =MROUND(I84*4*'Rate Card'!$B$47,100) -> 6800 | L84: =MROUND(H84*120*'Rate Card'!$B$48,500) -> 366000 | M84: =MROUND(I84*120*'Rate Card'!$B$48,500) -> 182500 | O84: 0.92 | P84: 1
A85: 75 | B85: Vibrating Roller | C85: BOMAG | D85: VR-14 | E85: BW-138 AD | F85: 2016 | H85: =MROUND('Rate Card'!$I$10*O85*P85,10) -> 3590 | I85: =MROUND('Rate Card'!$K$10*O85*P85,10) -> 1790 | J85: =MROUND(H85*4*'Rate Card'!$B$47,100) -> 13600 | K85: =MROUND(I85*4*'Rate Card'!$B$47,100) -> 6800 | L85: =MROUND(H85*120*'Rate Card'!$B$48,500) -> 366000 | M85: =MROUND(I85*120*'Rate Card'!$B$48,500) -> 182500 | O85: 0.92 | P85: 1
A86: 76 | B86: Vibrating Roller | C86: BOMAG | D86: VR-18 | E86: SA-00-350 | F86: 2016 | H86: =MROUND('Rate Card'!$I$10*O86*P86,10) -> 3590 | I86: =MROUND('Rate Card'!$K$10*O86*P86,10) -> 1790 | J86: =MROUND(H86*4*'Rate Card'!$B$47,100) -> 13600 | K86: =MROUND(I86*4*'Rate Card'!$B$47,100) -> 6800 | L86: =MROUND(H86*120*'Rate Card'!$B$48,500) -> 366000 | M86: =MROUND(I86*120*'Rate Card'!$B$48,500) -> 182500 | O86: 0.92 | P86: 1
A87: 77 | B87: Vibrating Roller | C87: BOMAG | D87: VR-31 | E87: BW 75 H | F87: 2016 | H87: =MROUND('Rate Card'!$I$10*O87*P87,10) -> 3590 | I87: =MROUND('Rate Card'!$K$10*O87*P87,10) -> 1790 | J87: =MROUND(H87*4*'Rate Card'!$B$47,100) -> 13600 | K87: =MROUND(I87*4*'Rate Card'!$B$47,100) -> 6800 | L87: =MROUND(H87*120*'Rate Card'!$B$48,500) -> 366000 | M87: =MROUND(I87*120*'Rate Card'!$B$48,500) -> 182500 | O87: 0.92 | P87: 1
A88: 78 | B88: Vibrating Roller | C88: TACOM | D88: VR-30 | E88: TFR60TDS | F88: 2016 | H88: =MROUND('Rate Card'!$I$10*O88*P88,10) -> 3590 | I88: =MROUND('Rate Card'!$K$10*O88*P88,10) -> 1790 | J88: =MROUND(H88*4*'Rate Card'!$B$47,100) -> 13600 | K88: =MROUND(I88*4*'Rate Card'!$B$47,100) -> 6800 | L88: =MROUND(H88*120*'Rate Card'!$B$48,500) -> 366000 | M88: =MROUND(I88*120*'Rate Card'!$B$48,500) -> 182500 | O88: 0.92 | P88: 1
A89: 79 | B89: Vibrating Roller | C89: TACOM | D89: VR-32 | E89: BW 75 H | F89: 2016 | H89: =MROUND('Rate Card'!$I$10*O89*P89,10) -> 3590 | I89: =MROUND('Rate Card'!$K$10*O89*P89,10) -> 1790 | J89: =MROUND(H89*4*'Rate Card'!$B$47,100) -> 13600 | K89: =MROUND(I89*4*'Rate Card'!$B$47,100) -> 6800 | L89: =MROUND(H89*120*'Rate Card'!$B$48,500) -> 366000 | M89: =MROUND(I89*120*'Rate Card'!$B$48,500) -> 182500 | O89: 0.92 | P89: 1
A90: 80 | B90: Vibrating Roller | C90: TACOM | D90: VR-69 | E90: BW 75 H | F90: 2016 | H90: =MROUND('Rate Card'!$I$10*O90*P90,10) -> 3590 | I90: =MROUND('Rate Card'!$K$10*O90*P90,10) -> 1790 | J90: =MROUND(H90*4*'Rate Card'!$B$47,100) -> 13600 | K90: =MROUND(I90*4*'Rate Card'!$B$47,100) -> 6800 | L90: =MROUND(H90*120*'Rate Card'!$B$48,500) -> 366000 | M90: =MROUND(I90*120*'Rate Card'!$B$48,500) -> 182500 | O90: 0.92 | P90: 1
A91: 81 | B91: Vibrating Roller | C91: (Unknown) | D91: VR-04 | E91: — | F91: 2010 | H91: =MROUND('Rate Card'!$I$10*O91*P91,10) -> 3590 | I91: =MROUND('Rate Card'!$K$10*O91*P91,10) -> 1790 | J91: =MROUND(H91*4*'Rate Card'!$B$47,100) -> 13600 | K91: =MROUND(I91*4*'Rate Card'!$B$47,100) -> 6800 | L91: =MROUND(H91*120*'Rate Card'!$B$48,500) -> 366000 | M91: =MROUND(I91*120*'Rate Card'!$B$48,500) -> 182500 | O91: 0.92 | P91: 1
A92: 82 | B92: Vibrating Roller | C92: BOMAG | D92: VR-28 | E92: BW 75 H | F92: 2015 | H92: =MROUND('Rate Card'!$I$10*O92*P92,10) -> 3590 | I92: =MROUND('Rate Card'!$K$10*O92*P92,10) -> 1790 | J92: =MROUND(H92*4*'Rate Card'!$B$47,100) -> 13600 | K92: =MROUND(I92*4*'Rate Card'!$B$47,100) -> 6800 | L92: =MROUND(H92*120*'Rate Card'!$B$48,500) -> 366000 | M92: =MROUND(I92*120*'Rate Card'!$B$48,500) -> 182500 | O92: 0.92 | P92: 1
A93: 83 | B93: Vibrating Roller | C93: TACOM | D93: VR-29 | E93: TFR60TDS | F93: 2015 | H93: =MROUND('Rate Card'!$I$10*O93*P93,10) -> 3590 | I93: =MROUND('Rate Card'!$K$10*O93*P93,10) -> 1790 | J93: =MROUND(H93*4*'Rate Card'!$B$47,100) -> 13600 | K93: =MROUND(I93*4*'Rate Card'!$B$47,100) -> 6800 | L93: =MROUND(H93*120*'Rate Card'!$B$48,500) -> 366000 | M93: =MROUND(I93*120*'Rate Card'!$B$48,500) -> 182500 | O93: 0.92 | P93: 1
... A111: 101 | B111: Vibrating Roller | C111: (Unknown) | D111: VR-17 | E111: — | F111: 2010 | H111: =MROUND('Rate Card'!$I$10*O111*P111,10) -> 3200 | I111: =MROUND('Rate Card'!$K$10*O111*P111,10) -> 1600 | J111: =MROUND(H111*4*'Rate Card'!$B$47,100) -> 12200 | K111: =MROUND(I111*4*'Rate Card'!$B$47,100) -> 6100 | L111: =MROUND(H111*120*'Rate Card'!$B$48,500) -> 326500 | M111: =MROUND(I111*120*'Rate Card'!$B$48,500) -> 163000 | O111: 0.82 | P111: 1
A112: 102 | B112: Vibrating Roller | C112: (Unknown) | D112: VR-19 | E112: — | F112: — | H112: =MROUND('Rate Card'!$I$10*O112*P112,10) -> 2260 | I112: =MROUND('Rate Card'!$K$10*O112*P112,10) -> 1130 | J112: =MROUND(H112*4*'Rate Card'!$B$47,100) -> 8600 | K112: =MROUND(I112*4*'Rate Card'!$B$47,100) -> 4300 | L112: =MROUND(H112*120*'Rate Card'!$B$48,500) -> 230500 | M112: =MROUND(I112*120*'Rate Card'!$B$48,500) -> 115500 | N112: year unknown → 58% factor | O112: 0.58 | P112: 1
A113: 103 | B113: Vibrating Roller | C113: (Unknown) | D113: VR-22 | E113: — | F113: — | H113: =MROUND('Rate Card'!$I$10*O113*P113,10) -> 2260 | I113: =MROUND('Rate Card'!$K$10*O113*P113,10) -> 1130 | J113: =MROUND(H113*4*'Rate Card'!$B$47,100) -> 8600 | K113: =MROUND(I113*4*'Rate Card'!$B$47,100) -> 4300 | L113: =MROUND(H113*120*'Rate Card'!$B$48,500) -> 230500 | M113: =MROUND(I113*120*'Rate Card'!$B$48,500) -> 115500 | N113: year unknown → 58% factor | O113: 0.58 | P113: 1
A114: 104 | B114: Vibrating Roller | C114: (Unknown) | D114: VR-23 | E114: — | F114: — | H114: =MROUND('Rate Card'!$I$10*O114*P114,10) -> 2260 | I114: =MROUND('Rate Card'!$K$10*O114*P114,10) -> 1130 | J114: =MROUND(H114*4*'Rate Card'!$B$47,100) -> 8600 | K114: =MROUND(I114*4*'Rate Card'!$B$47,100) -> 4300 | L114: =MROUND(H114*120*'Rate Card'!$B$48,500) -> 230500 | M114: =MROUND(I114*120*'Rate Card'!$B$48,500) -> 115500 | N114: year unknown → 58% factor | O114: 0.58 | P114: 1
A115: 105 | B115: Vibrating Roller | C115: BOMAG | D115: VR-25 | E115: — | F115: — | H115: =MROUND('Rate Card'!$I$10*O115*P115,10) -> 2260 | I115: =MROUND('Rate Card'!$K$10*O115*P115,10) -> 1130 | J115: =MROUND(H115*4*'Rate Card'!$B$47,100) -> 8600 | K115: =MROUND(I115*4*'Rate Card'!$B$47,100) -> 4300 | L115: =MROUND(H115*120*'Rate Card'!$B$48,500) -> 230500 | M115: =MROUND(I115*120*'Rate Card'!$B$48,500) -> 115500 | N115: year unknown → 58% factor | O115: 0.58 | P115: 1
A116: 106 | B116: Vibrating Roller | C116: (Unknown) | D116: VR-26 | E116: — | F116: — | H116: =MROUND('Rate Card'!$I$10*O116*P116,10) -> 2260 | I116: =MROUND('Rate Card'!$K$10*O116*P116,10) -> 1130 | J116: =MROUND(H116*4*'Rate Card'!$B$47,100) -> 8600 | K116: =MROUND(I116*4*'Rate Card'!$B$47,100) -> 4300 | L116: =MROUND(H116*120*'Rate Card'!$B$48,500) -> 230500 | M116: =MROUND(I116*120*'Rate Card'!$B$48,500) -> 115500 | N116: year unknown → 58% factor | O116: 0.58 | P116: 1
A117: 107 | B117: Vibrating Roller | C117: TACOM | D117: VR-33 | E117: — | F117: — | H117: =MROUND('Rate Card'!$I$10*O117*P117,10) -> 2260 | I117: =MROUND('Rate Card'!$K$10*O117*P117,10) -> 1130 | J117: =MROUND(H117*4*'Rate Card'!$B$47,100) -> 8600 | K117: =MROUND(I117*4*'Rate Card'!$B$47,100) -> 4300 | L117: =MROUND(H117*120*'Rate Card'!$B$48,500) -> 230500 | M117: =MROUND(I117*120*'Rate Card'!$B$48,500) -> 115500 | N117: year unknown → 58% factor | O117: 0.58 | P117: 1
A118: 108 | B118: Vibrating Roller | C118: (Unknown) | D118: VR-34 | E118: — | F118: — | H118: =MROUND('Rate Card'!$I$10*O118*P118,10) -> 2260 | I118: =MROUND('Rate Card'!$K$10*O118*P118,10) -> 1130 | J118: =MROUND(H118*4*'Rate Card'!$B$47,100) -> 8600 | K118: =MROUND(I118*4*'Rate Card'!$B$47,100) -> 4300 | L118: =MROUND(H118*120*'Rate Card'!$B$48,500) -> 230500 | M118: =MROUND(I118*120*'Rate Card'!$B$48,500) -> 115500 | N118: year unknown → 58% factor | O118: 0.58 | P118: 1
A119: 109 | B119: Vibrating Roller | C119: (Unknown) | D119: VR-35 | E119: — | F119: — | H119: =MROUND('Rate Card'!$I$10*O119*P119,10) -> 2260 | I119: =MROUND('Rate Card'!$K$10*O119*P119,10) -> 1130 | J119: =MROUND(H119*4*'Rate Card'!$B$47,100) -> 8600 | K119: =MROUND(I119*4*'Rate Card'!$B$47,100) -> 4300 | L119: =MROUND(H119*120*'Rate Card'!$B$48,500) -> 230500 | M119: =MROUND(I119*120*'Rate Card'!$B$48,500) -> 115500 | N119: year unknown → 58% factor | O119: 0.58 | P119: 1
A120: 110 | B120: Vibrating Roller | C120: (Unknown) | D120: VR-36 | E120: — | F120: — | H120: =MROUND('Rate Card'!$I$10*O120*P120,10) -> 2260 | I120: =MROUND('Rate Card'!$K$10*O120*P120,10) -> 1130 | J120: =MROUND(H120*4*'Rate Card'!$B$47,100) -> 8600 | K120: =MROUND(I120*4*'Rate Card'!$B$47,100) -> 4300 | L120: =MROUND(H120*120*'Rate Card'!$B$48,500) -> 230500 | M120: =MROUND(I120*120*'Rate Card'!$B$48,500) -> 115500 | N120: year unknown → 58% factor | O120: 0.58 | P120: 1
A121: 111 | B121: Vibrating Roller | C121: SAKAI | D121: VR-37 | E121: — | F121: — | H121: =MROUND('Rate Card'!$I$10*O121*P121,10) -> 2260 | I121: =MROUND('Rate Card'!$K$10*O121*P121,10) -> 1130 | J121: =MROUND(H121*4*'Rate Card'!$B$47,100) -> 8600 | K121: =MROUND(I121*4*'Rate Card'!$B$47,100) -> 4300 | L121: =MROUND(H121*120*'Rate Card'!$B$48,500) -> 230500 | M121: =MROUND(I121*120*'Rate Card'!$B$48,500) -> 115500 | N121: year unknown → 58% factor | O121: 0.58 | P121: 1
A122: 112 | B122: Vibrating Roller | C122: (Unknown) | D122: VR-38 | E122: — | F122: — | H122: =MROUND('Rate Card'!$I$10*O122*P122,10) -> 2260 | I122: =MROUND('Rate Card'!$K$10*O122*P122,10) -> 1130 | J122: =MROUND(H122*4*'Rate Card'!$B$47,100) -> 8600 | K122: =MROUND(I122*4*'Rate Card'!$B$47,100) -> 4300 | L122: =MROUND(H122*120*'Rate Card'!$B$48,500) -> 230500 | M122: =MROUND(I122*120*'Rate Card'!$B$48,500) -> 115500 | N122: year unknown → 58% factor | O122: 0.58 | P122: 1
A123: 113 | B123: Vibrating Roller | C123: (Unknown) | D123: VR-39 | E123: — | F123: — | H123: =MROUND('Rate Card'!$I$10*O123*P123,10) -> 2260 | I123: =MROUND('Rate Card'!$K$10*O123*P123,10) -> 1130 | J123: =MROUND(H123*4*'Rate Card'!$B$47,100) -> 8600 | K123: =MROUND(I123*4*'Rate Card'!$B$47,100) -> 4300 | L123: =MROUND(H123*120*'Rate Card'!$B$48,500) -> 230500 | M123: =MROUND(I123*120*'Rate Card'!$B$48,500) -> 115500 | N123: year unknown → 58% factor | O123: 0.58 | P123: 1
... A150: 140 | B150: Vibrating Roller | C150: CAT | D150: VR-44 | E150: CB-504C | F150: — | H150: =MROUND('Rate Card'!$I$10*O150*P150,10) -> 2260 | I150: =MROUND('Rate Card'!$K$10*O150*P150,10) -> 1130 | J150: =MROUND(H150*4*'Rate Card'!$B$47,100) -> 8600 | K150: =MROUND(I150*4*'Rate Card'!$B$47,100) -> 4300 | L150: =MROUND(H150*120*'Rate Card'!$B$48,500) -> 230500 | M150: =MROUND(I150*120*'Rate Card'!$B$48,500) -> 115500 | N150: year unknown → 58% factor | O150: 0.58 | P150: 1
A151: 141 | B151: Vibrating Roller | C151: SAKAI | E151: SW-300 | F151: — | H151: =MROUND('Rate Card'!$I$10*O151*P151,10) -> 2260 | I151: =MROUND('Rate Card'!$K$10*O151*P151,10) -> 1130 | J151: =MROUND(H151*4*'Rate Card'!$B$47,100) -> 8600 | K151: =MROUND(I151*4*'Rate Card'!$B$47,100) -> 4300 | L151: =MROUND(H151*120*'Rate Card'!$B$48,500) -> 230500 | M151: =MROUND(I151*120*'Rate Card'!$B$48,500) -> 115500 | N151: year unknown → 58% factor | O151: 0.58 | P151: 1
...

Sheet Market Research
A1: COMPETITOR PRICE SURVEY — Sri Lanka 2025–2026
A2: Sources: SLLDC (Govt), wedabima.com, krearthmovers, petersequipment.lk, ikman.lk, lankanrentals, boompeek, Tata Motors LK, SENOK, plus Indian rental benchmarks (IndiaMART, Rentkart).
A4: Category | B4: Competitor / Source | C4: Rate (as published) | D4: LKR equivalent | E4: Notes | F4: Our positioning
A5: Backhoe Loader | B5: SLLDC (Govt) – JCB 3CX | C5: Rs. 6,050/h wet | D5: Rs. 6,050/h | E5: Official govt hire rate, with fuel & operator | F5: ~50% below SLLDC
A6: Backhoe Loader | B6: KR Earthmovers (India ref) – JCB 3DX | C6: ₹1,100/h wet / ₹500/h dry | D6: ≈Rs. 3,960/Rs. 1,800 | E6: Monthly Rs.90,000 for 240 hrs | F6: Aligned with regional market
A7: Backhoe Loader | B7: Wedabima – private JCB | C7: Rs. 2,500–3,500/h wet | D7: Rs. 2,500–3,500 | E7: Small Colombo/Gampaha operators | F7: Matching mid-market
A8: Backhoe Loader | B8: Dayani Backhoe Centre | C8: On request | D8: Quote basis | E8: Yakkala/Gampaha district | F8: Our rate is public & transparent
A9: Wheel Loader | B9: SLLDC – Doosan Mega 250 | C9: Rs. 11,390–15,760/h wet | D9: Rs. 11,390–15,760 | E9: 2.0–2.4 cu.m | F9: 30–50% below SLLDC
A10: Wheel Loader | B10: Private SL suppliers | C10: Rs. 5,000–8,000/h | D10: Rs. 5,000–8,000 | E10: Used CAT/Komatsu 910/WA100 | F10: Priced at market mid-point
A11: Truck Mixer | B11: Tantri Lanka | C11: Quote basis | D11: Project-based | E11: Concrete mixer truck supply | F11: Fleet rental differentiator
A12: Truck Mixer | B12: Private SL operators | C12: Rs. 3,500–5,000/h with driver | D12: Rs. 3,500–5,000 | E12: Tata/Ashok Leyland mixers | F12: Competitive
A13: Self Loader Mixer | B13: KR Earthmovers (India ref) | C13: ₹1,500/h wet | D13: ≈Rs. 5,400 | E13: Fiori/Ajax self-loading mixer | F13: Below India rate
A14: Self Loader Mixer | B14: Private SL Fiori | C14: Rs. 4,500–6,000/h | D14: Rs. 4,500–6,000 | E14: 4–8 cu.m self-loader | F14: Aligned
A15: Static Roller | B15: Peters Equipment SL – 1T hand | C15: Rs. 3,500/day | D15: Rs. 3,500/day | E15: Walk-behind 1-ton roller | F15: Matching
... A43: Farm Tractor | B43: Private SL Massey/TAFE | C43: Rs. 1,200–1,800/h | D43: Rs. 1,200–1,800 | E43: 45–75 HP | F43: Mid-market

Sheet Fleet
I1: VEHICLE MACHINERY LISH AT EDWARD AND CHRISTIE | L1: CONVERTED VEHICLE
L2: SOLD
A3: NO | B3: EQUIPMENT DESCRIPTION | C3: E&C NUMBER | D3: BRAND | E3: TYPE OF VEHICLE | F3: MODEL NO | G3: REGISTRATION NO. | H3: CAPACITY | I3: YEAR OF MANUFACTURE | J3: SE.NO | K3: CHASSIS.NO | L3: ENGINE.NO | M3: GPS UNIT | N3: SITE
A4: 1 | B4: BACKHOE LOADER | C4: LB-01 | D4: JCB | E4: Backhoe Loader | F4: 3DX | G4: ZA-2609 | H4: 1.0 cu. m. | I4: 2012 | J4: 1487562 | L4: H00050004 | M4: NO | N4: ALAWWA SITE
A5: 2 | C5: LB-02 | D5: JCB | E5: Backhoe Loader | F5: 3DX | G5: ZA-2963 | H5: 1.0 cu. m. | I5: 2012 | J5: 1487765 | L5: H00032286 | M5: NO | N5: KATANA WATER PROJECT
A6: 3 | C6: LB-03 | D6: JCB | E6: Backhoe Loader | F6: 3DX | G6: ZA-2964 | H6: 1.0 cu. m. | I6: 2012 | J6: 1487793 | L6: H00032137 | M6: NO | N6: KADAWATHA WATER PROJECT
A7: 4 | C7: LB-04 | D7: JCB | E7: Backhoe Loader | F7: SLP3CX | G7: RS-0401 | H7: 1.0 cu. m. | I7: 1999 | J7: SLP3CX7SWE0470373 | L7: AA506060U870023D | M7: NO | N7: AUTO BACS
A8: 5 | C8: LB-05 | D8: JCB | E8: Backhoe Loader | F8: 3DX | G8: RS-0483 | H8: 1.0 cu. m. | I8: 2006 | J8: 1041419 | M8: NO | N8: KATANA WATER PROJECT
A9: 6 | C9: LB-06 | D9: JCB | E9: Backhoe Loader | F9: 3CX | G9: ZA-0447 | H9: 1.0 cu. m. | I9: 2002 | J9: CMT/596/2011/S/P | M9: NO | N9: BADALGAMA
A10: 7 | C10: LB-07 | D10: JCB | E10: Backhoe Loader | F10: JCB 3CX | G10: ZA-2608 | H10: 1.0 cu. m. | I10: 2004 | J10: *0943015 | L10: AK51093U592119K | M10: NO | N10: DORAMADALAWA PLANT
A11: 8 | C11: LB-08 | D11: JCB | E11: Backhoe Loader | F11: JCB 3DX | G11: ZA-6068 | H11: 1.0 cu. m. | I11: 2015 | J11: HAR3DXSUJ01494150 | L11: H00103100 | M11: NO | N11: CENTRAL EXPRESSWAY
A12: 9 | C12: LB-09 | D12: JCB | E12: Backhoe Loader | F12: JCB 3DX | G12: ZA-6069 | H12: 1.0 cu. m. | I12: 2015 | J12: HAR3DXSUE01494156 | L12: H00103915 | M12: NO | N12: GALENBIDUNUWEWA SITE(GALNAWA SITE)
A13: 10 | C13: LB-10 | D13: JCB | E13: Backhoe Loader | F13: JCB 3DX | G13: ZA-7034 | H13: 1.0 cu. m. | I13: 2016 | J13: HAR3DXSUK01497483 | L13: H00121591 | M13: NO | N13: GALNAWA SITE
A14: 11 | C14: LB-11 | D14: JCB | E14: Backhoe Loader | F14: JCB 3DX | G14: ZA-7092 | H14: 1.0 cu. m. | I14: 2016 | J14: HAR3DXSUE01497316 | L14: H000120453 | M14: NO | N14: MIHINTHALE SITE(THALAWA SITE)
A15: 12 | C15: LB-12 | D15: JCB | E15: Backhoe Loader | F15: 3DX | G15: ZA-8337 | H15: 1.0 cu. m. | I15: 2016 | J15: HAR3DXSUC001498720 | L15: H00128304 | M15: NO | N15: AMBANPOLA SITE
A16: 13 | C16: LB-13 | D16: JCB | E16: Backhoe Loader | F16: 3DX | G16: ZA-7965 | H16: 1.0 cu. m. | I16: 2016 | J16: HAR3DXSUJ01499221 | L16: H00130938 | M16: NO | N16: KATANA WATER PROJECT
A17: 14 | C17: LB-14 | D17: JCB | E17: Backhoe Loader | F17: 3DX | G17: ZA-7968 | H17: 1.0 cu. m. | I17: 2016 | J17: HAR3DXSUK01499198 | L17: H00130812 | M17: NO | N17: NOCHCHIYAGAMA SITE(ANU-199)
A18: 15 | C18: LB-15 | D18: J.C.B | E18: Backhoe Loader | F18: 570ST | G18: ZB-1047 | H18: 1.0 cu. m. | I18: 2019 | J18: NKJ570STCKKH00901 | L18: 8045.45.748.265437 | M18: NO | N18: GALENBIDUNUWEWA SITE
A19: 16 | C19: LB-16 | D19: J.C.B | E19: Backhoe Loader | F19: 3DX | G19: ZB-1547 | H19: 1.0 cu. m. | I19: 2020 | J19: HAR3DXSUL02722406 | L19: H00264328 | M19: NO | N19: ALAWWA SITE
A20: 17 | C20: LB-17 | D20: J.C.B | E20: Backhoe Loader | F20: 3DX | G20: ZB-1546 | H20: 1.0 cu. m. | I20: 2020 | J20: HAR3DXSUH02722410 | L20: H00264316 | M20: NO | N20: CHILLOW SITE
A21: 18 | C21: LB-18 | D21: J.C.B | E21: Backhoe Loader | F21: 3DX | G21: ZB-1548 | H21: 1.0 cu. m. | I21: 2020 | J21: HAR3DXSUH02722407 | L21: H00264525 | M21: NO | N21: MUNDALAMA ESTATE
... A27: 24 | C27: LB-24 | D27: BOB CAT | E27: Backhoe Loader | F27: B760 | G27: ZB-2583 | H27: 1.0 cu. m. | I27: 2021 | J27: DBIB5JDGLL0S11003* | L27: NL84759 | M27: NO | N27: GALENBIDUNUWEWA SITE
A29: 25 | B29: WHEEL LOADER | C29: LD-01 | D29: CAT | E29: Wheel Loader | F29: 910E | H29: 0.5 m3 | I29: 2009 | M29: NO | N29: TR-01 MUTUR
A30: 26 | C30: LD-02 | D30: CAT | E30: Wheel Loader | F30: CAT910 | H30: 0.75 m3 | I30: 2010 | M30: NO | N30: BADALGAMA
A31: 27 | C31: LD-03 | D31: KOMATSU | E31: Wheel Loader | F31: WA100 | H31: 0.75 m3 | I31: 2012 | M31: NO | N31: MIHINTHALE PLANT
A32: 28 | C32: LD-04 | D32: KOMATSU | E32: Wheel Loader | F32: 924F | H32: 0.5 m3 | I32: 2013 | M32: NO | N32: C.COM
A33: 29 | C33: LD-05 | D33: KOMATSU | E33: Wheel Loader | F33: WA150 | H33: 0.75 m3 | I33: 2014 | M33: NO | N33: BADALGAMA
A34: 30 | C34: LD-06 | D34: KOMATSU | E34: Wheel Loader | F34: 510 | G34: ZA-3116 | H34: 0.5 m3 | I34: 2013 | M34: NO | N34: BADALGAMA
A35: 31 | C35: LD-07 | D35: KOMATSU | E35: Wheel Loader | F35: WA-80SS | H35: 0.5 m3 | I35: 2015 | J35: 13297 | M35: NO | N35: MIHINTHALE PLANT
A36: 32 | C36: LD-08 | D36: SANTUI | E36: Wheel Loader | F36: SL30W | H36: 0.75 m3 | I36: 2014 | M36: NO | N36: BADALGAMA
A37: 33 | C37: LD-09 | D37: SHANTUI | E37: Wheel Loader | F37: SL-50WN | H37: 01 m3 | I37: 2020 | M37: NO | N37: WADAKADA
A39: 34 | B39: TRUCK MIXTURES | C39: TM-01 | D39: MITSUBISHI | E39: Truck Mixer | F39: KC-FH217C | G39: LK-5048 | H39: 2 m3 | I39: 1996 | J39: FH217C501291 | K39: FH217C501291 | L39: 6D16.831590 | M39: NO | N39: BADALGAMA
A40: 35 | C40: TM-03 | D40: ISUZU | E40: Truck Mixer | F40: KC-NRR33C20 | G40: LK-5047 | H40: 2 m3 | I40: 1996 | J40: NRR33C2-3001266 | K40: NRR33C2-3001266 | M40: NO | N40: ARAWWALA CONSTRUCTION(WALLAWAYA)
A41: 36 | C41: TM-05 | D41: MITSUBISHI | E41: Truck Mixer | F41: KC-FE517BN | G41: LH-5474 | H41: 1 m3 | I41: 1996 | J41: FE517BN520943 | K41: FE517BN520943 | L41: 4D33.E29583 | M41: NO | N41: BADALGAMA
A42: 37 | C42: TM-04 | D42: ISUZU | E42: Truck Mixer | F42: KK-NRR35C4 FORWARD | G42: LL-0690 | H42: 2 m3 | I42: 2000 | J42: NNR35C47000949 | K42: NNR35C47000949 | L42: 6HL1.313673 | M42: NO | N42: DORAMADALAWA PLANT
A43: 38 | C43: TM-06 | D43: MITSUBISHI | E43: Truck Mixer | F43: U.FE315BN | G43: LH-5475 | H43: 1 m3 | I43: 1991 | J43: FE315BN460526 | K43: FE315BN460526 | L43: 4D32.924436 | M43: NO | N43: BADALGAMA
A44: 39 | C44: TM-10 | D44: ASHOK LEYLAND | E44: Truck Mixer | F44: TUSKER SUPER 1613 | G44: ZA-6395 | H44: 4 m3 | I44: 2015 | J44: MB1ADJJA2FRDL3242 | K44: MB1ADJJA2FRDL3242 | L44: FDHZ403004 | M44: NO | N44: DORAMADALAWA PLANT
A45: 40 | C45: TM-09 | D45: MITSUBISHI | E45: Truck Mixer | F45: KK-FE73EB CANTER | G45: ZA-6255 | H45: 1 m3 | I45: 2003 | J45: FE73EB501255 | K45: FE73EB501255 | L45: 4M51-B12860 | M45: NO | N45: BADALGAMA
A46: 41 | C46: TM-08 | D46: ISUZU | E46: Truck Mixer | F46: KC-NRR33C20 | G46: LJ-8055 | H46: 2 m3 | I46: 1996 | J46: NNR33C23001295 | K46: NNR33C23001295 | L46: 6HH1-211921 | M46: NO | N46: MUTUR TR-01
A47: 42 | C47: TM-11 | D47: ELCHER | E47: Truck Mixer | F47: TERRA 16 | G47: ZA-7291 | H47: 4 m3 | I47: 2016 | J47: MC2K7ERCOGK054478 | K47: MC2K7ERCOGK054478 | L47: E613CDGK111850 | M47: NO | N47: BADALGAMA
A48: 43 | C48: TM-12 | D48: ELCHER | E48: Truck Mixer | F48: TERRA 16 | G48: ZA-7290 | H48: 4 m3 | I48: 2016 | J48: MC2K7ERCOGJ053783 | K48: MC2K7ERCOGJ053783 | L48: E613CDGJ1085564 | M48: NO | N48: MUTUR TR-01
A49: 44 | C49: TM-14 | D49: TATA | E49: Truck Mixer | F49: LPK 2518 | G49: ZA-7810 | H49: 7 m3 | I49: 2016 | J49: MAT448072G3R26771 | K49: MAT448072G3R26771 | L49: 6IL63557849 | M49: NO | N49: BADALGAMA
A50: 45 | C50: TM-15 | D50: TATA | E50: Truck Mixer | F50: LPK 2518 | G50: ZA-7925 | H50: 7 m3 | I50: 2016 | J50: MAT448072G3R22351 | K50: MAT448072G3R22351 | L50: 61J63544842 | M50: INSTRALLED | N50: BADALGAMA
A51: 46 | C51: TM-16 | D51: TATA | E51: Truck Mixer | F51: LPK 2518 | G51: ZA-8033 | H51: 7 m3 | I51: 2016 | J51: MAT448072G3R22347 | K51: MAT448072G3R22347 | L51: 61J63546762 | M51: NO | N51: CENTRAL EXPRESSWAY
A52: 47 | C52: TM-18 | D52: TATA | E52: Truck Mixer | F52: LPK 1618 | G52: ZA-8511 | H52: 4 m3 | I52: 2017 | J52: MAT449019H2R08585 | K52: MAT449019H2R08585 | L52: 71C84378059 | M52: INSTRALLED | N52: BADALGAMA
... A54: 49 | C54: TM-21 | D54: TATA | E54: Truck Mixer | F54: LPK 1618 | G54: ZA-0050 | H54: 4 m3 | I54: 2017 | J54: MAT449019H2R08190 | K54: MAT449019H2R08190 | L54: 71C84377627 | M54: NO | N54: CENTRAL EXPRESSWAY
A56: 50 | B56: SELF LOADER MIXTURES | C56: TM-13 | D56: FIORI | E56: Self Loader Mixer | F56: 8FO8H01246 | G56: Fiori | H56: 3.5m3 | I56: 2017 | J56: BFO8H01193 | L56: U636673B | M56: NO | N56: WELLAWAYA SITE
A57: 51 | C57: TM-17 | D57: FIORI | E57: Self Loader Mixer | F57: 8FO8H01252 | G57: Fiori | H57: 3.5m3 | I57: 2017 | J57: BFO8HO1246 | L57: RS81729*0641542C | M57: NO | N57: C.COM
A58: 52 | C58: TM-20 | D58: FIORI | E58: Self Loader Mixer | F58: BF08H01307 | G58: Fiori | H58: 3.5m3 | I58: 2018 | J58: BF08H01307 | M58: NO | N58: AMBANPOLA SITE
A60: 53 | B60: STATIC ROLLER | C60: SR-01 | E60: Static Roller | H60: 10 Ton | I60: 2012 | M60: NO | N60: SOLD
A61: 54 | C61: SR-02 | E61: Static Roller | H61: 8 Ton | I61: 2009 | M61: NO | N61: SOLD
A62: 55 | C62: SR-03 | E62: Static Roller | H62: 10 Ton | I62: 2012 | M62: NO | N62: SOLD
A63: 56 | C63: SR-04 | E63: Static Roller | F63: R12 | H63: 03 DRUM | I63: 2013 | M63: NO | N63: GALENBIDUNUWEWA SITE
A64: 57 | C64: SR-05 | D64: SAKAI | E64: Static Roller | F64: SW-900 | H64: 10 Ton | I64: 2014 | J64: VSW27-30127 | M64: NO | N64: CHILLOW SITE
A65: 58 | C65: SR-06 | D65: CASE | E65: Static Roller | H65: 10 Ton | I65: 2014 | M65: NO | N65: CENTRAL EXPRESSWAY
A66: 59 | C66: SR-07 | D66: IR | E66: Static Roller | F66: 2860-01 | H66: 10 Ton | I66: 2010 | J66: 166756 | M66: NO | N66: SOLD
A67: 60 | C67: SR-08 | D67: CASE | E67: Static Roller | F67: 1107EXD | H67: 10 Ton | I67: 2017 | J67: NKJ1107ELGKT00064 | K67: 62038313 | M67: NO | N67: CENTRAL EXPRESSWAY
A68: 61 | C68: SR-09 | D68: CASE | E68: Static Roller | F68: 1107EXD | H68: 10 Ton | I68: 2017 | J68: MKJ1107EXGKT00227 | M68: NO | N68: CENTRAL EXPRESSWAY
A69: 62 | C69: SR-10 | E69: Static Roller | H69: 03 DRUM | M69: NO | N69: PUTHTHALAMA SITE
A70: 63 | C70: SR-11 | D70: HAMM | E70: Static Roller | F70: HAMM 311D | H70: 10 Ton | J70: WHBOH216TJ0003198 | K70: 81D84477073 | M70: NO | N70: THISSAMAHARAMA SITE(SOLUTION)
A71: 64 | C71: SR-12 | D71: HAMM | E71: Static Roller | F71: HAMM 311D | H71: 10 Ton | I71: 2016 | J71: WHBOH216KJ0003236 | K71: 81E84483259 | M71: NO | N71: GALENBIDUNUWEWA SITE
A72: 65 | C72: SR-13 | D72: DYNAPAC | E72: Static Roller | F72: CA250D | H72: 10 Ton | J72: 10300127HLE007006 | M72: NO | N72: KILINOCHCHIYA SITE
A73: 66 | C73: SR-14 | D73: SAKAI | E73: Static Roller | F73: R2V | H73: 03 DRUM | M73: NO | N73: BADALGAMA
A74: 67 | C74: SR-15 | D74: MACADAM | E74: Static Roller | H74: 03 DRUM | M74: NO
A75: 68 | C75: SR-16 | D75: DYNAPAC | E75: Static Roller | F75: CA30D | H75: 10 Ton | J75: 10300180ALE010382 | M75: NO | N75: GALENBIDUNUWEWA SITE
A76: 69 | C76: SR-17 | D76: DYNAPAC | E76: Static Roller | F76: CC425 | H76: 08 Ton | I76: 2021 | J76: 10300383LME010505-0121 | M76: NO | N76: CENTRAL EXPRESSWAY
A77: 70 | C77: SR-18 | D77: DYNAPAC | E77: Static Roller | F77: CA30D | H77: 10 Ton | I77: 2021 | J77: 10300180JME010993-0933 | M77: NO | N77: NOCHCHIYAGAMA SITE(ANU-199)
A78: 71 | C78: SR-19 | D78: DYNAPAC | E78: Static Roller | F78: CA30D | H78: 10 Ton | I78: 2021 | J78: 10300180AME010996-0996 | M78: NO | N78: BADALGAMA
A80: 72 | B80: VIBRATING ROLLER | C80: VR-01 | E80: Vibrating Roller | H80: 01 Ton | I80: 2010 | M80: NO
A81: 73 | C81: VR-02 | D81: KOMATSU | E81: Vibrating Roller | H81: 04 Ton | I81: 2012 | M81: NO | N81: BADALGAMA
A82: 74 | C82: VR-03 | E82: Vibrating Roller | H82: 04 Ton | I82: 2013 | M82: NO | N82: MAGGONA BRIDGE
A83: 75 | C83: VR-04 | E83: Vibrating Roller | H83: 04 Ton | I83: 2010 | M83: NO
A84: 76 | C84: VR-05 | E84: Vibrating Roller | H84: 04 Ton | I84: 2012 | M84: NO
A85: 77 | C85: VR-06 | E85: Vibrating Roller | H85: 01 Ton | I85: 2015 | M85: NO
A86: 78 | C86: VR-07 | D86: CAT | E86: Vibrating Roller | F86: 1650NK0285 | H86: 04 Ton | I86: 2013 | M86: NO | N86: BADALGAMA
A87: 79 | C87: VR-08 | D87: BOMAG | E87: Vibrating Roller | H87: 02 Ton | I87: 2013 | M87: NO | N87: BADALGAMA
A88: 80 | C88: VR-08 | D88: ATLAS | E88: Vibrating Roller | H88: 02 Ton | M88: NO | N88: BADALGAMA
A89: 81 | C89: VR-09 | D89: DYNAPAC | E89: Vibrating Roller | F89: CC142 II | H89: 04 Ton | I89: 2013 | M89: NO | N89: BADALGAMA
A90: 82 | C90: VR-10 | D90: BOMAG | E90: Vibrating Roller | F90: BW 138 AD-05 | H90: 04 Ton | I90: 2013 | J90: 101650301735 | L90: 7FL0908 | M90: NO | N90: BADALGAMA
A91: 83 | C91: VR-11 | D91: DYNAPAC | E91: Vibrating Roller | F91: CC1300 | H91: 04 Ton | I91: 2013 | J91: 100000334E0A012191 | M91: NO | N91: SOLD
A92: 84 | C92: VR-12 | D92: BOMAG | E92: Vibrating Roller | F92: BW 138 AD-05 | H92: 04 Ton | I92: 2013 | J92: 7FL0734 | L92: 101650301736 | M92: NO | N92: GALENBIDUNUWEWA SITE
A93: 85 | C93: VR-13 | D93: HAMM | E93: Vibrating Roller | H93: 04 Ton | I93: 2012 | M93: NO | N93: BADALGAMA
A94: 86 | C94: VR-14 | D94: BOMAG | E94: Vibrating Roller | F94: BW-138 AD | H94: 04 Ton | I94: 2016 | J94: *101650371052 | K94: *101650371052 | M94: NO | N94: BUTHTHALA SITE
A95: 87 | C95: VR-15 | E95: Vibrating Roller | M95: NO
A96: 88 | C96: VR-16 | E96: Vibrating Roller | M96: NO
A97: 89 | C97: VR-17 | E97: Vibrating Roller | M97: NO
A98: 90 | C98: VR-18 | D98: BOMAG | E98: Vibrating Roller | F98: SA-00-350 | H98: 04 Ton | I98: 2016 | M98: NO
A99: 91 | C99: VR-19 | E99: Vibrating Roller | H99: 01 Ton | I99: 2016 | M99: NO
A100: 92 | C100: VR-20 | D100: SAKAI | E100: Vibrating Roller | F100: SW-300 | H100: 04 Ton | I100: 2013 | M100: NO | N100: BADALGAMA
A101: 93 | C101: VR-21 | D101: TACOM | E101: Vibrating Roller | F101: TFR60TDS | H101: 01 Ton | I101: 2014 | J101: 509047 | M101: NO | N101: BADALGAMA
A102: 94 | C102: VR-22 | E102: Vibrating Roller | H102: 01 Ton | I102: 2017 | M102: NO | N102: BADALGAMA
A103: 95 | C103: VR-23 | E103: Vibrating Roller | F103: SL203468 | H103: 04 Ton | I103: 2017 | M103: NO | N103: BADALGAMA
A104: 96 | C104: VR-24 | D104: BOMAG | E104: Vibrating Roller | F104: BW 75 H | H104: 01 Ton | I104: 2013 | J104: 861100822773 | L104: 101650371052 | M104: NO | N104: BADALGAMA
A105: 97 | C105: VR-25 | D105: BOMAG | E105: Vibrating Roller | F105: BW 75 H | H105: 01 Ton | I105: 2013 | J105: 861100822772 | M105: NO | N105: BADALGAMA
A106: 98 | C106: VR-26 | E106: Vibrating Roller | H106: 04 Ton | I106: 2012 | M106: NO
A107: 99 | C107: VR-27 | D107: BOMAG | E107: Vibrating Roller | F107: BW 75 H | H107: 02 TON | I107: 2014 | J107: 861100822771 | L107: SC9407 | M107: NO | N107: BADALGAMA
A108: 100 | C108: VR-28 | D108: BOMAG | E108: Vibrating Roller | F108: BW 75 H | H108: 01 TON | I108: 2015 | J108: 861100822770 | L108: SC9401 | M108: NO
A109: 101 | C109: VR-29 | D109: TACOM | E109: Vibrating Roller | F109: TFR60TDS | H109: 01 TON | I109: 2015 | M109: NO | N109: JA-ELA/GAMPAHA BRIDGE
A110: 102 | C110: VR-30 | D110: TACOM | E110: Vibrating Roller | F110: TFR60TDS | H110: 01 TON | I110: 2016 | M110: NO
A111: 103 | C111: VR-31 | D111: BOMAG | E111: Vibrating Roller | F111: BW 75 H | H111: 01 TON | I111: 2016 | J111: 861100822768 | L111: SC9408 | M111: NO | N111: BADALGAMA
...

Sheet Engineering Assumptions
A1: ENGINEERING COST ASSUMPTIONS — 2026
A2: Blue cells = editable inputs. All figures in LKR unless stated.
A4: GLOBAL INPUTS
A5: Auto-diesel price (LKR/L) | B5: 382 | C5: Source: CPC / Lanka IOC, March 2026
A6: Monthly working hours (min) | B6: 120 | C6: Given by management
A7: Daily working hours (min) | B7: 4 | C7: Given by management
A8: Operator rate (LKR/hour) | B8: 650 | C8: Given by management
A9: Operator minimum monthly pay (LKR) | B9: 78000 | C9: Given by management — applies when hours × rate < this
A10: Overhead rate (% on direct cost) | B10: 0.15 | C10: Yard, admin, insurance, transport, depreciation recovery
A11: Gross profit margin (% on total cost) | B11: 0.2 | C11: Management target
A12: Working days per month | B12: 26 | C12: 6-day work week
A13: Annual inflation on parts | B13: 0.08 | C13: Applied when projecting multi-year
A16: CATEGORY ENGINEERING DATA
A17: # | B17: Category | C17: Fuel (L/h) | D17: PM base (LKR/h) | E17: Major-repair base (LKR/h) | F17: Brand-new price (LKR mln) | G17: Service life (yrs) | H17: Reliability / market note | I17: Wet hourly fuel cost (LKR)
A18: 1 | B18: Backhoe Loader | C18: 5.5 | D18: 180 | E18: 220 | F18: 18.5 | G18: 12 | H18: JCB 3DX Plus new ~Rs. 15–18M; strong resale | I18: =C18*'Engineering Assumptions'!$B$5 -> 2101
A19: 2 | B19: Wheel Loader | C19: 13 | D19: 350 | E19: 480 | F19: 42 | G19: 15 | H19: SHANTUI SL50W / CAT 910E ~Rs. 35–55M | I19: =C19*'Engineering Assumptions'!$B$5 -> 4966
A20: 3 | B20: Truck Mixer | C20: 7 | D20: 220 | E20: 280 | F20: 22 | G20: 12 | H20: TATA LPK2518 + mixer ~Rs. 20–25M | I20: =C20*'Engineering Assumptions'!$B$5 -> 2674
A21: 4 | B21: Self Loader Mixer | C21: 8 | D21: 260 | E21: 320 | F21: 28 | G21: 10 | H21: FIORI DB350 new ~Rs. 26–30M, niche machine | I21: =C21*'Engineering Assumptions'!$B$5 -> 3056
A22: 5 | B22: Static Roller | C22: 8 | D22: 230 | E22: 310 | F22: 22 | G22: 15 | H22: HAMM 311D / SAKAI SW-900 ~Rs. 20–28M | I22: =C22*'Engineering Assumptions'!$B$5 -> 3056
A23: 6 | B23: Vibrating Roller | C23: 5 | D23: 180 | E23: 240 | F23: 14 | G23: 12 | H23: BOMAG BW138/Dynapac CC1300 ~Rs. 12–18M | I23: =C23*'Engineering Assumptions'!$B$5 -> 1910
A24: 7 | B24: Pneumatic Roller | C24: 7 | D24: 200 | E24: 270 | F24: 19 | G24: 15 | H24: Dynapac CP201 / SAKAI ~Rs. 18–22M | I24: =C24*'Engineering Assumptions'!$B$5 -> 2674
A25: 8 | B25: Motor Grader | C25: 15 | D25: 420 | E25: 600 | F25: 55 | G25: 18 | H25: SANY STG170 / CAT 140 new ~Rs. 45–65M | I25: =C25*'Engineering Assumptions'!$B$5 -> 5730
A26: 9 | B26: Skid Steer | C26: 4.5 | D26: 160 | E26: 200 | F26: 11 | G26: 10 | H26: BOBCAT S450/S770 new ~Rs. 9–13M | I26: =C26*'Engineering Assumptions'!$B$5 -> 1719
A27: 10 | B27: Asphalt Paver | C27: 12 | D27: 420 | E27: 560 | F27: 48 | G27: 12 | H27: VOLVO P6820 / SUMITOMO HA60 ~Rs. 40–55M | I27: =C27*'Engineering Assumptions'!$B$5 -> 4584
A28: 11 | B28: Bitumen Bowser | C28: 6.5 | D28: 170 | E28: 210 | F28: 14 | G28: 15 | H28: DFAC/Foton chassis + insulated tank ~Rs. 12–16M | I28: =C28*'Engineering Assumptions'!$B$5 -> 2483
A29: 12 | B29: Mobile Crane | C29: 10 | D29: 340 | E29: 480 | F29: 48 | G29: 20 | H29: KOBELCO RK250 25T new ~Rs. 45–55M | I29: =C29*'Engineering Assumptions'!$B$5 -> 3820
... A46: 29 | B46: Forklift | C46: 3.5 | D46: 160 | E46: 210 | F46: 12 | G46: 15 | H46: 3T diesel forklift ~Rs. 10–14M | I46: =C46*'Engineering Assumptions'!$B$5 -> 1337
A49: AGE MULTIPLIERS (how costs escalate with age)
A50: Machine age (yrs) | B50: PM multiplier | C50: Major-repair mult | D50: Rationale
A51: 0 – 5 | B51: 1 | C51: 0.3 | D51: Under warranty / basic service only
A52: 6 – 10 | B52: 1.25 | C52: 0.75 | D52: Out of warranty; filters, brakes wear normally
A53: 11 – 15 | B53: 1.55 | C53: 1.35 | D53: First major overhaul window; hydraulic seals, bearings
A54: 16 – 20 | B54: 1.95 | C54: 2.1 | D54: Engine rebuild territory; parts harder to source
A55: Over 20 / unknown | B55: 2.4 | C55: 3 | D55: End-of-life — likely uneconomical to keep
A58: TYPICAL CONSUMABLE PRICES (Sri Lanka 2026)
A59: Item | B59: Pack size | C59: Price (LKR) | D59: Typical lifetime | E59: Source
A60: Engine oil 15W-40 (Caltex Delo / Chevron) | B60: 20 L pail | C60: 53895 | D60: 250–500 hrs | E60: Chevron Lanka price list Jan 2024
A61: Engine oil 15W-40 (Caltex Delo) | B61: 1 L bottle | C61: 3220 | D61: — | E61: Chevron Lanka
A62: Hydraulic oil AW-68 (Rando HD 68) | B62: 20 L | C62: 4600 | D62: 1,000–2,000 hrs | E62: greasemonkey.lk
A63: Oil filter (diesel engine) | B63: 1 pc | C63: 2500 | D63: 250–500 hrs | E63: Greasemonkey/Sakura avg
A64: Fuel filter + water separator | B64: set | C64: 3500 | D64: 500 hrs | E64: Local dealer avg
A65: Air filter element (primary) | B65: 1 pc | C65: 4500 | D65: 500 hrs | E65: Local dealer avg
A66: Hydraulic return filter | B66: 1 pc | C66: 6500 | D66: 1,000 hrs | E66: Local dealer avg
A67: Multi-purpose grease (EP-2) | B67: 18 kg drum | C67: 18000 | D67: — | E67: Caltex / Shell
A68: Coolant / antifreeze | B68: 5 L | C68: 4800 | D68: Annual | E68: Local dealer avg
A69: Gear oil (SAE 90) | B69: 20 L | C69: 22000 | D69: 1,000 hrs | E69: Local dealer avg
A70: Tyre 10.00-20 (truck/tipper) | B70: 1 pc | C70: 135000 | D70: 50,000 km | E70: ikman / Damro avg
A71: Tyre 18.4-26 (backhoe rear) | B71: 1 pc | C71: 220000 | D71: 3,000 hrs | E71: SENOK / local importer avg
... A74: Battery N100 (heavy duty) | B74: 1 pc | C74: 42000 | D74: 2 years | E74: Exide / Lucas

Sheet Engineering Cost
A1: ENGINEERING COST BUILD-UP — per hour rate construction
A2: For every fleet unit: Fuel + Operator + Preventive maintenance + Major repair + Overhead + 20% profit = recommended WET rate
A4: # | B4: Category | C4: Brand / Model | D4: E&C No. | E4: Registration No. | F4: Year | G4: Age | H4: Fuel cost/h | I4: Operator/h | J4: PM/h (age-adj.) | K4: Major repair/h (age-adj.) | L4: Direct cost/h | M4: Overhead/h | N4: Total cost/h | O4: Profit/h (20%) | P4: Suggested WET /h | Q4: Current WET /h (Fleet sheet) | R4: P | S4: Q | T4: R | U4: S
A5: BACKHOE LOADER
A6: 1 | B6: Backhoe Loader | C6: BOB CAT B760 | D6: LB-22 | E6: ZB-2586 | F6: 2021 | G6: 5 | H6: ='Engineering Assumptions'!$C$18*'Engineering Assumptions'!$B$5*U6 -> 2101 | I6: ='Engineering Assumptions'!$B$8 -> 650 | J6: ='Engineering Assumptions'!$D$18*S6*U6 -> 180 | K6: ='Engineering Assumptions'!$E$18*T6*U6 -> 66 | L6: =H6+I6+J6+K6 -> 2997 | M6: =L6*'Engineering Assumptions'!$B$10 -> 449.55 | N6: =L6+M6 -> 3446.55 | O6: =N6*'Engineering Assumptions'!$B$11 -> 689.31 | P6: =MROUND(N6+O6,10) -> 4140 | Q6: ='Fleet Pricing'!H6 -> 4150 | R6: 5 | S6: 1 | T6: 0.3 | U6: 1
A7: 2 | B7: Backhoe Loader | C7: BOB CAT B760 | D7: LB-23 | E7: ZB-2587 | F7: 2021 | G7: 5 | H7: ='Engineering Assumptions'!$C$18*'Engineering Assumptions'!$B$5*U7 -> 2101 | I7: ='Engineering Assumptions'!$B$8 -> 650 | J7: ='Engineering Assumptions'!$D$18*S7*U7 -> 180 | K7: ='Engineering Assumptions'!$E$18*T7*U7 -> 66 | L7: =H7+I7+J7+K7 -> 2997 | M7: =L7*'Engineering Assumptions'!$B$10 -> 449.55 | N7: =L7+M7 -> 3446.55 | O7: =N7*'Engineering Assumptions'!$B$11 -> 689.31 | P7: =MROUND(N7+O7,10) -> 4140 | Q7: ='Fleet Pricing'!H7 -> 4150 | R7: 5 | S7: 1 | T7: 0.3 | U7: 1
A8: 3 | B8: Backhoe Loader | C8: BOB CAT B760 | D8: LB-24 | E8: ZB-2583 | F8: 2021 | G8: 5 | H8: ='Engineering Assumptions'!$C$18*'Engineering Assumptions'!$B$5*U8 -> 2101 | I8: ='Engineering Assumptions'!$B$8 -> 650 | J8: ='Engineering Assumptions'!$D$18*S8*U8 -> 180 | K8: ='Engineering Assumptions'!$E$18*T8*U8 -> 66 | L8: =H8+I8+J8+K8 -> 2997 | M8: =L8*'Engineering Assumptions'!$B$10 -> 449.55 | N8: =L8+M8 -> 3446.55 | O8: =N8*'Engineering Assumptions'!$B$11 -> 689.31 | P8: =MROUND(N8+O8,10) -> 4140 | Q8: ='Fleet Pricing'!H8 -> 4150 | R8: 5 | S8: 1 | T8: 0.3 | U8: 1
A9: 4 | B9: Backhoe Loader | C9: J.C.B 3DX | D9: LB-16 | E9: ZB-1547 | F9: 2020 | G9: 6 | H9: ='Engineering Assumptions'!$C$18*'Engineering Assumptions'!$B$5*U9 -> 2101 | I9: ='Engineering Assumptions'!$B$8 -> 650 | J9: ='Engineering Assumptions'!$D$18*S9*U9 -> 225 | K9: ='Engineering Assumptions'!$E$18*T9*U9 -> 165 | L9: =H9+I9+J9+K9 -> 3141 | M9: =L9*'Engineering Assumptions'!$B$10 -> 471.15 | N9: =L9+M9 -> 3612.15 | O9: =N9*'Engineering Assumptions'!$B$11 -> 722.43 | P9: =MROUND(N9+O9,10) -> 4330 | Q9: ='Fleet Pricing'!H9 -> 4150 | R9: 6 | S9: 1.25 | T9: 0.75 | U9: 1
A10: 5 | B10: Backhoe Loader | C10: J.C.B 3DX | D10: LB-17 | E10: ZB-1546 | F10: 2020 | G10: 6 | H10: ='Engineering Assumptions'!$C$18*'Engineering Assumptions'!$B$5*U10 -> 2101 | I10: ='Engineering Assumptions'!$B$8 -> 650 | J10: ='Engineering Assumptions'!$D$18*S10*U10 -> 225 | K10: ='Engineering Assumptions'!$E$18*T10*U10 -> 165 | L10: =H10+I10+J10+K10 -> 3141 | M10: =L10*'Engineering Assumptions'!$B$10 -> 471.15 | N10: =L10+M10 -> 3612.15 | O10: =N10*'Engineering Assumptions'!$B$11 -> 722.43 | P10: =MROUND(N10+O10,10) -> 4330 | Q10: ='Fleet Pricing'!H10 -> 4150 | R10: 6 | S10: 1.25 | T10: 0.75 | U10: 1
A11: 6 | B11: Backhoe Loader | C11: J.C.B 3DX | D11: LB-18 | E11: ZB-1548 | F11: 2020 | G11: 6 | H11: ='Engineering Assumptions'!$C$18*'Engineering Assumptions'!$B$5*U11 -> 2101 | I11: ='Engineering Assumptions'!$B$8 -> 650 | J11: ='Engineering Assumptions'!$D$18*S11*U11 -> 225 | K11: ='Engineering Assumptions'!$E$18*T11*U11 -> 165 | L11: =H11+I11+J11+K11 -> 3141 | M11: =L11*'Engineering Assumptions'!$B$10 -> 471.15 | N11: =L11+M11 -> 3612.15 | O11: =N11*'Engineering Assumptions'!$B$11 -> 722.43 | P11: =MROUND(N11+O11,10) -> 4330 | Q11: ='Fleet Pricing'!H11 -> 4150 | R11: 6 | S11: 1.25 | T11: 0.75 | U11: 1
A12: 7 | B12: Backhoe Loader | C12: J.C.B 3DX | D12: LB-19 | E12: ZB-1978 | F12: 2020 | G12: 6 | H12: ='Engineering Assumptions'!$C$18*'Engineering Assumptions'!$B$5*U12 -> 2101 | I12: ='Engineering Assumptions'!$B$8 -> 650 | J12: ='Engineering Assumptions'!$D$18*S12*U12 -> 225 | K12: ='Engineering Assumptions'!$E$18*T12*U12 -> 165 | L12: =H12+I12+J12+K12 -> 3141 | M12: =L12*'Engineering Assumptions'!$B$10 -> 471.15 | N12: =L12+M12 -> 3612.15 | O12: =N12*'Engineering Assumptions'!$B$11 -> 722.43 | P12: =MROUND(N12+O12,10) -> 4330 | Q12: ='Fleet Pricing'!H12 -> 4150 | R12: 6 | S12: 1.25 | T12: 0.75 | U12: 1
A13: 8 | B13: Backhoe Loader | C13: J.C.B 3DX | D13: LB-20 | E13: ZB-1979 | F13: 2020 | G13: 6 | H13: ='Engineering Assumptions'!$C$18*'Engineering Assumptions'!$B$5*U13 -> 2101 | I13: ='Engineering Assumptions'!$B$8 -> 650 | J13: ='Engineering Assumptions'!$D$18*S13*U13 -> 225 | K13: ='Engineering Assumptions'!$E$18*T13*U13 -> 165 | L13: =H13+I13+J13+K13 -> 3141 | M13: =L13*'Engineering Assumptions'!$B$10 -> 471.15 | N13: =L13+M13 -> 3612.15 | O13: =N13*'Engineering Assumptions'!$B$11 -> 722.43 | P13: =MROUND(N13+O13,10) -> 4330 | Q13: ='Fleet Pricing'!H13 -> 4150 | R13: 6 | S13: 1.25 | T13: 0.75 | U13: 1
A14: 9 | B14: Backhoe Loader | C14: J.C.B 3DX | D14: LB-21 | E14: ZB-1980 | F14: 2020 | G14: 6 | H14: ='Engineering Assumptions'!$C$18*'Engineering Assumptions'!$B$5*U14 -> 2101 | I14: ='Engineering Assumptions'!$B$8 -> 650 | J14: ='Engineering Assumptions'!$D$18*S14*U14 -> 225 | K14: ='Engineering Assumptions'!$E$18*T14*U14 -> 165 | L14: =H14+I14+J14+K14 -> 3141 | M14: =L14*'Engineering Assumptions'!$B$10 -> 471.15 | N14: =L14+M14 -> 3612.15 | O14: =N14*'Engineering Assumptions'!$B$11 -> 722.43 | P14: =MROUND(N14+O14,10) -> 4330 | Q14: ='Fleet Pricing'!H14 -> 4150 | R14: 6 | S14: 1.25 | T14: 0.75 | U14: 1
A15: 10 | B15: Backhoe Loader | C15: J.C.B 570ST | D15: LB-15 | E15: ZB-1047 | F15: 2019 | G15: 7 | H15: ='Engineering Assumptions'!$C$18*'Engineering Assumptions'!$B$5*U15 -> 2101 | I15: ='Engineering Assumptions'!$B$8 -> 650 | J15: ='Engineering Assumptions'!$D$18*S15*U15 -> 225 | K15: ='Engineering Assumptions'!$E$18*T15*U15 -> 165 | L15: =H15+I15+J15+K15 -> 3141 | M15: =L15*'Engineering Assumptions'!$B$10 -> 471.15 | N15: =L15+M15 -> 3612.15 | O15: =N15*'Engineering Assumptions'!$B$11 -> 722.43 | P15: =MROUND(N15+O15,10) -> 4330 | Q15: ='Fleet Pricing'!H15 -> 3820 | R15: 7 | S15: 1.25 | T15: 0.75 | U15: 1
A16: 11 | B16: Backhoe Loader | C16: JCB JCB 3DX | D16: LB-10 | E16: ZA-7034 | F16: 2016 | G16: 10 | H16: ='Engineering Assumptions'!$C$18*'Engineering Assumptions'!$B$5*U16 -> 2101 | I16: ='Engineering Assumptions'!$B$8 -> 650 | J16: ='Engineering Assumptions'!$D$18*S16*U16 -> 225 | K16: ='Engineering Assumptions'!$E$18*T16*U16 -> 165 | L16: =H16+I16+J16+K16 -> 3141 | M16: =L16*'Engineering Assumptions'!$B$10 -> 471.15 | N16: =L16+M16 -> 3612.15 | O16: =N16*'Engineering Assumptions'!$B$11 -> 722.43 | P16: =MROUND(N16+O16,10) -> 4330 | Q16: ='Fleet Pricing'!H16 -> 3820 | R16: 10 | S16: 1.25 | T16: 0.75 | U16: 1
A17: 12 | B17: Backhoe Loader | C17: JCB JCB 3DX | D17: LB-11 | E17: ZA-7092 | F17: 2016 | G17: 10 | H17: ='Engineering Assumptions'!$C$18*'Engineering Assumptions'!$B$5*U17 -> 2101 | I17: ='Engineering Assumptions'!$B$8 -> 650 | J17: ='Engineering Assumptions'!$D$18*S17*U17 -> 225 | K17: ='Engineering Assumptions'!$E$18*T17*U17 -> 165 | L17: =H17+I17+J17+K17 -> 3141 | M17: =L17*'Engineering Assumptions'!$B$10 -> 471.15 | N17: =L17+M17 -> 3612.15 | O17: =N17*'Engineering Assumptions'!$B$11 -> 722.43 | P17: =MROUND(N17+O17,10) -> 4330 | Q17: ='Fleet Pricing'!H17 -> 3820 | R17: 10 | S17: 1.25 | T17: 0.75 | U17: 1
... A29: 24 | B29: Backhoe Loader | C29: JCB SLP3CX | D29: LB-04 | E29: RS-0401 | F29: 1999 | G29: 27 | H29: ='Engineering Assumptions'!$C$18*'Engineering Assumptions'!$B$5*U29 -> 2101 | I29: ='Engineering Assumptions'!$B$8 -> 650 | J29: ='Engineering Assumptions'!$D$18*S29*U29 -> 432 | K29: ='Engineering Assumptions'!$E$18*T29*U29 -> 660 | L29: =H29+I29+J29+K29 -> 3843 | M29: =L29*'Engineering Assumptions'!$B$10 -> 576.45 | N29: =L29+M29 -> 4419.45 | O29: =N29*'Engineering Assumptions'!$B$11 -> 883.89 | P29: =MROUND(N29+O29,10) -> 5300 | Q29: ='Fleet Pricing'!H29 -> 2410 | R29: 27 | S29: 2.4 | T29: 3 | U29: 1
A30: WHEEL LOADER
A31: 25 | B31: Wheel Loader | C31: SHANTUI SL-50WN | D31: LD-09 | F31: 2020 | G31: 6 | H31: ='Engineering Assumptions'!$C$19*'Engineering Assumptions'!$B$5*U31 -> 4966 | I31: ='Engineering Assumptions'!$B$8 -> 650 | J31: ='Engineering Assumptions'!$D$19*S31*U31 -> 437.5 | K31: ='Engineering Assumptions'!$E$19*T31*U31 -> 360 | L31: =H31+I31+J31+K31 -> 6413.5 | M31: =L31*'Engineering Assumptions'!$B$10 -> 962.025 | N31: =L31+M31 -> 7375.525 | O31: =N31*'Engineering Assumptions'!$B$11 -> 1475.105 | P31: =MROUND(N31+O31,10) -> 8850 | Q31: ='Fleet Pricing'!H31 -> 8450 | R31: 6 | S31: 1.25 | T31: 0.75 | U31: 1
A32: 26 | B32: Wheel Loader | C32: KOMATSU WA-80SS | D32: LD-07 | F32: 2015 | G32: 11 | H32: ='Engineering Assumptions'!$C$19*'Engineering Assumptions'!$B$5*U32 -> 4966 | I32: ='Engineering Assumptions'!$B$8 -> 650 | J32: ='Engineering Assumptions'!$D$19*S32*U32 -> 542.5 | K32: ='Engineering Assumptions'!$E$19*T32*U32 -> 648 | L32: =H32+I32+J32+K32 -> 6806.5 | M32: =L32*'Engineering Assumptions'!$B$10 -> 1020.975 | N32: =L32+M32 -> 7827.475 | O32: =N32*'Engineering Assumptions'!$B$11 -> 1565.495 | P32: =MROUND(N32+O32,10) -> 9390 | Q32: ='Fleet Pricing'!H32 -> 7770 | R32: 11 | S32: 1.55 | T32: 1.35 | U32: 1
A33: 27 | B33: Wheel Loader | C33: KOMATSU WA150 | D33: LD-05 | F33: 2014 | G33: 12 | H33: ='Engineering Assumptions'!$C$19*'Engineering Assumptions'!$B$5*U33 -> 4966 | I33: ='Engineering Assumptions'!$B$8 -> 650 | J33: ='Engineering Assumptions'!$D$19*S33*U33 -> 542.5 | K33: ='Engineering Assumptions'!$E$19*T33*U33 -> 648 | L33: =H33+I33+J33+K33 -> 6806.5 | M33: =L33*'Engineering Assumptions'!$B$10 -> 1020.975 | N33: =L33+M33 -> 7827.475 | O33: =N33*'Engineering Assumptions'!$B$11 -> 1565.495 | P33: =MROUND(N33+O33,10) -> 9390 | Q33: ='Fleet Pricing'!H33 -> 6930 | R33: 12 | S33: 1.55 | T33: 1.35 | U33: 1
A34: 28 | B34: Wheel Loader | C34: SANTUI SL30W | D34: LD-08 | F34: 2014 | G34: 12 | H34: ='Engineering Assumptions'!$C$19*'Engineering Assumptions'!$B$5*U34 -> 4966 | I34: ='Engineering Assumptions'!$B$8 -> 650 | J34: ='Engineering Assumptions'!$D$19*S34*U34 -> 542.5 | K34: ='Engineering Assumptions'!$E$19*T34*U34 -> 648 | L34: =H34+I34+J34+K34 -> 6806.5 | M34: =L34*'Engineering Assumptions'!$B$10 -> 1020.975 | N34: =L34+M34 -> 7827.475 | O34: =N34*'Engineering Assumptions'!$B$11 -> 1565.495 | P34: =MROUND(N34+O34,10) -> 9390 | Q34: ='Fleet Pricing'!H34 -> 6930 | R34: 12 | S34: 1.55 | T34: 1.35 | U34: 1
A35: 29 | B35: Wheel Loader | C35: KOMATSU 924F | D35: LD-04 | F35: 2013 | G35: 13 | H35: ='Engineering Assumptions'!$C$19*'Engineering Assumptions'!$B$5*U35 -> 4966 | I35: ='Engineering Assumptions'!$B$8 -> 650 | J35: ='Engineering Assumptions'!$D$19*S35*U35 -> 542.5 | K35: ='Engineering Assumptions'!$E$19*T35*U35 -> 648 | L35: =H35+I35+J35+K35 -> 6806.5 | M35: =L35*'Engineering Assumptions'!$B$10 -> 1020.975 | N35: =L35+M35 -> 7827.475 | O35: =N35*'Engineering Assumptions'!$B$11 -> 1565.495 | P35: =MROUND(N35+O35,10) -> 9390 | Q35: ='Fleet Pricing'!H35 -> 6930 | R35: 13 | S35: 1.55 | T35: 1.35 | U35: 1
A36: 30 | B36: Wheel Loader | C36: KOMATSU 510 | D36: LD-06 | E36: ZA-3116 | F36: 2013 | G36: 13 | H36: ='Engineering Assumptions'!$C$19*'Engineering Assumptions'!$B$5*U36 -> 4966 | I36: ='Engineering Assumptions'!$B$8 -> 650 | J36: ='Engineering Assumptions'!$D$19*S36*U36 -> 542.5 | K36: ='Engineering Assumptions'!$E$19*T36*U36 -> 648 | L36: =H36+I36+J36+K36 -> 6806.5 | M36: =L36*'Engineering Assumptions'!$B$10 -> 1020.975 | N36: =L36+M36 -> 7827.475 | O36: =N36*'Engineering Assumptions'!$B$11 -> 1565.495 | P36: =MROUND(N36+O36,10) -> 9390 | Q36: ='Fleet Pricing'!H36 -> 6930 | R36: 13 | S36: 1.55 | T36: 1.35 | U36: 1
A37: 31 | B37: Wheel Loader | C37: KOMATSU WA100 | D37: LD-03 | F37: 2012 | G37: 14 | H37: ='Engineering Assumptions'!$C$19*'Engineering Assumptions'!$B$5*U37 -> 4966 | I37: ='Engineering Assumptions'!$B$8 -> 650 | J37: ='Engineering Assumptions'!$D$19*S37*U37 -> 542.5 | K37: ='Engineering Assumptions'!$E$19*T37*U37 -> 648 | L37: =H37+I37+J37+K37 -> 6806.5 | M37: =L37*'Engineering Assumptions'!$B$10 -> 1020.975 | N37: =L37+M37 -> 7827.475 | O37: =N37*'Engineering Assumptions'!$B$11 -> 1565.495 | P37: =MROUND(N37+O37,10) -> 9390 | Q37: ='Fleet Pricing'!H37 -> 6930 | R37: 14 | S37: 1.55 | T37: 1.35 | U37: 1
A38: 32 | B38: Wheel Loader | C38: CAT CAT910 | D38: LD-02 | F38: 2010 | G38: 16 | H38: ='Engineering Assumptions'!$C$19*'Engineering Assumptions'!$B$5*U38 -> 4966 | I38: ='Engineering Assumptions'!$B$8 -> 650 | J38: ='Engineering Assumptions'!$D$19*S38*U38 -> 682.5 | K38: ='Engineering Assumptions'!$E$19*T38*U38 -> 1008 | L38: =H38+I38+J38+K38 -> 7306.5 | M38: =L38*'Engineering Assumptions'!$B$10 -> 1095.975 | N38: =L38+M38 -> 8402.475 | O38: =N38*'Engineering Assumptions'!$B$11 -> 1680.495 | P38: =MROUND(N38+O38,10) -> 10080 | Q38: ='Fleet Pricing'!H38 -> 6930 | R38: 16 | S38: 1.95 | T38: 2.1 | U38: 1
A39: 33 | B39: Wheel Loader | C39: CAT 910E | D39: LD-01 | F39: 2009 | G39: 17 | H39: ='Engineering Assumptions'!$C$19*'Engineering Assumptions'!$B$5*U39 -> 4966 | I39: ='Engineering Assumptions'!$B$8 -> 650 | J39: ='Engineering Assumptions'!$D$19*S39*U39 -> 682.5 | K39: ='Engineering Assumptions'!$E$19*T39*U39 -> 1008 | L39: =H39+I39+J39+K39 -> 7306.5 | M39: =L39*'Engineering Assumptions'!$B$10 -> 1095.975 | N39: =L39+M39 -> 8402.475 | O39: =N39*'Engineering Assumptions'!$B$11 -> 1680.495 | P39: =MROUND(N39+O39,10) -> 10080 | Q39: ='Fleet Pricing'!H39 -> 6080 | R39: 17 | S39: 1.95 | T39: 2.1 | U39: 1
A40: TRUCK MIXER
A41: 34 | B41: Truck Mixer | C41: TATA LPK 1618 | D41: TM-18 | E41: ZA-8511 | F41: 2017 | G41: 9 | H41: ='Engineering Assumptions'!$C$20*'Engineering Assumptions'!$B$5*U41 -> 2674 | I41: ='Engineering Assumptions'!$B$8 -> 650 | J41: ='Engineering Assumptions'!$D$20*S41*U41 -> 275 | K41: ='Engineering Assumptions'!$E$20*T41*U41 -> 210 | L41: =H41+I41+J41+K41 -> 3809 | M41: =L41*'Engineering Assumptions'!$B$10 -> 571.35 | N41: =L41+M41 -> 4380.35 | O41: =N41*'Engineering Assumptions'!$B$11 -> 876.07 | P41: =MROUND(N41+O41,10) -> 5260 | Q41: ='Fleet Pricing'!H41 -> 4460 | R41: 9 | S41: 1.25 | T41: 0.75 | U41: 1
A42: 35 | B42: Truck Mixer | C42: TATA LPK 2518 | D42: TM-19 | E42: ZA-8445 | F42: 2017 | G42: 9 | H42: ='Engineering Assumptions'!$C$20*'Engineering Assumptions'!$B$5*U42 -> 2674 | I42: ='Engineering Assumptions'!$B$8 -> 650 | J42: ='Engineering Assumptions'!$D$20*S42*U42 -> 275 | K42: ='Engineering Assumptions'!$E$20*T42*U42 -> 210 | L42: =H42+I42+J42+K42 -> 3809 | M42: =L42*'Engineering Assumptions'!$B$10 -> 571.35 | N42: =L42+M42 -> 4380.35 | O42: =N42*'Engineering Assumptions'!$B$11 -> 876.07 | P42: =MROUND(N42+O42,10) -> 5260 | Q42: ='Fleet Pricing'!H42 -> 4460 | R42: 9 | S42: 1.25 | T42: 0.75 | U42: 1
A43: 36 | B43: Truck Mixer | C43: TATA LPK 1618 | D43: TM-21 | E43: ZA-0050 | F43: 2017 | G43: 9 | H43: ='Engineering Assumptions'!$C$20*'Engineering Assumptions'!$B$5*U43 -> 2674 | I43: ='Engineering Assumptions'!$B$8 -> 650 | J43: ='Engineering Assumptions'!$D$20*S43*U43 -> 275 | K43: ='Engineering Assumptions'!$E$20*T43*U43 -> 210 | L43: =H43+I43+J43+K43 -> 3809 | M43: =L43*'Engineering Assumptions'!$B$10 -> 571.35 | N43: =L43+M43 -> 4380.35 | O43: =N43*'Engineering Assumptions'!$B$11 -> 876.07 | P43: =MROUND(N43+O43,10) -> 5260 | Q43: ='Fleet Pricing'!H43 -> 4460 | R43: 9 | S43: 1.25 | T43: 0.75 | U43: 1
A44: 37 | B44: Truck Mixer | C44: ELCHER TERRA 16 | D44: TM-11 | E44: ZA-7291 | F44: 2016 | G44: 10 | H44: ='Engineering Assumptions'!$C$20*'Engineering Assumptions'!$B$5*U44 -> 2674 | I44: ='Engineering Assumptions'!$B$8 -> 650 | J44: ='Engineering Assumptions'!$D$20*S44*U44 -> 275 | K44: ='Engineering Assumptions'!$E$20*T44*U44 -> 210 | L44: =H44+I44+J44+K44 -> 3809 | M44: =L44*'Engineering Assumptions'!$B$10 -> 571.35 | N44: =L44+M44 -> 4380.35 | O44: =N44*'Engineering Assumptions'!$B$11 -> 876.07 | P44: =MROUND(N44+O44,10) -> 5260 | Q44: ='Fleet Pricing'!H44 -> 4460 | R44: 10 | S44: 1.25 | T44: 0.75 | U44: 1
A45: 38 | B45: Truck Mixer | C45: ELCHER TERRA 16 | D45: TM-12 | E45: ZA-7290 | F45: 2016 | G45: 10 | H45: ='Engineering Assumptions'!$C$20*'Engineering Assumptions'!$B$5*U45 -> 2674 | I45: ='Engineering Assumptions'!$B$8 -> 650 | J45: ='Engineering Assumptions'!$D$20*S45*U45 -> 275 | K45: ='Engineering Assumptions'!$E$20*T45*U45 -> 210 | L45: =H45+I45+J45+K45 -> 3809 | M45: =L45*'Engineering Assumptions'!$B$10 -> 571.35 | N45: =L45+M45 -> 4380.35 | O45: =N45*'Engineering Assumptions'!$B$11 -> 876.07 | P45: =MROUND(N45+O45,10) -> 5260 | Q45: ='Fleet Pricing'!H45 -> 4460 | R45: 10 | S45: 1.25 | T45: 0.75 | U45: 1
A46: 39 | B46: Truck Mixer | C46: TATA LPK 2518 | D46: TM-14 | E46: ZA-7810 | F46: 2016 | G46: 10 | H46: ='Engineering Assumptions'!$C$20*'Engineering Assumptions'!$B$5*U46 -> 2674 | I46: ='Engineering Assumptions'!$B$8 -> 650 | J46: ='Engineering Assumptions'!$D$20*S46*U46 -> 275 | K46: ='Engineering Assumptions'!$E$20*T46*U46 -> 210 | L46: =H46+I46+J46+K46 -> 3809 | M46: =L46*'Engineering Assumptions'!$B$10 -> 571.35 | N46: =L46+M46 -> 4380.35 | O46: =N46*'Engineering Assumptions'!$B$11 -> 876.07 | P46: =MROUND(N46+O46,10) -> 5260 | Q46: ='Fleet Pricing'!H46 -> 4460 | R46: 10 | S46: 1.25 | T46: 0.75 | U46: 1
A47: 40 | B47: Truck Mixer | C47: TATA LPK 2518 | D47: TM-15 | E47: ZA-7925 | F47: 2016 | G47: 10 | H47: ='Engineering Assumptions'!$C$20*'Engineering Assumptions'!$B$5*U47 -> 2674 | I47: ='Engineering Assumptions'!$B$8 -> 650 | J47: ='Engineering Assumptions'!$D$20*S47*U47 -> 275 | K47: ='Engineering Assumptions'!$E$20*T47*U47 -> 210 | L47: =H47+I47+J47+K47 -> 3809 | M47: =L47*'Engineering Assumptions'!$B$10 -> 571.35 | N47: =L47+M47 -> 4380.35 | O47: =N47*'Engineering Assumptions'!$B$11 -> 876.07 | P47: =MROUND(N47+O47,10) -> 5260 | Q47: ='Fleet Pricing'!H47 -> 4460 | R47: 10 | S47: 1.25 | T47: 0.75 | U47: 1
A48: 41 | B48: Truck Mixer | C48: TATA LPK 2518 | D48: TM-16 | E48: ZA-8033 | F48: 2016 | G48: 10 | H48: ='Engineering Assumptions'!$C$20*'Engineering Assumptions'!$B$5*U48 -> 2674 | I48: ='Engineering Assumptions'!$B$8 -> 650 | J48: ='Engineering Assumptions'!$D$20*S48*U48 -> 275 | K48: ='Engineering Assumptions'!$E$20*T48*U48 -> 210 | L48: =H48+I48+J48+K48 -> 3809 | M48: =L48*'Engineering Assumptions'!$B$10 -> 571.35 | N48: =L48+M48 -> 4380.35 | O48: =N48*'Engineering Assumptions'!$B$11 -> 876.07 | P48: =MROUND(N48+O48,10) -> 5260 | Q48: ='Fleet Pricing'!H48 -> 4460 | R48: 10 | S48: 1.25 | T48: 0.75 | U48: 1
A49: 42 | B49: Truck Mixer | C49: ASHOK LEYLAND TUSKER SUPER 1613 | D49: TM-10 | E49: ZA-6395 | F49: 2015 | G49: 11 | H49: ='Engineering Assumptions'!$C$20*'Engineering Assumptions'!$B$5*U49 -> 2674 | I49: ='Engineering Assumptions'!$B$8 -> 650 | J49: ='Engineering Assumptions'!$D$20*S49*U49 -> 341 | K49: ='Engineering Assumptions'!$E$20*T49*U49 -> 378 | L49: =H49+I49+J49+K49 -> 4043 | M49: =L49*'Engineering Assumptions'!$B$10 -> 606.45 | N49: =L49+M49 -> 4649.45 | O49: =N49*'Engineering Assumptions'!$B$11 -> 929.89 | P49: =MROUND(N49+O49,10) -> 5580 | Q49: ='Fleet Pricing'!H49 -> 4460 | R49: 11 | S49: 1.55 | T49: 1.35 | U49: 1
A50: 43 | B50: Truck Mixer | C50: MITSUBISHI KK-FE73EB CANTER | D50: TM-09 | E50: ZA-6255 | F50: 2003 | G50: 23 | H50: ='Engineering Assumptions'!$C$20*'Engineering Assumptions'!$B$5*U50 -> 2674 | I50: ='Engineering Assumptions'!$B$8 -> 650 | J50: ='Engineering Assumptions'!$D$20*S50*U50 -> 528 | K50: ='Engineering Assumptions'!$E$20*T50*U50 -> 840 | L50: =H50+I50+J50+K50 -> 4692 | M50: =L50*'Engineering Assumptions'!$B$10 -> 703.8 | N50: =L50+M50 -> 5395.8 | O50: =N50*'Engineering Assumptions'!$B$11 -> 1079.16 | P50: =MROUND(N50+O50,10) -> 6470 | Q50: ='Fleet Pricing'!H50 -> 3150 | R50: 23 | S50: 2.4 | T50: 3 | U50: 1
A51: 44 | B51: Truck Mixer | C51: ISUZU KK-NRR35C4 FORWARD | D51: TM-04 | E51: LL-0690 | F51: 2000 | G51: 26 | H51: ='Engineering Assumptions'!$C$20*'Engineering Assumptions'!$B$5*U51 -> 2674 | I51: ='Engineering Assumptions'!$B$8 -> 650 | J51: ='Engineering Assumptions'!$D$20*S51*U51 -> 528 | K51: ='Engineering Assumptions'!$E$20*T51*U51 -> 840 | L51: =H51+I51+J51+K51 -> 4692 | M51: =L51*'Engineering Assumptions'!$B$10 -> 703.8 | N51: =L51+M51 -> 5395.8 | O51: =N51*'Engineering Assumptions'!$B$11 -> 1079.16 | P51: =MROUND(N51+O51,10) -> 6470 | Q51: ='Fleet Pricing'!H51 -> 3150 | R51: 26 | S51: 2.4 | T51: 3 | U51: 1
A52: 45 | B52: Truck Mixer | C52: ISUZU KC-NRR33C20 | D52: TM-03 | E52: LK-5047 | F52: 1996 | G52: 30 | H52: ='Engineering Assumptions'!$C$20*'Engineering Assumptions'!$B$5*U52 -> 2674 | I52: ='Engineering Assumptions'!$B$8 -> 650 | J52: ='Engineering Assumptions'!$D$20*S52*U52 -> 528 | K52: ='Engineering Assumptions'!$E$20*T52*U52 -> 840 | L52: =H52+I52+J52+K52 -> 4692 | M52: =L52*'Engineering Assumptions'!$B$10 -> 703.8 | N52: =L52+M52 -> 5395.8 | O52: =N52*'Engineering Assumptions'!$B$11 -> 1079.16 | P52: =MROUND(N52+O52,10) -> 6470 | Q52: ='Fleet Pricing'!H52 -> 2810 | R52: 30 | S52: 2.4 | T52: 3 | U52: 1
... A56: 49 | B56: Truck Mixer | C56: MITSUBISHI U.FE315BN | D56: TM-06 | E56: LH-5475 | F56: 1991 | G56: 35 | H56: ='Engineering Assumptions'!$C$20*'Engineering Assumptions'!$B$5*U56 -> 2674 | I56: ='Engineering Assumptions'!$B$8 -> 650 | J56: ='Engineering Assumptions'!$D$20*S56*U56 -> 528 | K56: ='Engineering Assumptions'!$E$20*T56*U56 -> 840 | L56: =H56+I56+J56+K56 -> 4692 | M56: =L56*'Engineering Assumptions'!$B$10 -> 703.8 | N56: =L56+M56 -> 5395.8 | O56: =N56*'Engineering Assumptions'!$B$11 -> 1079.16 | P56: =MROUND(N56+O56,10) -> 6470 | Q56: ='Fleet Pricing'!H56 -> 2810 | R56: 35 | S56: 2.4 | T56: 3 | U56: 1
A57: SELF LOADER MIXER
A58: 50 | B58: Self Loader Mixer | C58: FIORI BF08H01307 | D58: TM-20 | E58: Fiori | F58: 2018 | G58: 8 | H58: ='Engineering Assumptions'!$C$21*'Engineering Assumptions'!$B$5*U58 -> 3056 | I58: ='Engineering Assumptions'!$B$8 -> 650 | J58: ='Engineering Assumptions'!$D$21*S58*U58 -> 325 | K58: ='Engineering Assumptions'!$E$21*T58*U58 -> 240 | L58: =H58+I58+J58+K58 -> 4271 | M58: =L58*'Engineering Assumptions'!$B$10 -> 640.65 | N58: =L58+M58 -> 4911.65 | O58: =N58*'Engineering Assumptions'!$B$11 -> 982.33 | P58: =MROUND(N58+O58,10) -> 5890 | Q58: ='Fleet Pricing'!H58 -> 4880 | R58: 8 | S58: 1.25 | T58: 0.75 | U58: 1
A59: 51 | B59: Self Loader Mixer | C59: FIORI 8FO8H01246 | D59: TM-13 | E59: Fiori | F59: 2017 | G59: 9 | H59: ='Engineering Assumptions'!$C$21*'Engineering Assumptions'!$B$5*U59 -> 3056 | I59: ='Engineering Assumptions'!$B$8 -> 650 | J59: ='Engineering Assumptions'!$D$21*S59*U59 -> 325 | K59: ='Engineering Assumptions'!$E$21*T59*U59 -> 240 | L59: =H59+I59+J59+K59 -> 4271 | M59: =L59*'Engineering Assumptions'!$B$10 -> 640.65 | N59: =L59+M59 -> 4911.65 | O59: =N59*'Engineering Assumptions'!$B$11 -> 982.33 | P59: =MROUND(N59+O59,10) -> 5890 | Q59: ='Fleet Pricing'!H59 -> 4880 | R59: 9 | S59: 1.25 | T59: 0.75 | U59: 1
A60: 52 | B60: Self Loader Mixer | C60: FIORI 8FO8H01252 | D60: TM-17 | E60: Fiori | F60: 2017 | G60: 9 | H60: ='Engineering Assumptions'!$C$21*'Engineering Assumptions'!$B$5*U60 -> 3056 | I60: ='Engineering Assumptions'!$B$8 -> 650 | J60: ='Engineering Assumptions'!$D$21*S60*U60 -> 325 | K60: ='Engineering Assumptions'!$E$21*T60*U60 -> 240 | L60: =H60+I60+J60+K60 -> 4271 | M60: =L60*'Engineering Assumptions'!$B$10 -> 640.65 | N60: =L60+M60 -> 4911.65 | O60: =N60*'Engineering Assumptions'!$B$11 -> 982.33 | P60: =MROUND(N60+O60,10) -> 5890 | Q60: ='Fleet Pricing'!H60 -> 4880 | R60: 9 | S60: 1.25 | T60: 0.75 | U60: 1
A61: STATIC ROLLER
A62: 53 | B62: Static Roller | C62: DYNAPAC CC425 | D62: SR-17 | F62: 2021 | G62: 5 | H62: ='Engineering Assumptions'!$C$22*'Engineering Assumptions'!$B$5*U62 -> 3056 | I62: ='Engineering Assumptions'!$B$8 -> 650 | J62: ='Engineering Assumptions'!$D$22*S62*U62 -> 230 | K62: ='Engineering Assumptions'!$E$22*T62*U62 -> 93 | L62: =H62+I62+J62+K62 -> 4029 | M62: =L62*'Engineering Assumptions'!$B$10 -> 604.35 | N62: =L62+M62 -> 4633.35 | O62: =N62*'Engineering Assumptions'!$B$11 -> 926.67 | P62: =MROUND(N62+O62,10) -> 5560 | Q62: ='Fleet Pricing'!H62 -> 4600 | R62: 5 | S62: 1 | T62: 0.3 | U62: 1
A63: 54 | B63: Static Roller | C63: DYNAPAC CA30D | D63: SR-18 | F63: 2021 | G63: 5 | H63: ='Engineering Assumptions'!$C$22*'Engineering Assumptions'!$B$5*U63 -> 3056 | I63: ='Engineering Assumptions'!$B$8 -> 650 | J63: ='Engineering Assumptions'!$D$22*S63*U63 -> 230 | K63: ='Engineering Assumptions'!$E$22*T63*U63 -> 93 | L63: =H63+I63+J63+K63 -> 4029 | M63: =L63*'Engineering Assumptions'!$B$10 -> 604.35 | N63: =L63+M63 -> 4633.35 | O63: =N63*'Engineering Assumptions'!$B$11 -> 926.67 | P63: =MROUND(N63+O63,10) -> 5560 | Q63: ='Fleet Pricing'!H63 -> 4600 | R63: 5 | S63: 1 | T63: 0.3 | U63: 1
A64: 55 | B64: Static Roller | C64: DYNAPAC CA30D | D64: SR-19 | F64: 2021 | G64: 5 | H64: ='Engineering Assumptions'!$C$22*'Engineering Assumptions'!$B$5*U64 -> 3056 | I64: ='Engineering Assumptions'!$B$8 -> 650 | J64: ='Engineering Assumptions'!$D$22*S64*U64 -> 230 | K64: ='Engineering Assumptions'!$E$22*T64*U64 -> 93 | L64: =H64+I64+J64+K64 -> 4029 | M64: =L64*'Engineering Assumptions'!$B$10 -> 604.35 | N64: =L64+M64 -> 4633.35 | O64: =N64*'Engineering Assumptions'!$B$11 -> 926.67 | P64: =MROUND(N64+O64,10) -> 5560 | Q64: ='Fleet Pricing'!H64 -> 4600 | R64: 5 | S64: 1 | T64: 0.3 | U64: 1
A65: 56 | B65: Static Roller | C65: CASE 1107EXD | D65: SR-08 | F65: 2017 | G65: 9 | H65: ='Engineering Assumptions'!$C$22*'Engineering Assumptions'!$B$5*U65 -> 3056 | I65: ='Engineering Assumptions'!$B$8 -> 650 | J65: ='Engineering Assumptions'!$D$22*S65*U65 -> 287.5 | K65: ='Engineering Assumptions'!$E$22*T65*U65 -> 232.5 | L65: =H65+I65+J65+K65 -> 4226 | M65: =L65*'Engineering Assumptions'!$B$10 -> 633.9 | N65: =L65+M65 -> 4859.9 | O65: =N65*'Engineering Assumptions'!$B$11 -> 971.98 | P65: =MROUND(N65+O65,10) -> 5830 | Q65: ='Fleet Pricing'!H65 -> 4230 | R65: 9 | S65: 1.25 | T65: 0.75 | U65: 1
A66: 57 | B66: Static Roller | C66: CASE 1107EXD | D66: SR-09 | F66: 2017 | G66: 9 | H66: ='Engineering Assumptions'!$C$22*'Engineering Assumptions'!$B$5*U66 -> 3056 | I66: ='Engineering Assumptions'!$B$8 -> 650 | J66: ='Engineering Assumptions'!$D$22*S66*U66 -> 287.5 | K66: ='Engineering Assumptions'!$E$22*T66*U66 -> 232.5 | L66: =H66+I66+J66+K66 -> 4226 | M66: =L66*'Engineering Assumptions'!$B$10 -> 633.9 | N66: =L66+M66 -> 4859.9 | O66: =N66*'Engineering Assumptions'!$B$11 -> 971.98 | P66: =MROUND(N66+O66,10) -> 5830 | Q66: ='Fleet Pricing'!H66 -> 4230 | R66: 9 | S66: 1.25 | T66: 0.75 | U66: 1
A67: 58 | B67: Static Roller | C67: HAMM HAMM 311D | D67: SR-12 | F67: 2016 | G67: 10 | H67: ='Engineering Assumptions'!$C$22*'Engineering Assumptions'!$B$5*U67 -> 3056 | I67: ='Engineering Assumptions'!$B$8 -> 650 | J67: ='Engineering Assumptions'!$D$22*S67*U67 -> 287.5 | K67: ='Engineering Assumptions'!$E$22*T67*U67 -> 232.5 | L67: =H67+I67+J67+K67 -> 4226 | M67: =L67*'Engineering Assumptions'!$B$10 -> 633.9 | N67: =L67+M67 -> 4859.9 | O67: =N67*'Engineering Assumptions'!$B$11 -> 971.98 | P67: =MROUND(N67+O67,10) -> 5830 | Q67: ='Fleet Pricing'!H67 -> 4230 | R67: 10 | S67: 1.25 | T67: 0.75 | U67: 1
A68: 59 | B68: Static Roller | C68: CASE — | D68: SR-06 | F68: 2014 | G68: 12 | H68: ='Engineering Assumptions'!$C$22*'Engineering Assumptions'!$B$5*U68 -> 3056 | I68: ='Engineering Assumptions'!$B$8 -> 650 | J68: ='Engineering Assumptions'!$D$22*S68*U68 -> 356.5 | K68: ='Engineering Assumptions'!$E$22*T68*U68 -> 418.5 | L68: =H68+I68+J68+K68 -> 4481 | M68: =L68*'Engineering Assumptions'!$B$10 -> 672.15 | N68: =L68+M68 -> 5153.15 | O68: =N68*'Engineering Assumptions'!$B$11 -> 1030.63 | P68: =MROUND(N68+O68,10) -> 6180 | Q68: ='Fleet Pricing'!H68 -> 3770 | R68: 12 | S68: 1.55 | T68: 1.35 | U68: 1
A69: 60 | B69: Static Roller | C69: SAKAI SW-900 | D69: SR-05 | F69: 2014 | G69: 12 | H69: ='Engineering Assumptions'!$C$22*'Engineering Assumptions'!$B$5*U69 -> 3056 | I69: ='Engineering Assumptions'!$B$8 -> 650 | J69: ='Engineering Assumptions'!$D$22*S69*U69 -> 356.5 | K69: ='Engineering Assumptions'!$E$22*T69*U69 -> 418.5 | L69: =H69+I69+J69+K69 -> 4481 | M69: =L69*'Engineering Assumptions'!$B$10 -> 672.15 | N69: =L69+M69 -> 5153.15 | O69: =N69*'Engineering Assumptions'!$B$11 -> 1030.63 | P69: =MROUND(N69+O69,10) -> 6180 | Q69: ='Fleet Pricing'!H69 -> 3770 | R69: 12 | S69: 1.55 | T69: 1.35 | U69: 1
A70: 61 | B70: Static Roller | C70: (Unknown) R12 | D70: SR-04 | F70: 2013 | G70: 13 | H70: ='Engineering Assumptions'!$C$22*'Engineering Assumptions'!$B$5*U70 -> 3056 | I70: ='Engineering Assumptions'!$B$8 -> 650 | J70: ='Engineering Assumptions'!$D$22*S70*U70 -> 356.5 | K70: ='Engineering Assumptions'!$E$22*T70*U70 -> 418.5 | L70: =H70+I70+J70+K70 -> 4481 | M70: =L70*'Engineering Assumptions'!$B$10 -> 672.15 | N70: =L70+M70 -> 5153.15 | O70: =N70*'Engineering Assumptions'!$B$11 -> 1030.63 | P70: =MROUND(N70+O70,10) -> 6180 | Q70: ='Fleet Pricing'!H70 -> 3770 | R70: 13 | S70: 1.55 | T70: 1.35 | U70: 1
A71: 62 | B71: Static Roller | C71: (Unknown) — | D71: SR-01 | F71: 2012 | G71: 14 | H71: ='Engineering Assumptions'!$C$22*'Engineering Assumptions'!$B$5*U71 -> 3056 | I71: ='Engineering Assumptions'!$B$8 -> 650 | J71: ='Engineering Assumptions'!$D$22*S71*U71 -> 356.5 | K71: ='Engineering Assumptions'!$E$22*T71*U71 -> 418.5 | L71: =H71+I71+J71+K71 -> 4481 | M71: =L71*'Engineering Assumptions'!$B$10 -> 672.15 | N71: =L71+M71 -> 5153.15 | O71: =N71*'Engineering Assumptions'!$B$11 -> 1030.63 | P71: =MROUND(N71+O71,10) -> 6180 | Q71: ='Fleet Pricing'!H71 -> 3770 | R71: 14 | S71: 1.55 | T71: 1.35 | U71: 1
A72: 63 | B72: Static Roller | C72: (Unknown) — | D72: SR-03 | F72: 2012 | G72: 14 | H72: ='Engineering Assumptions'!$C$22*'Engineering Assumptions'!$B$5*U72 -> 3056 | I72: ='Engineering Assumptions'!$B$8 -> 650 | J72: ='Engineering Assumptions'!$D$22*S72*U72 -> 356.5 | K72: ='Engineering Assumptions'!$E$22*T72*U72 -> 418.5 | L72: =H72+I72+J72+K72 -> 4481 | M72: =L72*'Engineering Assumptions'!$B$10 -> 672.15 | N72: =L72+M72 -> 5153.15 | O72: =N72*'Engineering Assumptions'!$B$11 -> 1030.63 | P72: =MROUND(N72+O72,10) -> 6180 | Q72: ='Fleet Pricing'!H72 -> 3770 | R72: 14 | S72: 1.55 | T72: 1.35 | U72: 1
A73: 64 | B73: Static Roller | C73: IR 2860-01 | D73: SR-07 | F73: 2010 | G73: 16 | H73: ='Engineering Assumptions'!$C$22*'Engineering Assumptions'!$B$5*U73 -> 3056 | I73: ='Engineering Assumptions'!$B$8 -> 650 | J73: ='Engineering Assumptions'!$D$22*S73*U73 -> 448.5 | K73: ='Engineering Assumptions'!$E$22*T73*U73 -> 651 | L73: =H73+I73+J73+K73 -> 4805.5 | M73: =L73*'Engineering Assumptions'!$B$10 -> 720.825 | N73: =L73+M73 -> 5526.325 | O73: =N73*'Engineering Assumptions'!$B$11 -> 1105.265 | P73: =MROUND(N73+O73,10) -> 6630 | Q73: ='Fleet Pricing'!H73 -> 3770 | R73: 16 | S73: 1.95 | T73: 2.1 | U73: 1
... A80: 71 | B80: Static Roller | C80: SAKAI R2V | D80: SR-14 | F80: — | G80: 30 | H80: ='Engineering Assumptions'!$C$22*'Engineering Assumptions'!$B$5*U80 -> 3056 | I80: ='Engineering Assumptions'!$B$8 -> 650 | J80: ='Engineering Assumptions'!$D$22*S80*U80 -> 552 | K80: ='Engineering Assumptions'!$E$22*T80*U80 -> 930 | L80: =H80+I80+J80+K80 -> 5188 | M80: =L80*'Engineering Assumptions'!$B$10 -> 778.2 | N80: =L80+M80 -> 5966.2 | O80: =N80*'Engineering Assumptions'!$B$11 -> 1193.24 | P80: =MROUND(N80+O80,10) -> 7160 | Q80: ='Fleet Pricing'!H80 -> 2670 | R80: 30 | S80: 2.4 | T80: 3 | U80: 1
A81: VIBRATING ROLLER
A82: 72 | B82: Vibrating Roller | C82: (Unknown) — | D82: VR-22 | F82: 2017 | G82: 9 | H82: ='Engineering Assumptions'!$C$23*'Engineering Assumptions'!$B$5*U82 -> 1910 | I82: ='Engineering Assumptions'!$B$8 -> 650 | J82: ='Engineering Assumptions'!$D$23*S82*U82 -> 225 | K82: ='Engineering Assumptions'!$E$23*T82*U82 -> 180 | L82: =H82+I82+J82+K82 -> 2965 | M82: =L82*'Engineering Assumptions'!$B$10 -> 444.75 | N82: =L82+M82 -> 3409.75 | O82: =N82*'Engineering Assumptions'!$B$11 -> 681.95 | P82: =MROUND(N82+O82,10) -> 4090 | Q82: ='Fleet Pricing'!H82 -> 3590 | R82: 9 | S82: 1.25 | T82: 0.75 | U82: 1
A83: 73 | B83: Vibrating Roller | C83: (Unknown) SL203468 | D83: VR-23 | F83: 2017 | G83: 9 | H83: ='Engineering Assumptions'!$C$23*'Engineering Assumptions'!$B$5*U83 -> 1910 | I83: ='Engineering Assumptions'!$B$8 -> 650 | J83: ='Engineering Assumptions'!$D$23*S83*U83 -> 225 | K83: ='Engineering Assumptions'!$E$23*T83*U83 -> 180 | L83: =H83+I83+J83+K83 -> 2965 | M83: =L83*'Engineering Assumptions'!$B$10 -> 444.75 | N83: =L83+M83 -> 3409.75 | O83: =N83*'Engineering Assumptions'!$B$11 -> 681.95 | P83: =MROUND(N83+O83,10) -> 4090 | Q83: ='Fleet Pricing'!H83 -> 3590 | R83: 9 | S83: 1.25 | T83: 0.75 | U83: 1
A84: 74 | B84: Vibrating Roller | C84: (Unknown) — | D84: VR-19 | F84: 2016 | G84: 10 | H84: ='Engineering Assumptions'!$C$23*'Engineering Assumptions'!$B$5*U84 -> 1910 | I84: ='Engineering Assumptions'!$B$8 -> 650 | J84: ='Engineering Assumptions'!$D$23*S84*U84 -> 225 | K84: ='Engineering Assumptions'!$E$23*T84*U84 -> 180 | L84: =H84+I84+J84+K84 -> 2965 | M84: =L84*'Engineering Assumptions'!$B$10 -> 444.75 | N84: =L84+M84 -> 3409.75 | O84: =N84*'Engineering Assumptions'!$B$11 -> 681.95 | P84: =MROUND(N84+O84,10) -> 4090 | Q84: ='Fleet Pricing'!H84 -> 3590 | R84: 10 | S84: 1.25 | T84: 0.75 | U84: 1
A85: 75 | B85: Vibrating Roller | C85: BOMAG BW-138 AD | D85: VR-14 | F85: 2016 | G85: 10 | H85: ='Engineering Assumptions'!$C$23*'Engineering Assumptions'!$B$5*U85 -> 1910 | I85: ='Engineering Assumptions'!$B$8 -> 650 | J85: ='Engineering Assumptions'!$D$23*S85*U85 -> 225 | K85: ='Engineering Assumptions'!$E$23*T85*U85 -> 180 | L85: =H85+I85+J85+K85 -> 2965 | M85: =L85*'Engineering Assumptions'!$B$10 -> 444.75 | N85: =L85+M85 -> 3409.75 | O85: =N85*'Engineering Assumptions'!$B$11 -> 681.95 | P85: =MROUND(N85+O85,10) -> 4090 | Q85: ='Fleet Pricing'!H85 -> 3590 | R85: 10 | S85: 1.25 | T85: 0.75 | U85: 1
A86: 76 | B86: Vibrating Roller | C86: BOMAG SA-00-350 | D86: VR-18 | F86: 2016 | G86: 10 | H86: ='Engineering Assumptions'!$C$23*'Engineering Assumptions'!$B$5*U86 -> 1910 | I86: ='Engineering Assumptions'!$B$8 -> 650 | J86: ='Engineering Assumptions'!$D$23*S86*U86 -> 225 | K86: ='Engineering Assumptions'!$E$23*T86*U86 -> 180 | L86: =H86+I86+J86+K86 -> 2965 | M86: =L86*'Engineering Assumptions'!$B$10 -> 444.75 | N86: =L86+M86 -> 3409.75 | O86: =N86*'Engineering Assumptions'!$B$11 -> 681.95 | P86: =MROUND(N86+O86,10) -> 4090 | Q86: ='Fleet Pricing'!H86 -> 3590 | R86: 10 | S86: 1.25 | T86: 0.75 | U86: 1
A87: 77 | B87: Vibrating Roller | C87: BOMAG BW 75 H | D87: VR-31 | F87: 2016 | G87: 10 | H87: ='Engineering Assumptions'!$C$23*'Engineering Assumptions'!$B$5*U87 -> 1910 | I87: ='Engineering Assumptions'!$B$8 -> 650 | J87: ='Engineering Assumptions'!$D$23*S87*U87 -> 225 | K87: ='Engineering Assumptions'!$E$23*T87*U87 -> 180 | L87: =H87+I87+J87+K87 -> 2965 | M87: =L87*'Engineering Assumptions'!$B$10 -> 444.75 | N87: =L87+M87 -> 3409.75 | O87: =N87*'Engineering Assumptions'!$B$11 -> 681.95 | P87: =MROUND(N87+O87,10) -> 4090 | Q87: ='Fleet Pricing'!H87 -> 3590 | R87: 10 | S87: 1.25 | T87: 0.75 | U87: 1
A88: 78 | B88: Vibrating Roller | C88: TACOM TFR60TDS | D88: VR-30 | F88: 2016 | G88: 10 | H88: ='Engineering Assumptions'!$C$23*'Engineering Assumptions'!$B$5*U88 -> 1910 | I88: ='Engineering Assumptions'!$B$8 -> 650 | J88: ='Engineering Assumptions'!$D$23*S88*U88 -> 225 | K88: ='Engineering Assumptions'!$E$23*T88*U88 -> 180 | L88: =H88+I88+J88+K88 -> 2965 | M88: =L88*'Engineering Assumptions'!$B$10 -> 444.75 | N88: =L88+M88 -> 3409.75 | O88: =N88*'Engineering Assumptions'!$B$11 -> 681.95 | P88: =MROUND(N88+O88,10) -> 4090 | Q88: ='Fleet Pricing'!H88 -> 3590 | R88: 10 | S88: 1.25 | T88: 0.75 | U88: 1
A89: 79 | B89: Vibrating Roller | C89: TACOM BW 75 H | D89: VR-32 | F89: 2016 | G89: 10 | H89: ='Engineering Assumptions'!$C$23*'Engineering Assumptions'!$B$5*U89 -> 1910 | I89: ='Engineering Assumptions'!$B$8 -> 650 | J89: ='Engineering Assumptions'!$D$23*S89*U89 -> 225 | K89: ='Engineering Assumptions'!$E$23*T89*U89 -> 180 | L89: =H89+I89+J89+K89 -> 2965 | M89: =L89*'Engineering Assumptions'!$B$10 -> 444.75 | N89: =L89+M89 -> 3409.75 | O89: =N89*'Engineering Assumptions'!$B$11 -> 681.95 | P89: =MROUND(N89+O89,10) -> 4090 | Q89: ='Fleet Pricing'!H89 -> 3590 | R89: 10 | S89: 1.25 | T89: 0.75 | U89: 1
A90: 80 | B90: Vibrating Roller | C90: TACOM BW 75 H | D90: VR-33 | F90: 2016 | G90: 10 | H90: ='Engineering Assumptions'!$C$23*'Engineering Assumptions'!$B$5*U90 -> 1910 | I90: ='Engineering Assumptions'!$B$8 -> 650 | J90: ='Engineering Assumptions'!$D$23*S90*U90 -> 225 | K90: ='Engineering Assumptions'!$E$23*T90*U90 -> 180 | L90: =H90+I90+J90+K90 -> 2965 | M90: =L90*'Engineering Assumptions'!$B$10 -> 444.75 | N90: =L90+M90 -> 3409.75 | O90: =N90*'Engineering Assumptions'!$B$11 -> 681.95 | P90: =MROUND(N90+O90,10) -> 4090 | Q90: ='Fleet Pricing'!H90 -> 3590 | R90: 10 | S90: 1.25 | T90: 0.75 | U90: 1
A91: 81 | B91: Vibrating Roller | C91: (Unknown) — | D91: VR-06 | F91: 2015 | G91: 11 | H91: ='Engineering Assumptions'!$C$23*'Engineering Assumptions'!$B$5*U91 -> 1910 | I91: ='Engineering Assumptions'!$B$8 -> 650 | J91: ='Engineering Assumptions'!$D$23*S91*U91 -> 279 | K91: ='Engineering Assumptions'!$E$23*T91*U91 -> 324 | L91: =H91+I91+J91+K91 -> 3163 | M91: =L91*'Engineering Assumptions'!$B$10 -> 474.45 | N91: =L91+M91 -> 3637.45 | O91: =N91*'Engineering Assumptions'!$B$11 -> 727.49 | P91: =MROUND(N91+O91,10) -> 4360 | Q91: ='Fleet Pricing'!H91 -> 3590 | R91: 11 | S91: 1.55 | T91: 1.35 | U91: 1
A92: 82 | B92: Vibrating Roller | C92: BOMAG BW 75 H | D92: VR-28 | F92: 2015 | G92: 11 | H92: ='Engineering Assumptions'!$C$23*'Engineering Assumptions'!$B$5*U92 -> 1910 | I92: ='Engineering Assumptions'!$B$8 -> 650 | J92: ='Engineering Assumptions'!$D$23*S92*U92 -> 279 | K92: ='Engineering Assumptions'!$E$23*T92*U92 -> 324 | L92: =H92+I92+J92+K92 -> 3163 | M92: =L92*'Engineering Assumptions'!$B$10 -> 474.45 | N92: =L92+M92 -> 3637.45 | O92: =N92*'Engineering Assumptions'!$B$11 -> 727.49 | P92: =MROUND(N92+O92,10) -> 4360 | Q92: ='Fleet Pricing'!H92 -> 3590 | R92: 11 | S92: 1.55 | T92: 1.35 | U92: 1
A93: 83 | B93: Vibrating Roller | C93: TACOM TFR60TDS | D93: VR-29 | F93: 2015 | G93: 11 | H93: ='Engineering Assumptions'!$C$23*'Engineering Assumptions'!$B$5*U93 -> 1910 | I93: ='Engineering Assumptions'!$B$8 -> 650 | J93: ='Engineering Assumptions'!$D$23*S93*U93 -> 279 | K93: ='Engineering Assumptions'!$E$23*T93*U93 -> 324 | L93: =H93+I93+J93+K93 -> 3163 | M93: =L93*'Engineering Assumptions'!$B$10 -> 474.45 | N93: =L93+M93 -> 3637.45 | O93: =N93*'Engineering Assumptions'!$B$11 -> 727.49 | P93: =MROUND(N93+O93,10) -> 4360 | Q93: ='Fleet Pricing'!H93 -> 3590 | R93: 11 | S93: 1.55 | T93: 1.35 | U93: 1
... A148: 138 | B148: Vibrating Roller | C148: (Unknown) CC-1250 | D148: VR-71 | F148: — | G148: 30 | H148: ='Engineering Assumptions'!$C$23*'Engineering Assumptions'!$B$5*U148 -> 1910 | I148: ='Engineering Assumptions'!$B$8 -> 650 | J148: ='Engineering Assumptions'!$D$23*S148*U148 -> 432 | K148: ='Engineering Assumptions'!$E$23*T148*U148 -> 720 | L148: =H148+I148+J148+K148 -> 3712 | M148: =L148*'Engineering Assumptions'!$B$10 -> 556.8 | N148: =L148+M148 -> 4268.8 | O148: =N148*'Engineering Assumptions'!$B$11 -> 853.76 | P148: =MROUND(N148+O148,10) -> 5120 | Q148: ='Fleet Pricing'!H148 -> 2260 | R148: 30 | S148: 2.4 | T148: 3 | U148: 1
A149: 139 | B149: Vibrating Roller | C149: ATLAS — | F149: — | G149: 30 | H149: ='Engineering Assumptions'!$C$23*'Engineering Assumptions'!$B$5*U149 -> 1910 | I149: ='Engineering Assumptions'!$B$8 -> 650 | J149: ='Engineering Assumptions'!$D$23*S149*U149 -> 432 | K149: ='Engineering Assumptions'!$E$23*T149*U149 -> 720 | L149: =H149+I149+J149+K149 -> 3712 | M149: =L149*'Engineering Assumptions'!$B$10 -> 556.8 | N149: =L149+M149 -> 4268.8 | O149: =N149*'Engineering Assumptions'!$B$11 -> 853.76 | P149: =MROUND(N149+O149,10) -> 5120 | Q149: ='Fleet Pricing'!H149 -> 2260 | R149: 30 | S149: 2.4 | T149: 3 | U149: 1
